Workbook
Name WeeksList: #REF!

Sheet Data
A1: Data | E1: Average | G1: Totals | I1: 45656 | K1: 45809 | M1: 45670 | O1: 45677 | Q1: 45684 | S1: 45718 | U1: 45932 | W1: 45705 | Y1: 45712 | AA1: 45719 | AC1: 45933 | AE1: 45733 | AG1: 45740 | AI1: 45747 | AK1: 45842 | AM1: 45761 | AO1: 45768 | AQ1: 45775 | AS1: 45782 | AU1: 45996 | AW1: 45796 | AY1: 45803 | BA1: 45694 | BC1: 45906 | BE1: 45824 | BG1: 45831 | BI1: 45838 | BK1: 45845 | BM1: 45852 | BO1: 45859 | BQ1: 45866 | BS1: 45755 | BU1: 45969 | BW1: 45887 | BY1: 45894 | CA1: 45666 | CC1: 45878 | CE1: 45915 | CG1: 45922 | CI1: 45929 | CK1: 45818 | CM1: 45943 | CO1: 45950 | CQ1: 45957 | CS1: 45727 | CU1: 45941 | CW1: 45978 | CY1: 45985 | DA1: 45669 | DC1: 45881 | DE1: 46006 | DG1: 46013 | DI1: 46020 | DK1: 46027 | DM1: 46034 | DO1: 46041 | DQ1: 46048 | DS1: 46055 | DU1: 46062 | DW1: 46069 | DY1: 46076 | EA1: 46083 | EC1: 46090 | EE1: 46097 | EG1: 46104 | EI1: 46111 | EK1: 46118 | EM1: 46125 | EO1: 46132 | EQ1: 46139 | ES1: 46146
A2: > Sub-Department | C2: Product Code | D2: Product Description | E2: Sales excl. VAT | F2: Sales Quantity | G2: Sales excl. VAT | H2: Sales Quantity | I2: Sales excl. VAT | J2: Sales Quantity | K2: Sales excl. VAT | L2: Sales Quantity | M2: Sales excl. VAT | N2: Sales Quantity | O2: Sales excl. VAT | P2: Sales Quantity | Q2: Sales excl. VAT | R2: Sales Quantity | S2: Sales excl. VAT | T2: Sales Quantity | U2: Sales excl. VAT | V2: Sales Quantity | W2: Sales excl. VAT | X2: Sales Quantity | Y2: Sales excl. VAT | Z2: Sales Quantity | AA2: Sales excl. VAT | AB2: Sales Quantity | AC2: Sales excl. VAT | AD2: Sales Quantity | AE2: Sales excl. VAT | AF2: Sales Quantity | AG2: Sales excl. VAT | AH2: Sales Quantity | AI2: Sales excl. VAT | AJ2: Sales Quantity | AK2: Sales excl. VAT | AL2: Sales Quantity | AM2: Sales excl. VAT | AN2: Sales Quantity | AO2: Sales excl. VAT | AP2: Sales Quantity | AQ2: Sales excl. VAT | AR2: Sales Quantity | AS2: Sales excl. VAT | AT2: Sales Quantity | AU2: Sales excl. VAT | AV2: Sales Quantity | AW2: Sales excl. VAT | AX2: Sales Quantity | AY2: Sales excl. VAT | AZ2: Sales Quantity | BA2: Sales excl. VAT | BB2: Sales Quantity | BC2: Sales excl. VAT | BD2: Sales Quantity | BE2: Sales excl. VAT | BF2: Sales Quantity | BG2: Sales excl. VAT | BH2: Sales Quantity | BI2: Sales excl. VAT | BJ2: Sales Quantity | BK2: Sales excl. VAT | BL2: Sales Quantity | BM2: Sales excl. VAT | BN2: Sales Quantity | BO2: Sales excl. VAT | BP2: Sales Quantity | BQ2: Sales excl. VAT | BR2: Sales Quantity | BS2: Sales excl. VAT | BT2: Sales Quantity | BU2: Sales excl. VAT | BV2: Sales Quantity | BW2: Sales excl. VAT | BX2: Sales Quantity | BY2: Sales excl. VAT | BZ2: Sales Quantity | CA2: Sales excl. VAT | CB2: Sales Quantity | CC2: Sales excl. VAT | CD2: Sales Quantity | CE2: Sales excl. VAT | CF2: Sales Quantity | CG2: Sales excl. VAT | CH2: Sales Quantity | CI2: Sales excl. VAT | CJ2: Sales Quantity | CK2: Sales excl. VAT | CL2: Sales Quantity | CM2: Sales excl. VAT | CN2: Sales Quantity | CO2: Sales excl. VAT | CP2: Sales Quantity | CQ2: Sales excl. VAT | CR2: Sales Quantity | CS2: Sales excl. VAT | CT2: Sales Quantity | CU2: Sales excl. VAT | CV2: Sales Quantity | CW2: Sales excl. VAT | CX2: Sales Quantity | CY2: Sales excl. VAT | CZ2: Sales Quantity | DA2: Sales excl. VAT | DB2: Sales Quantity | DC2: Sales excl. VAT | DD2: Sales Quantity | DE2: Sales excl. VAT | DF2: Sales Quantity | DG2: Sales excl. VAT | DH2: Sales Quantity | DI2: Sales excl. VAT | DJ2: Sales Quantity | DK2: Sales excl. VAT | DL2: Sales Quantity | DM2: Sales excl. VAT | DN2: Sales Quantity | DO2: Sales excl. VAT | DP2: Sales Quantity | DQ2: Sales excl. VAT | DR2: Sales Quantity | DS2: Sales excl. VAT | DT2: Sales Quantity | DU2: Sales excl. VAT | DV2: Sales Quantity | DW2: Sales excl. VAT | DX2: Sales Quantity | DY2: Sales excl. VAT | DZ2: Sales Quantity | EA2: Sales excl. VAT | EB2: Sales Quantity | EC2: Sales excl. VAT | ED2: Sales Quantity | EE2: Sales excl. VAT | EF2: Sales Quantity | EG2: Sales excl. VAT | EH2: Sales Quantity | EI2: Sales excl. VAT | EJ2: Sales Quantity | EK2: Sales excl. VAT | EL2: Sales Quantity | EM2: Sales excl. VAT | EN2: Sales Quantity | EO2: Sales excl. VAT | EP2: Sales Quantity | EQ2: Sales excl. VAT | ER2: Sales Quantity | ES2: Sales excl. VAT | ET2: Sales Quantity
A3: 201 | B3: =LOOKUP(A3,Lookup!$A$1:$A$34,Lookup!$B$1:$B$34) -> BUTCHERY | C3: 11141 | D3: SPAR SLT PORK SPARERIB | E3: 0 | F3: 0 | G3: 0 | H3: 0 | I3: 0 | J3: 0 | K3: 0 | L3: 0 | M3: 0 | N3: 0 | O3: 0 | P3: 0 | Q3: 0 | R3: 0 | S3: 0 | T3: 0 | U3: 0 | V3: 0 | W3: 0 | X3: 0 | Y3: 0 | Z3: 0 | AA3: 0 | AB3: 0 | AC3: 0 | AD3: 0 | AE3: 0 | AF3: 0 | AG3: 0 | AH3: 0 | AI3: 0 | AJ3: 0 | AK3: 0 | AL3: 0 | AM3: 0 | AN3: 0 | AO3: 0 | AP3: 0 | AQ3: 0 | AR3: 0 | AS3: 0 | AT3: 0 | AU3: 0 | AV3: 0 | AW3: 0 | AX3: 0 | AY3: 0 | AZ3: 0 | BA3: 0 | BB3: 0 | BC3: 0 | BD3: 0 | BE3: 0 | BF3: 0 | BG3: 0 | BH3: 0 | BI3: 0 | BJ3: 0 | BK3: 0 | BL3: 0 | BM3: 0 | BN3: 0 | BO3: 0 | BP3: 0 | BQ3: 0 | BR3: 0 | BS3: 0 | BT3: 0 | BU3: 0 | BV3: 0 | BW3: 0 | BX3: 0 | BY3: 0 | BZ3: 0 | CA3: 0 | CB3: 0 | CC3: 0 | CD3: 0 | CE3: 0 | CF3: 0 | CG3: 0 | CH3: 0 | CI3: 0 | CJ3: 0 | CK3: 0 | CL3: 0 | CM3: 0 | CN3: 0 | CO3: 0 | CP3: 0 | CQ3: 0 | CR3: 0 | CS3: 0 | CT3: 0 | CU3: 0 | CV3: 0 | CW3: 0 | CX3: 0 | CY3: 0 | CZ3: 0 | DA3: 0 | DB3: 0 | DC3: 0 | DD3: 0 | DE3: 0 | DF3: 0 | DG3: 0 | DH3: 0 | DI3: 0 | DJ3: 0 | DK3: 0 | DL3: 0 | DM3: 0 | DN3: 0 | DO3: 0 | DP3: 0 | DQ3: 0 | DR3: 0 | DS3: 0 | DT3: 0 | DU3: 0 | DV3: 0 | DW3: 0 | DX3: 0 | DY3: 0 | DZ3: 0 | EA3: 0 | EB3: 0 | EC3: 0 | ED3: 0 | EE3: 0 | EF3: 0 | EG3: 0 | EH3: 0 | EI3: 0 | EJ3: 0 | EK3: 0 | EL3: 0 | EM3: 0 | EN3: 0 | EO3: 0 | EP3: 0 | EQ3: 0 | ER3: 0 | ES3: 0 | ET3: 0
A4: 201 | B4: =LOOKUP(A4,Lookup!$A$1:$A$34,Lookup!$B$1:$B$34) -> BUTCHERY | C4: 11385 | D4: ETLIN RIBS PORK SPARE FRZ | E4: 0 | F4: 0 | G4: 0 | H4: 0 | I4: 0 | J4: 0 | K4: 0 | L4: 0 | M4: 0 | N4: 0 | O4: 0 | P4: 0 | Q4: 0 | R4: 0 | S4: 0 | T4: 0 | U4: 0 | V4: 0 | W4: 0 | X4: 0 | Y4: 0 | Z4: 0 | AA4: 0 | AB4: 0 | AC4: 0 | AD4: 0 | AE4: 0 | AF4: 0 | AG4: 0 | AH4: 0 | AI4: 0 | AJ4: 0 | AK4: 0 | AL4: 0 | AM4: 0 | AN4: 0 | AO4: 0 | AP4: 0 | AQ4: 0 | AR4: 0 | AS4: 0 | AT4: 0 | AU4: 0 | AV4: 0 | AW4: 0 | AX4: 0 | AY4: 0 | AZ4: 0 | BA4: 0 | BB4: 0 | BC4: 0 | BD4: 0 | BE4: 0 | BF4: 0 | BG4: 0 | BH4: 0 | BI4: 0 | BJ4: 0 | BK4: 0 | BL4: 0 | BM4: 0 | BN4: 0 | BO4: 0 | BP4: 0 | BQ4: 0 | BR4: 0 | BS4: 0 | BT4: 0 | BU4: 0 | BV4: 0 | BW4: 0 | BX4: 0 | BY4: 0 | BZ4: 0 | CA4: 0 | CB4: 0 | CC4: 0 | CD4: 0 | CE4: 0 | CF4: 0 | CG4: 0 | CH4: 0 | CI4: 0 | CJ4: 0 | CK4: 0 | CL4: 0 | CM4: 0 | CN4: 0 | CO4: 0 | CP4: 0 | CQ4: 0 | CR4: 0 | CS4: 0 | CT4: 0 | CU4: 0 | CV4: 0 | CW4: 0 | CX4: 0 | CY4: 0 | CZ4: 0 | DA4: 0 | DB4: 0 | DC4: 0 | DD4: 0 | DE4: 0 | DF4: 0 | DG4: 0 | DH4: 0 | DI4: 0 | DJ4: 0 | DK4: 0 | DL4: 0 | DM4: 0 | DN4: 0 | DO4: 0 | DP4: 0 | DQ4: 0 | DR4: 0 | DS4: 0 | DT4: 0 | DU4: 0 | DV4: 0 | DW4: 0 | DX4: 0 | DY4: 0 | DZ4: 0 | EA4: 0 | EB4: 0 | EC4: 0 | ED4: 0 | EE4: 0 | EF4: 0 | EG4: 0 | EH4: 0 | EI4: 0 | EJ4: 0 | EK4: 0 | EL4: 0 | EM4: 0 | EN4: 0 | EO4: 0 | EP4: 0 | EQ4: 0 | ER4: 0 | ES4: 0 | ET4: 0
A5: 201 | B5: =LOOKUP(A5,Lookup!$A$1:$A$34,Lookup!$B$1:$B$34) -> BUTCHERY | C5: 11388 | D5: ETLIN CHIC SAHA MDM | E5: 0 | F5: 0 | G5: 0 | H5: 0 | I5: 0 | J5: 0 | K5: 0 | L5: 0 | M5: 0 | N5: 0 | O5: 0 | P5: 0 | Q5: 0 | R5: 0 | S5: 0 | T5: 0 | U5: 0 | V5: 0 | W5: 0 | X5: 0 | Y5: 0 | Z5: 0 | AA5: 0 | AB5: 0 | AC5: 0 | AD5: 0 | AE5: 0 | AF5: 0 | AG5: 0 | AH5: 0 | AI5: 0 | AJ5: 0 | AK5: 0 | AL5: 0 | AM5: 0 | AN5: 0 | AO5: 0 | AP5: 0 | AQ5: 0 | AR5: 0 | AS5: 0 | AT5: 0 | AU5: 0 | AV5: 0 | AW5: 0 | AX5: 0 | AY5: 0 | AZ5: 0 | BA5: 0 | BB5: 0 | BC5: 0 | BD5: 0 | BE5: 0 | BF5: 0 | BG5: 0 | BH5: 0 | BI5: 0 | BJ5: 0 | BK5: 0 | BL5: 0 | BM5: 0 | BN5: 0 | BO5: 0 | BP5: 0 | BQ5: 0 | BR5: 0 | BS5: 0 | BT5: 0 | BU5: 0 | BV5: 0 | BW5: 0 | BX5: 0 | BY5: 0 | BZ5: 0 | CA5: 0 | CB5: 0 | CC5: 0 | CD5: 0 | CE5: 0 | CF5: 0 | CG5: 0 | CH5: 0 | CI5: 0 | CJ5: 0 | CK5: 0 | CL5: 0 | CM5: 0 | CN5: 0 | CO5: 0 | CP5: 0 | CQ5: 0 | CR5: 0 | CS5: 0 | CT5: 0 | CU5: 0 | CV5: 0 | CW5: 0 | CX5: 0 | CY5: 0 | CZ5: 0 | DA5: 0 | DB5: 0 | DC5: 0 | DD5: 0 | DE5: 0 | DF5: 0 | DG5: 0 | DH5: 0 | DI5: 0 | DJ5: 0 | DK5: 0 | DL5: 0 | DM5: 0 | DN5: 0 | DO5: 0 | DP5: 0 | DQ5: 0 | DR5: 0 | DS5: 0 | DT5: 0 | DU5: 0 | DV5: 0 | DW5: 0 | DX5: 0 | DY5: 0 | DZ5: 0 | EA5: 0 | EB5: 0 | EC5: 0 | ED5: 0 | EE5: 0 | EF5: 0 | EG5: 0 | EH5: 0 | EI5: 0 | EJ5: 0 | EK5: 0 | EL5: 0 | EM5: 0 | EN5: 0 | EO5: 0 | EP5: 0 | EQ5: 0 | ER5: 0 | ES5: 0 | ET5: 0
A6: 201 | B6: =LOOKUP(A6,Lookup!$A$1:$A$34,Lookup!$B$1:$B$34) -> BUTCHERY | C6: 12151 | D6: SPAR SLT BEEF CHUCK B/IN | E6: 0 | F6: 0 | G6: 0 | H6: 0 | I6: 0 | J6: 0 | K6: 0 | L6: 0 | M6: 0 | N6: 0 | O6: 0 | P6: 0 | Q6: 0 | R6: 0 | S6: 0 | T6: 0 | U6: 0 | V6: 0 | W6: 0 | X6: 0 | Y6: 0 | Z6: 0 | AA6: 0 | AB6: 0 | AC6: 0 | AD6: 0 | AE6: 0 | AF6: 0 | AG6: 0 | AH6: 0 | AI6: 0 | AJ6: 0 | AK6: 0 | AL6: 0 | AM6: 0 | AN6: 0 | AO6: 0 | AP6: 0 | AQ6: 0 | AR6: 0 | AS6: 0 | AT6: 0 | AU6: 0 | AV6: 0 | AW6: 0 | AX6: 0 | AY6: 0 | AZ6: 0 | BA6: 0 | BB6: 0 | BC6: 0 | BD6: 0 | BE6: 0 | BF6: 0 | BG6: 0 | BH6: 0 | BI6: 0 | BJ6: 0 | BK6: 0 | BL6: 0 | BM6: 0 | BN6: 0 | BO6: 0 | BP6: 0 | BQ6: 0 | BR6: 0 | BS6: 0 | BT6: 0 | BU6: 0 | BV6: 0 | BW6: 0 | BX6: 0 | BY6: 0 | BZ6: 0 | CA6: 0 | CB6: 0 | CC6: 0 | CD6: 0 | CE6: 0 | CF6: 0 | CG6: 0 | CH6: 0 | CI6: 0 | CJ6: 0 | CK6: 0 | CL6: 0 | CM6: 0 | CN6: 0 | CO6: 0 | CP6: 0 | CQ6: 0 | CR6: 0 | CS6: 0 | CT6: 0 | CU6: 0 | CV6: 0 | CW6: 0 | CX6: 0 | CY6: 0 | CZ6: 0 | DA6: 0 | DB6: 0 | DC6: 0 | DD6: 0 | DE6: 0 | DF6: 0 | DG6: 0 | DH6: 0 | DI6: 0 | DJ6: 0 | DK6: 0 | DL6: 0 | DM6: 0 | DN6: 0 | DO6: 0 | DP6: 0 | DQ6: 0 | DR6: 0 | DS6: 0 | DT6: 0 | DU6: 0 | DV6: 0 | DW6: 0 | DX6: 0 | DY6: 0 | DZ6: 0 | EA6: 0 | EB6: 0 | EC6: 0 | ED6: 0 | EE6: 0 | EF6: 0 | EG6: 0 | EH6: 0 | EI6: 0 | EJ6: 0 | EK6: 0 | EL6: 0 | EM6: 0 | EN6: 0 | EO6: 0 | EP6: 0 | EQ6: 0 | ER6: 0 | ES6: 0 | ET6: 0
A7: 201 | B7: =LOOKUP(A7,Lookup!$A$1:$A$34,Lookup!$B$1:$B$34) -> BUTCHERY | C7: 12194 | D7: SPAR T&T GAMMON/TONGUE | E7: 6.8259645 | F7: 0.063 | G7: 484.64348 | H7: 4.459 | I7: 0 | J7: 0 | K7: 0 | L7: 0 | M7: 0 | N7: 0 | O7: 0 | P7: 0 | Q7: 0 | R7: 0 | S7: 0 | T7: 0 | U7: 0 | V7: 0 | W7: 0 | X7: 0 | Y7: 0 | Z7: 0 | AA7: 0 | AB7: 0 | AC7: 0 | AD7: 0 | AE7: 0 | AF7: 0 | AG7: 0 | AH7: 0 | AI7: 0 | AJ7: 0 | AK7: 0 | AL7: 0 | AM7: 0 | AN7: 0 | AO7: 0 | AP7: 0 | AQ7: 0 | AR7: 0 | AS7: 0 | AT7: 0 | AU7: 0 | AV7: 0 | AW7: 0 | AX7: 0 | AY7: 0 | AZ7: 0 | BA7: 0 | BB7: 0 | BC7: 0 | BD7: 0 | BE7: 0 | BF7: 0 | BG7: 0 | BH7: 0 | BI7: 0 | BJ7: 0 | BK7: 0 | BL7: 0 | BM7: 0 | BN7: 0 | BO7: 0 | BP7: 0 | BQ7: 0 | BR7: 0 | BS7: 0 | BT7: 0 | BU7: 0 | BV7: 0 | BW7: 0 | BX7: 0 | BY7: 0 | BZ7: 0 | CA7: 0 | CB7: 0 | CC7: 0 | CD7: 0 | CE7: 0 | CF7: 0 | CG7: 0 | CH7: 0 | CI7: 0 | CJ7: 0 | CK7: 0 | CL7: 0 | CM7: 0 | CN7: 0 | CO7: 0 | CP7: 0 | CQ7: 0 | CR7: 0 | CS7: 0 | CT7: 0 | CU7: 0 | CV7: 0 | CW7: 0 | CX7: 0 | CY7: 0 | CZ7: 0 | DA7: 484.64348 | DB7: 4.459 | DC7: 0 | DD7: 0 | DE7: 0 | DF7: 0 | DG7: 0 | DH7: 0 | DI7: 0 | DJ7: 0 | DK7: 0 | DL7: 0 | DM7: 0 | DN7: 0 | DO7: 0 | DP7: 0 | DQ7: 0 | DR7: 0 | DS7: 0 | DT7: 0 | DU7: 0 | DV7: 0 | DW7: 0 | DX7: 0 | DY7: 0 | DZ7: 0 | EA7: 0 | EB7: 0 | EC7: 0 | ED7: 0 | EE7: 0 | EF7: 0 | EG7: 0 | EH7: 0 | EI7: 0 | EJ7: 0 | EK7: 0 | EL7: 0 | EM7: 0 | EN7: 0 | EO7: 0 | EP7: 0 | EQ7: 0 | ER7: 0 | ES7: 0 | ET7: 0
A8: 201 | B8: =LOOKUP(A8,Lookup!$A$1:$A$34,Lookup!$B$1:$B$34) -> BUTCHERY | C8: 12314 | D8: T&T TONGUE/GAMON BOX | E8: 0 | F8: 0 | G8: 0 | H8: 0 | I8: 0 | J8: 0 | K8: 0 | L8: 0 | M8: 0 | N8: 0 | O8: 0 | P8: 0 | Q8: 0 | R8: 0 | S8: 0 | T8: 0 | U8: 0 | V8: 0 | W8: 0 | X8: 0 | Y8: 0 | Z8: 0 | AA8: 0 | AB8: 0 | AC8: 0 | AD8: 0 | AE8: 0 | AF8: 0 | AG8: 0 | AH8: 0 | AI8: 0 | AJ8: 0 | AK8: 0 | AL8: 0 | AM8: 0 | AN8: 0 | AO8: 0 | AP8: 0 | AQ8: 0 | AR8: 0 | AS8: 0 | AT8: 0 | AU8: 0 | AV8: 0 | AW8: 0 | AX8: 0 | AY8: 0 | AZ8: 0 | BA8: 0 | BB8: 0 | BC8: 0 | BD8: 0 | BE8: 0 | BF8: 0 | BG8: 0 | BH8: 0 | BI8: 0 | BJ8: 0 | BK8: 0 | BL8: 0 | BM8: 0 | BN8: 0 | BO8: 0 | BP8: 0 | BQ8: 0 | BR8: 0 | BS8: 0 | BT8: 0 | BU8: 0 | BV8: 0 | BW8: 0 | BX8: 0 | BY8: 0 | BZ8: 0 | CA8: 0 | CB8: 0 | CC8: 0 | CD8: 0 | CE8: 0 | CF8: 0 | CG8: 0 | CH8: 0 | CI8: 0 | CJ8: 0 | CK8: 0 | CL8: 0 | CM8: 0 | CN8: 0 | CO8: 0 | CP8: 0 | CQ8: 0 | CR8: 0 | CS8: 0 | CT8: 0 | CU8: 0 | CV8: 0 | CW8: 0 | CX8: 0 | CY8: 0 | CZ8: 0 | DA8: 0 | DB8: 0 | DC8: 0 | DD8: 0 | DE8: 0 | DF8: 0 | DG8: 0 | DH8: 0 | DI8: 0 | DJ8: 0 | DK8: 0 | DL8: 0 | DM8: 0 | DN8: 0 | DO8: 0 | DP8: 0 | DQ8: 0 | DR8: 0 | DS8: 0 | DT8: 0 | DU8: 0 | DV8: 0 | DW8: 0 | DX8: 0 | DY8: 0 | DZ8: 0 | EA8: 0 | EB8: 0 | EC8: 0 | ED8: 0 | EE8: 0 | EF8: 0 | EG8: 0 | EH8: 0 | EI8: 0 | EJ8: 0 | EK8: 0 | EL8: 0 | EM8: 0 | EN8: 0 | EO8: 0 | EP8: 0 | EQ8: 0 | ER8: 0 | ES8: 0 | ET8: 0
A9: 201 | B9: =LOOKUP(A9,Lookup!$A$1:$A$34,Lookup!$B$1:$B$34) -> BUTCHERY | C9: 15219 | D9: SPAR SLT LAMB LEG | E9: 0 | F9: 0 | G9: 0 | H9: 0 | I9: 0 | J9: 0 | K9: 0 | L9: 0 | M9: 0 | N9: 0 | O9: 0 | P9: 0 | Q9: 0 | R9: 0 | S9: 0 | T9: 0 | U9: 0 | V9: 0 | W9: 0 | X9: 0 | Y9: 0 | Z9: 0 | AA9: 0 | AB9: 0 | AC9: 0 | AD9: 0 | AE9: 0 | AF9: 0 | AG9: 0 | AH9: 0 | AI9: 0 | AJ9: 0 | AK9: 0 | AL9: 0 | AM9: 0 | AN9: 0 | AO9: 0 | AP9: 0 | AQ9: 0 | AR9: 0 | AS9: 0 | AT9: 0 | AU9: 0 | AV9: 0 | AW9: 0 | AX9: 0 | AY9: 0 | AZ9: 0 | BA9: 0 | BB9: 0 | BC9: 0 | BD9: 0 | BE9: 0 | BF9: 0 | BG9: 0 | BH9: 0 | BI9: 0 | BJ9: 0 | BK9: 0 | BL9: 0 | BM9: 0 | BN9: 0 | BO9: 0 | BP9: 0 | BQ9: 0 | BR9: 0 | BS9: 0 | BT9: 0 | BU9: 0 | BV9: 0 | BW9: 0 | BX9: 0 | BY9: 0 | BZ9: 0 | CA9: 0 | CB9: 0 | CC9: 0 | CD9: 0 | CE9: 0 | CF9: 0 | CG9: 0 | CH9: 0 | CI9: 0 | CJ9: 0 | CK9: 0 | CL9: 0 | CM9: 0 | CN9: 0 | CO9: 0 | CP9: 0 | CQ9: 0 | CR9: 0 | CS9: 0 | CT9: 0 | CU9: 0 | CV9: 0 | CW9: 0 | CX9: 0 | CY9: 0 | CZ9: 0 | DA9: 0 | DB9: 0 | DC9: 0 | DD9: 0 | DE9: 0 | DF9: 0 | DG9: 0 | DH9: 0 | DI9: 0 | DJ9: 0 | DK9: 0 | DL9: 0 | DM9: 0 | DN9: 0 | DO9: 0 | DP9: 0 | DQ9: 0 | DR9: 0 | DS9: 0 | DT9: 0 | DU9: 0 | DV9: 0 | DW9: 0 | DX9: 0 | DY9: 0 | DZ9: 0 | EA9: 0 | EB9: 0 | EC9: 0 | ED9: 0 | EE9: 0 | EF9: 0 | EG9: 0 | EH9: 0 | EI9: 0 | EJ9: 0 | EK9: 0 | EL9: 0 | EM9: 0 | EN9: 0 | EO9: 0 | EP9: 0 | EQ9: 0 | ER9: 0 | ES9: 0 | ET9: 0
A10: 201 | B10: =LOOKUP(A10,Lookup!$A$1:$A$34,Lookup!$B$1:$B$34) -> BUTCHERY | C10: 15227 | D10: SPAR SLT LAMB SHOULDER | E10: 0 | F10: 0 | G10: 0 | H10: 0 | I10: 0 | J10: 0 | K10: 0 | L10: 0 | M10: 0 | N10: 0 | O10: 0 | P10: 0 | Q10: 0 | R10: 0 | S10: 0 | T10: 0 | U10: 0 | V10: 0 | W10: 0 | X10: 0 | Y10: 0 | Z10: 0 | AA10: 0 | AB10: 0 | AC10: 0 | AD10: 0 | AE10: 0 | AF10: 0 | AG10: 0 | AH10: 0 | AI10: 0 | AJ10: 0 | AK10: 0 | AL10: 0 | AM10: 0 | AN10: 0 | AO10: 0 | AP10: 0 | AQ10: 0 | AR10: 0 | AS10: 0 | AT10: 0 | AU10: 0 | AV10: 0 | AW10: 0 | AX10: 0 | AY10: 0 | AZ10: 0 | BA10: 0 | BB10: 0 | BC10: 0 | BD10: 0 | BE10: 0 | BF10: 0 | BG10: 0 | BH10: 0 | BI10: 0 | BJ10: 0 | BK10: 0 | BL10: 0 | BM10: 0 | BN10: 0 | BO10: 0 | BP10: 0 | BQ10: 0 | BR10: 0 | BS10: 0 | BT10: 0 | BU10: 0 | BV10: 0 | BW10: 0 | BX10: 0 | BY10: 0 | BZ10: 0 | CA10: 0 | CB10: 0 | CC10: 0 | CD10: 0 | CE10: 0 | CF10: 0 | CG10: 0 | CH10: 0 | CI10: 0 | CJ10: 0 | CK10: 0 | CL10: 0 | CM10: 0 | CN10: 0 | CO10: 0 | CP10: 0 | CQ10: 0 | CR10: 0 | CS10: 0 | CT10: 0 | CU10: 0 | CV10: 0 | CW10: 0 | CX10: 0 | CY10: 0 | CZ10: 0 | DA10: 0 | DB10: 0 | DC10: 0 | DD10: 0 | DE10: 0 | DF10: 0 | DG10: 0 | DH10: 0 | DI10: 0 | DJ10: 0 | DK10: 0 | DL10: 0 | DM10: 0 | DN10: 0 | DO10: 0 | DP10: 0 | DQ10: 0 | DR10: 0 | DS10: 0 | DT10: 0 | DU10: 0 | DV10: 0 | DW10: 0 | DX10: 0 | DY10: 0 | DZ10: 0 | EA10: 0 | EB10: 0 | EC10: 0 | ED10: 0 | EE10: 0 | EF10: 0 | EG10: 0 | EH10: 0 | EI10: 0 | EJ10: 0 | EK10: 0 | EL10: 0 | EM10: 0 | EN10: 0 | EO10: 0 | EP10: 0 | EQ10: 0 | ER10: 0 | ES10: 0 | ET10: 0
A11: 201 | B11: =LOOKUP(A11,Lookup!$A$1:$A$34,Lookup!$B$1:$B$34) -> BUTCHERY | C11: 34176 | D11: BEEF STEAK BURGER | E11: 0 | F11: 0 | G11: 0 | H11: 0 | I11: 0 | J11: 0 | K11: 0 | L11: 0 | M11: 0 | N11: 0 | O11: 0 | P11: 0 | Q11: 0 | R11: 0 | S11: 0 | T11: 0 | U11: 0 | V11: 0 | W11: 0 | X11: 0 | Y11: 0 | Z11: 0 | AA11: 0 | AB11: 0 | AC11: 0 | AD11: 0 | AE11: 0 | AF11: 0 | AG11: 0 | AH11: 0 | AI11: 0 | AJ11: 0 | AK11: 0 | AL11: 0 | AM11: 0 | AN11: 0 | AO11: 0 | AP11: 0 | AQ11: 0 | AR11: 0 | AS11: 0 | AT11: 0 | AU11: 0 | AV11: 0 | AW11: 0 | AX11: 0 | AY11: 0 | AZ11: 0 | BA11: 0 | BB11: 0 | BC11: 0 | BD11: 0 | BE11: 0 | BF11: 0 | BG11: 0 | BH11: 0 | BI11: 0 | BJ11: 0 | BK11: 0 | BL11: 0 | BM11: 0 | BN11: 0 | BO11: 0 | BP11: 0 | BQ11: 0 | BR11: 0 | BS11: 0 | BT11: 0 | BU11: 0 | BV11: 0 | BW11: 0 | BX11: 0 | BY11: 0 | BZ11: 0 | CA11: 0 | CB11: 0 | CC11: 0 | CD11: 0 | CE11: 0 | CF11: 0 | CG11: 0 | CH11: 0 | CI11: 0 | CJ11: 0 | CK11: 0 | CL11: 0 | CM11: 0 | CN11: 0 | CO11: 0 | CP11: 0 | CQ11: 0 | CR11: 0 | CS11: 0 | CT11: 0 | CU11: 0 | CV11: 0 | CW11: 0 | CX11: 0 | CY11: 0 | CZ11: 0 | DA11: 0 | DB11: 0 | DC11: 0 | DD11: 0 | DE11: 0 | DF11: 0 | DG11: 0 | DH11: 0 | DI11: 0 | DJ11: 0 | DK11: 0 | DL11: 0 | DM11: 0 | DN11: 0 | DO11: 0 | DP11: 0 | DQ11: 0 | DR11: 0 | DS11: 0 | DT11: 0 | DU11: 0 | DV11: 0 | DW11: 0 | DX11: 0 | DY11: 0 | DZ11: 0 | EA11: 0 | EB11: 0 | EC11: 0 | ED11: 0 | EE11: 0 | EF11: 0 | EG11: 0 | EH11: 0 | EI11: 0 | EJ11: 0 | EK11: 0 | EL11: 0 | EM11: 0 | EN11: 0 | EO11: 0 | EP11: 0 | EQ11: 0 | ER11: 0 | ES11: 0 | ET11: 0
A12: 201 | B12: =LOOKUP(A12,Lookup!$A$1:$A$34,Lookup!$B$1:$B$34) -> BUTCHERY | C12: 34233 | D12: GAMMON BONELESS | E12: 0 | F12: 0 | G12: 0 | H12: 0 | I12: 0 | J12: 0 | K12: 0 | L12: 0 | M12: 0 | N12: 0 | O12: 0 | P12: 0 | Q12: 0 | R12: 0 | S12: 0 | T12: 0 | U12: 0 | V12: 0 | W12: 0 | X12: 0 | Y12: 0 | Z12: 0 | AA12: 0 | AB12: 0 | AC12: 0 | AD12: 0 | AE12: 0 | AF12: 0 | AG12: 0 | AH12: 0 | AI12: 0 | AJ12: 0 | AK12: 0 | AL12: 0 | AM12: 0 | AN12: 0 | AO12: 0 | AP12: 0 | AQ12: 0 | AR12: 0 | AS12: 0 | AT12: 0 | AU12: 0 | AV12: 0 | AW12: 0 | AX12: 0 | AY12: 0 | AZ12: 0 | BA12: 0 | BB12: 0 | BC12: 0 | BD12: 0 | BE12: 0 | BF12: 0 | BG12: 0 | BH12: 0 | BI12: 0 | BJ12: 0 | BK12: 0 | BL12: 0 | BM12: 0 | BN12: 0 | BO12: 0 | BP12: 0 | BQ12: 0 | BR12: 0 | BS12: 0 | BT12: 0 | BU12: 0 | BV12: 0 | BW12: 0 | BX12: 0 | BY12: 0 | BZ12: 0 | CA12: 0 | CB12: 0 | CC12: 0 | CD12: 0 | CE12: 0 | CF12: 0 | CG12: 0 | CH12: 0 | CI12: 0 | CJ12: 0 | CK12: 0 | CL12: 0 | CM12: 0 | CN12: 0 | CO12: 0 | CP12: 0 | CQ12: 0 | CR12: 0 | CS12: 0 | CT12: 0 | CU12: 0 | CV12: 0 | CW12: 0 | CX12: 0 | CY12: 0 | CZ12: 0 | DA12: 0 | DB12: 0 | DC12: 0 | DD12: 0 | DE12: 0 | DF12: 0 | DG12: 0 | DH12: 0 | DI12: 0 | DJ12: 0 | DK12: 0 | DL12: 0 | DM12: 0 | DN12: 0 | DO12: 0 | DP12: 0 | DQ12: 0 | DR12: 0 | DS12: 0 | DT12: 0 | DU12: 0 | DV12: 0 | DW12: 0 | DX12: 0 | DY12: 0 | DZ12: 0 | EA12: 0 | EB12: 0 | EC12: 0 | ED12: 0 | EE12: 0 | EF12: 0 | EG12: 0 | EH12: 0 | EI12: 0 | EJ12: 0 | EK12: 0 | EL12: 0 | EM12: 0 | EN12: 0 | EO12: 0 | EP12: 0 | EQ12: 0 | ER12: 0 | ES12: 0 | ET12: 0
A13: 201 | B13: =LOOKUP(A13,Lookup!$A$1:$A$34,Lookup!$B$1:$B$34) -> BUTCHERY | C13: 34234 | D13: GAMMON STEAKS | E13: 0 | F13: 0 | G13: 0 | H13: 0 | I13: 0 | J13: 0 | K13: 0 | L13: 0 | M13: 0 | N13: 0 | O13: 0 | P13: 0 | Q13: 0 | R13: 0 | S13: 0 | T13: 0 | U13: 0 | V13: 0 | W13: 0 | X13: 0 | Y13: 0 | Z13: 0 | AA13: 0 | AB13: 0 | AC13: 0 | AD13: 0 | AE13: 0 | AF13: 0 | AG13: 0 | AH13: 0 | AI13: 0 | AJ13: 0 | AK13: 0 | AL13: 0 | AM13: 0 | AN13: 0 | AO13: 0 | AP13: 0 | AQ13: 0 | AR13: 0 | AS13: 0 | AT13: 0 | AU13: 0 | AV13: 0 | AW13: 0 | AX13: 0 | AY13: 0 | AZ13: 0 | BA13: 0 | BB13: 0 | BC13: 0 | BD13: 0 | BE13: 0 | BF13: 0 | BG13: 0 | BH13: 0 | BI13: 0 | BJ13: 0 | BK13: 0 | BL13: 0 | BM13: 0 | BN13: 0 | BO13: 0 | BP13: 0 | BQ13: 0 | BR13: 0 | BS13: 0 | BT13: 0 | BU13: 0 | BV13: 0 | BW13: 0 | BX13: 0 | BY13: 0 | BZ13: 0 | CA13: 0 | CB13: 0 | CC13: 0 | CD13: 0 | CE13: 0 | CF13: 0 | CG13: 0 | CH13: 0 | CI13: 0 | CJ13: 0 | CK13: 0 | CL13: 0 | CM13: 0 | CN13: 0 | CO13: 0 | CP13: 0 | CQ13: 0 | CR13: 0 | CS13: 0 | CT13: 0 | CU13: 0 | CV13: 0 | CW13: 0 | CX13: 0 | CY13: 0 | CZ13: 0 | DA13: 0 | DB13: 0 | DC13: 0 | DD13: 0 | DE13: 0 | DF13: 0 | DG13: 0 | DH13: 0 | DI13: 0 | DJ13: 0 | DK13: 0 | DL13: 0 | DM13: 0 | DN13: 0 | DO13: 0 | DP13: 0 | DQ13: 0 | DR13: 0 | DS13: 0 | DT13: 0 | DU13: 0 | DV13: 0 | DW13: 0 | DX13: 0 | DY13: 0 | DZ13: 0 | EA13: 0 | EB13: 0 | EC13: 0 | ED13: 0 | EE13: 0 | EF13: 0 | EG13: 0 | EH13: 0 | EI13: 0 | EJ13: 0 | EK13: 0 | EL13: 0 | EM13: 0 | EN13: 0 | EO13: 0 | EP13: 0 | EQ13: 0 | ER13: 0 | ES13: 0 | ET13: 0
A14: 201 | B14: =LOOKUP(A14,Lookup!$A$1:$A$34,Lookup!$B$1:$B$34) -> BUTCHERY | C14: 34306 | D14: STEAK MINCE (EXTRA LEAN) | E14: 0 | F14: 0 | G14: 0 | H14: 0 | I14: 0 | J14: 0 | K14: 0 | L14: 0 | M14: 0 | N14: 0 | O14: 0 | P14: 0 | Q14: 0 | R14: 0 | S14: 0 | T14: 0 | U14: 0 | V14: 0 | W14: 0 | X14: 0 | Y14: 0 | Z14: 0 | AA14: 0 | AB14: 0 | AC14: 0 | AD14: 0 | AE14: 0 | AF14: 0 | AG14: 0 | AH14: 0 | AI14: 0 | AJ14: 0 | AK14: 0 | AL14: 0 | AM14: 0 | AN14: 0 | AO14: 0 | AP14: 0 | AQ14: 0 | AR14: 0 | AS14: 0 | AT14: 0 | AU14: 0 | AV14: 0 | AW14: 0 | AX14: 0 | AY14: 0 | AZ14: 0 | BA14: 0 | BB14: 0 | BC14: 0 | BD14: 0 | BE14: 0 | BF14: 0 | BG14: 0 | BH14: 0 | BI14: 0 | BJ14: 0 | BK14: 0 | BL14: 0 | BM14: 0 | BN14: 0 | BO14: 0 | BP14: 0 | BQ14: 0 | BR14: 0 | BS14: 0 | BT14: 0 | BU14: 0 | BV14: 0 | BW14: 0 | BX14: 0 | BY14: 0 | BZ14: 0 | CA14: 0 | CB14: 0 | CC14: 0 | CD14: 0 | CE14: 0 | CF14: 0 | CG14: 0 | CH14: 0 | CI14: 0 | CJ14: 0 | CK14: 0 | CL14: 0 | CM14: 0 | CN14: 0 | CO14: 0 | CP14: 0 | CQ14: 0 | CR14: 0 | CS14: 0 | CT14: 0 | CU14: 0 | CV14: 0 | CW14: 0 | CX14: 0 | CY14: 0 | CZ14: 0 | DA14: 0 | DB14: 0 | DC14: 0 | DD14: 0 | DE14: 0 | DF14: 0 | DG14: 0 | DH14: 0 | DI14: 0 | DJ14: 0 | DK14: 0 | DL14: 0 | DM14: 0 | DN14: 0 | DO14: 0 | DP14: 0 | DQ14: 0 | DR14: 0 | DS14: 0 | DT14: 0 | DU14: 0 | DV14: 0 | DW14: 0 | DX14: 0 | DY14: 0 | DZ14: 0 | EA14: 0 | EB14: 0 | EC14: 0 | ED14: 0 | EE14: 0 | EF14: 0 | EG14: 0 | EH14: 0 | EI14: 0 | EJ14: 0 | EK14: 0 | EL14: 0 | EM14: 0 | EN14: 0 | EO14: 0 | EP14: 0 | EQ14: 0 | ER14: 0 | ES14: 0 | ET14: 0
... A553: 229 | B553: =LOOKUP(A553,Lookup!$A$1:$A$34,Lookup!$B$1:$B$34) -> INGREDIENTS | C553: 63808 | D553: WILTSHIRE PORK SAUSAGE | E553: 0 | F553: 0 | G553: 0 | H553: 0 | I553: 0 | J553: 0 | K553: 0 | L553: 0 | M553: 0 | N553: 0 | O553: 0 | P553: 0 | Q553: 0 | R553: 0 | S553: 0 | T553: 0 | U553: 0 | V553: 0 | W553: 0 | X553: 0 | Y553: 0 | Z553: 0 | AA553: 0 | AB553: 0 | AC553: 0 | AD553: 0 | AE553: 0 | AF553: 0 | AG553: 0 | AH553: 0 | AI553: 0 | AJ553: 0 | AK553: 0 | AL553: 0 | AM553: 0 | AN553: 0 | AO553: 0 | AP553: 0 | AQ553: 0 | AR553: 0 | AS553: 0 | AT553: 0 | AU553: 0 | AV553: 0 | AW553: 0 | AX553: 0 | AY553: 0 | AZ553: 0 | BA553: 0 | BB553: 0 | BC553: 0 | BD553: 0 | BE553: 0 | BF553: 0 | BG553: 0 | BH553: 0 | BI553: 0 | BJ553: 0 | BK553: 0 | BL553: 0 | BM553: 0 | BN553: 0 | BO553: 0 | BP553: 0 | BQ553: 0 | BR553: 0 | BS553: 0 | BT553: 0 | BU553: 0 | BV553: 0 | BW553: 0 | BX553: 0 | BY553: 0 | BZ553: 0 | CA553: 0 | CB553: 0 | CC553: 0 | CD553: 0 | CE553: 0 | CF553: 0 | CG553: 0 | CH553: 0 | CI553: 0 | CJ553: 0 | CK553: 0 | CL553: 0 | CM553: 0 | CN553: 0 | CO553: 0 | CP553: 0 | CQ553: 0 | CR553: 0 | CS553: 0 | CT553: 0 | CU553: 0 | CV553: 0 | CW553: 0 | CX553: 0 | CY553: 0 | CZ553: 0 | DA553: 0 | DB553: 0 | DC553: 0 | DD553: 0 | DE553: 0 | DF553: 0 | DG553: 0 | DH553: 0 | DI553: 0 | DJ553: 0 | DK553: 0 | DL553: 0 | DM553: 0 | DN553: 0 | DO553: 0 | DP553: 0 | DQ553: 0 | DR553: 0 | DS553: 0 | DT553: 0 | DU553: 0 | DV553: 0 | DW553: 0 | DX553: 0 | DY553: 0 | DZ553: 0 | EA553: 0 | EB553: 0 | EC553: 0 | ED553: 0 | EE553: 0 | EF553: 0 | EG553: 0 | EH553: 0 | EI553: 0 | EJ553: 0 | EK553: 0 | EL553: 0 | EM553: 0 | EN553: 0 | EO553: 0 | EP553: 0 | EQ553: 0 | ER553: 0 | ES553: 0 | ET553: 0

Sheet 2025 vs 2026 Analysis
A1: Sub-Dept Code | B1: Sub-Department | C1: Product Code | D1: Product Description | E1: 2025 Sales (Wk1-19) | F1: 2026 Sales (Wk1-19) | G1: Sales Change | H1: Sales % Change | I1: 2025 Qty (Wk1-19) | J1: 2026 Qty (Wk1-19) | K1: Qty Change | L1: Qty % Change | M1: Trend Indicator | O1: Summary Metric | P1: Value
A2: =Data!A3 -> 201 | B2: =Data!B3 -> BUTCHERY | C2: =Data!C3 -> 11141 | D2: =Data!D3 | E2: =SUM(Data!I3,Data!K3,Data!M3,Data!O3,Data!Q3,Data!S3,Data!U3,Data!W3,Data!Y3,Data!AA3,Data!AC3,Data!AE3,Data!AG3,Data!AI3,Data!AK3,Data!AM3,Data!AO3,Data!AQ3,Data!AS3) -> 0 | F2: =SUM(Data!DI3,Data!DK3,Data!DM3,Data!DO3,Data!DQ3,Data!DS3,Data!DU3,Data!DW3,Data!DY3,Data!EA3,Data!EC3,Data!EE3,Data!EG3,Data!EI3,Data!EK3,Data!EM3,Data!EO3,Data!EQ3,Data!ES3) -> 0 | G2: =F2-E2 -> 0 | H2: =IF(E2=0,IF(F2>0,"New",0),(F2-E2)/E2) -> 0 | I2: =SUM(Data!J3,Data!L3,Data!N3,Data!P3,Data!R3,Data!T3,Data!V3,Data!X3,Data!Z3,Data!AB3,Data!AD3,Data!AF3,Data!AH3,Data!AJ3,Data!AL3,Data!AN3,Data!AP3,Data!AR3,Data!AT3) -> 0 | J2: =SUM(Data!DJ3,Data!DL3,Data!DN3,Data!DP3,Data!DR3,Data!DT3,Data!DV3,Data!DX3,Data!DZ3,Data!EB3,Data!ED3,Data!EF3,Data!EH3,Data!EJ3,Data!EL3,Data!EN3,Data!EP3,Data!ER3,Data!ET3) -> 0 | K2: =J2-I2 -> 0 | L2: =IF(I2=0,IF(J2>0,"New",0),(J2-I2)/I2) -> 0 | M2: =IF(F2=0,"No 2026 Sales",IF(E2=0,"New Product",IF(AND(ISNUMBER(H2),H2>0.1),"↑ Strong Growth",IF(AND(ISNUMBER(H2),H2>0),"↗ Growth",IF(AND(ISNUMBER(H2),H2<-0.1),"↓ Strong Decline",IF(AND(ISNUMBER(H2),H2<0),"↘ Decline","→ Stable")))))) -> No 2026 Sales | O2: Products with 2026 Sales | P2: =COUNTIF(F2:F554,">0") -> 155
A3: =Data!A4 -> 201 | B3: =Data!B4 -> BUTCHERY | C3: =Data!C4 -> 11385 | D3: =Data!D4 | E3: =SUM(Data!I4,Data!K4,Data!M4,Data!O4,Data!Q4,Data!S4,Data!U4,Data!W4,Data!Y4,Data!AA4,Data!AC4,Data!AE4,Data!AG4,Data!AI4,Data!AK4,Data!AM4,Data!AO4,Data!AQ4,Data!AS4) -> 0 | F3: =SUM(Data!DI4,Data!DK4,Data!DM4,Data!DO4,Data!DQ4,Data!DS4,Data!DU4,Data!DW4,Data!DY4,Data!EA4,Data!EC4,Data!EE4,Data!EG4,Data!EI4,Data!EK4,Data!EM4,Data!EO4,Data!EQ4,Data!ES4) -> 0 | G3: =F3-E3 -> 0 | H3: =IF(E3=0,IF(F3>0,"New",0),(F3-E3)/E3) -> 0 | I3: =SUM(Data!J4,Data!L4,Data!N4,Data!P4,Data!R4,Data!T4,Data!V4,Data!X4,Data!Z4,Data!AB4,Data!AD4,Data!AF4,Data!AH4,Data!AJ4,Data!AL4,Data!AN4,Data!AP4,Data!AR4,Data!AT4) -> 0 | J3: =SUM(Data!DJ4,Data!DL4,Data!DN4,Data!DP4,Data!DR4,Data!DT4,Data!DV4,Data!DX4,Data!DZ4,Data!EB4,Data!ED4,Data!EF4,Data!EH4,Data!EJ4,Data!EL4,Data!EN4,Data!EP4,Data!ER4,Data!ET4) -> 0 | K3: =J3-I3 -> 0 | L3: =IF(I3=0,IF(J3>0,"New",0),(J3-I3)/I3) -> 0 | M3: =IF(F3=0,"No 2026 Sales",IF(E3=0,"New Product",IF(AND(ISNUMBER(H3),H3>0.1),"↑ Strong Growth",IF(AND(ISNUMBER(H3),H3>0),"↗ Growth",IF(AND(ISNUMBER(H3),H3<-0.1),"↓ Strong Decline",IF(AND(ISNUMBER(H3),H3<0),"↘ Decline","→ Stable")))))) -> No 2026 Sales | O3: ↳ with Sales Growth | P3: =COUNTIFS(F2:F554,">0",H2:H554,">0") -> 58
A4: =Data!A5 -> 201 | B4: =Data!B5 -> BUTCHERY | C4: =Data!C5 -> 11388 | D4: =Data!D5 | E4: =SUM(Data!I5,Data!K5,Data!M5,Data!O5,Data!Q5,Data!S5,Data!U5,Data!W5,Data!Y5,Data!AA5,Data!AC5,Data!AE5,Data!AG5,Data!AI5,Data!AK5,Data!AM5,Data!AO5,Data!AQ5,Data!AS5) -> 0 | F4: =SUM(Data!DI5,Data!DK5,Data!DM5,Data!DO5,Data!DQ5,Data!DS5,Data!DU5,Data!DW5,Data!DY5,Data!EA5,Data!EC5,Data!EE5,Data!EG5,Data!EI5,Data!EK5,Data!EM5,Data!EO5,Data!EQ5,Data!ES5) -> 0 | G4: =F4-E4 -> 0 | H4: =IF(E4=0,IF(F4>0,"New",0),(F4-E4)/E4) -> 0 | I4: =SUM(Data!J5,Data!L5,Data!N5,Data!P5,Data!R5,Data!T5,Data!V5,Data!X5,Data!Z5,Data!AB5,Data!AD5,Data!AF5,Data!AH5,Data!AJ5,Data!AL5,Data!AN5,Data!AP5,Data!AR5,Data!AT5) -> 0 | J4: =SUM(Data!DJ5,Data!DL5,Data!DN5,Data!DP5,Data!DR5,Data!DT5,Data!DV5,Data!DX5,Data!DZ5,Data!EB5,Data!ED5,Data!EF5,Data!EH5,Data!EJ5,Data!EL5,Data!EN5,Data!EP5,Data!ER5,Data!ET5) -> 0 | K4: =J4-I4 -> 0 | L4: =IF(I4=0,IF(J4>0,"New",0),(J4-I4)/I4) -> 0 | M4: =IF(F4=0,"No 2026 Sales",IF(E4=0,"New Product",IF(AND(ISNUMBER(H4),H4>0.1),"↑ Strong Growth",IF(AND(ISNUMBER(H4),H4>0),"↗ Growth",IF(AND(ISNUMBER(H4),H4<-0.1),"↓ Strong Decline",IF(AND(ISNUMBER(H4),H4<0),"↘ Decline","→ Stable")))))) -> No 2026 Sales | O4: ↳ with Sales Decline | P4: =COUNTIFS(F2:F554,">0",H2:H554,"<0") -> 44
A5: =Data!A6 -> 201 | B5: =Data!B6 -> BUTCHERY | C5: =Data!C6 -> 12151 | D5: =Data!D6 | E5: =SUM(Data!I6,Data!K6,Data!M6,Data!O6,Data!Q6,Data!S6,Data!U6,Data!W6,Data!Y6,Data!AA6,Data!AC6,Data!AE6,Data!AG6,Data!AI6,Data!AK6,Data!AM6,Data!AO6,Data!AQ6,Data!AS6) -> 0 | F5: =SUM(Data!DI6,Data!DK6,Data!DM6,Data!DO6,Data!DQ6,Data!DS6,Data!DU6,Data!DW6,Data!DY6,Data!EA6,Data!EC6,Data!EE6,Data!EG6,Data!EI6,Data!EK6,Data!EM6,Data!EO6,Data!EQ6,Data!ES6) -> 0 | G5: =F5-E5 -> 0 | H5: =IF(E5=0,IF(F5>0,"New",0),(F5-E5)/E5) -> 0 | I5: =SUM(Data!J6,Data!L6,Data!N6,Data!P6,Data!R6,Data!T6,Data!V6,Data!X6,Data!Z6,Data!AB6,Data!AD6,Data!AF6,Data!AH6,Data!AJ6,Data!AL6,Data!AN6,Data!AP6,Data!AR6,Data!AT6) -> 0 | J5: =SUM(Data!DJ6,Data!DL6,Data!DN6,Data!DP6,Data!DR6,Data!DT6,Data!DV6,Data!DX6,Data!DZ6,Data!EB6,Data!ED6,Data!EF6,Data!EH6,Data!EJ6,Data!EL6,Data!EN6,Data!EP6,Data!ER6,Data!ET6) -> 0 | K5: =J5-I5 -> 0 | L5: =IF(I5=0,IF(J5>0,"New",0),(J5-I5)/I5) -> 0 | M5: =IF(F5=0,"No 2026 Sales",IF(E5=0,"New Product",IF(AND(ISNUMBER(H5),H5>0.1),"↑ Strong Growth",IF(AND(ISNUMBER(H5),H5>0),"↗ Growth",IF(AND(ISNUMBER(H5),H5<-0.1),"↓ Strong Decline",IF(AND(ISNUMBER(H5),H5<0),"↘ Decline","→ Stable")))))) -> No 2026 Sales | O5: ↳ New in 2026 | P5: =COUNTIF(H2:H554,"New") -> 53
A6: =Data!A7 -> 201 | B6: =Data!B7 -> BUTCHERY | C6: =Data!C7 -> 12194 | D6: =Data!D7 | E6: =SUM(Data!I7,Data!K7,Data!M7,Data!O7,Data!Q7,Data!S7,Data!U7,Data!W7,Data!Y7,Data!AA7,Data!AC7,Data!AE7,Data!AG7,Data!AI7,Data!AK7,Data!AM7,Data!AO7,Data!AQ7,Data!AS7) -> 0 | F6: =SUM(Data!DI7,Data!DK7,Data!DM7,Data!DO7,Data!DQ7,Data!DS7,Data!DU7,Data!DW7,Data!DY7,Data!EA7,Data!EC7,Data!EE7,Data!EG7,Data!EI7,Data!EK7,Data!EM7,Data!EO7,Data!EQ7,Data!ES7) -> 0 | G6: =F6-E6 -> 0 | H6: =IF(E6=0,IF(F6>0,"New",0),(F6-E6)/E6) -> 0 | I6: =SUM(Data!J7,Data!L7,Data!N7,Data!P7,Data!R7,Data!T7,Data!V7,Data!X7,Data!Z7,Data!AB7,Data!AD7,Data!AF7,Data!AH7,Data!AJ7,Data!AL7,Data!AN7,Data!AP7,Data!AR7,Data!AT7) -> 0 | J6: =SUM(Data!DJ7,Data!DL7,Data!DN7,Data!DP7,Data!DR7,Data!DT7,Data!DV7,Data!DX7,Data!DZ7,Data!EB7,Data!ED7,Data!EF7,Data!EH7,Data!EJ7,Data!EL7,Data!EN7,Data!EP7,Data!ER7,Data!ET7) -> 0 | K6: =J6-I6 -> 0 | L6: =IF(I6=0,IF(J6>0,"New",0),(J6-I6)/I6) -> 0 | M6: =IF(F6=0,"No 2026 Sales",IF(E6=0,"New Product",IF(AND(ISNUMBER(H6),H6>0.1),"↑ Strong Growth",IF(AND(ISNUMBER(H6),H6>0),"↗ Growth",IF(AND(ISNUMBER(H6),H6<-0.1),"↓ Strong Decline",IF(AND(ISNUMBER(H6),H6<0),"↘ Decline","→ Stable")))))) -> No 2026 Sales
A7: =Data!A8 -> 201 | B7: =Data!B8 -> BUTCHERY | C7: =Data!C8 -> 12314 | D7: =Data!D8 | E7: =SUM(Data!I8,Data!K8,Data!M8,Data!O8,Data!Q8,Data!S8,Data!U8,Data!W8,Data!Y8,Data!AA8,Data!AC8,Data!AE8,Data!AG8,Data!AI8,Data!AK8,Data!AM8,Data!AO8,Data!AQ8,Data!AS8) -> 0 | F7: =SUM(Data!DI8,Data!DK8,Data!DM8,Data!DO8,Data!DQ8,Data!DS8,Data!DU8,Data!DW8,Data!DY8,Data!EA8,Data!EC8,Data!EE8,Data!EG8,Data!EI8,Data!EK8,Data!EM8,Data!EO8,Data!EQ8,Data!ES8) -> 0 | G7: =F7-E7 -> 0 | H7: =IF(E7=0,IF(F7>0,"New",0),(F7-E7)/E7) -> 0 | I7: =SUM(Data!J8,Data!L8,Data!N8,Data!P8,Data!R8,Data!T8,Data!V8,Data!X8,Data!Z8,Data!AB8,Data!AD8,Data!AF8,Data!AH8,Data!AJ8,Data!AL8,Data!AN8,Data!AP8,Data!AR8,Data!AT8) -> 0 | J7: =SUM(Data!DJ8,Data!DL8,Data!DN8,Data!DP8,Data!DR8,Data!DT8,Data!DV8,Data!DX8,Data!DZ8,Data!EB8,Data!ED8,Data!EF8,Data!EH8,Data!EJ8,Data!EL8,Data!EN8,Data!EP8,Data!ER8,Data!ET8) -> 0 | K7: =J7-I7 -> 0 | L7: =IF(I7=0,IF(J7>0,"New",0),(J7-I7)/I7) -> 0 | M7: =IF(F7=0,"No 2026 Sales",IF(E7=0,"New Product",IF(AND(ISNUMBER(H7),H7>0.1),"↑ Strong Growth",IF(AND(ISNUMBER(H7),H7>0),"↗ Growth",IF(AND(ISNUMBER(H7),H7<-0.1),"↓ Strong Decline",IF(AND(ISNUMBER(H7),H7<0),"↘ Decline","→ Stable")))))) -> No 2026 Sales | O7: 2025 Sales (Wk1-19, products w/ 2026 sales) | P7: =SUMIF(F2:F554,">0",E2:E554) -> 1429049.1
A8: =Data!A9 -> 201 | B8: =Data!B9 -> BUTCHERY | C8: =Data!C9 -> 15219 | D8: =Data!D9 | E8: =SUM(Data!I9,Data!K9,Data!M9,Data!O9,Data!Q9,Data!S9,Data!U9,Data!W9,Data!Y9,Data!AA9,Data!AC9,Data!AE9,Data!AG9,Data!AI9,Data!AK9,Data!AM9,Data!AO9,Data!AQ9,Data!AS9) -> 0 | F8: =SUM(Data!DI9,Data!DK9,Data!DM9,Data!DO9,Data!DQ9,Data!DS9,Data!DU9,Data!DW9,Data!DY9,Data!EA9,Data!EC9,Data!EE9,Data!EG9,Data!EI9,Data!EK9,Data!EM9,Data!EO9,Data!EQ9,Data!ES9) -> 0 | G8: =F8-E8 -> 0 | H8: =IF(E8=0,IF(F8>0,"New",0),(F8-E8)/E8) -> 0 | I8: =SUM(Data!J9,Data!L9,Data!N9,Data!P9,Data!R9,Data!T9,Data!V9,Data!X9,Data!Z9,Data!AB9,Data!AD9,Data!AF9,Data!AH9,Data!AJ9,Data!AL9,Data!AN9,Data!AP9,Data!AR9,Data!AT9) -> 0 | J8: =SUM(Data!DJ9,Data!DL9,Data!DN9,Data!DP9,Data!DR9,Data!DT9,Data!DV9,Data!DX9,Data!DZ9,Data!EB9,Data!ED9,Data!EF9,Data!EH9,Data!EJ9,Data!EL9,Data!EN9,Data!EP9,Data!ER9,Data!ET9) -> 0 | K8: =J8-I8 -> 0 | L8: =IF(I8=0,IF(J8>0,"New",0),(J8-I8)/I8) -> 0 | M8: =IF(F8=0,"No 2026 Sales",IF(E8=0,"New Product",IF(AND(ISNUMBER(H8),H8>0.1),"↑ Strong Growth",IF(AND(ISNUMBER(H8),H8>0),"↗ Growth",IF(AND(ISNUMBER(H8),H8<-0.1),"↓ Strong Decline",IF(AND(ISNUMBER(H8),H8<0),"↘ Decline","→ Stable")))))) -> No 2026 Sales | O8: 2026 Sales (Wk1-19, all) | P8: =SUM(F2:F554) -> 2135325.6
A9: =Data!A10 -> 201 | B9: =Data!B10 -> BUTCHERY | C9: =Data!C10 -> 15227 | D9: =Data!D10 | E9: =SUM(Data!I10,Data!K10,Data!M10,Data!O10,Data!Q10,Data!S10,Data!U10,Data!W10,Data!Y10,Data!AA10,Data!AC10,Data!AE10,Data!AG10,Data!AI10,Data!AK10,Data!AM10,Data!AO10,Data!AQ10,Data!AS10) -> 0 | F9: =SUM(Data!DI10,Data!DK10,Data!DM10,Data!DO10,Data!DQ10,Data!DS10,Data!DU10,Data!DW10,Data!DY10,Data!EA10,Data!EC10,Data!EE10,Data!EG10,Data!EI10,Data!EK10,Data!EM10,Data!EO10,Data!EQ10,Data!ES10) -> 0 | G9: =F9-E9 -> 0 | H9: =IF(E9=0,IF(F9>0,"New",0),(F9-E9)/E9) -> 0 | I9: =SUM(Data!J10,Data!L10,Data!N10,Data!P10,Data!R10,Data!T10,Data!V10,Data!X10,Data!Z10,Data!AB10,Data!AD10,Data!AF10,Data!AH10,Data!AJ10,Data!AL10,Data!AN10,Data!AP10,Data!AR10,Data!AT10) -> 0 | J9: =SUM(Data!DJ10,Data!DL10,Data!DN10,Data!DP10,Data!DR10,Data!DT10,Data!DV10,Data!DX10,Data!DZ10,Data!EB10,Data!ED10,Data!EF10,Data!EH10,Data!EJ10,Data!EL10,Data!EN10,Data!EP10,Data!ER10,Data!ET10) -> 0 | K9: =J9-I9 -> 0 | L9: =IF(I9=0,IF(J9>0,"New",0),(J9-I9)/I9) -> 0 | M9: =IF(F9=0,"No 2026 Sales",IF(E9=0,"New Product",IF(AND(ISNUMBER(H9),H9>0.1),"↑ Strong Growth",IF(AND(ISNUMBER(H9),H9>0),"↗ Growth",IF(AND(ISNUMBER(H9),H9<-0.1),"↓ Strong Decline",IF(AND(ISNUMBER(H9),H9<0),"↘ Decline","→ Stable")))))) -> No 2026 Sales | O9: Sales Change | P9: =P8-P7 -> 706276.55
A10: =Data!A11 -> 201 | B10: =Data!B11 -> BUTCHERY | C10: =Data!C11 -> 34176 | D10: =Data!D11 | E10: =SUM(Data!I11,Data!K11,Data!M11,Data!O11,Data!Q11,Data!S11,Data!U11,Data!W11,Data!Y11,Data!AA11,Data!AC11,Data!AE11,Data!AG11,Data!AI11,Data!AK11,Data!AM11,Data!AO11,Data!AQ11,Data!AS11) -> 0 | F10: =SUM(Data!DI11,Data!DK11,Data!DM11,Data!DO11,Data!DQ11,Data!DS11,Data!DU11,Data!DW11,Data!DY11,Data!EA11,Data!EC11,Data!EE11,Data!EG11,Data!EI11,Data!EK11,Data!EM11,Data!EO11,Data!EQ11,Data!ES11) -> 0 | G10: =F10-E10 -> 0 | H10: =IF(E10=0,IF(F10>0,"New",0),(F10-E10)/E10) -> 0 | I10: =SUM(Data!J11,Data!L11,Data!N11,Data!P11,Data!R11,Data!T11,Data!V11,Data!X11,Data!Z11,Data!AB11,Data!AD11,Data!AF11,Data!AH11,Data!AJ11,Data!AL11,Data!AN11,Data!AP11,Data!AR11,Data!AT11) -> 0 | J10: =SUM(Data!DJ11,Data!DL11,Data!DN11,Data!DP11,Data!DR11,Data!DT11,Data!DV11,Data!DX11,Data!DZ11,Data!EB11,Data!ED11,Data!EF11,Data!EH11,Data!EJ11,Data!EL11,Data!EN11,Data!EP11,Data!ER11,Data!ET11) -> 0 | K10: =J10-I10 -> 0 | L10: =IF(I10=0,IF(J10>0,"New",0),(J10-I10)/I10) -> 0 | M10: =IF(F10=0,"No 2026 Sales",IF(E10=0,"New Product",IF(AND(ISNUMBER(H10),H10>0.1),"↑ Strong Growth",IF(AND(ISNUMBER(H10),H10>0),"↗ Growth",IF(AND(ISNUMBER(H10),H10<-0.1),"↓ Strong Decline",IF(AND(ISNUMBER(H10),H10<0),"↘ Decline","→ Stable")))))) -> No 2026 Sales | O10: Sales % Change | P10: =IF(P7=0,0,P9/P7) -> 0.49422834
A11: =Data!A12 -> 201 | B11: =Data!B12 -> BUTCHERY | C11: =Data!C12 -> 34233 | D11: =Data!D12 | E11: =SUM(Data!I12,Data!K12,Data!M12,Data!O12,Data!Q12,Data!S12,Data!U12,Data!W12,Data!Y12,Data!AA12,Data!AC12,Data!AE12,Data!AG12,Data!AI12,Data!AK12,Data!AM12,Data!AO12,Data!AQ12,Data!AS12) -> 0 | F11: =SUM(Data!DI12,Data!DK12,Data!DM12,Data!DO12,Data!DQ12,Data!DS12,Data!DU12,Data!DW12,Data!DY12,Data!EA12,Data!EC12,Data!EE12,Data!EG12,Data!EI12,Data!EK12,Data!EM12,Data!EO12,Data!EQ12,Data!ES12) -> 0 | G11: =F11-E11 -> 0 | H11: =IF(E11=0,IF(F11>0,"New",0),(F11-E11)/E11) -> 0 | I11: =SUM(Data!J12,Data!L12,Data!N12,Data!P12,Data!R12,Data!T12,Data!V12,Data!X12,Data!Z12,Data!AB12,Data!AD12,Data!AF12,Data!AH12,Data!AJ12,Data!AL12,Data!AN12,Data!AP12,Data!AR12,Data!AT12) -> 0 | J11: =SUM(Data!DJ12,Data!DL12,Data!DN12,Data!DP12,Data!DR12,Data!DT12,Data!DV12,Data!DX12,Data!DZ12,Data!EB12,Data!ED12,Data!EF12,Data!EH12,Data!EJ12,Data!EL12,Data!EN12,Data!EP12,Data!ER12,Data!ET12) -> 0 | K11: =J11-I11 -> 0 | L11: =IF(I11=0,IF(J11>0,"New",0),(J11-I11)/I11) -> 0 | M11: =IF(F11=0,"No 2026 Sales",IF(E11=0,"New Product",IF(AND(ISNUMBER(H11),H11>0.1),"↑ Strong Growth",IF(AND(ISNUMBER(H11),H11>0),"↗ Growth",IF(AND(ISNUMBER(H11),H11<-0.1),"↓ Strong Decline",IF(AND(ISNUMBER(H11),H11<0),"↘ Decline","→ Stable")))))) -> No 2026 Sales
A12: =Data!A13 -> 201 | B12: =Data!B13 -> BUTCHERY | C12: =Data!C13 -> 34234 | D12: =Data!D13 | E12: =SUM(Data!I13,Data!K13,Data!M13,Data!O13,Data!Q13,Data!S13,Data!U13,Data!W13,Data!Y13,Data!AA13,Data!AC13,Data!AE13,Data!AG13,Data!AI13,Data!AK13,Data!AM13,Data!AO13,Data!AQ13,Data!AS13) -> 0 | F12: =SUM(Data!DI13,Data!DK13,Data!DM13,Data!DO13,Data!DQ13,Data!DS13,Data!DU13,Data!DW13,Data!DY13,Data!EA13,Data!EC13,Data!EE13,Data!EG13,Data!EI13,Data!EK13,Data!EM13,Data!EO13,Data!EQ13,Data!ES13) -> 0 | G12: =F12-E12 -> 0 | H12: =IF(E12=0,IF(F12>0,"New",0),(F12-E12)/E12) -> 0 | I12: =SUM(Data!J13,Data!L13,Data!N13,Data!P13,Data!R13,Data!T13,Data!V13,Data!X13,Data!Z13,Data!AB13,Data!AD13,Data!AF13,Data!AH13,Data!AJ13,Data!AL13,Data!AN13,Data!AP13,Data!AR13,Data!AT13) -> 0 | J12: =SUM(Data!DJ13,Data!DL13,Data!DN13,Data!DP13,Data!DR13,Data!DT13,Data!DV13,Data!DX13,Data!DZ13,Data!EB13,Data!ED13,Data!EF13,Data!EH13,Data!EJ13,Data!EL13,Data!EN13,Data!EP13,Data!ER13,Data!ET13) -> 0 | K12: =J12-I12 -> 0 | L12: =IF(I12=0,IF(J12>0,"New",0),(J12-I12)/I12) -> 0 | M12: =IF(F12=0,"No 2026 Sales",IF(E12=0,"New Product",IF(AND(ISNUMBER(H12),H12>0.1),"↑ Strong Growth",IF(AND(ISNUMBER(H12),H12>0),"↗ Growth",IF(AND(ISNUMBER(H12),H12<-0.1),"↓ Strong Decline",IF(AND(ISNUMBER(H12),H12<0),"↘ Decline","→ Stable")))))) -> No 2026 Sales | O12: 2025 Qty (Wk1-19, products w/ 2026 sales) | P12: =SUMIF(J2:J554,">0",I2:I554) -> 20173.462
A13: =Data!A14 -> 201 | B13: =Data!B14 -> BUTCHERY | C13: =Data!C14 -> 34306 | D13: =Data!D14 | E13: =SUM(Data!I14,Data!K14,Data!M14,Data!O14,Data!Q14,Data!S14,Data!U14,Data!W14,Data!Y14,Data!AA14,Data!AC14,Data!AE14,Data!AG14,Data!AI14,Data!AK14,Data!AM14,Data!AO14,Data!AQ14,Data!AS14) -> 0 | F13: =SUM(Data!DI14,Data!DK14,Data!DM14,Data!DO14,Data!DQ14,Data!DS14,Data!DU14,Data!DW14,Data!DY14,Data!EA14,Data!EC14,Data!EE14,Data!EG14,Data!EI14,Data!EK14,Data!EM14,Data!EO14,Data!EQ14,Data!ES14) -> 0 | G13: =F13-E13 -> 0 | H13: =IF(E13=0,IF(F13>0,"New",0),(F13-E13)/E13) -> 0 | I13: =SUM(Data!J14,Data!L14,Data!N14,Data!P14,Data!R14,Data!T14,Data!V14,Data!X14,Data!Z14,Data!AB14,Data!AD14,Data!AF14,Data!AH14,Data!AJ14,Data!AL14,Data!AN14,Data!AP14,Data!AR14,Data!AT14) -> 0 | J13: =SUM(Data!DJ14,Data!DL14,Data!DN14,Data!DP14,Data!DR14,Data!DT14,Data!DV14,Data!DX14,Data!DZ14,Data!EB14,Data!ED14,Data!EF14,Data!EH14,Data!EJ14,Data!EL14,Data!EN14,Data!EP14,Data!ER14,Data!ET14) -> 0 | K13: =J13-I13 -> 0 | L13: =IF(I13=0,IF(J13>0,"New",0),(J13-I13)/I13) -> 0 | M13: =IF(F13=0,"No 2026 Sales",IF(E13=0,"New Product",IF(AND(ISNUMBER(H13),H13>0.1),"↑ Strong Growth",IF(AND(ISNUMBER(H13),H13>0),"↗ Growth",IF(AND(ISNUMBER(H13),H13<-0.1),"↓ Strong Decline",IF(AND(ISNUMBER(H13),H13<0),"↘ Decline","→ Stable")))))) -> No 2026 Sales | O13: 2026 Qty (Wk1-19, all) | P13: =SUM(J2:J554) -> 24454.402
A14: =Data!A15 -> 201 | B14: =Data!B15 -> BUTCHERY | C14: =Data!C15 -> 41246 | D14: =Data!D15 | E14: =SUM(Data!I15,Data!K15,Data!M15,Data!O15,Data!Q15,Data!S15,Data!U15,Data!W15,Data!Y15,Data!AA15,Data!AC15,Data!AE15,Data!AG15,Data!AI15,Data!AK15,Data!AM15,Data!AO15,Data!AQ15,Data!AS15) -> 0 | F14: =SUM(Data!DI15,Data!DK15,Data!DM15,Data!DO15,Data!DQ15,Data!DS15,Data!DU15,Data!DW15,Data!DY15,Data!EA15,Data!EC15,Data!EE15,Data!EG15,Data!EI15,Data!EK15,Data!EM15,Data!EO15,Data!EQ15,Data!ES15) -> 0 | G14: =F14-E14 -> 0 | H14: =IF(E14=0,IF(F14>0,"New",0),(F14-E14)/E14) -> 0 | I14: =SUM(Data!J15,Data!L15,Data!N15,Data!P15,Data!R15,Data!T15,Data!V15,Data!X15,Data!Z15,Data!AB15,Data!AD15,Data!AF15,Data!AH15,Data!AJ15,Data!AL15,Data!AN15,Data!AP15,Data!AR15,Data!AT15) -> 0 | J14: =SUM(Data!DJ15,Data!DL15,Data!DN15,Data!DP15,Data!DR15,Data!DT15,Data!DV15,Data!DX15,Data!DZ15,Data!EB15,Data!ED15,Data!EF15,Data!EH15,Data!EJ15,Data!EL15,Data!EN15,Data!EP15,Data!ER15,Data!ET15) -> 0 | K14: =J14-I14 -> 0 | L14: =IF(I14=0,IF(J14>0,"New",0),(J14-I14)/I14) -> 0 | M14: =IF(F14=0,"No 2026 Sales",IF(E14=0,"New Product",IF(AND(ISNUMBER(H14),H14>0.1),"↑ Strong Growth",IF(AND(ISNUMBER(H14),H14>0),"↗ Growth",IF(AND(ISNUMBER(H14),H14<-0.1),"↓ Strong Decline",IF(AND(ISNUMBER(H14),H14<0),"↘ Decline","→ Stable")))))) -> No 2026 Sales | O14: Qty Change | P14: =P13-P12 -> 4280.94
A15: =Data!A16 -> 201 | B15: =Data!B16 -> BUTCHERY | C15: =Data!C16 -> 49848 | D15: =Data!D16 | E15: =SUM(Data!I16,Data!K16,Data!M16,Data!O16,Data!Q16,Data!S16,Data!U16,Data!W16,Data!Y16,Data!AA16,Data!AC16,Data!AE16,Data!AG16,Data!AI16,Data!AK16,Data!AM16,Data!AO16,Data!AQ16,Data!AS16) -> 0 | F15: =SUM(Data!DI16,Data!DK16,Data!DM16,Data!DO16,Data!DQ16,Data!DS16,Data!DU16,Data!DW16,Data!DY16,Data!EA16,Data!EC16,Data!EE16,Data!EG16,Data!EI16,Data!EK16,Data!EM16,Data!EO16,Data!EQ16,Data!ES16) -> 0 | G15: =F15-E15 -> 0 | H15: =IF(E15=0,IF(F15>0,"New",0),(F15-E15)/E15) -> 0 | I15: =SUM(Data!J16,Data!L16,Data!N16,Data!P16,Data!R16,Data!T16,Data!V16,Data!X16,Data!Z16,Data!AB16,Data!AD16,Data!AF16,Data!AH16,Data!AJ16,Data!AL16,Data!AN16,Data!AP16,Data!AR16,Data!AT16) -> 0 | J15: =SUM(Data!DJ16,Data!DL16,Data!DN16,Data!DP16,Data!DR16,Data!DT16,Data!DV16,Data!DX16,Data!DZ16,Data!EB16,Data!ED16,Data!EF16,Data!EH16,Data!EJ16,Data!EL16,Data!EN16,Data!EP16,Data!ER16,Data!ET16) -> 0 | K15: =J15-I15 -> 0 | L15: =IF(I15=0,IF(J15>0,"New",0),(J15-I15)/I15) -> 0 | M15: =IF(F15=0,"No 2026 Sales",IF(E15=0,"New Product",IF(AND(ISNUMBER(H15),H15>0.1),"↑ Strong Growth",IF(AND(ISNUMBER(H15),H15>0),"↗ Growth",IF(AND(ISNUMBER(H15),H15<-0.1),"↓ Strong Decline",IF(AND(ISNUMBER(H15),H15<0),"↘ Decline","→ Stable")))))) -> No 2026 Sales | O15: Qty % Change | P15: =IF(P12=0,0,P14/P12) -> 0.21220651
A16: =Data!A17 -> 201 | B16: =Data!B17 -> BUTCHERY | C16: =Data!C17 -> 52212 | D16: =Data!D17 | E16: =SUM(Data!I17,Data!K17,Data!M17,Data!O17,Data!Q17,Data!S17,Data!U17,Data!W17,Data!Y17,Data!AA17,Data!AC17,Data!AE17,Data!AG17,Data!AI17,Data!AK17,Data!AM17,Data!AO17,Data!AQ17,Data!AS17) -> 0 | F16: =SUM(Data!DI17,Data!DK17,Data!DM17,Data!DO17,Data!DQ17,Data!DS17,Data!DU17,Data!DW17,Data!DY17,Data!EA17,Data!EC17,Data!EE17,Data!EG17,Data!EI17,Data!EK17,Data!EM17,Data!EO17,Data!EQ17,Data!ES17) -> 0 | G16: =F16-E16 -> 0 | H16: =IF(E16=0,IF(F16>0,"New",0),(F16-E16)/E16) -> 0 | I16: =SUM(Data!J17,Data!L17,Data!N17,Data!P17,Data!R17,Data!T17,Data!V17,Data!X17,Data!Z17,Data!AB17,Data!AD17,Data!AF17,Data!AH17,Data!AJ17,Data!AL17,Data!AN17,Data!AP17,Data!AR17,Data!AT17) -> 0 | J16: =SUM(Data!DJ17,Data!DL17,Data!DN17,Data!DP17,Data!DR17,Data!DT17,Data!DV17,Data!DX17,Data!DZ17,Data!EB17,Data!ED17,Data!EF17,Data!EH17,Data!EJ17,Data!EL17,Data!EN17,Data!EP17,Data!ER17,Data!ET17) -> 0 | K16: =J16-I16 -> 0 | L16: =IF(I16=0,IF(J16>0,"New",0),(J16-I16)/I16) -> 0 | M16: =IF(F16=0,"No 2026 Sales",IF(E16=0,"New Product",IF(AND(ISNUMBER(H16),H16>0.1),"↑ Strong Growth",IF(AND(ISNUMBER(H16),H16>0),"↗ Growth",IF(AND(ISNUMBER(H16),H16<-0.1),"↓ Strong Decline",IF(AND(ISNUMBER(H16),H16<0),"↘ Decline","→ Stable")))))) -> No 2026 Sales
A17: =Data!A18 -> 201 | B17: =Data!B18 -> BUTCHERY | C17: =Data!C18 -> 53975 | D17: =Data!D18 | E17: =SUM(Data!I18,Data!K18,Data!M18,Data!O18,Data!Q18,Data!S18,Data!U18,Data!W18,Data!Y18,Data!AA18,Data!AC18,Data!AE18,Data!AG18,Data!AI18,Data!AK18,Data!AM18,Data!AO18,Data!AQ18,Data!AS18) -> 0 | F17: =SUM(Data!DI18,Data!DK18,Data!DM18,Data!DO18,Data!DQ18,Data!DS18,Data!DU18,Data!DW18,Data!DY18,Data!EA18,Data!EC18,Data!EE18,Data!EG18,Data!EI18,Data!EK18,Data!EM18,Data!EO18,Data!EQ18,Data!ES18) -> 0 | G17: =F17-E17 -> 0 | H17: =IF(E17=0,IF(F17>0,"New",0),(F17-E17)/E17) -> 0 | I17: =SUM(Data!J18,Data!L18,Data!N18,Data!P18,Data!R18,Data!T18,Data!V18,Data!X18,Data!Z18,Data!AB18,Data!AD18,Data!AF18,Data!AH18,Data!AJ18,Data!AL18,Data!AN18,Data!AP18,Data!AR18,Data!AT18) -> 0 | J17: =SUM(Data!DJ18,Data!DL18,Data!DN18,Data!DP18,Data!DR18,Data!DT18,Data!DV18,Data!DX18,Data!DZ18,Data!EB18,Data!ED18,Data!EF18,Data!EH18,Data!EJ18,Data!EL18,Data!EN18,Data!EP18,Data!ER18,Data!ET18) -> 0 | K17: =J17-I17 -> 0 | L17: =IF(I17=0,IF(J17>0,"New",0),(J17-I17)/I17) -> 0 | M17: =IF(F17=0,"No 2026 Sales",IF(E17=0,"New Product",IF(AND(ISNUMBER(H17),H17>0.1),"↑ Strong Growth",IF(AND(ISNUMBER(H17),H17>0),"↗ Growth",IF(AND(ISNUMBER(H17),H17<-0.1),"↓ Strong Decline",IF(AND(ISNUMBER(H17),H17<0),"↘ Decline","→ Stable")))))) -> No 2026 Sales | O17: Trend Category | P17: Count
A18: =Data!A19 -> 201 | B18: =Data!B19 -> BUTCHERY | C18: =Data!C19 -> 55974 | D18: =Data!D19 | E18: =SUM(Data!I19,Data!K19,Data!M19,Data!O19,Data!Q19,Data!S19,Data!U19,Data!W19,Data!Y19,Data!AA19,Data!AC19,Data!AE19,Data!AG19,Data!AI19,Data!AK19,Data!AM19,Data!AO19,Data!AQ19,Data!AS19) -> 0 | F18: =SUM(Data!DI19,Data!DK19,Data!DM19,Data!DO19,Data!DQ19,Data!DS19,Data!DU19,Data!DW19,Data!DY19,Data!EA19,Data!EC19,Data!EE19,Data!EG19,Data!EI19,Data!EK19,Data!EM19,Data!EO19,Data!EQ19,Data!ES19) -> 0 | G18: =F18-E18 -> 0 | H18: =IF(E18=0,IF(F18>0,"New",0),(F18-E18)/E18) -> 0 | I18: =SUM(Data!J19,Data!L19,Data!N19,Data!P19,Data!R19,Data!T19,Data!V19,Data!X19,Data!Z19,Data!AB19,Data!AD19,Data!AF19,Data!AH19,Data!AJ19,Data!AL19,Data!AN19,Data!AP19,Data!AR19,Data!AT19) -> 0 | J18: =SUM(Data!DJ19,Data!DL19,Data!DN19,Data!DP19,Data!DR19,Data!DT19,Data!DV19,Data!DX19,Data!DZ19,Data!EB19,Data!ED19,Data!EF19,Data!EH19,Data!EJ19,Data!EL19,Data!EN19,Data!EP19,Data!ER19,Data!ET19) -> 0 | K18: =J18-I18 -> 0 | L18: =IF(I18=0,IF(J18>0,"New",0),(J18-I18)/I18) -> 0 | M18: =IF(F18=0,"No 2026 Sales",IF(E18=0,"New Product",IF(AND(ISNUMBER(H18),H18>0.1),"↑ Strong Growth",IF(AND(ISNUMBER(H18),H18>0),"↗ Growth",IF(AND(ISNUMBER(H18),H18<-0.1),"↓ Strong Decline",IF(AND(ISNUMBER(H18),H18<0),"↘ Decline","→ Stable")))))) -> No 2026 Sales | O18: ↑ Strong Growth (>10%) | P18: =COUNTIF(M2:M554,"↑ Strong Growth") -> 47
A19: =Data!A20 -> 201 | B19: =Data!B20 -> BUTCHERY | C19: =Data!C20 -> 56247 | D19: =Data!D20 | E19: =SUM(Data!I20,Data!K20,Data!M20,Data!O20,Data!Q20,Data!S20,Data!U20,Data!W20,Data!Y20,Data!AA20,Data!AC20,Data!AE20,Data!AG20,Data!AI20,Data!AK20,Data!AM20,Data!AO20,Data!AQ20,Data!AS20) -> 55919.6 | F19: =SUM(Data!DI20,Data!DK20,Data!DM20,Data!DO20,Data!DQ20,Data!DS20,Data!DU20,Data!DW20,Data!DY20,Data!EA20,Data!EC20,Data!EE20,Data!EG20,Data!EI20,Data!EK20,Data!EM20,Data!EO20,Data!EQ20,Data!ES20) -> 6837.8 | G19: =F19-E19 -> -49081.8 | H19: =IF(E19=0,IF(F19>0,"New",0),(F19-E19)/E19) -> -0.87772087 | I19: =SUM(Data!J20,Data!L20,Data!N20,Data!P20,Data!R20,Data!T20,Data!V20,Data!X20,Data!Z20,Data!AB20,Data!AD20,Data!AF20,Data!AH20,Data!AJ20,Data!AL20,Data!AN20,Data!AP20,Data!AR20,Data!AT20) -> 3188 | J19: =SUM(Data!DJ20,Data!DL20,Data!DN20,Data!DP20,Data!DR20,Data!DT20,Data!DV20,Data!DX20,Data!DZ20,Data!EB20,Data!ED20,Data!EF20,Data!EH20,Data!EJ20,Data!EL20,Data!EN20,Data!EP20,Data!ER20,Data!ET20) -> 382 | K19: =J19-I19 -> -2806 | L19: =IF(I19=0,IF(J19>0,"New",0),(J19-I19)/I19) -> -0.88017566 | M19: =IF(F19=0,"No 2026 Sales",IF(E19=0,"New Product",IF(AND(ISNUMBER(H19),H19>0.1),"↑ Strong Growth",IF(AND(ISNUMBER(H19),H19>0),"↗ Growth",IF(AND(ISNUMBER(H19),H19<-0.1),"↓ Strong Decline",IF(AND(ISNUMBER(H19),H19<0),"↘ Decline","→ Stable")))))) -> ↓ Strong Decline | O19: ↗ Growth (0-10%) | P19: =COUNTIF(M2:M554,"↗ Growth") -> 11
A20: =Data!A21 -> 201 | B20: =Data!B21 -> BUTCHERY | C20: =Data!C21 -> 58663 | D20: =Data!D21 | E20: =SUM(Data!I21,Data!K21,Data!M21,Data!O21,Data!Q21,Data!S21,Data!U21,Data!W21,Data!Y21,Data!AA21,Data!AC21,Data!AE21,Data!AG21,Data!AI21,Data!AK21,Data!AM21,Data!AO21,Data!AQ21,Data!AS21) -> 0 | F20: =SUM(Data!DI21,Data!DK21,Data!DM21,Data!DO21,Data!DQ21,Data!DS21,Data!DU21,Data!DW21,Data!DY21,Data!EA21,Data!EC21,Data!EE21,Data!EG21,Data!EI21,Data!EK21,Data!EM21,Data!EO21,Data!EQ21,Data!ES21) -> 0 | G20: =F20-E20 -> 0 | H20: =IF(E20=0,IF(F20>0,"New",0),(F20-E20)/E20) -> 0 | I20: =SUM(Data!J21,Data!L21,Data!N21,Data!P21,Data!R21,Data!T21,Data!V21,Data!X21,Data!Z21,Data!AB21,Data!AD21,Data!AF21,Data!AH21,Data!AJ21,Data!AL21,Data!AN21,Data!AP21,Data!AR21,Data!AT21) -> 0 | J20: =SUM(Data!DJ21,Data!DL21,Data!DN21,Data!DP21,Data!DR21,Data!DT21,Data!DV21,Data!DX21,Data!DZ21,Data!EB21,Data!ED21,Data!EF21,Data!EH21,Data!EJ21,Data!EL21,Data!EN21,Data!EP21,Data!ER21,Data!ET21) -> 0 | K20: =J20-I20 -> 0 | L20: =IF(I20=0,IF(J20>0,"New",0),(J20-I20)/I20) -> 0 | M20: =IF(F20=0,"No 2026 Sales",IF(E20=0,"New Product",IF(AND(ISNUMBER(H20),H20>0.1),"↑ Strong Growth",IF(AND(ISNUMBER(H20),H20>0),"↗ Growth",IF(AND(ISNUMBER(H20),H20<-0.1),"↓ Strong Decline",IF(AND(ISNUMBER(H20),H20<0),"↘ Decline","→ Stable")))))) -> No 2026 Sales | O20: → Stable | P20: =COUNTIF(M2:M554,"→ Stable") -> 0
A21: =Data!A22 -> 201 | B21: =Data!B22 -> BUTCHERY | C21: =Data!C22 -> 61370 | D21: =Data!D22 | E21: =SUM(Data!I22,Data!K22,Data!M22,Data!O22,Data!Q22,Data!S22,Data!U22,Data!W22,Data!Y22,Data!AA22,Data!AC22,Data!AE22,Data!AG22,Data!AI22,Data!AK22,Data!AM22,Data!AO22,Data!AQ22,Data!AS22) -> 0 | F21: =SUM(Data!DI22,Data!DK22,Data!DM22,Data!DO22,Data!DQ22,Data!DS22,Data!DU22,Data!DW22,Data!DY22,Data!EA22,Data!EC22,Data!EE22,Data!EG22,Data!EI22,Data!EK22,Data!EM22,Data!EO22,Data!EQ22,Data!ES22) -> 302.50435 | G21: =F21-E21 -> 302.50435 | H21: =IF(E21=0,IF(F21>0,"New",0),(F21-E21)/E21) -> New | I21: =SUM(Data!J22,Data!L22,Data!N22,Data!P22,Data!R22,Data!T22,Data!V22,Data!X22,Data!Z22,Data!AB22,Data!AD22,Data!AF22,Data!AH22,Data!AJ22,Data!AL22,Data!AN22,Data!AP22,Data!AR22,Data!AT22) -> 0 | J21: =SUM(Data!DJ22,Data!DL22,Data!DN22,Data!DP22,Data!DR22,Data!DT22,Data!DV22,Data!DX22,Data!DZ22,Data!EB22,Data!ED22,Data!EF22,Data!EH22,Data!EJ22,Data!EL22,Data!EN22,Data!EP22,Data!ER22,Data!ET22) -> 12 | K21: =J21-I21 -> 12 | L21: =IF(I21=0,IF(J21>0,"New",0),(J21-I21)/I21) -> New | M21: =IF(F21=0,"No 2026 Sales",IF(E21=0,"New Product",IF(AND(ISNUMBER(H21),H21>0.1),"↑ Strong Growth",IF(AND(ISNUMBER(H21),H21>0),"↗ Growth",IF(AND(ISNUMBER(H21),H21<-0.1),"↓ Strong Decline",IF(AND(ISNUMBER(H21),H21<0),"↘ Decline","→ Stable")))))) -> New Product | O21: ↘ Decline (0 to -10%) | P21: =COUNTIF(M2:M554,"↘ Decline") -> 12
A22: =Data!A23 -> 201 | B22: =Data!B23 -> BUTCHERY | C22: =Data!C23 -> 64127 | D22: =Data!D23 | E22: =SUM(Data!I23,Data!K23,Data!M23,Data!O23,Data!Q23,Data!S23,Data!U23,Data!W23,Data!Y23,Data!AA23,Data!AC23,Data!AE23,Data!AG23,Data!AI23,Data!AK23,Data!AM23,Data!AO23,Data!AQ23,Data!AS23) -> 0 | F22: =SUM(Data!DI23,Data!DK23,Data!DM23,Data!DO23,Data!DQ23,Data!DS23,Data!DU23,Data!DW23,Data!DY23,Data!EA23,Data!EC23,Data!EE23,Data!EG23,Data!EI23,Data!EK23,Data!EM23,Data!EO23,Data!EQ23,Data!ES23) -> 0 | G22: =F22-E22 -> 0 | H22: =IF(E22=0,IF(F22>0,"New",0),(F22-E22)/E22) -> 0 | I22: =SUM(Data!J23,Data!L23,Data!N23,Data!P23,Data!R23,Data!T23,Data!V23,Data!X23,Data!Z23,Data!AB23,Data!AD23,Data!AF23,Data!AH23,Data!AJ23,Data!AL23,Data!AN23,Data!AP23,Data!AR23,Data!AT23) -> 0 | J22: =SUM(Data!DJ23,Data!DL23,Data!DN23,Data!DP23,Data!DR23,Data!DT23,Data!DV23,Data!DX23,Data!DZ23,Data!EB23,Data!ED23,Data!EF23,Data!EH23,Data!EJ23,Data!EL23,Data!EN23,Data!EP23,Data!ER23,Data!ET23) -> 0 | K22: =J22-I22 -> 0 | L22: =IF(I22=0,IF(J22>0,"New",0),(J22-I22)/I22) -> 0 | M22: =IF(F22=0,"No 2026 Sales",IF(E22=0,"New Product",IF(AND(ISNUMBER(H22),H22>0.1),"↑ Strong Growth",IF(AND(ISNUMBER(H22),H22>0),"↗ Growth",IF(AND(ISNUMBER(H22),H22<-0.1),"↓ Strong Decline",IF(AND(ISNUMBER(H22),H22<0),"↘ Decline","→ Stable")))))) -> No 2026 Sales | O22: ↓ Strong Decline (>-10%) | P22: =COUNTIF(M2:M554,"↓ Strong Decline") -> 32
A23: =Data!A24 -> 201 | B23: =Data!B24 -> BUTCHERY | C23: =Data!C24 -> 64128 | D23: =Data!D24 | E23: =SUM(Data!I24,Data!K24,Data!M24,Data!O24,Data!Q24,Data!S24,Data!U24,Data!W24,Data!Y24,Data!AA24,Data!AC24,Data!AE24,Data!AG24,Data!AI24,Data!AK24,Data!AM24,Data!AO24,Data!AQ24,Data!AS24) -> 0 | F23: =SUM(Data!DI24,Data!DK24,Data!DM24,Data!DO24,Data!DQ24,Data!DS24,Data!DU24,Data!DW24,Data!DY24,Data!EA24,Data!EC24,Data!EE24,Data!EG24,Data!EI24,Data!EK24,Data!EM24,Data!EO24,Data!EQ24,Data!ES24) -> 0 | G23: =F23-E23 -> 0 | H23: =IF(E23=0,IF(F23>0,"New",0),(F23-E23)/E23) -> 0 | I23: =SUM(Data!J24,Data!L24,Data!N24,Data!P24,Data!R24,Data!T24,Data!V24,Data!X24,Data!Z24,Data!AB24,Data!AD24,Data!AF24,Data!AH24,Data!AJ24,Data!AL24,Data!AN24,Data!AP24,Data!AR24,Data!AT24) -> 0 | J23: =SUM(Data!DJ24,Data!DL24,Data!DN24,Data!DP24,Data!DR24,Data!DT24,Data!DV24,Data!DX24,Data!DZ24,Data!EB24,Data!ED24,Data!EF24,Data!EH24,Data!EJ24,Data!EL24,Data!EN24,Data!EP24,Data!ER24,Data!ET24) -> 0 | K23: =J23-I23 -> 0 | L23: =IF(I23=0,IF(J23>0,"New",0),(J23-I23)/I23) -> 0 | M23: =IF(F23=0,"No 2026 Sales",IF(E23=0,"New Product",IF(AND(ISNUMBER(H23),H23>0.1),"↑ Strong Growth",IF(AND(ISNUMBER(H23),H23>0),"↗ Growth",IF(AND(ISNUMBER(H23),H23<-0.1),"↓ Strong Decline",IF(AND(ISNUMBER(H23),H23<0),"↘ Decline","→ Stable")))))) -> No 2026 Sales | O23: New Products | P23: =COUNTIF(M2:M554,"New Product") -> 53
A24: =Data!A25 -> 201 | B24: =Data!B25 -> BUTCHERY | C24: =Data!C25 -> 64129 | D24: =Data!D25 | E24: =SUM(Data!I25,Data!K25,Data!M25,Data!O25,Data!Q25,Data!S25,Data!U25,Data!W25,Data!Y25,Data!AA25,Data!AC25,Data!AE25,Data!AG25,Data!AI25,Data!AK25,Data!AM25,Data!AO25,Data!AQ25,Data!AS25) -> 0 | F24: =SUM(Data!DI25,Data!DK25,Data!DM25,Data!DO25,Data!DQ25,Data!DS25,Data!DU25,Data!DW25,Data!DY25,Data!EA25,Data!EC25,Data!EE25,Data!EG25,Data!EI25,Data!EK25,Data!EM25,Data!EO25,Data!EQ25,Data!ES25) -> 0 | G24: =F24-E24 -> 0 | H24: =IF(E24=0,IF(F24>0,"New",0),(F24-E24)/E24) -> 0 | I24: =SUM(Data!J25,Data!L25,Data!N25,Data!P25,Data!R25,Data!T25,Data!V25,Data!X25,Data!Z25,Data!AB25,Data!AD25,Data!AF25,Data!AH25,Data!AJ25,Data!AL25,Data!AN25,Data!AP25,Data!AR25,Data!AT25) -> 0 | J24: =SUM(Data!DJ25,Data!DL25,Data!DN25,Data!DP25,Data!DR25,Data!DT25,Data!DV25,Data!DX25,Data!DZ25,Data!EB25,Data!ED25,Data!EF25,Data!EH25,Data!EJ25,Data!EL25,Data!EN25,Data!EP25,Data!ER25,Data!ET25) -> 0 | K24: =J24-I24 -> 0 | L24: =IF(I24=0,IF(J24>0,"New",0),(J24-I24)/I24) -> 0 | M24: =IF(F24=0,"No 2026 Sales",IF(E24=0,"New Product",IF(AND(ISNUMBER(H24),H24>0.1),"↑ Strong Growth",IF(AND(ISNUMBER(H24),H24>0),"↗ Growth",IF(AND(ISNUMBER(H24),H24<-0.1),"↓ Strong Decline",IF(AND(ISNUMBER(H24),H24<0),"↘ Decline","→ Stable")))))) -> No 2026 Sales
A25: =Data!A26 -> 201 | B25: =Data!B26 -> BUTCHERY | C25: =Data!C26 -> 64130 | D25: =Data!D26 | E25: =SUM(Data!I26,Data!K26,Data!M26,Data!O26,Data!Q26,Data!S26,Data!U26,Data!W26,Data!Y26,Data!AA26,Data!AC26,Data!AE26,Data!AG26,Data!AI26,Data!AK26,Data!AM26,Data!AO26,Data!AQ26,Data!AS26) -> 0 | F25: =SUM(Data!DI26,Data!DK26,Data!DM26,Data!DO26,Data!DQ26,Data!DS26,Data!DU26,Data!DW26,Data!DY26,Data!EA26,Data!EC26,Data!EE26,Data!EG26,Data!EI26,Data!EK26,Data!EM26,Data!EO26,Data!EQ26,Data!ES26) -> 0 | G25: =F25-E25 -> 0 | H25: =IF(E25=0,IF(F25>0,"New",0),(F25-E25)/E25) -> 0 | I25: =SUM(Data!J26,Data!L26,Data!N26,Data!P26,Data!R26,Data!T26,Data!V26,Data!X26,Data!Z26,Data!AB26,Data!AD26,Data!AF26,Data!AH26,Data!AJ26,Data!AL26,Data!AN26,Data!AP26,Data!AR26,Data!AT26) -> 0 | J25: =SUM(Data!DJ26,Data!DL26,Data!DN26,Data!DP26,Data!DR26,Data!DT26,Data!DV26,Data!DX26,Data!DZ26,Data!EB26,Data!ED26,Data!EF26,Data!EH26,Data!EJ26,Data!EL26,Data!EN26,Data!EP26,Data!ER26,Data!ET26) -> 0 | K25: =J25-I25 -> 0 | L25: =IF(I25=0,IF(J25>0,"New",0),(J25-I25)/I25) -> 0 | M25: =IF(F25=0,"No 2026 Sales",IF(E25=0,"New Product",IF(AND(ISNUMBER(H25),H25>0.1),"↑ Strong Growth",IF(AND(ISNUMBER(H25),H25>0),"↗ Growth",IF(AND(ISNUMBER(H25),H25<-0.1),"↓ Strong Decline",IF(AND(ISNUMBER(H25),H25<0),"↘ Decline","→ Stable")))))) -> No 2026 Sales | O25: Top 10 Growing Products (by Sales)
A26: =Data!A27 -> 201 | B26: =Data!B27 -> BUTCHERY | C26: =Data!C27 -> 64131 | D26: =Data!D27 | E26: =SUM(Data!I27,Data!K27,Data!M27,Data!O27,Data!Q27,Data!S27,Data!U27,Data!W27,Data!Y27,Data!AA27,Data!AC27,Data!AE27,Data!AG27,Data!AI27,Data!AK27,Data!AM27,Data!AO27,Data!AQ27,Data!AS27) -> 0 | F26: =SUM(Data!DI27,Data!DK27,Data!DM27,Data!DO27,Data!DQ27,Data!DS27,Data!DU27,Data!DW27,Data!DY27,Data!EA27,Data!EC27,Data!EE27,Data!EG27,Data!EI27,Data!EK27,Data!EM27,Data!EO27,Data!EQ27,Data!ES27) -> 0 | G26: =F26-E26 -> 0 | H26: =IF(E26=0,IF(F26>0,"New",0),(F26-E26)/E26) -> 0 | I26: =SUM(Data!J27,Data!L27,Data!N27,Data!P27,Data!R27,Data!T27,Data!V27,Data!X27,Data!Z27,Data!AB27,Data!AD27,Data!AF27,Data!AH27,Data!AJ27,Data!AL27,Data!AN27,Data!AP27,Data!AR27,Data!AT27) -> 0 | J26: =SUM(Data!DJ27,Data!DL27,Data!DN27,Data!DP27,Data!DR27,Data!DT27,Data!DV27,Data!DX27,Data!DZ27,Data!EB27,Data!ED27,Data!EF27,Data!EH27,Data!EJ27,Data!EL27,Data!EN27,Data!EP27,Data!ER27,Data!ET27) -> 0 | K26: =J26-I26 -> 0 | L26: =IF(I26=0,IF(J26>0,"New",0),(J26-I26)/I26) -> 0 | M26: =IF(F26=0,"No 2026 Sales",IF(E26=0,"New Product",IF(AND(ISNUMBER(H26),H26>0.1),"↑ Strong Growth",IF(AND(ISNUMBER(H26),H26>0),"↗ Growth",IF(AND(ISNUMBER(H26),H26<-0.1),"↓ Strong Decline",IF(AND(ISNUMBER(H26),H26<0),"↘ Decline","→ Stable")))))) -> No 2026 Sales | O26: Product | P26: 2025 Sales | Q26: 2026 Sales | R26: % Change
A27: =Data!A28 -> 201 | B27: =Data!B28 -> BUTCHERY | C27: =Data!C28 -> 64132 | D27: =Data!D28 | E27: =SUM(Data!I28,Data!K28,Data!M28,Data!O28,Data!Q28,Data!S28,Data!U28,Data!W28,Data!Y28,Data!AA28,Data!AC28,Data!AE28,Data!AG28,Data!AI28,Data!AK28,Data!AM28,Data!AO28,Data!AQ28,Data!AS28) -> 0 | F27: =SUM(Data!DI28,Data!DK28,Data!DM28,Data!DO28,Data!DQ28,Data!DS28,Data!DU28,Data!DW28,Data!DY28,Data!EA28,Data!EC28,Data!EE28,Data!EG28,Data!EI28,Data!EK28,Data!EM28,Data!EO28,Data!EQ28,Data!ES28) -> 0 | G27: =F27-E27 -> 0 | H27: =IF(E27=0,IF(F27>0,"New",0),(F27-E27)/E27) -> 0 | I27: =SUM(Data!J28,Data!L28,Data!N28,Data!P28,Data!R28,Data!T28,Data!V28,Data!X28,Data!Z28,Data!AB28,Data!AD28,Data!AF28,Data!AH28,Data!AJ28,Data!AL28,Data!AN28,Data!AP28,Data!AR28,Data!AT28) -> 0 | J27: =SUM(Data!DJ28,Data!DL28,Data!DN28,Data!DP28,Data!DR28,Data!DT28,Data!DV28,Data!DX28,Data!DZ28,Data!EB28,Data!ED28,Data!EF28,Data!EH28,Data!EJ28,Data!EL28,Data!EN28,Data!EP28,Data!ER28,Data!ET28) -> 0 | K27: =J27-I27 -> 0 | L27: =IF(I27=0,IF(J27>0,"New",0),(J27-I27)/I27) -> 0 | M27: =IF(F27=0,"No 2026 Sales",IF(E27=0,"New Product",IF(AND(ISNUMBER(H27),H27>0.1),"↑ Strong Growth",IF(AND(ISNUMBER(H27),H27>0),"↗ Growth",IF(AND(ISNUMBER(H27),H27<-0.1),"↓ Strong Decline",IF(AND(ISNUMBER(H27),H27<0),"↘ Decline","→ Stable")))))) -> No 2026 Sales | O27: BULK OPPIE-KOPPIE B/WORS | P27: 2953.1043 | Q27: 21912.748 | R27: 6.4202416
A28: =Data!A29 -> 201 | B28: =Data!B29 -> BUTCHERY | C28: =Data!C29 -> 64487 | D28: =Data!D29 | E28: =SUM(Data!I29,Data!K29,Data!M29,Data!O29,Data!Q29,Data!S29,Data!U29,Data!W29,Data!Y29,Data!AA29,Data!AC29,Data!AE29,Data!AG29,Data!AI29,Data!AK29,Data!AM29,Data!AO29,Data!AQ29,Data!AS29) -> 0 | F28: =SUM(Data!DI29,Data!DK29,Data!DM29,Data!DO29,Data!DQ29,Data!DS29,Data!DU29,Data!DW29,Data!DY29,Data!EA29,Data!EC29,Data!EE29,Data!EG29,Data!EI29,Data!EK29,Data!EM29,Data!EO29,Data!EQ29,Data!ES29) -> 0 | G28: =F28-E28 -> 0 | H28: =IF(E28=0,IF(F28>0,"New",0),(F28-E28)/E28) -> 0 | I28: =SUM(Data!J29,Data!L29,Data!N29,Data!P29,Data!R29,Data!T29,Data!V29,Data!X29,Data!Z29,Data!AB29,Data!AD29,Data!AF29,Data!AH29,Data!AJ29,Data!AL29,Data!AN29,Data!AP29,Data!AR29,Data!AT29) -> 0 | J28: =SUM(Data!DJ29,Data!DL29,Data!DN29,Data!DP29,Data!DR29,Data!DT29,Data!DV29,Data!DX29,Data!DZ29,Data!EB29,Data!ED29,Data!EF29,Data!EH29,Data!EJ29,Data!EL29,Data!EN29,Data!EP29,Data!ER29,Data!ET29) -> 0 | K28: =J28-I28 -> 0 | L28: =IF(I28=0,IF(J28>0,"New",0),(J28-I28)/I28) -> 0 | M28: =IF(F28=0,"No 2026 Sales",IF(E28=0,"New Product",IF(AND(ISNUMBER(H28),H28>0.1),"↑ Strong Growth",IF(AND(ISNUMBER(H28),H28>0),"↗ Growth",IF(AND(ISNUMBER(H28),H28<-0.1),"↓ Strong Decline",IF(AND(ISNUMBER(H28),H28<0),"↘ Decline","→ Stable")))))) -> No 2026 Sales | O28: OPPIE-KOPPIE BOEREWORS | P28: 2901.4783 | Q28: 18843.087 | R28: 5.4943058
A29: =Data!A30 -> 201 | B29: =Data!B30 -> BUTCHERY | C29: =Data!C30 -> 64922 | D29: =Data!D30 | E29: =SUM(Data!I30,Data!K30,Data!M30,Data!O30,Data!Q30,Data!S30,Data!U30,Data!W30,Data!Y30,Data!AA30,Data!AC30,Data!AE30,Data!AG30,Data!AI30,Data!AK30,Data!AM30,Data!AO30,Data!AQ30,Data!AS30) -> 0 | F29: =SUM(Data!DI30,Data!DK30,Data!DM30,Data!DO30,Data!DQ30,Data!DS30,Data!DU30,Data!DW30,Data!DY30,Data!EA30,Data!EC30,Data!EE30,Data!EG30,Data!EI30,Data!EK30,Data!EM30,Data!EO30,Data!EQ30,Data!ES30) -> 0 | G29: =F29-E29 -> 0 | H29: =IF(E29=0,IF(F29>0,"New",0),(F29-E29)/E29) -> 0 | I29: =SUM(Data!J30,Data!L30,Data!N30,Data!P30,Data!R30,Data!T30,Data!V30,Data!X30,Data!Z30,Data!AB30,Data!AD30,Data!AF30,Data!AH30,Data!AJ30,Data!AL30,Data!AN30,Data!AP30,Data!AR30,Data!AT30) -> 0 | J29: =SUM(Data!DJ30,Data!DL30,Data!DN30,Data!DP30,Data!DR30,Data!DT30,Data!DV30,Data!DX30,Data!DZ30,Data!EB30,Data!ED30,Data!EF30,Data!EH30,Data!EJ30,Data!EL30,Data!EN30,Data!EP30,Data!ER30,Data!ET30) -> 0 | K29: =J29-I29 -> 0 | L29: =IF(I29=0,IF(J29>0,"New",0),(J29-I29)/I29) -> 0 | M29: =IF(F29=0,"No 2026 Sales",IF(E29=0,"New Product",IF(AND(ISNUMBER(H29),H29>0.1),"↑ Strong Growth",IF(AND(ISNUMBER(H29),H29>0),"↗ Growth",IF(AND(ISNUMBER(H29),H29<-0.1),"↓ Strong Decline",IF(AND(ISNUMBER(H29),H29<0),"↘ Decline","→ Stable")))))) -> No 2026 Sales | O29: T&T BACON STREAKY | P29: 121.73043 | Q29: 730.37391 | R29: 4.9999286
A30: =Data!A31 -> 201 | B30: =Data!B31 -> BUTCHERY | C30: =Data!C31 -> 64923 | D30: =Data!D31 | E30: =SUM(Data!I31,Data!K31,Data!M31,Data!O31,Data!Q31,Data!S31,Data!U31,Data!W31,Data!Y31,Data!AA31,Data!AC31,Data!AE31,Data!AG31,Data!AI31,Data!AK31,Data!AM31,Data!AO31,Data!AQ31,Data!AS31) -> 0 | F30: =SUM(Data!DI31,Data!DK31,Data!DM31,Data!DO31,Data!DQ31,Data!DS31,Data!DU31,Data!DW31,Data!DY31,Data!EA31,Data!EC31,Data!EE31,Data!EG31,Data!EI31,Data!EK31,Data!EM31,Data!EO31,Data!EQ31,Data!ES31) -> 0 | G30: =F30-E30 -> 0 | H30: =IF(E30=0,IF(F30>0,"New",0),(F30-E30)/E30) -> 0 | I30: =SUM(Data!J31,Data!L31,Data!N31,Data!P31,Data!R31,Data!T31,Data!V31,Data!X31,Data!Z31,Data!AB31,Data!AD31,Data!AF31,Data!AH31,Data!AJ31,Data!AL31,Data!AN31,Data!AP31,Data!AR31,Data!AT31) -> 0 | J30: =SUM(Data!DJ31,Data!DL31,Data!DN31,Data!DP31,Data!DR31,Data!DT31,Data!DV31,Data!DX31,Data!DZ31,Data!EB31,Data!ED31,Data!EF31,Data!EH31,Data!EJ31,Data!EL31,Data!EN31,Data!EP31,Data!ER31,Data!ET31) -> 0 | K30: =J30-I30 -> 0 | L30: =IF(I30=0,IF(J30>0,"New",0),(J30-I30)/I30) -> 0 | M30: =IF(F30=0,"No 2026 Sales",IF(E30=0,"New Product",IF(AND(ISNUMBER(H30),H30>0.1),"↑ Strong Growth",IF(AND(ISNUMBER(H30),H30>0),"↗ Growth",IF(AND(ISNUMBER(H30),H30<-0.1),"↓ Strong Decline",IF(AND(ISNUMBER(H30),H30<0),"↘ Decline","→ Stable")))))) -> No 2026 Sales | O30: LAMB BRAAI CHOPS | P30: 1382.6696 | Q30: 7642.1217 | R30: 4.5270774
A31: =Data!A32 -> 201 | B31: =Data!B32 -> BUTCHERY | C31: =Data!C32 -> 64924 | D31: =Data!D32 | E31: =SUM(Data!I32,Data!K32,Data!M32,Data!O32,Data!Q32,Data!S32,Data!U32,Data!W32,Data!Y32,Data!AA32,Data!AC32,Data!AE32,Data!AG32,Data!AI32,Data!AK32,Data!AM32,Data!AO32,Data!AQ32,Data!AS32) -> 0 | F31: =SUM(Data!DI32,Data!DK32,Data!DM32,Data!DO32,Data!DQ32,Data!DS32,Data!DU32,Data!DW32,Data!DY32,Data!EA32,Data!EC32,Data!EE32,Data!EG32,Data!EI32,Data!EK32,Data!EM32,Data!EO32,Data!EQ32,Data!ES32) -> 0 | G31: =F31-E31 -> 0 | H31: =IF(E31=0,IF(F31>0,"New",0),(F31-E31)/E31) -> 0 | I31: =SUM(Data!J32,Data!L32,Data!N32,Data!P32,Data!R32,Data!T32,Data!V32,Data!X32,Data!Z32,Data!AB32,Data!AD32,Data!AF32,Data!AH32,Data!AJ32,Data!AL32,Data!AN32,Data!AP32,Data!AR32,Data!AT32) -> 0 | J31: =SUM(Data!DJ32,Data!DL32,Data!DN32,Data!DP32,Data!DR32,Data!DT32,Data!DV32,Data!DX32,Data!DZ32,Data!EB32,Data!ED32,Data!EF32,Data!EH32,Data!EJ32,Data!EL32,Data!EN32,Data!EP32,Data!ER32,Data!ET32) -> 0 | K31: =J31-I31 -> 0 | L31: =IF(I31=0,IF(J31>0,"New",0),(J31-I31)/I31) -> 0 | M31: =IF(F31=0,"No 2026 Sales",IF(E31=0,"New Product",IF(AND(ISNUMBER(H31),H31>0.1),"↑ Strong Growth",IF(AND(ISNUMBER(H31),H31>0),"↗ Growth",IF(AND(ISNUMBER(H31),H31<-0.1),"↓ Strong Decline",IF(AND(ISNUMBER(H31),H31<0),"↘ Decline","→ Stable")))))) -> No 2026 Sales | O31: ROOIBERG B/WORS | P31: 4831.0957 | Q31: 26588.696 | R31: 4.5036575
A32: =Data!A33 -> 201 | B32: =Data!B33 -> BUTCHERY | C32: =Data!C33 -> 64928 | D32: =Data!D33 | E32: =SUM(Data!I33,Data!K33,Data!M33,Data!O33,Data!Q33,Data!S33,Data!U33,Data!W33,Data!Y33,Data!AA33,Data!AC33,Data!AE33,Data!AG33,Data!AI33,Data!AK33,Data!AM33,Data!AO33,Data!AQ33,Data!AS33) -> 0 | F32: =SUM(Data!DI33,Data!DK33,Data!DM33,Data!DO33,Data!DQ33,Data!DS33,Data!DU33,Data!DW33,Data!DY33,Data!EA33,Data!EC33,Data!EE33,Data!EG33,Data!EI33,Data!EK33,Data!EM33,Data!EO33,Data!EQ33,Data!ES33) -> 0 | G32: =F32-E32 -> 0 | H32: =IF(E32=0,IF(F32>0,"New",0),(F32-E32)/E32) -> 0 | I32: =SUM(Data!J33,Data!L33,Data!N33,Data!P33,Data!R33,Data!T33,Data!V33,Data!X33,Data!Z33,Data!AB33,Data!AD33,Data!AF33,Data!AH33,Data!AJ33,Data!AL33,Data!AN33,Data!AP33,Data!AR33,Data!AT33) -> 0 | J32: =SUM(Data!DJ33,Data!DL33,Data!DN33,Data!DP33,Data!DR33,Data!DT33,Data!DV33,Data!DX33,Data!DZ33,Data!EB33,Data!ED33,Data!EF33,Data!EH33,Data!EJ33,Data!EL33,Data!EN33,Data!EP33,Data!ER33,Data!ET33) -> 0 | K32: =J32-I32 -> 0 | L32: =IF(I32=0,IF(J32>0,"New",0),(J32-I32)/I32) -> 0 | M32: =IF(F32=0,"No 2026 Sales",IF(E32=0,"New Product",IF(AND(ISNUMBER(H32),H32>0.1),"↑ Strong Growth",IF(AND(ISNUMBER(H32),H32>0),"↗ Growth",IF(AND(ISNUMBER(H32),H32<-0.1),"↓ Strong Decline",IF(AND(ISNUMBER(H32),H32<0),"↘ Decline","→ Stable")))))) -> No 2026 Sales | O32: BULK ROOIBERG B/WORS | P32: 4723.0435 | Q32: 21505.348 | R32: 3.5532818
A33: =Data!A34 -> 201 | B33: =Data!B34 -> BUTCHERY | C33: =Data!C34 -> 64929 | D33: =Data!D34 | E33: =SUM(Data!I34,Data!K34,Data!M34,Data!O34,Data!Q34,Data!S34,Data!U34,Data!W34,Data!Y34,Data!AA34,Data!AC34,Data!AE34,Data!AG34,Data!AI34,Data!AK34,Data!AM34,Data!AO34,Data!AQ34,Data!AS34) -> 0 | F33: =SUM(Data!DI34,Data!DK34,Data!DM34,Data!DO34,Data!DQ34,Data!DS34,Data!DU34,Data!DW34,Data!DY34,Data!EA34,Data!EC34,Data!EE34,Data!EG34,Data!EI34,Data!EK34,Data!EM34,Data!EO34,Data!EQ34,Data!ES34) -> 0 | G33: =F33-E33 -> 0 | H33: =IF(E33=0,IF(F33>0,"New",0),(F33-E33)/E33) -> 0 | I33: =SUM(Data!J34,Data!L34,Data!N34,Data!P34,Data!R34,Data!T34,Data!V34,Data!X34,Data!Z34,Data!AB34,Data!AD34,Data!AF34,Data!AH34,Data!AJ34,Data!AL34,Data!AN34,Data!AP34,Data!AR34,Data!AT34) -> 0 | J33: =SUM(Data!DJ34,Data!DL34,Data!DN34,Data!DP34,Data!DR34,Data!DT34,Data!DV34,Data!DX34,Data!DZ34,Data!EB34,Data!ED34,Data!EF34,Data!EH34,Data!EJ34,Data!EL34,Data!EN34,Data!EP34,Data!ER34,Data!ET34) -> 0 | K33: =J33-I33 -> 0 | L33: =IF(I33=0,IF(J33>0,"New",0),(J33-I33)/I33) -> 0 | M33: =IF(F33=0,"No 2026 Sales",IF(E33=0,"New Product",IF(AND(ISNUMBER(H33),H33>0.1),"↑ Strong Growth",IF(AND(ISNUMBER(H33),H33>0),"↗ Growth",IF(AND(ISNUMBER(H33),H33<-0.1),"↓ Strong Decline",IF(AND(ISNUMBER(H33),H33<0),"↘ Decline","→ Stable")))))) -> No 2026 Sales | O33: MUTTON STEW | P33: 2248.1739 | Q33: 7482.2435 | R33: 2.3281426
A34: =Data!A35 -> 201 | B34: =Data!B35 -> BUTCHERY | C34: =Data!C35 -> 64930 | D34: =Data!D35 | E34: =SUM(Data!I35,Data!K35,Data!M35,Data!O35,Data!Q35,Data!S35,Data!U35,Data!W35,Data!Y35,Data!AA35,Data!AC35,Data!AE35,Data!AG35,Data!AI35,Data!AK35,Data!AM35,Data!AO35,Data!AQ35,Data!AS35) -> 0 | F34: =SUM(Data!DI35,Data!DK35,Data!DM35,Data!DO35,Data!DQ35,Data!DS35,Data!DU35,Data!DW35,Data!DY35,Data!EA35,Data!EC35,Data!EE35,Data!EG35,Data!EI35,Data!EK35,Data!EM35,Data!EO35,Data!EQ35,Data!ES35) -> 0 | G34: =F34-E34 -> 0 | H34: =IF(E34=0,IF(F34>0,"New",0),(F34-E34)/E34) -> 0 | I34: =SUM(Data!J35,Data!L35,Data!N35,Data!P35,Data!R35,Data!T35,Data!V35,Data!X35,Data!Z35,Data!AB35,Data!AD35,Data!AF35,Data!AH35,Data!AJ35,Data!AL35,Data!AN35,Data!AP35,Data!AR35,Data!AT35) -> 0 | J34: =SUM(Data!DJ35,Data!DL35,Data!DN35,Data!DP35,Data!DR35,Data!DT35,Data!DV35,Data!DX35,Data!DZ35,Data!EB35,Data!ED35,Data!EF35,Data!EH35,Data!EJ35,Data!EL35,Data!EN35,Data!EP35,Data!ER35,Data!ET35) -> 0 | K34: =J34-I34 -> 0 | L34: =IF(I34=0,IF(J34>0,"New",0),(J34-I34)/I34) -> 0 | M34: =IF(F34=0,"No 2026 Sales",IF(E34=0,"New Product",IF(AND(ISNUMBER(H34),H34>0.1),"↑ Strong Growth",IF(AND(ISNUMBER(H34),H34>0),"↗ Growth",IF(AND(ISNUMBER(H34),H34<-0.1),"↓ Strong Decline",IF(AND(ISNUMBER(H34),H34<0),"↘ Decline","→ Stable")))))) -> No 2026 Sales | O34: LAM STERTJIES | P34: 1068.2 | Q34: 3400.4522 | R34: 2.1833479
A35: =Data!A36 -> 201 | B35: =Data!B36 -> BUTCHERY | C35: =Data!C36 -> 64933 | D35: =Data!D36 | E35: =SUM(Data!I36,Data!K36,Data!M36,Data!O36,Data!Q36,Data!S36,Data!U36,Data!W36,Data!Y36,Data!AA36,Data!AC36,Data!AE36,Data!AG36,Data!AI36,Data!AK36,Data!AM36,Data!AO36,Data!AQ36,Data!AS36) -> 0 | F35: =SUM(Data!DI36,Data!DK36,Data!DM36,Data!DO36,Data!DQ36,Data!DS36,Data!DU36,Data!DW36,Data!DY36,Data!EA36,Data!EC36,Data!EE36,Data!EG36,Data!EI36,Data!EK36,Data!EM36,Data!EO36,Data!EQ36,Data!ES36) -> 0 | G35: =F35-E35 -> 0 | H35: =IF(E35=0,IF(F35>0,"New",0),(F35-E35)/E35) -> 0 | I35: =SUM(Data!J36,Data!L36,Data!N36,Data!P36,Data!R36,Data!T36,Data!V36,Data!X36,Data!Z36,Data!AB36,Data!AD36,Data!AF36,Data!AH36,Data!AJ36,Data!AL36,Data!AN36,Data!AP36,Data!AR36,Data!AT36) -> 0 | J35: =SUM(Data!DJ36,Data!DL36,Data!DN36,Data!DP36,Data!DR36,Data!DT36,Data!DV36,Data!DX36,Data!DZ36,Data!EB36,Data!ED36,Data!EF36,Data!EH36,Data!EJ36,Data!EL36,Data!EN36,Data!EP36,Data!ER36,Data!ET36) -> 0 | K35: =J35-I35 -> 0 | L35: =IF(I35=0,IF(J35>0,"New",0),(J35-I35)/I35) -> 0 | M35: =IF(F35=0,"No 2026 Sales",IF(E35=0,"New Product",IF(AND(ISNUMBER(H35),H35>0.1),"↑ Strong Growth",IF(AND(ISNUMBER(H35),H35>0),"↗ Growth",IF(AND(ISNUMBER(H35),H35<-0.1),"↓ Strong Decline",IF(AND(ISNUMBER(H35),H35<0),"↘ Decline","→ Stable")))))) -> No 2026 Sales | O35: LAMB STEW | P35: 3361.6609 | Q35: 10240.826 | R35: 2.0463591
A36: =Data!A37 -> 201 | B36: =Data!B37 -> BUTCHERY | C36: =Data!C37 -> 64934 | D36: =Data!D37 | E36: =SUM(Data!I37,Data!K37,Data!M37,Data!O37,Data!Q37,Data!S37,Data!U37,Data!W37,Data!Y37,Data!AA37,Data!AC37,Data!AE37,Data!AG37,Data!AI37,Data!AK37,Data!AM37,Data!AO37,Data!AQ37,Data!AS37) -> 0 | F36: =SUM(Data!DI37,Data!DK37,Data!DM37,Data!DO37,Data!DQ37,Data!DS37,Data!DU37,Data!DW37,Data!DY37,Data!EA37,Data!EC37,Data!EE37,Data!EG37,Data!EI37,Data!EK37,Data!EM37,Data!EO37,Data!EQ37,Data!ES37) -> 0 | G36: =F36-E36 -> 0 | H36: =IF(E36=0,IF(F36>0,"New",0),(F36-E36)/E36) -> 0 | I36: =SUM(Data!J37,Data!L37,Data!N37,Data!P37,Data!R37,Data!T37,Data!V37,Data!X37,Data!Z37,Data!AB37,Data!AD37,Data!AF37,Data!AH37,Data!AJ37,Data!AL37,Data!AN37,Data!AP37,Data!AR37,Data!AT37) -> 0 | J36: =SUM(Data!DJ37,Data!DL37,Data!DN37,Data!DP37,Data!DR37,Data!DT37,Data!DV37,Data!DX37,Data!DZ37,Data!EB37,Data!ED37,Data!EF37,Data!EH37,Data!EJ37,Data!EL37,Data!EN37,Data!EP37,Data!ER37,Data!ET37) -> 0 | K36: =J36-I36 -> 0 | L36: =IF(I36=0,IF(J36>0,"New",0),(J36-I36)/I36) -> 0 | M36: =IF(F36=0,"No 2026 Sales",IF(E36=0,"New Product",IF(AND(ISNUMBER(H36),H36>0.1),"↑ Strong Growth",IF(AND(ISNUMBER(H36),H36>0),"↗ Growth",IF(AND(ISNUMBER(H36),H36<-0.1),"↓ Strong Decline",IF(AND(ISNUMBER(H36),H36<0),"↘ Decline","→ Stable")))))) -> No 2026 Sales | O36: BRITOS PRIME CUT BACON | P36: 3133.6261 | Q36: 9008.7304 | R36: 1.8748581
A37: =Data!A38 -> 201 | B37: =Data!B38 -> BUTCHERY | C37: =Data!C38 -> 65132 | D37: =Data!D38 | E37: =SUM(Data!I38,Data!K38,Data!M38,Data!O38,Data!Q38,Data!S38,Data!U38,Data!W38,Data!Y38,Data!AA38,Data!AC38,Data!AE38,Data!AG38,Data!AI38,Data!AK38,Data!AM38,Data!AO38,Data!AQ38,Data!AS38) -> 0 | F37: =SUM(Data!DI38,Data!DK38,Data!DM38,Data!DO38,Data!DQ38,Data!DS38,Data!DU38,Data!DW38,Data!DY38,Data!EA38,Data!EC38,Data!EE38,Data!EG38,Data!EI38,Data!EK38,Data!EM38,Data!EO38,Data!EQ38,Data!ES38) -> 0 | G37: =F37-E37 -> 0 | H37: =IF(E37=0,IF(F37>0,"New",0),(F37-E37)/E37) -> 0 | I37: =SUM(Data!J38,Data!L38,Data!N38,Data!P38,Data!R38,Data!T38,Data!V38,Data!X38,Data!Z38,Data!AB38,Data!AD38,Data!AF38,Data!AH38,Data!AJ38,Data!AL38,Data!AN38,Data!AP38,Data!AR38,Data!AT38) -> 0 | J37: =SUM(Data!DJ38,Data!DL38,Data!DN38,Data!DP38,Data!DR38,Data!DT38,Data!DV38,Data!DX38,Data!DZ38,Data!EB38,Data!ED38,Data!EF38,Data!EH38,Data!EJ38,Data!EL38,Data!EN38,Data!EP38,Data!ER38,Data!ET38) -> 0 | K37: =J37-I37 -> 0 | L37: =IF(I37=0,IF(J37>0,"New",0),(J37-I37)/I37) -> 0 | M37: =IF(F37=0,"No 2026 Sales",IF(E37=0,"New Product",IF(AND(ISNUMBER(H37),H37>0.1),"↑ Strong Growth",IF(AND(ISNUMBER(H37),H37>0),"↗ Growth",IF(AND(ISNUMBER(H37),H37<-0.1),"↓ Strong Decline",IF(AND(ISNUMBER(H37),H37<0),"↘ Decline","→ Stable")))))) -> No 2026 Sales
A38: =Data!A39 -> 201 | B38: =Data!B39 -> BUTCHERY | C38: =Data!C39 -> 65133 | D38: =Data!D39 | E38: =SUM(Data!I39,Data!K39,Data!M39,Data!O39,Data!Q39,Data!S39,Data!U39,Data!W39,Data!Y39,Data!AA39,Data!AC39,Data!AE39,Data!AG39,Data!AI39,Data!AK39,Data!AM39,Data!AO39,Data!AQ39,Data!AS39) -> 0 | F38: =SUM(Data!DI39,Data!DK39,Data!DM39,Data!DO39,Data!DQ39,Data!DS39,Data!DU39,Data!DW39,Data!DY39,Data!EA39,Data!EC39,Data!EE39,Data!EG39,Data!EI39,Data!EK39,Data!EM39,Data!EO39,Data!EQ39,Data!ES39) -> 0 | G38: =F38-E38 -> 0 | H38: =IF(E38=0,IF(F38>0,"New",0),(F38-E38)/E38) -> 0 | I38: =SUM(Data!J39,Data!L39,Data!N39,Data!P39,Data!R39,Data!T39,Data!V39,Data!X39,Data!Z39,Data!AB39,Data!AD39,Data!AF39,Data!AH39,Data!AJ39,Data!AL39,Data!AN39,Data!AP39,Data!AR39,Data!AT39) -> 0 | J38: =SUM(Data!DJ39,Data!DL39,Data!DN39,Data!DP39,Data!DR39,Data!DT39,Data!DV39,Data!DX39,Data!DZ39,Data!EB39,Data!ED39,Data!EF39,Data!EH39,Data!EJ39,Data!EL39,Data!EN39,Data!EP39,Data!ER39,Data!ET39) -> 0 | K38: =J38-I38 -> 0 | L38: =IF(I38=0,IF(J38>0,"New",0),(J38-I38)/I38) -> 0 | M38: =IF(F38=0,"No 2026 Sales",IF(E38=0,"New Product",IF(AND(ISNUMBER(H38),H38>0.1),"↑ Strong Growth",IF(AND(ISNUMBER(H38),H38>0),"↗ Growth",IF(AND(ISNUMBER(H38),H38<-0.1),"↓ Strong Decline",IF(AND(ISNUMBER(H38),H38<0),"↘ Decline","→ Stable")))))) -> No 2026 Sales | O38: Top 10 Declining Products (by Sales)
A39: =Data!A40 -> 201 | B39: =Data!B40 -> BUTCHERY | C39: =Data!C40 -> 65134 | D39: =Data!D40 | E39: =SUM(Data!I40,Data!K40,Data!M40,Data!O40,Data!Q40,Data!S40,Data!U40,Data!W40,Data!Y40,Data!AA40,Data!AC40,Data!AE40,Data!AG40,Data!AI40,Data!AK40,Data!AM40,Data!AO40,Data!AQ40,Data!AS40) -> 0 | F39: =SUM(Data!DI40,Data!DK40,Data!DM40,Data!DO40,Data!DQ40,Data!DS40,Data!DU40,Data!DW40,Data!DY40,Data!EA40,Data!EC40,Data!EE40,Data!EG40,Data!EI40,Data!EK40,Data!EM40,Data!EO40,Data!EQ40,Data!ES40) -> 0 | G39: =F39-E39 -> 0 | H39: =IF(E39=0,IF(F39>0,"New",0),(F39-E39)/E39) -> 0 | I39: =SUM(Data!J40,Data!L40,Data!N40,Data!P40,Data!R40,Data!T40,Data!V40,Data!X40,Data!Z40,Data!AB40,Data!AD40,Data!AF40,Data!AH40,Data!AJ40,Data!AL40,Data!AN40,Data!AP40,Data!AR40,Data!AT40) -> 0 | J39: =SUM(Data!DJ40,Data!DL40,Data!DN40,Data!DP40,Data!DR40,Data!DT40,Data!DV40,Data!DX40,Data!DZ40,Data!EB40,Data!ED40,Data!EF40,Data!EH40,Data!EJ40,Data!EL40,Data!EN40,Data!EP40,Data!ER40,Data!ET40) -> 0 | K39: =J39-I39 -> 0 | L39: =IF(I39=0,IF(J39>0,"New",0),(J39-I39)/I39) -> 0 | M39: =IF(F39=0,"No 2026 Sales",IF(E39=0,"New Product",IF(AND(ISNUMBER(H39),H39>0.1),"↑ Strong Growth",IF(AND(ISNUMBER(H39),H39>0),"↗ Growth",IF(AND(ISNUMBER(H39),H39<-0.1),"↓ Strong Decline",IF(AND(ISNUMBER(H39),H39<0),"↘ Decline","→ Stable")))))) -> No 2026 Sales | O39: Product | P39: 2025 Sales | Q39: 2026 Sales | R39: % Change
A40: =Data!A41 -> 201 | B40: =Data!B41 -> BUTCHERY | C40: =Data!C41 -> 65135 | D40: =Data!D41 | E40: =SUM(Data!I41,Data!K41,Data!M41,Data!O41,Data!Q41,Data!S41,Data!U41,Data!W41,Data!Y41,Data!AA41,Data!AC41,Data!AE41,Data!AG41,Data!AI41,Data!AK41,Data!AM41,Data!AO41,Data!AQ41,Data!AS41) -> 0 | F40: =SUM(Data!DI41,Data!DK41,Data!DM41,Data!DO41,Data!DQ41,Data!DS41,Data!DU41,Data!DW41,Data!DY41,Data!EA41,Data!EC41,Data!EE41,Data!EG41,Data!EI41,Data!EK41,Data!EM41,Data!EO41,Data!EQ41,Data!ES41) -> 0 | G40: =F40-E40 -> 0 | H40: =IF(E40=0,IF(F40>0,"New",0),(F40-E40)/E40) -> 0 | I40: =SUM(Data!J41,Data!L41,Data!N41,Data!P41,Data!R41,Data!T41,Data!V41,Data!X41,Data!Z41,Data!AB41,Data!AD41,Data!AF41,Data!AH41,Data!AJ41,Data!AL41,Data!AN41,Data!AP41,Data!AR41,Data!AT41) -> 0 | J40: =SUM(Data!DJ41,Data!DL41,Data!DN41,Data!DP41,Data!DR41,Data!DT41,Data!DV41,Data!DX41,Data!DZ41,Data!EB41,Data!ED41,Data!EF41,Data!EH41,Data!EJ41,Data!EL41,Data!EN41,Data!EP41,Data!ER41,Data!ET41) -> 0 | K40: =J40-I40 -> 0 | L40: =IF(I40=0,IF(J40>0,"New",0),(J40-I40)/I40) -> 0 | M40: =IF(F40=0,"No 2026 Sales",IF(E40=0,"New Product",IF(AND(ISNUMBER(H40),H40>0.1),"↑ Strong Growth",IF(AND(ISNUMBER(H40),H40>0),"↗ Growth",IF(AND(ISNUMBER(H40),H40<-0.1),"↓ Strong Decline",IF(AND(ISNUMBER(H40),H40<0),"↘ Decline","→ Stable")))))) -> No 2026 Sales | O40: LAMB LEG CHOPS | P40: 9069.1652 | Q40: 86.704348 | R40: -0.99043966
A41: =Data!A42 -> 201 | B41: =Data!B42 -> BUTCHERY | C41: =Data!C42 -> 65241 | D41: =Data!D42 | E41: =SUM(Data!I42,Data!K42,Data!M42,Data!O42,Data!Q42,Data!S42,Data!U42,Data!W42,Data!Y42,Data!AA42,Data!AC42,Data!AE42,Data!AG42,Data!AI42,Data!AK42,Data!AM42,Data!AO42,Data!AQ42,Data!AS42) -> 0 | F41: =SUM(Data!DI42,Data!DK42,Data!DM42,Data!DO42,Data!DQ42,Data!DS42,Data!DU42,Data!DW42,Data!DY42,Data!EA42,Data!EC42,Data!EE42,Data!EG42,Data!EI42,Data!EK42,Data!EM42,Data!EO42,Data!EQ42,Data!ES42) -> 0 | G41: =F41-E41 -> 0 | H41: =IF(E41=0,IF(F41>0,"New",0),(F41-E41)/E41) -> 0 | I41: =SUM(Data!J42,Data!L42,Data!N42,Data!P42,Data!R42,Data!T42,Data!V42,Data!X42,Data!Z42,Data!AB42,Data!AD42,Data!AF42,Data!AH42,Data!AJ42,Data!AL42,Data!AN42,Data!AP42,Data!AR42,Data!AT42) -> 0 | J41: =SUM(Data!DJ42,Data!DL42,Data!DN42,Data!DP42,Data!DR42,Data!DT42,Data!DV42,Data!DX42,Data!DZ42,Data!EB42,Data!ED42,Data!EF42,Data!EH42,Data!EJ42,Data!EL42,Data!EN42,Data!EP42,Data!ER42,Data!ET42) -> 0 | K41: =J41-I41 -> 0 | L41: =IF(I41=0,IF(J41>0,"New",0),(J41-I41)/I41) -> 0 | M41: =IF(F41=0,"No 2026 Sales",IF(E41=0,"New Product",IF(AND(ISNUMBER(H41),H41>0.1),"↑ Strong Growth",IF(AND(ISNUMBER(H41),H41>0),"↗ Growth",IF(AND(ISNUMBER(H41),H41<-0.1),"↓ Strong Decline",IF(AND(ISNUMBER(H41),H41<0),"↘ Decline","→ Stable")))))) -> No 2026 Sales | O41: BEEF BILTONG | P41: 2671.2348 | Q41: 62.817391 | R41: -0.97648376
A42: =Data!A43 -> 201 | B42: =Data!B43 -> BUTCHERY | C42: =Data!C43 -> 65242 | D42: =Data!D43 | E42: =SUM(Data!I43,Data!K43,Data!M43,Data!O43,Data!Q43,Data!S43,Data!U43,Data!W43,Data!Y43,Data!AA43,Data!AC43,Data!AE43,Data!AG43,Data!AI43,Data!AK43,Data!AM43,Data!AO43,Data!AQ43,Data!AS43) -> 0 | F42: =SUM(Data!DI43,Data!DK43,Data!DM43,Data!DO43,Data!DQ43,Data!DS43,Data!DU43,Data!DW43,Data!DY43,Data!EA43,Data!EC43,Data!EE43,Data!EG43,Data!EI43,Data!EK43,Data!EM43,Data!EO43,Data!EQ43,Data!ES43) -> 0 | G42: =F42-E42 -> 0 | H42: =IF(E42=0,IF(F42>0,"New",0),(F42-E42)/E42) -> 0 | I42: =SUM(Data!J43,Data!L43,Data!N43,Data!P43,Data!R43,Data!T43,Data!V43,Data!X43,Data!Z43,Data!AB43,Data!AD43,Data!AF43,Data!AH43,Data!AJ43,Data!AL43,Data!AN43,Data!AP43,Data!AR43,Data!AT43) -> 0 | J42: =SUM(Data!DJ43,Data!DL43,Data!DN43,Data!DP43,Data!DR43,Data!DT43,Data!DV43,Data!DX43,Data!DZ43,Data!EB43,Data!ED43,Data!EF43,Data!EH43,Data!EJ43,Data!EL43,Data!EN43,Data!EP43,Data!ER43,Data!ET43) -> 0 | K42: =J42-I42 -> 0 | L42: =IF(I42=0,IF(J42>0,"New",0),(J42-I42)/I42) -> 0 | M42: =IF(F42=0,"No 2026 Sales",IF(E42=0,"New Product",IF(AND(ISNUMBER(H42),H42>0.1),"↑ Strong Growth",IF(AND(ISNUMBER(H42),H42>0),"↗ Growth",IF(AND(ISNUMBER(H42),H42<-0.1),"↓ Strong Decline",IF(AND(ISNUMBER(H42),H42<0),"↘ Decline","→ Stable")))))) -> No 2026 Sales | O42: BW BEEF BITES CHUTNEY | P42: 6105.8 | Q42: 382.27826 | R42: -0.93739096
A43: =Data!A44 -> 201 | B43: =Data!B44 -> BUTCHERY | C43: =Data!C44 -> 65711 | D43: =Data!D44 | E43: =SUM(Data!I44,Data!K44,Data!M44,Data!O44,Data!Q44,Data!S44,Data!U44,Data!W44,Data!Y44,Data!AA44,Data!AC44,Data!AE44,Data!AG44,Data!AI44,Data!AK44,Data!AM44,Data!AO44,Data!AQ44,Data!AS44) -> 0 | F43: =SUM(Data!DI44,Data!DK44,Data!DM44,Data!DO44,Data!DQ44,Data!DS44,Data!DU44,Data!DW44,Data!DY44,Data!EA44,Data!EC44,Data!EE44,Data!EG44,Data!EI44,Data!EK44,Data!EM44,Data!EO44,Data!EQ44,Data!ES44) -> 0 | G43: =F43-E43 -> 0 | H43: =IF(E43=0,IF(F43>0,"New",0),(F43-E43)/E43) -> 0 | I43: =SUM(Data!J44,Data!L44,Data!N44,Data!P44,Data!R44,Data!T44,Data!V44,Data!X44,Data!Z44,Data!AB44,Data!AD44,Data!AF44,Data!AH44,Data!AJ44,Data!AL44,Data!AN44,Data!AP44,Data!AR44,Data!AT44) -> 0 | J43: =SUM(Data!DJ44,Data!DL44,Data!DN44,Data!DP44,Data!DR44,Data!DT44,Data!DV44,Data!DX44,Data!DZ44,Data!EB44,Data!ED44,Data!EF44,Data!EH44,Data!EJ44,Data!EL44,Data!EN44,Data!EP44,Data!ER44,Data!ET44) -> 0 | K43: =J43-I43 -> 0 | L43: =IF(I43=0,IF(J43>0,"New",0),(J43-I43)/I43) -> 0 | M43: =IF(F43=0,"No 2026 Sales",IF(E43=0,"New Product",IF(AND(ISNUMBER(H43),H43>0.1),"↑ Strong Growth",IF(AND(ISNUMBER(H43),H43>0),"↗ Growth",IF(AND(ISNUMBER(H43),H43<-0.1),"↓ Strong Decline",IF(AND(ISNUMBER(H43),H43<0),"↘ Decline","→ Stable")))))) -> No 2026 Sales | O43: LAMB LEG ROAST | P43: 635.95652 | Q43: 73.730435 | R43: -0.88406372
A44: =Data!A45 -> 201 | B44: =Data!B45 -> BUTCHERY | C44: =Data!C45 -> 65712 | D44: =Data!D45 | E44: =SUM(Data!I45,Data!K45,Data!M45,Data!O45,Data!Q45,Data!S45,Data!U45,Data!W45,Data!Y45,Data!AA45,Data!AC45,Data!AE45,Data!AG45,Data!AI45,Data!AK45,Data!AM45,Data!AO45,Data!AQ45,Data!AS45) -> 0 | F44: =SUM(Data!DI45,Data!DK45,Data!DM45,Data!DO45,Data!DQ45,Data!DS45,Data!DU45,Data!DW45,Data!DY45,Data!EA45,Data!EC45,Data!EE45,Data!EG45,Data!EI45,Data!EK45,Data!EM45,Data!EO45,Data!EQ45,Data!ES45) -> 0 | G44: =F44-E44 -> 0 | H44: =IF(E44=0,IF(F44>0,"New",0),(F44-E44)/E44) -> 0 | I44: =SUM(Data!J45,Data!L45,Data!N45,Data!P45,Data!R45,Data!T45,Data!V45,Data!X45,Data!Z45,Data!AB45,Data!AD45,Data!AF45,Data!AH45,Data!AJ45,Data!AL45,Data!AN45,Data!AP45,Data!AR45,Data!AT45) -> 0 | J44: =SUM(Data!DJ45,Data!DL45,Data!DN45,Data!DP45,Data!DR45,Data!DT45,Data!DV45,Data!DX45,Data!DZ45,Data!EB45,Data!ED45,Data!EF45,Data!EH45,Data!EJ45,Data!EL45,Data!EN45,Data!EP45,Data!ER45,Data!ET45) -> 0 | K44: =J44-I44 -> 0 | L44: =IF(I44=0,IF(J44>0,"New",0),(J44-I44)/I44) -> 0 | M44: =IF(F44=0,"No 2026 Sales",IF(E44=0,"New Product",IF(AND(ISNUMBER(H44),H44>0.1),"↑ Strong Growth",IF(AND(ISNUMBER(H44),H44>0),"↗ Growth",IF(AND(ISNUMBER(H44),H44<-0.1),"↓ Strong Decline",IF(AND(ISNUMBER(H44),H44<0),"↘ Decline","→ Stable")))))) -> No 2026 Sales | O44: B/WORS ROLL BUTCH | P44: 55919.6 | Q44: 6837.8 | R44: -0.87772087
A45: =Data!A46 -> 201 | B45: =Data!B46 -> BUTCHERY | C45: =Data!C46 -> 65713 | D45: =Data!D46 | E45: =SUM(Data!I46,Data!K46,Data!M46,Data!O46,Data!Q46,Data!S46,Data!U46,Data!W46,Data!Y46,Data!AA46,Data!AC46,Data!AE46,Data!AG46,Data!AI46,Data!AK46,Data!AM46,Data!AO46,Data!AQ46,Data!AS46) -> 0 | F45: =SUM(Data!DI46,Data!DK46,Data!DM46,Data!DO46,Data!DQ46,Data!DS46,Data!DU46,Data!DW46,Data!DY46,Data!EA46,Data!EC46,Data!EE46,Data!EG46,Data!EI46,Data!EK46,Data!EM46,Data!EO46,Data!EQ46,Data!ES46) -> 0 | G45: =F45-E45 -> 0 | H45: =IF(E45=0,IF(F45>0,"New",0),(F45-E45)/E45) -> 0 | I45: =SUM(Data!J46,Data!L46,Data!N46,Data!P46,Data!R46,Data!T46,Data!V46,Data!X46,Data!Z46,Data!AB46,Data!AD46,Data!AF46,Data!AH46,Data!AJ46,Data!AL46,Data!AN46,Data!AP46,Data!AR46,Data!AT46) -> 0 | J45: =SUM(Data!DJ46,Data!DL46,Data!DN46,Data!DP46,Data!DR46,Data!DT46,Data!DV46,Data!DX46,Data!DZ46,Data!EB46,Data!ED46,Data!EF46,Data!EH46,Data!EJ46,Data!EL46,Data!EN46,Data!EP46,Data!ER46,Data!ET46) -> 0 | K45: =J45-I45 -> 0 | L45: =IF(I45=0,IF(J45>0,"New",0),(J45-I45)/I45) -> 0 | M45: =IF(F45=0,"No 2026 Sales",IF(E45=0,"New Product",IF(AND(ISNUMBER(H45),H45>0.1),"↑ Strong Growth",IF(AND(ISNUMBER(H45),H45>0),"↗ Growth",IF(AND(ISNUMBER(H45),H45<-0.1),"↓ Strong Decline",IF(AND(ISNUMBER(H45),H45<0),"↘ Decline","→ Stable")))))) -> No 2026 Sales | O45: BW BEEF BITES PLAIN | P45: 7803 | Q45: 1374.6696 | R45: -0.82382807
A46: =Data!A47 -> 201 | B46: =Data!B47 -> BUTCHERY | C46: =Data!C47 -> 65714 | D46: =Data!D47 | E46: =SUM(Data!I47,Data!K47,Data!M47,Data!O47,Data!Q47,Data!S47,Data!U47,Data!W47,Data!Y47,Data!AA47,Data!AC47,Data!AE47,Data!AG47,Data!AI47,Data!AK47,Data!AM47,Data!AO47,Data!AQ47,Data!AS47) -> 0 | F46: =SUM(Data!DI47,Data!DK47,Data!DM47,Data!DO47,Data!DQ47,Data!DS47,Data!DU47,Data!DW47,Data!DY47,Data!EA47,Data!EC47,Data!EE47,Data!EG47,Data!EI47,Data!EK47,Data!EM47,Data!EO47,Data!EQ47,Data!ES47) -> 0 | G46: =F46-E46 -> 0 | H46: =IF(E46=0,IF(F46>0,"New",0),(F46-E46)/E46) -> 0 | I46: =SUM(Data!J47,Data!L47,Data!N47,Data!P47,Data!R47,Data!T47,Data!V47,Data!X47,Data!Z47,Data!AB47,Data!AD47,Data!AF47,Data!AH47,Data!AJ47,Data!AL47,Data!AN47,Data!AP47,Data!AR47,Data!AT47) -> 0 | J46: =SUM(Data!DJ47,Data!DL47,Data!DN47,Data!DP47,Data!DR47,Data!DT47,Data!DV47,Data!DX47,Data!DZ47,Data!EB47,Data!ED47,Data!EF47,Data!EH47,Data!EJ47,Data!EL47,Data!EN47,Data!EP47,Data!ER47,Data!ET47) -> 0 | K46: =J46-I46 -> 0 | L46: =IF(I46=0,IF(J46>0,"New",0),(J46-I46)/I46) -> 0 | M46: =IF(F46=0,"No 2026 Sales",IF(E46=0,"New Product",IF(AND(ISNUMBER(H46),H46>0.1),"↑ Strong Growth",IF(AND(ISNUMBER(H46),H46>0),"↗ Growth",IF(AND(ISNUMBER(H46),H46<-0.1),"↓ Strong Decline",IF(AND(ISNUMBER(H46),H46<0),"↘ Decline","→ Stable")))))) -> No 2026 Sales | O46: BRITOS BUDGET PATTIES | P46: 8955.6261 | Q46: 1721.5478 | R46: -0.80776913
A47: =Data!A48 -> 201 | B47: =Data!B48 -> BUTCHERY | C47: =Data!C48 -> 66122 | D47: =Data!D48 | E47: =SUM(Data!I48,Data!K48,Data!M48,Data!O48,Data!Q48,Data!S48,Data!U48,Data!W48,Data!Y48,Data!AA48,Data!AC48,Data!AE48,Data!AG48,Data!AI48,Data!AK48,Data!AM48,Data!AO48,Data!AQ48,Data!AS48) -> 0 | F47: =SUM(Data!DI48,Data!DK48,Data!DM48,Data!DO48,Data!DQ48,Data!DS48,Data!DU48,Data!DW48,Data!DY48,Data!EA48,Data!EC48,Data!EE48,Data!EG48,Data!EI48,Data!EK48,Data!EM48,Data!EO48,Data!EQ48,Data!ES48) -> 0 | G47: =F47-E47 -> 0 | H47: =IF(E47=0,IF(F47>0,"New",0),(F47-E47)/E47) -> 0 | I47: =SUM(Data!J48,Data!L48,Data!N48,Data!P48,Data!R48,Data!T48,Data!V48,Data!X48,Data!Z48,Data!AB48,Data!AD48,Data!AF48,Data!AH48,Data!AJ48,Data!AL48,Data!AN48,Data!AP48,Data!AR48,Data!AT48) -> 0 | J47: =SUM(Data!DJ48,Data!DL48,Data!DN48,Data!DP48,Data!DR48,Data!DT48,Data!DV48,Data!DX48,Data!DZ48,Data!EB48,Data!ED48,Data!EF48,Data!EH48,Data!EJ48,Data!EL48,Data!EN48,Data!EP48,Data!ER48,Data!ET48) -> 0 | K47: =J47-I47 -> 0 | L47: =IF(I47=0,IF(J47>0,"New",0),(J47-I47)/I47) -> 0 | M47: =IF(F47=0,"No 2026 Sales",IF(E47=0,"New Product",IF(AND(ISNUMBER(H47),H47>0.1),"↑ Strong Growth",IF(AND(ISNUMBER(H47),H47>0),"↗ Growth",IF(AND(ISNUMBER(H47),H47<-0.1),"↓ Strong Decline",IF(AND(ISNUMBER(H47),H47<0),"↘ Decline","→ Stable")))))) -> No 2026 Sales | O47: 1/4 MUTTON | P47: 45824.861 | Q47: 9130.6783 | R47: -0.80074837
A48: =Data!A49 -> 201 | B48: =Data!B49 -> BUTCHERY | C48: =Data!C49 -> 66123 | D48: =Data!D49 | E48: =SUM(Data!I49,Data!K49,Data!M49,Data!O49,Data!Q49,Data!S49,Data!U49,Data!W49,Data!Y49,Data!AA49,Data!AC49,Data!AE49,Data!AG49,Data!AI49,Data!AK49,Data!AM49,Data!AO49,Data!AQ49,Data!AS49) -> 0 | F48: =SUM(Data!DI49,Data!DK49,Data!DM49,Data!DO49,Data!DQ49,Data!DS49,Data!DU49,Data!DW49,Data!DY49,Data!EA49,Data!EC49,Data!EE49,Data!EG49,Data!EI49,Data!EK49,Data!EM49,Data!EO49,Data!EQ49,Data!ES49) -> 0 | G48: =F48-E48 -> 0 | H48: =IF(E48=0,IF(F48>0,"New",0),(F48-E48)/E48) -> 0 | I48: =SUM(Data!J49,Data!L49,Data!N49,Data!P49,Data!R49,Data!T49,Data!V49,Data!X49,Data!Z49,Data!AB49,Data!AD49,Data!AF49,Data!AH49,Data!AJ49,Data!AL49,Data!AN49,Data!AP49,Data!AR49,Data!AT49) -> 0 | J48: =SUM(Data!DJ49,Data!DL49,Data!DN49,Data!DP49,Data!DR49,Data!DT49,Data!DV49,Data!DX49,Data!DZ49,Data!EB49,Data!ED49,Data!EF49,Data!EH49,Data!EJ49,Data!EL49,Data!EN49,Data!EP49,Data!ER49,Data!ET49) -> 0 | K48: =J48-I48 -> 0 | L48: =IF(I48=0,IF(J48>0,"New",0),(J48-I48)/I48) -> 0 | M48: =IF(F48=0,"No 2026 Sales",IF(E48=0,"New Product",IF(AND(ISNUMBER(H48),H48>0.1),"↑ Strong Growth",IF(AND(ISNUMBER(H48),H48>0),"↗ Growth",IF(AND(ISNUMBER(H48),H48<-0.1),"↓ Strong Decline",IF(AND(ISNUMBER(H48),H48<0),"↘ Decline","→ Stable")))))) -> No 2026 Sales | O48: CHEESE BURGER | P48: 22889.374 | Q48: 5562.6 | R48: -0.75697894
A49: =Data!A50 -> 201 | B49: =Data!B50 -> BUTCHERY | C49: =Data!C50 -> 66709 | D49: =Data!D50 | E49: =SUM(Data!I50,Data!K50,Data!M50,Data!O50,Data!Q50,Data!S50,Data!U50,Data!W50,Data!Y50,Data!AA50,Data!AC50,Data!AE50,Data!AG50,Data!AI50,Data!AK50,Data!AM50,Data!AO50,Data!AQ50,Data!AS50) -> 0 | F49: =SUM(Data!DI50,Data!DK50,Data!DM50,Data!DO50,Data!DQ50,Data!DS50,Data!DU50,Data!DW50,Data!DY50,Data!EA50,Data!EC50,Data!EE50,Data!EG50,Data!EI50,Data!EK50,Data!EM50,Data!EO50,Data!EQ50,Data!ES50) -> 0 | G49: =F49-E49 -> 0 | H49: =IF(E49=0,IF(F49>0,"New",0),(F49-E49)/E49) -> 0 | I49: =SUM(Data!J50,Data!L50,Data!N50,Data!P50,Data!R50,Data!T50,Data!V50,Data!X50,Data!Z50,Data!AB50,Data!AD50,Data!AF50,Data!AH50,Data!AJ50,Data!AL50,Data!AN50,Data!AP50,Data!AR50,Data!AT50) -> 0 | J49: =SUM(Data!DJ50,Data!DL50,Data!DN50,Data!DP50,Data!DR50,Data!DT50,Data!DV50,Data!DX50,Data!DZ50,Data!EB50,Data!ED50,Data!EF50,Data!EH50,Data!EJ50,Data!EL50,Data!EN50,Data!EP50,Data!ER50,Data!ET50) -> 0 | K49: =J49-I49 -> 0 | L49: =IF(I49=0,IF(J49>0,"New",0),(J49-I49)/I49) -> 0 | M49: =IF(F49=0,"No 2026 Sales",IF(E49=0,"New Product",IF(AND(ISNUMBER(H49),H49>0.1),"↑ Strong Growth",IF(AND(ISNUMBER(H49),H49>0),"↗ Growth",IF(AND(ISNUMBER(H49),H49<-0.1),"↓ Strong Decline",IF(AND(ISNUMBER(H49),H49<0),"↘ Decline","→ Stable")))))) -> No 2026 Sales | O49: BEEF ROAST | P49: 2444.3913 | Q49: 602.66957 | R49: -0.753448
A50: =Data!A51 -> 201 | B50: =Data!B51 -> BUTCHERY | C50: =Data!C51 -> 66710 | D50: =Data!D51 | E50: =SUM(Data!I51,Data!K51,Data!M51,Data!O51,Data!Q51,Data!S51,Data!U51,Data!W51,Data!Y51,Data!AA51,Data!AC51,Data!AE51,Data!AG51,Data!AI51,Data!AK51,Data!AM51,Data!AO51,Data!AQ51,Data!AS51) -> 0 | F50: =SUM(Data!DI51,Data!DK51,Data!DM51,Data!DO51,Data!DQ51,Data!DS51,Data!DU51,Data!DW51,Data!DY51,Data!EA51,Data!EC51,Data!EE51,Data!EG51,Data!EI51,Data!EK51,Data!EM51,Data!EO51,Data!EQ51,Data!ES51) -> 0 | G50: =F50-E50 -> 0 | H50: =IF(E50=0,IF(F50>0,"New",0),(F50-E50)/E50) -> 0 | I50: =SUM(Data!J51,Data!L51,Data!N51,Data!P51,Data!R51,Data!T51,Data!V51,Data!X51,Data!Z51,Data!AB51,Data!AD51,Data!AF51,Data!AH51,Data!AJ51,Data!AL51,Data!AN51,Data!AP51,Data!AR51,Data!AT51) -> 0 | J50: =SUM(Data!DJ51,Data!DL51,Data!DN51,Data!DP51,Data!DR51,Data!DT51,Data!DV51,Data!DX51,Data!DZ51,Data!EB51,Data!ED51,Data!EF51,Data!EH51,Data!EJ51,Data!EL51,Data!EN51,Data!EP51,Data!ER51,Data!ET51) -> 0 | K50: =J50-I50 -> 0 | L50: =IF(I50=0,IF(J50>0,"New",0),(J50-I50)/I50) -> 0 | M50: =IF(F50=0,"No 2026 Sales",IF(E50=0,"New Product",IF(AND(ISNUMBER(H50),H50>0.1),"↑ Strong Growth",IF(AND(ISNUMBER(H50),H50>0),"↗ Growth",IF(AND(ISNUMBER(H50),H50<-0.1),"↓ Strong Decline",IF(AND(ISNUMBER(H50),H50<0),"↘ Decline","→ Stable")))))) -> No 2026 Sales
A51: =Data!A52 -> 201 | B51: =Data!B52 -> BUTCHERY | C51: =Data!C52 -> 66711 | D51: =Data!D52 | E51: =SUM(Data!I52,Data!K52,Data!M52,Data!O52,Data!Q52,Data!S52,Data!U52,Data!W52,Data!Y52,Data!AA52,Data!AC52,Data!AE52,Data!AG52,Data!AI52,Data!AK52,Data!AM52,Data!AO52,Data!AQ52,Data!AS52) -> 0 | F51: =SUM(Data!DI52,Data!DK52,Data!DM52,Data!DO52,Data!DQ52,Data!DS52,Data!DU52,Data!DW52,Data!DY52,Data!EA52,Data!EC52,Data!EE52,Data!EG52,Data!EI52,Data!EK52,Data!EM52,Data!EO52,Data!EQ52,Data!ES52) -> 0 | G51: =F51-E51 -> 0 | H51: =IF(E51=0,IF(F51>0,"New",0),(F51-E51)/E51) -> 0 | I51: =SUM(Data!J52,Data!L52,Data!N52,Data!P52,Data!R52,Data!T52,Data!V52,Data!X52,Data!Z52,Data!AB52,Data!AD52,Data!AF52,Data!AH52,Data!AJ52,Data!AL52,Data!AN52,Data!AP52,Data!AR52,Data!AT52) -> 0 | J51: =SUM(Data!DJ52,Data!DL52,Data!DN52,Data!DP52,Data!DR52,Data!DT52,Data!DV52,Data!DX52,Data!DZ52,Data!EB52,Data!ED52,Data!EF52,Data!EH52,Data!EJ52,Data!EL52,Data!EN52,Data!EP52,Data!ER52,Data!ET52) -> 0 | K51: =J51-I51 -> 0 | L51: =IF(I51=0,IF(J51>0,"New",0),(J51-I51)/I51) -> 0 | M51: =IF(F51=0,"No 2026 Sales",IF(E51=0,"New Product",IF(AND(ISNUMBER(H51),H51>0.1),"↑ Strong Growth",IF(AND(ISNUMBER(H51),H51>0),"↗ Growth",IF(AND(ISNUMBER(H51),H51<-0.1),"↓ Strong Decline",IF(AND(ISNUMBER(H51),H51<0),"↘ Decline","→ Stable")))))) -> No 2026 Sales
A52: =Data!A53 -> 201 | B52: =Data!B53 -> BUTCHERY | C52: =Data!C53 -> 66712 | D52: =Data!D53 | E52: =SUM(Data!I53,Data!K53,Data!M53,Data!O53,Data!Q53,Data!S53,Data!U53,Data!W53,Data!Y53,Data!AA53,Data!AC53,Data!AE53,Data!AG53,Data!AI53,Data!AK53,Data!AM53,Data!AO53,Data!AQ53,Data!AS53) -> 0 | F52: =SUM(Data!DI53,Data!DK53,Data!DM53,Data!DO53,Data!DQ53,Data!DS53,Data!DU53,Data!DW53,Data!DY53,Data!EA53,Data!EC53,Data!EE53,Data!EG53,Data!EI53,Data!EK53,Data!EM53,Data!EO53,Data!EQ53,Data!ES53) -> 0 | G52: =F52-E52 -> 0 | H52: =IF(E52=0,IF(F52>0,"New",0),(F52-E52)/E52) -> 0 | I52: =SUM(Data!J53,Data!L53,Data!N53,Data!P53,Data!R53,Data!T53,Data!V53,Data!X53,Data!Z53,Data!AB53,Data!AD53,Data!AF53,Data!AH53,Data!AJ53,Data!AL53,Data!AN53,Data!AP53,Data!AR53,Data!AT53) -> 0 | J52: =SUM(Data!DJ53,Data!DL53,Data!DN53,Data!DP53,Data!DR53,Data!DT53,Data!DV53,Data!DX53,Data!DZ53,Data!EB53,Data!ED53,Data!EF53,Data!EH53,Data!EJ53,Data!EL53,Data!EN53,Data!EP53,Data!ER53,Data!ET53) -> 0 | K52: =J52-I52 -> 0 | L52: =IF(I52=0,IF(J52>0,"New",0),(J52-I52)/I52) -> 0 | M52: =IF(F52=0,"No 2026 Sales",IF(E52=0,"New Product",IF(AND(ISNUMBER(H52),H52>0.1),"↑ Strong Growth",IF(AND(ISNUMBER(H52),H52>0),"↗ Growth",IF(AND(ISNUMBER(H52),H52<-0.1),"↓ Strong Decline",IF(AND(ISNUMBER(H52),H52<0),"↘ Decline","→ Stable")))))) -> No 2026 Sales
A53: =Data!A54 -> 201 | B53: =Data!B54 -> BUTCHERY | C53: =Data!C54 -> 66713 | D53: =Data!D54 | E53: =SUM(Data!I54,Data!K54,Data!M54,Data!O54,Data!Q54,Data!S54,Data!U54,Data!W54,Data!Y54,Data!AA54,Data!AC54,Data!AE54,Data!AG54,Data!AI54,Data!AK54,Data!AM54,Data!AO54,Data!AQ54,Data!AS54) -> 0 | F53: =SUM(Data!DI54,Data!DK54,Data!DM54,Data!DO54,Data!DQ54,Data!DS54,Data!DU54,Data!DW54,Data!DY54,Data!EA54,Data!EC54,Data!EE54,Data!EG54,Data!EI54,Data!EK54,Data!EM54,Data!EO54,Data!EQ54,Data!ES54) -> 0 | G53: =F53-E53 -> 0 | H53: =IF(E53=0,IF(F53>0,"New",0),(F53-E53)/E53) -> 0 | I53: =SUM(Data!J54,Data!L54,Data!N54,Data!P54,Data!R54,Data!T54,Data!V54,Data!X54,Data!Z54,Data!AB54,Data!AD54,Data!AF54,Data!AH54,Data!AJ54,Data!AL54,Data!AN54,Data!AP54,Data!AR54,Data!AT54) -> 0 | J53: =SUM(Data!DJ54,Data!DL54,Data!DN54,Data!DP54,Data!DR54,Data!DT54,Data!DV54,Data!DX54,Data!DZ54,Data!EB54,Data!ED54,Data!EF54,Data!EH54,Data!EJ54,Data!EL54,Data!EN54,Data!EP54,Data!ER54,Data!ET54) -> 0 | K53: =J53-I53 -> 0 | L53: =IF(I53=0,IF(J53>0,"New",0),(J53-I53)/I53) -> 0 | M53: =IF(F53=0,"No 2026 Sales",IF(E53=0,"New Product",IF(AND(ISNUMBER(H53),H53>0.1),"↑ Strong Growth",IF(AND(ISNUMBER(H53),H53>0),"↗ Growth",IF(AND(ISNUMBER(H53),H53<-0.1),"↓ Strong Decline",IF(AND(ISNUMBER(H53),H53<0),"↘ Decline","→ Stable")))))) -> No 2026 Sales
A54: =Data!A55 -> 201 | B54: =Data!B55 -> BUTCHERY | C54: =Data!C55 -> 66714 | D54: =Data!D55 | E54: =SUM(Data!I55,Data!K55,Data!M55,Data!O55,Data!Q55,Data!S55,Data!U55,Data!W55,Data!Y55,Data!AA55,Data!AC55,Data!AE55,Data!AG55,Data!AI55,Data!AK55,Data!AM55,Data!AO55,Data!AQ55,Data!AS55) -> 0 | F54: =SUM(Data!DI55,Data!DK55,Data!DM55,Data!DO55,Data!DQ55,Data!DS55,Data!DU55,Data!DW55,Data!DY55,Data!EA55,Data!EC55,Data!EE55,Data!EG55,Data!EI55,Data!EK55,Data!EM55,Data!EO55,Data!EQ55,Data!ES55) -> 0 | G54: =F54-E54 -> 0 | H54: =IF(E54=0,IF(F54>0,"New",0),(F54-E54)/E54) -> 0 | I54: =SUM(Data!J55,Data!L55,Data!N55,Data!P55,Data!R55,Data!T55,Data!V55,Data!X55,Data!Z55,Data!AB55,Data!AD55,Data!AF55,Data!AH55,Data!AJ55,Data!AL55,Data!AN55,Data!AP55,Data!AR55,Data!AT55) -> 0 | J54: =SUM(Data!DJ55,Data!DL55,Data!DN55,Data!DP55,Data!DR55,Data!DT55,Data!DV55,Data!DX55,Data!DZ55,Data!EB55,Data!ED55,Data!EF55,Data!EH55,Data!EJ55,Data!EL55,Data!EN55,Data!EP55,Data!ER55,Data!ET55) -> 0 | K54: =J54-I54 -> 0 | L54: =IF(I54=0,IF(J54>0,"New",0),(J54-I54)/I54) -> 0 | M54: =IF(F54=0,"No 2026 Sales",IF(E54=0,"New Product",IF(AND(ISNUMBER(H54),H54>0.1),"↑ Strong Growth",IF(AND(ISNUMBER(H54),H54>0),"↗ Growth",IF(AND(ISNUMBER(H54),H54<-0.1),"↓ Strong Decline",IF(AND(ISNUMBER(H54),H54<0),"↘ Decline","→ Stable")))))) -> No 2026 Sales
A55: =Data!A56 -> 201 | B55: =Data!B56 -> BUTCHERY | C55: =Data!C56 -> 66715 | D55: =Data!D56 | E55: =SUM(Data!I56,Data!K56,Data!M56,Data!O56,Data!Q56,Data!S56,Data!U56,Data!W56,Data!Y56,Data!AA56,Data!AC56,Data!AE56,Data!AG56,Data!AI56,Data!AK56,Data!AM56,Data!AO56,Data!AQ56,Data!AS56) -> 0 | F55: =SUM(Data!DI56,Data!DK56,Data!DM56,Data!DO56,Data!DQ56,Data!DS56,Data!DU56,Data!DW56,Data!DY56,Data!EA56,Data!EC56,Data!EE56,Data!EG56,Data!EI56,Data!EK56,Data!EM56,Data!EO56,Data!EQ56,Data!ES56) -> 0 | G55: =F55-E55 -> 0 | H55: =IF(E55=0,IF(F55>0,"New",0),(F55-E55)/E55) -> 0 | I55: =SUM(Data!J56,Data!L56,Data!N56,Data!P56,Data!R56,Data!T56,Data!V56,Data!X56,Data!Z56,Data!AB56,Data!AD56,Data!AF56,Data!AH56,Data!AJ56,Data!AL56,Data!AN56,Data!AP56,Data!AR56,Data!AT56) -> 0 | J55: =SUM(Data!DJ56,Data!DL56,Data!DN56,Data!DP56,Data!DR56,Data!DT56,Data!DV56,Data!DX56,Data!DZ56,Data!EB56,Data!ED56,Data!EF56,Data!EH56,Data!EJ56,Data!EL56,Data!EN56,Data!EP56,Data!ER56,Data!ET56) -> 0 | K55: =J55-I55 -> 0 | L55: =IF(I55=0,IF(J55>0,"New",0),(J55-I55)/I55) -> 0 | M55: =IF(F55=0,"No 2026 Sales",IF(E55=0,"New Product",IF(AND(ISNUMBER(H55),H55>0.1),"↑ Strong Growth",IF(AND(ISNUMBER(H55),H55>0),"↗ Growth",IF(AND(ISNUMBER(H55),H55<-0.1),"↓ Strong Decline",IF(AND(ISNUMBER(H55),H55<0),"↘ Decline","→ Stable")))))) -> No 2026 Sales
A56: =Data!A57 -> 201 | B56: =Data!B57 -> BUTCHERY | C56: =Data!C57 -> 99990201 | D56: =Data!D57 | E56: =SUM(Data!I57,Data!K57,Data!M57,Data!O57,Data!Q57,Data!S57,Data!U57,Data!W57,Data!Y57,Data!AA57,Data!AC57,Data!AE57,Data!AG57,Data!AI57,Data!AK57,Data!AM57,Data!AO57,Data!AQ57,Data!AS57) -> 20678.991 | F56: =SUM(Data!DI57,Data!DK57,Data!DM57,Data!DO57,Data!DQ57,Data!DS57,Data!DU57,Data!DW57,Data!DY57,Data!EA57,Data!EC57,Data!EE57,Data!EG57,Data!EI57,Data!EK57,Data!EM57,Data!EO57,Data!EQ57,Data!ES57) -> 14401.678 | G56: =F56-E56 -> -6277.313 | H56: =IF(E56=0,IF(F56>0,"New",0),(F56-E56)/E56) -> -0.30355992 | I56: =SUM(Data!J57,Data!L57,Data!N57,Data!P57,Data!R57,Data!T57,Data!V57,Data!X57,Data!Z57,Data!AB57,Data!AD57,Data!AF57,Data!AH57,Data!AJ57,Data!AL57,Data!AN57,Data!AP57,Data!AR57,Data!AT57) -> 682 | J56: =SUM(Data!DJ57,Data!DL57,Data!DN57,Data!DP57,Data!DR57,Data!DT57,Data!DV57,Data!DX57,Data!DZ57,Data!EB57,Data!ED57,Data!EF57,Data!EH57,Data!EJ57,Data!EL57,Data!EN57,Data!EP57,Data!ER57,Data!ET57) -> 196 | K56: =J56-I56 -> -486 | L56: =IF(I56=0,IF(J56>0,"New",0),(J56-I56)/I56) -> -0.71260997 | M56: =IF(F56=0,"No 2026 Sales",IF(E56=0,"New Product",IF(AND(ISNUMBER(H56),H56>0.1),"↑ Strong Growth",IF(AND(ISNUMBER(H56),H56>0),"↗ Growth",IF(AND(ISNUMBER(H56),H56<-0.1),"↓ Strong Decline",IF(AND(ISNUMBER(H56),H56<0),"↘ Decline","→ Stable")))))) -> ↓ Strong Decline
A57: =Data!A58 -> 202 | B57: =Data!B58 -> BEEF | C57: =Data!C58 -> 2748 | D57: =Data!D58 | E57: =SUM(Data!I58,Data!K58,Data!M58,Data!O58,Data!Q58,Data!S58,Data!U58,Data!W58,Data!Y58,Data!AA58,Data!AC58,Data!AE58,Data!AG58,Data!AI58,Data!AK58,Data!AM58,Data!AO58,Data!AQ58,Data!AS58) -> 0 | F57: =SUM(Data!DI58,Data!DK58,Data!DM58,Data!DO58,Data!DQ58,Data!DS58,Data!DU58,Data!DW58,Data!DY58,Data!EA58,Data!EC58,Data!EE58,Data!EG58,Data!EI58,Data!EK58,Data!EM58,Data!EO58,Data!EQ58,Data!ES58) -> 0 | G57: =F57-E57 -> 0 | H57: =IF(E57=0,IF(F57>0,"New",0),(F57-E57)/E57) -> 0 | I57: =SUM(Data!J58,Data!L58,Data!N58,Data!P58,Data!R58,Data!T58,Data!V58,Data!X58,Data!Z58,Data!AB58,Data!AD58,Data!AF58,Data!AH58,Data!AJ58,Data!AL58,Data!AN58,Data!AP58,Data!AR58,Data!AT58) -> 0 | J57: =SUM(Data!DJ58,Data!DL58,Data!DN58,Data!DP58,Data!DR58,Data!DT58,Data!DV58,Data!DX58,Data!DZ58,Data!EB58,Data!ED58,Data!EF58,Data!EH58,Data!EJ58,Data!EL58,Data!EN58,Data!EP58,Data!ER58,Data!ET58) -> 0 | K57: =J57-I57 -> 0 | L57: =IF(I57=0,IF(J57>0,"New",0),(J57-I57)/I57) -> 0 | M57: =IF(F57=0,"No 2026 Sales",IF(E57=0,"New Product",IF(AND(ISNUMBER(H57),H57>0.1),"↑ Strong Growth",IF(AND(ISNUMBER(H57),H57>0),"↗ Growth",IF(AND(ISNUMBER(H57),H57<-0.1),"↓ Strong Decline",IF(AND(ISNUMBER(H57),H57<0),"↘ Decline","→ Stable")))))) -> No 2026 Sales
A58: =Data!A59 -> 202 | B58: =Data!B59 -> BEEF | C58: =Data!C59 -> 12112 | D58: =Data!D59 | E58: =SUM(Data!I59,Data!K59,Data!M59,Data!O59,Data!Q59,Data!S59,Data!U59,Data!W59,Data!Y59,Data!AA59,Data!AC59,Data!AE59,Data!AG59,Data!AI59,Data!AK59,Data!AM59,Data!AO59,Data!AQ59,Data!AS59) -> 0 | F58: =SUM(Data!DI59,Data!DK59,Data!DM59,Data!DO59,Data!DQ59,Data!DS59,Data!DU59,Data!DW59,Data!DY59,Data!EA59,Data!EC59,Data!EE59,Data!EG59,Data!EI59,Data!EK59,Data!EM59,Data!EO59,Data!EQ59,Data!ES59) -> 0 | G58: =F58-E58 -> 0 | H58: =IF(E58=0,IF(F58>0,"New",0),(F58-E58)/E58) -> 0 | I58: =SUM(Data!J59,Data!L59,Data!N59,Data!P59,Data!R59,Data!T59,Data!V59,Data!X59,Data!Z59,Data!AB59,Data!AD59,Data!AF59,Data!AH59,Data!AJ59,Data!AL59,Data!AN59,Data!AP59,Data!AR59,Data!AT59) -> 0 | J58: =SUM(Data!DJ59,Data!DL59,Data!DN59,Data!DP59,Data!DR59,Data!DT59,Data!DV59,Data!DX59,Data!DZ59,Data!EB59,Data!ED59,Data!EF59,Data!EH59,Data!EJ59,Data!EL59,Data!EN59,Data!EP59,Data!ER59,Data!ET59) -> 0 | K58: =J58-I58 -> 0 | L58: =IF(I58=0,IF(J58>0,"New",0),(J58-I58)/I58) -> 0 | M58: =IF(F58=0,"No 2026 Sales",IF(E58=0,"New Product",IF(AND(ISNUMBER(H58),H58>0.1),"↑ Strong Growth",IF(AND(ISNUMBER(H58),H58>0),"↗ Growth",IF(AND(ISNUMBER(H58),H58<-0.1),"↓ Strong Decline",IF(AND(ISNUMBER(H58),H58<0),"↘ Decline","→ Stable")))))) -> No 2026 Sales
A59: =Data!A60 -> 202 | B59: =Data!B60 -> BEEF | C59: =Data!C60 -> 12113 | D59: =Data!D60 | E59: =SUM(Data!I60,Data!K60,Data!M60,Data!O60,Data!Q60,Data!S60,Data!U60,Data!W60,Data!Y60,Data!AA60,Data!AC60,Data!AE60,Data!AG60,Data!AI60,Data!AK60,Data!AM60,Data!AO60,Data!AQ60,Data!AS60) -> 155.76522 | F59: =SUM(Data!DI60,Data!DK60,Data!DM60,Data!DO60,Data!DQ60,Data!DS60,Data!DU60,Data!DW60,Data!DY60,Data!EA60,Data!EC60,Data!EE60,Data!EG60,Data!EI60,Data!EK60,Data!EM60,Data!EO60,Data!EQ60,Data!ES60) -> 0 | G59: =F59-E59 -> -155.76522 | H59: =IF(E59=0,IF(F59>0,"New",0),(F59-E59)/E59) -> -1 | I59: =SUM(Data!J60,Data!L60,Data!N60,Data!P60,Data!R60,Data!T60,Data!V60,Data!X60,Data!Z60,Data!AB60,Data!AD60,Data!AF60,Data!AH60,Data!AJ60,Data!AL60,Data!AN60,Data!AP60,Data!AR60,Data!AT60) -> 1.12 | J59: =SUM(Data!DJ60,Data!DL60,Data!DN60,Data!DP60,Data!DR60,Data!DT60,Data!DV60,Data!DX60,Data!DZ60,Data!EB60,Data!ED60,Data!EF60,Data!EH60,Data!EJ60,Data!EL60,Data!EN60,Data!EP60,Data!ER60,Data!ET60) -> 0 | K59: =J59-I59 -> -1.12 | L59: =IF(I59=0,IF(J59>0,"New",0),(J59-I59)/I59) -> -1 | M59: =IF(F59=0,"No 2026 Sales",IF(E59=0,"New Product",IF(AND(ISNUMBER(H59),H59>0.1),"↑ Strong Growth",IF(AND(ISNUMBER(H59),H59>0),"↗ Growth",IF(AND(ISNUMBER(H59),H59<-0.1),"↓ Strong Decline",IF(AND(ISNUMBER(H59),H59<0),"↘ Decline","→ Stable")))))) -> No 2026 Sales
A60: =Data!A61 -> 202 | B60: =Data!B61 -> BEEF | C60: =Data!C61 -> 12118 | D60: =Data!D61 | E60: =SUM(Data!I61,Data!K61,Data!M61,Data!O61,Data!Q61,Data!S61,Data!U61,Data!W61,Data!Y61,Data!AA61,Data!AC61,Data!AE61,Data!AG61,Data!AI61,Data!AK61,Data!AM61,Data!AO61,Data!AQ61,Data!AS61) -> 7458.287 | F60: =SUM(Data!DI61,Data!DK61,Data!DM61,Data!DO61,Data!DQ61,Data!DS61,Data!DU61,Data!DW61,Data!DY61,Data!EA61,Data!EC61,Data!EE61,Data!EG61,Data!EI61,Data!EK61,Data!EM61,Data!EO61,Data!EQ61,Data!ES61) -> 0 | G60: =F60-E60 -> -7458.287 | H60: =IF(E60=0,IF(F60>0,"New",0),(F60-E60)/E60) -> -1 | I60: =SUM(Data!J61,Data!L61,Data!N61,Data!P61,Data!R61,Data!T61,Data!V61,Data!X61,Data!Z61,Data!AB61,Data!AD61,Data!AF61,Data!AH61,Data!AJ61,Data!AL61,Data!AN61,Data!AP61,Data!AR61,Data!AT61) -> 56.796 | J60: =SUM(Data!DJ61,Data!DL61,Data!DN61,Data!DP61,Data!DR61,Data!DT61,Data!DV61,Data!DX61,Data!DZ61,Data!EB61,Data!ED61,Data!EF61,Data!EH61,Data!EJ61,Data!EL61,Data!EN61,Data!EP61,Data!ER61,Data!ET61) -> 0 | K60: =J60-I60 -> -56.796 | L60: =IF(I60=0,IF(J60>0,"New",0),(J60-I60)/I60) -> -1 | M60: =IF(F60=0,"No 2026 Sales",IF(E60=0,"New Product",IF(AND(ISNUMBER(H60),H60>0.1),"↑ Strong Growth",IF(AND(ISNUMBER(H60),H60>0),"↗ Growth",IF(AND(ISNUMBER(H60),H60<-0.1),"↓ Strong Decline",IF(AND(ISNUMBER(H60),H60<0),"↘ Decline","→ Stable")))))) -> No 2026 Sales
A61: =Data!A62 -> 202 | B61: =Data!B62 -> BEEF | C61: =Data!C62 -> 12119 | D61: =Data!D62 | E61: =SUM(Data!I62,Data!K62,Data!M62,Data!O62,Data!Q62,Data!S62,Data!U62,Data!W62,Data!Y62,Data!AA62,Data!AC62,Data!AE62,Data!AG62,Data!AI62,Data!AK62,Data!AM62,Data!AO62,Data!AQ62,Data!AS62) -> 0 | F61: =SUM(Data!DI62,Data!DK62,Data!DM62,Data!DO62,Data!DQ62,Data!DS62,Data!DU62,Data!DW62,Data!DY62,Data!EA62,Data!EC62,Data!EE62,Data!EG62,Data!EI62,Data!EK62,Data!EM62,Data!EO62,Data!EQ62,Data!ES62) -> 0 | G61: =F61-E61 -> 0 | H61: =IF(E61=0,IF(F61>0,"New",0),(F61-E61)/E61) -> 0 | I61: =SUM(Data!J62,Data!L62,Data!N62,Data!P62,Data!R62,Data!T62,Data!V62,Data!X62,Data!Z62,Data!AB62,Data!AD62,Data!AF62,Data!AH62,Data!AJ62,Data!AL62,Data!AN62,Data!AP62,Data!AR62,Data!AT62) -> 0 | J61: =SUM(Data!DJ62,Data!DL62,Data!DN62,Data!DP62,Data!DR62,Data!DT62,Data!DV62,Data!DX62,Data!DZ62,Data!EB62,Data!ED62,Data!EF62,Data!EH62,Data!EJ62,Data!EL62,Data!EN62,Data!EP62,Data!ER62,Data!ET62) -> 0 | K61: =J61-I61 -> 0 | L61: =IF(I61=0,IF(J61>0,"New",0),(J61-I61)/I61) -> 0 | M61: =IF(F61=0,"No 2026 Sales",IF(E61=0,"New Product",IF(AND(ISNUMBER(H61),H61>0.1),"↑ Strong Growth",IF(AND(ISNUMBER(H61),H61>0),"↗ Growth",IF(AND(ISNUMBER(H61),H61<-0.1),"↓ Strong Decline",IF(AND(ISNUMBER(H61),H61<0),"↘ Decline","→ Stable")))))) -> No 2026 Sales
... A552: =Data!A553 -> 229 | B552: =Data!B553 -> INGREDIENTS | C552: =Data!C553 -> 63808 | D552: =Data!D553 | E552: =SUM(Data!I553,Data!K553,Data!M553,Data!O553,Data!Q553,Data!S553,Data!U553,Data!W553,Data!Y553,Data!AA553,Data!AC553,Data!AE553,Data!AG553,Data!AI553,Data!AK553,Data!AM553,Data!AO553,Data!AQ553,Data!AS553) -> 0 | F552: =SUM(Data!DI553,Data!DK553,Data!DM553,Data!DO553,Data!DQ553,Data!DS553,Data!DU553,Data!DW553,Data!DY553,Data!EA553,Data!EC553,Data!EE553,Data!EG553,Data!EI553,Data!EK553,Data!EM553,Data!EO553,Data!EQ553,Data!ES553) -> 0 | G552: =F552-E552 -> 0 | H552: =IF(E552=0,IF(F552>0,"New",0),(F552-E552)/E552) -> 0 | I552: =SUM(Data!J553,Data!L553,Data!N553,Data!P553,Data!R553,Data!T553,Data!V553,Data!X553,Data!Z553,Data!AB553,Data!AD553,Data!AF553,Data!AH553,Data!AJ553,Data!AL553,Data!AN553,Data!AP553,Data!AR553,Data!AT553) -> 0 | J552: =SUM(Data!DJ553,Data!DL553,Data!DN553,Data!DP553,Data!DR553,Data!DT553,Data!DV553,Data!DX553,Data!DZ553,Data!EB553,Data!ED553,Data!EF553,Data!EH553,Data!EJ553,Data!EL553,Data!EN553,Data!EP553,Data!ER553,Data!ET553) -> 0 | K552: =J552-I552 -> 0 | L552: =IF(I552=0,IF(J552>0,"New",0),(J552-I552)/I552) -> 0 | M552: =IF(F552=0,"No 2026 Sales",IF(E552=0,"New Product",IF(AND(ISNUMBER(H552),H552>0.1),"↑ Strong Growth",IF(AND(ISNUMBER(H552),H552>0),"↗ Growth",IF(AND(ISNUMBER(H552),H552<-0.1),"↓ Strong Decline",IF(AND(ISNUMBER(H552),H552<0),"↘ Decline","→ Stable")))))) -> No 2026 Sales
A553: =Data!A554 | B553: =Data!B554 | C553: =Data!C554 | D553: =Data!D554 | E553: =SUM(Data!I554,Data!CA554,Data!M554,Data!O554,Data!Q554,Data!BA554,Data!W554,Data!S554,Data!AA554,Data!CS554,Data!AE554,Data!AG554,Data!AI554,Data!BS554,Data!AM554,Data!AO554,Data!AQ554) -> 0 | F553: =SUM(Data!DK554,Data!DM554,Data!DO554,Data!DQ554,Data!DS554,Data!DU554,Data!DY554,Data!EA554,Data!EC554,Data!EE554,Data!EG554,Data!EI554,Data!EK554,Data!EM554,Data!EO554,Data!EQ554,Data!ES554) -> 0 | G553: =F553-E553 -> 0 | H553: =IF(E553=0,IF(F553>0,"New",0),(F553-E553)/E553) -> 0 | I553: =SUM(Data!J554,Data!CB554,Data!N554,Data!P554,Data!R554,Data!BB554,Data!X554,Data!T554,Data!AB554,Data!CT554,Data!AF554,Data!AH554,Data!AJ554,Data!BT554,Data!AN554,Data!AP554,Data!AR554) -> 0 | J553: =SUM(Data!DL554,Data!DN554,Data!DP554,Data!DR554,Data!DT554,Data!DV554,Data!DZ554,Data!EB554,Data!ED554,Data!EF554,Data!EH554,Data!EJ554,Data!EL554,Data!EN554,Data!EP554,Data!ER554,Data!ET554) -> 0 | K553: =J553-I553 -> 0 | L553: =IF(I553=0,IF(J553>0,"New",0),(J553-I553)/I553) -> 0 | M553: =IF(F553=0,"No 2026 Sales",IF(E553=0,"New Product",IF(AND(ISNUMBER(H553),H553>0.1),"↑ Strong Growth",IF(AND(ISNUMBER(H553),H553>0),"↗ Growth",IF(AND(ISNUMBER(H553),H553<-0.1),"↓ Strong Decline",IF(AND(ISNUMBER(H553),H553<0),"↘ Decline","→ Stable")))))) -> No 2026 Sales
A554: =Data!A555 -> 0 | B554: =Data!B555 -> 0 | C554: =Data!C555 -> 0 | D554: =Data!D555 -> 0 | E554: =SUM(Data!I555,Data!CA555,Data!M555,Data!O555,Data!Q555,Data!BA555,Data!W555,Data!S555,Data!AA555,Data!CS555,Data!AE555,Data!AG555,Data!AI555,Data!BS555,Data!AM555,Data!AO555,Data!AQ555) -> 0 | F554: =SUM(Data!DK555,Data!DM555,Data!DO555,Data!DQ555,Data!DS555,Data!DU555,Data!DY555,Data!EA555,Data!EC555,Data!EE555,Data!EG555,Data!EI555,Data!EK555,Data!EM555,Data!EO555,Data!EQ555,Data!ES555) -> 0 | G554: =F554-E554 -> 0 | H554: =IF(E554=0,IF(F554>0,"New",0),(F554-E554)/E554) -> 0 | I554: =SUM(Data!J555,Data!CB555,Data!N555,Data!P555,Data!R555,Data!BB555,Data!X555,Data!T555,Data!AB555,Data!CT555,Data!AF555,Data!AH555,Data!AJ555,Data!BT555,Data!AN555,Data!AP555,Data!AR555) -> 0 | J554: =SUM(Data!DL555,Data!DN555,Data!DP555,Data!DR555,Data!DT555,Data!DV555,Data!DZ555,Data!EB555,Data!ED555,Data!EF555,Data!EH555,Data!EJ555,Data!EL555,Data!EN555,Data!EP555,Data!ER555,Data!ET555) -> 0 | K554: =J554-I554 -> 0 | L554: =IF(I554=0,IF(J554>0,"New",0),(J554-I554)/I554) -> 0 | M554: =IF(F554=0,"No 2026 Sales",IF(E554=0,"New Product",IF(AND(ISNUMBER(H554),H554>0.1),"↑ Strong Growth",IF(AND(ISNUMBER(H554),H554>0),"↗ Growth",IF(AND(ISNUMBER(H554),H554<-0.1),"↓ Strong Decline",IF(AND(ISNUMBER(H554),H554<0),"↘ Decline","→ Stable")))))) -> No 2026 Sales

Sheet Target Setting
A1: 🎯 Weekly Target Setting Tool | T1: 📅 SASSA Payment Dates 2026
A2: Select a future week (Monday date) to set sales and quantity targets by sub-department and product. | T2: Month | U2: Date | V2: Grant Type
A3: 💡 TIP: Use the dropdown in B5 to select the target week. YTD data covers weeks 1-19 (matching weeks for YoY comparison). 2026 Week 1 starts 29/12/2025; 2025 Week 1 starts 30/12/2024. | T3: January | U3: 46028 | V3: Old Age/Pension
E4: 2025 YTD Total: | F4: =E187 -> 1348847.8 | G4: 2026 YTD Total: | H4: =G187 -> 2133287.9 | I4: YoY Growth: | J4: =IF(F4>0,(H4-F4)/F4,"") -> 0.58156314 | K4: Avg Sales/Wk: | L4: =I187 -> 733.84516 | M4: Avg Qty/Wk: | N4: =J187 -> 8.4039677 | O4: Products: | P4: =COUNTA(C8:C184) -> 153 | Q4: SASSA Week: | R4: =IF(U40>0,U40&" payment(s)","None") -> None | T4: January | U4: 46029 | V4: Disability
A5: Select Target Week: | B5: 25/05/2026 | D5: Last Actual Week: | E5: 46146 | G5: Prior Month: | H5: 46111 | L5: Prior Year: | M5: =IFERROR(INDEX('Week Mapping'!$B$5:$B$23,MATCH(DATE(RIGHT($B$5,4),MID($B$5,4,2),LEFT($B$5,2)),'Week Mapping'!$G$5:$G$23,1)),DATE(RIGHT($B$5,4)-1,MID($B$5,4,2),LEFT($B$5,2))) -> 45782 | T5: January | U5: 46030 | V5: Children & Others
I6: 2026 Avg/Wk (19 wks) | K6: ="Prior Wk: "&TEXT($E$5,"yyyy/mm/dd") -> Prior Wk: 2026/05/04 | M6: ="Prior Month: "&TEXT($H$5,"yyyy/mm/dd") -> Prior Month: 2026/03/30 | O6: ="Prior Year: "&TEXT($M$5,"yyyy/mm/dd") -> Prior Year: 2025/05/05 | Q6: TARGET INPUT | T6: February | U6: 46056 | V6: Old Age/Pension
A7: Sub-Dept Code | B7: Sub-Department | C7: Product Code | D7: Product Description | E7: 2025 YTD Sales (Wk1-19) | F7: 2025 YTD Qty (Wk1-19) | G7: 2026 YTD Sales (Wk1-19) | H7: 2026 YTD Qty (Wk1-19) | I7: Avg Sales/Wk | J7: Avg Qty/Wk | K7: Prior Week Sales | L7: Prior Week Qty | M7: Prior Month Sales | N7: Prior Month Qty | O7: Prior Year Sales | P7: Prior Year Qty | Q7: Target Sales (Auto) | R7: Target Qty | T7: February | U7: 46057 | V7: Disability
A8: 201 | B8: BUTCHERY | C8: 99990201 | D8: BUTCHERY 15% | E8: 18398.026 | F8: 673 | G8: =SUMIF(Data!$C:$C,C8,Data!$DI:$DI)+SUMIF(Data!$C:$C,C8,Data!$DK:$DK)+SUMIF(Data!$C:$C,C8,Data!$DM:$DM)+SUMIF(Data!$C:$C,C8,Data!$DO:$DO)+SUMIF(Data!$C:$C,C8,Data!$DQ:$DQ)+SUMIF(Data!$C:$C,C8,Data!$DS:$DS)+SUMIF(Data!$C:$C,C8,Data!$DU:$DU)+SUMIF(Data!$C:$C,C8,Data!$DW:$DW)+SUMIF(Data!$C:$C,C8,Data!$DY:$DY)+SUMIF(Data!$C:$C,C8,Data!$EA:$EA)+SUMIF(Data!$C:$C,C8,Data!$EC:$EC)+SUMIF(Data!$C:$C,C8,Data!$EE:$EE)+SUMIF(Data!$C:$C,C8,Data!$EG:$EG)+SUMIF(Data!$C:$C,C8,Data!$EI:$EI)+SUMIF(Data!$C:$C,C8,Data!$EK:$EK)+SUMIF(Data!$C:$C,C8,Data!$EM:$EM)+SUMIF(Data!$C:$C,C8,Data!$EO:$EO)+SUMIF(Data!$C:$C,C8,Data!$EQ:$EQ)+SUMIF(Data!$C:$C,C8,Data!$ES:$ES) -> 14401.678 | H8: =SUMIF(Data!$C:$C,C8,Data!$DJ:$DJ)+SUMIF(Data!$C:$C,C8,Data!$DL:$DL)+SUMIF(Data!$C:$C,C8,Data!$DN:$DN)+SUMIF(Data!$C:$C,C8,Data!$DP:$DP)+SUMIF(Data!$C:$C,C8,Data!$DR:$DR)+SUMIF(Data!$C:$C,C8,Data!$DT:$DT)+SUMIF(Data!$C:$C,C8,Data!$DV:$DV)+SUMIF(Data!$C:$C,C8,Data!$DX:$DX)+SUMIF(Data!$C:$C,C8,Data!$DZ:$DZ)+SUMIF(Data!$C:$C,C8,Data!$EB:$EB)+SUMIF(Data!$C:$C,C8,Data!$ED:$ED)+SUMIF(Data!$C:$C,C8,Data!$EF:$EF)+SUMIF(Data!$C:$C,C8,Data!$EH:$EH)+SUMIF(Data!$C:$C,C8,Data!$EJ:$EJ)+SUMIF(Data!$C:$C,C8,Data!$EL:$EL)+SUMIF(Data!$C:$C,C8,Data!$EN:$EN)+SUMIF(Data!$C:$C,C8,Data!$EP:$EP)+SUMIF(Data!$C:$C,C8,Data!$ER:$ER)+SUMIF(Data!$C:$C,C8,Data!$ET:$ET) -> 196 | I8: =G8/19 -> 757.98307 | J8: =H8/19 -> 10.315789 | K8: =IFERROR(INDEX(Data!$ES:$ES,MATCH(C8,Data!$C:$C,0)),0) -> 4007.2435 | L8: =IFERROR(INDEX(Data!$ET:$ET,MATCH(C8,Data!$C:$C,0)),0) -> 9 | M8: =IFERROR(INDEX(Data!$I$3:$ER$553,MATCH($C8,Data!$C$3:$C$553,0),MATCH(DATE(RIGHT($B$5,4),MID($B$5,4,2),LEFT($B$5,2))-42,Data!$I$1:$ER$1,0)),0) -> -272.33913 | N8: {=IFERROR(INDEX(Data!$I$3:$ER$553,MATCH($C8,Data!$C$3:$C$553,0),MATCH(DATE(RIGHT($B$5,4),MID($B$5,4,2),LEFT($B$5,2))-42,Data!$I$1:$ER$1,0)+1),0)} -> -2 | O8: =IFERROR(INDEX(Data!$I$3:$ER$553,MATCH($C8,Data!$C$3:$C$553,0),MATCH($M$5,Data!$I$1:$ER$1,0)),0) -> 2280.9652 | P8: {=IFERROR(INDEX(Data!$I$3:$ER$553,MATCH($C8,Data!$C$3:$C$553,0),MATCH($M$5,Data!$I$1:$ER$1,0)+1),0)} -> 9 | Q8: =IF(R8="","",IF(H8=0,0,R8*(G8/H8))) | T8: February | U8: 46058 | V8: Children & Others
A9: 201 | B9: BUTCHERY | C9: 56247 | D9: B/WORS ROLL BUTCH | E9: 51766.8 | F9: 2956 | G9: =SUMIF(Data!$C:$C,C9,Data!$DI:$DI)+SUMIF(Data!$C:$C,C9,Data!$DK:$DK)+SUMIF(Data!$C:$C,C9,Data!$DM:$DM)+SUMIF(Data!$C:$C,C9,Data!$DO:$DO)+SUMIF(Data!$C:$C,C9,Data!$DQ:$DQ)+SUMIF(Data!$C:$C,C9,Data!$DS:$DS)+SUMIF(Data!$C:$C,C9,Data!$DU:$DU)+SUMIF(Data!$C:$C,C9,Data!$DW:$DW)+SUMIF(Data!$C:$C,C9,Data!$DY:$DY)+SUMIF(Data!$C:$C,C9,Data!$EA:$EA)+SUMIF(Data!$C:$C,C9,Data!$EC:$EC)+SUMIF(Data!$C:$C,C9,Data!$EE:$EE)+SUMIF(Data!$C:$C,C9,Data!$EG:$EG)+SUMIF(Data!$C:$C,C9,Data!$EI:$EI)+SUMIF(Data!$C:$C,C9,Data!$EK:$EK)+SUMIF(Data!$C:$C,C9,Data!$EM:$EM)+SUMIF(Data!$C:$C,C9,Data!$EO:$EO)+SUMIF(Data!$C:$C,C9,Data!$EQ:$EQ)+SUMIF(Data!$C:$C,C9,Data!$ES:$ES) -> 6837.8 | H9: =SUMIF(Data!$C:$C,C9,Data!$DJ:$DJ)+SUMIF(Data!$C:$C,C9,Data!$DL:$DL)+SUMIF(Data!$C:$C,C9,Data!$DN:$DN)+SUMIF(Data!$C:$C,C9,Data!$DP:$DP)+SUMIF(Data!$C:$C,C9,Data!$DR:$DR)+SUMIF(Data!$C:$C,C9,Data!$DT:$DT)+SUMIF(Data!$C:$C,C9,Data!$DV:$DV)+SUMIF(Data!$C:$C,C9,Data!$DX:$DX)+SUMIF(Data!$C:$C,C9,Data!$DZ:$DZ)+SUMIF(Data!$C:$C,C9,Data!$EB:$EB)+SUMIF(Data!$C:$C,C9,Data!$ED:$ED)+SUMIF(Data!$C:$C,C9,Data!$EF:$EF)+SUMIF(Data!$C:$C,C9,Data!$EH:$EH)+SUMIF(Data!$C:$C,C9,Data!$EJ:$EJ)+SUMIF(Data!$C:$C,C9,Data!$EL:$EL)+SUMIF(Data!$C:$C,C9,Data!$EN:$EN)+SUMIF(Data!$C:$C,C9,Data!$EP:$EP)+SUMIF(Data!$C:$C,C9,Data!$ER:$ER)+SUMIF(Data!$C:$C,C9,Data!$ET:$ET) -> 382 | I9: =G9/19 -> 359.88421 | J9: =H9/19 -> 20.105263 | K9: =IFERROR(INDEX(Data!$ES:$ES,MATCH(C9,Data!$C:$C,0)),0) -> 0 | L9: =IFERROR(INDEX(Data!$ET:$ET,MATCH(C9,Data!$C:$C,0)),0) -> 0 | M9: =IFERROR(INDEX(Data!$I$3:$ER$553,MATCH($C9,Data!$C$3:$C$553,0),MATCH(DATE(RIGHT($B$5,4),MID($B$5,4,2),LEFT($B$5,2))-42,Data!$I$1:$ER$1,0)),0) -> 0 | N9: {=IFERROR(INDEX(Data!$I$3:$ER$553,MATCH($C9,Data!$C$3:$C$553,0),MATCH(DATE(RIGHT($B$5,4),MID($B$5,4,2),LEFT($B$5,2))-42,Data!$I$1:$ER$1,0)+1),0)} -> 0 | O9: =IFERROR(INDEX(Data!$I$3:$ER$553,MATCH($C9,Data!$C$3:$C$553,0),MATCH($M$5,Data!$I$1:$ER$1,0)),0) -> 4152.8 | P9: {=IFERROR(INDEX(Data!$I$3:$ER$553,MATCH($C9,Data!$C$3:$C$553,0),MATCH($M$5,Data!$I$1:$ER$1,0)+1),0)} -> 232 | Q9: =IF(R9="","",IF(H9=0,0,R9*(G9/H9))) | T9: March | U9: 46084 | V9: Old Age/Pension
A10: 201 | B10: BUTCHERY | C10: 61370 | D10: SPAR T&T BEEF 35GR BILTONG ORI | E10: 0 | F10: 0 | G10: =SUMIF(Data!$C:$C,C10,Data!$DI:$DI)+SUMIF(Data!$C:$C,C10,Data!$DK:$DK)+SUMIF(Data!$C:$C,C10,Data!$DM:$DM)+SUMIF(Data!$C:$C,C10,Data!$DO:$DO)+SUMIF(Data!$C:$C,C10,Data!$DQ:$DQ)+SUMIF(Data!$C:$C,C10,Data!$DS:$DS)+SUMIF(Data!$C:$C,C10,Data!$DU:$DU)+SUMIF(Data!$C:$C,C10,Data!$DW:$DW)+SUMIF(Data!$C:$C,C10,Data!$DY:$DY)+SUMIF(Data!$C:$C,C10,Data!$EA:$EA)+SUMIF(Data!$C:$C,C10,Data!$EC:$EC)+SUMIF(Data!$C:$C,C10,Data!$EE:$EE)+SUMIF(Data!$C:$C,C10,Data!$EG:$EG)+SUMIF(Data!$C:$C,C10,Data!$EI:$EI)+SUMIF(Data!$C:$C,C10,Data!$EK:$EK)+SUMIF(Data!$C:$C,C10,Data!$EM:$EM)+SUMIF(Data!$C:$C,C10,Data!$EO:$EO)+SUMIF(Data!$C:$C,C10,Data!$EQ:$EQ)+SUMIF(Data!$C:$C,C10,Data!$ES:$ES) -> 302.50435 | H10: =SUMIF(Data!$C:$C,C10,Data!$DJ:$DJ)+SUMIF(Data!$C:$C,C10,Data!$DL:$DL)+SUMIF(Data!$C:$C,C10,Data!$DN:$DN)+SUMIF(Data!$C:$C,C10,Data!$DP:$DP)+SUMIF(Data!$C:$C,C10,Data!$DR:$DR)+SUMIF(Data!$C:$C,C10,Data!$DT:$DT)+SUMIF(Data!$C:$C,C10,Data!$DV:$DV)+SUMIF(Data!$C:$C,C10,Data!$DX:$DX)+SUMIF(Data!$C:$C,C10,Data!$DZ:$DZ)+SUMIF(Data!$C:$C,C10,Data!$EB:$EB)+SUMIF(Data!$C:$C,C10,Data!$ED:$ED)+SUMIF(Data!$C:$C,C10,Data!$EF:$EF)+SUMIF(Data!$C:$C,C10,Data!$EH:$EH)+SUMIF(Data!$C:$C,C10,Data!$EJ:$EJ)+SUMIF(Data!$C:$C,C10,Data!$EL:$EL)+SUMIF(Data!$C:$C,C10,Data!$EN:$EN)+SUMIF(Data!$C:$C,C10,Data!$EP:$EP)+SUMIF(Data!$C:$C,C10,Data!$ER:$ER)+SUMIF(Data!$C:$C,C10,Data!$ET:$ET) -> 12 | I10: =G10/19 -> 15.921281 | J10: =H10/19 -> 0.63157895 | K10: =IFERROR(INDEX(Data!$ES:$ES,MATCH(C10,Data!$C:$C,0)),0) -> 0 | L10: =IFERROR(INDEX(Data!$ET:$ET,MATCH(C10,Data!$C:$C,0)),0) -> 0 | M10: =IFERROR(INDEX(Data!$I$3:$ER$553,MATCH($C10,Data!$C$3:$C$553,0),MATCH(DATE(RIGHT($B$5,4),MID($B$5,4,2),LEFT($B$5,2))-42,Data!$I$1:$ER$1,0)),0) -> 0 | N10: {=IFERROR(INDEX(Data!$I$3:$ER$553,MATCH($C10,Data!$C$3:$C$553,0),MATCH(DATE(RIGHT($B$5,4),MID($B$5,4,2),LEFT($B$5,2))-42,Data!$I$1:$ER$1,0)+1),0)} -> 0 | O10: =IFERROR(INDEX(Data!$I$3:$ER$553,MATCH($C10,Data!$C$3:$C$553,0),MATCH($M$5,Data!$I$1:$ER$1,0)),0) -> 0 | P10: {=IFERROR(INDEX(Data!$I$3:$ER$553,MATCH($C10,Data!$C$3:$C$553,0),MATCH($M$5,Data!$I$1:$ER$1,0)+1),0)} -> 0 | Q10: =IF(R10="","",IF(H10=0,0,R10*(G10/H10))) | T10: March | U10: 46085 | V10: Disability
A11: BUTCHERY Subtotal | E11: =SUM(E8:E10) -> 70164.826 | F11: =SUM(F8:F10) -> 3629 | G11: =SUM(G8:G10) -> 21541.983 | H11: =SUM(H8:H10) -> 590 | I11: =AVERAGE(I8:I10) -> 377.92952 | J11: =AVERAGE(J8:J10) -> 10.350877 | K11: =SUM(K8:K10) -> 4007.2435 | L11: =SUM(L8:L10) -> 9 | M11: =SUM(M8:M10) -> -272.33913 | N11: =SUM(N8:N10) -> -2 | O11: =SUM(O8:O10) -> 6433.7652 | P11: =SUM(P8:P10) -> 241 | Q11: =SUM(Q8:Q10) -> 0 | R11: =SUM(R8:R10) -> 0 | T11: March | U11: 46086 | V11: Children & Others
T12: April | U12: 46114 | V12: Old Age/Pension
A13: 202 | B13: BEEF | C13: 34172 | D13: BULK BEEF SIRLOIN | E13: 51348.609 | F13: 341.628 | G13: =SUMIF(Data!$C:$C,C13,Data!$DI:$DI)+SUMIF(Data!$C:$C,C13,Data!$DK:$DK)+SUMIF(Data!$C:$C,C13,Data!$DM:$DM)+SUMIF(Data!$C:$C,C13,Data!$DO:$DO)+SUMIF(Data!$C:$C,C13,Data!$DQ:$DQ)+SUMIF(Data!$C:$C,C13,Data!$DS:$DS)+SUMIF(Data!$C:$C,C13,Data!$DU:$DU)+SUMIF(Data!$C:$C,C13,Data!$DW:$DW)+SUMIF(Data!$C:$C,C13,Data!$DY:$DY)+SUMIF(Data!$C:$C,C13,Data!$EA:$EA)+SUMIF(Data!$C:$C,C13,Data!$EC:$EC)+SUMIF(Data!$C:$C,C13,Data!$EE:$EE)+SUMIF(Data!$C:$C,C13,Data!$EG:$EG)+SUMIF(Data!$C:$C,C13,Data!$EI:$EI)+SUMIF(Data!$C:$C,C13,Data!$EK:$EK)+SUMIF(Data!$C:$C,C13,Data!$EM:$EM)+SUMIF(Data!$C:$C,C13,Data!$EO:$EO)+SUMIF(Data!$C:$C,C13,Data!$EQ:$EQ)+SUMIF(Data!$C:$C,C13,Data!$ES:$ES) -> 72748.478 | H13: =SUMIF(Data!$C:$C,C13,Data!$DJ:$DJ)+SUMIF(Data!$C:$C,C13,Data!$DL:$DL)+SUMIF(Data!$C:$C,C13,Data!$DN:$DN)+SUMIF(Data!$C:$C,C13,Data!$DP:$DP)+SUMIF(Data!$C:$C,C13,Data!$DR:$DR)+SUMIF(Data!$C:$C,C13,Data!$DT:$DT)+SUMIF(Data!$C:$C,C13,Data!$DV:$DV)+SUMIF(Data!$C:$C,C13,Data!$DX:$DX)+SUMIF(Data!$C:$C,C13,Data!$DZ:$DZ)+SUMIF(Data!$C:$C,C13,Data!$EB:$EB)+SUMIF(Data!$C:$C,C13,Data!$ED:$ED)+SUMIF(Data!$C:$C,C13,Data!$EF:$EF)+SUMIF(Data!$C:$C,C13,Data!$EH:$EH)+SUMIF(Data!$C:$C,C13,Data!$EJ:$EJ)+SUMIF(Data!$C:$C,C13,Data!$EL:$EL)+SUMIF(Data!$C:$C,C13,Data!$EN:$EN)+SUMIF(Data!$C:$C,C13,Data!$EP:$EP)+SUMIF(Data!$C:$C,C13,Data!$ER:$ER)+SUMIF(Data!$C:$C,C13,Data!$ET:$ET) -> 479.255 | I13: =G13/19 -> 3828.8673 | J13: =H13/19 -> 25.223947 | K13: =IFERROR(INDEX(Data!$ES:$ES,MATCH(C13,Data!$C:$C,0)),0) -> 3109.8957 | L13: =IFERROR(INDEX(Data!$ET:$ET,MATCH(C13,Data!$C:$C,0)),0) -> 18.824 | M13: =IFERROR(INDEX(Data!$I$3:$ER$553,MATCH($C13,Data!$C$3:$C$553,0),MATCH(DATE(RIGHT($B$5,4),MID($B$5,4,2),LEFT($B$5,2))-42,Data!$I$1:$ER$1,0)),0) -> 1135.3565 | N13: {=IFERROR(INDEX(Data!$I$3:$ER$553,MATCH($C13,Data!$C$3:$C$553,0),MATCH(DATE(RIGHT($B$5,4),MID($B$5,4,2),LEFT($B$5,2))-42,Data!$I$1:$ER$1,0)+1),0)} -> 5.935 | O13: =IFERROR(INDEX(Data!$I$3:$ER$553,MATCH($C13,Data!$C$3:$C$553,0),MATCH($M$5,Data!$I$1:$ER$1,0)),0) -> 1982.1826 | P13: {=IFERROR(INDEX(Data!$I$3:$ER$553,MATCH($C13,Data!$C$3:$C$553,0),MATCH($M$5,Data!$I$1:$ER$1,0)+1),0)} -> 11.998 | Q13: =IF(R13="","",IF(H13=0,0,R13*(G13/H13))) | T13: April | U13: 46119 | V13: Disability
A14: 202 | B14: BEEF | C14: 53487 | D14: STEAK PACK | E14: 62627.687 | F14: 682.951 | G14: =SUMIF(Data!$C:$C,C14,Data!$DI:$DI)+SUMIF(Data!$C:$C,C14,Data!$DK:$DK)+SUMIF(Data!$C:$C,C14,Data!$DM:$DM)+SUMIF(Data!$C:$C,C14,Data!$DO:$DO)+SUMIF(Data!$C:$C,C14,Data!$DQ:$DQ)+SUMIF(Data!$C:$C,C14,Data!$DS:$DS)+SUMIF(Data!$C:$C,C14,Data!$DU:$DU)+SUMIF(Data!$C:$C,C14,Data!$DW:$DW)+SUMIF(Data!$C:$C,C14,Data!$DY:$DY)+SUMIF(Data!$C:$C,C14,Data!$EA:$EA)+SUMIF(Data!$C:$C,C14,Data!$EC:$EC)+SUMIF(Data!$C:$C,C14,Data!$EE:$EE)+SUMIF(Data!$C:$C,C14,Data!$EG:$EG)+SUMIF(Data!$C:$C,C14,Data!$EI:$EI)+SUMIF(Data!$C:$C,C14,Data!$EK:$EK)+SUMIF(Data!$C:$C,C14,Data!$EM:$EM)+SUMIF(Data!$C:$C,C14,Data!$EO:$EO)+SUMIF(Data!$C:$C,C14,Data!$EQ:$EQ)+SUMIF(Data!$C:$C,C14,Data!$ES:$ES) -> 60935.896 | H14: =SUMIF(Data!$C:$C,C14,Data!$DJ:$DJ)+SUMIF(Data!$C:$C,C14,Data!$DL:$DL)+SUMIF(Data!$C:$C,C14,Data!$DN:$DN)+SUMIF(Data!$C:$C,C14,Data!$DP:$DP)+SUMIF(Data!$C:$C,C14,Data!$DR:$DR)+SUMIF(Data!$C:$C,C14,Data!$DT:$DT)+SUMIF(Data!$C:$C,C14,Data!$DV:$DV)+SUMIF(Data!$C:$C,C14,Data!$DX:$DX)+SUMIF(Data!$C:$C,C14,Data!$DZ:$DZ)+SUMIF(Data!$C:$C,C14,Data!$EB:$EB)+SUMIF(Data!$C:$C,C14,Data!$ED:$ED)+SUMIF(Data!$C:$C,C14,Data!$EF:$EF)+SUMIF(Data!$C:$C,C14,Data!$EH:$EH)+SUMIF(Data!$C:$C,C14,Data!$EJ:$EJ)+SUMIF(Data!$C:$C,C14,Data!$EL:$EL)+SUMIF(Data!$C:$C,C14,Data!$EN:$EN)+SUMIF(Data!$C:$C,C14,Data!$EP:$EP)+SUMIF(Data!$C:$C,C14,Data!$ER:$ER)+SUMIF(Data!$C:$C,C14,Data!$ET:$ET) -> 508.794 | I14: =G14/19 -> 3207.1524 | J14: =H14/19 -> 26.778632 | K14: =IFERROR(INDEX(Data!$ES:$ES,MATCH(C14,Data!$C:$C,0)),0) -> 1804.0609 | L14: =IFERROR(INDEX(Data!$ET:$ET,MATCH(C14,Data!$C:$C,0)),0) -> 14.82 | M14: =IFERROR(INDEX(Data!$I$3:$ER$553,MATCH($C14,Data!$C$3:$C$553,0),MATCH(DATE(RIGHT($B$5,4),MID($B$5,4,2),LEFT($B$5,2))-42,Data!$I$1:$ER$1,0)),0) -> 4882.8261 | N14: {=IFERROR(INDEX(Data!$I$3:$ER$553,MATCH($C14,Data!$C$3:$C$553,0),MATCH(DATE(RIGHT($B$5,4),MID($B$5,4,2),LEFT($B$5,2))-42,Data!$I$1:$ER$1,0)+1),0)} -> 40.112 | O14: =IFERROR(INDEX(Data!$I$3:$ER$553,MATCH($C14,Data!$C$3:$C$553,0),MATCH($M$5,Data!$I$1:$ER$1,0)),0) -> 2690.8348 | P14: {=IFERROR(INDEX(Data!$I$3:$ER$553,MATCH($C14,Data!$C$3:$C$553,0),MATCH($M$5,Data!$I$1:$ER$1,0)+1),0)} -> 30.17 | Q14: =IF(R14="","",IF(H14=0,0,R14*(G14/H14))) | T14: April | U14: 46120 | V14: Children & Others
A15: 202 | B15: BEEF | C15: 12141 | D15: BEEF SIRLOIN | E15: 39950.27 | F15: 246.641 | G15: =SUMIF(Data!$C:$C,C15,Data!$DI:$DI)+SUMIF(Data!$C:$C,C15,Data!$DK:$DK)+SUMIF(Data!$C:$C,C15,Data!$DM:$DM)+SUMIF(Data!$C:$C,C15,Data!$DO:$DO)+SUMIF(Data!$C:$C,C15,Data!$DQ:$DQ)+SUMIF(Data!$C:$C,C15,Data!$DS:$DS)+SUMIF(Data!$C:$C,C15,Data!$DU:$DU)+SUMIF(Data!$C:$C,C15,Data!$DW:$DW)+SUMIF(Data!$C:$C,C15,Data!$DY:$DY)+SUMIF(Data!$C:$C,C15,Data!$EA:$EA)+SUMIF(Data!$C:$C,C15,Data!$EC:$EC)+SUMIF(Data!$C:$C,C15,Data!$EE:$EE)+SUMIF(Data!$C:$C,C15,Data!$EG:$EG)+SUMIF(Data!$C:$C,C15,Data!$EI:$EI)+SUMIF(Data!$C:$C,C15,Data!$EK:$EK)+SUMIF(Data!$C:$C,C15,Data!$EM:$EM)+SUMIF(Data!$C:$C,C15,Data!$EO:$EO)+SUMIF(Data!$C:$C,C15,Data!$EQ:$EQ)+SUMIF(Data!$C:$C,C15,Data!$ES:$ES) -> 51283.13 | H15: =SUMIF(Data!$C:$C,C15,Data!$DJ:$DJ)+SUMIF(Data!$C:$C,C15,Data!$DL:$DL)+SUMIF(Data!$C:$C,C15,Data!$DN:$DN)+SUMIF(Data!$C:$C,C15,Data!$DP:$DP)+SUMIF(Data!$C:$C,C15,Data!$DR:$DR)+SUMIF(Data!$C:$C,C15,Data!$DT:$DT)+SUMIF(Data!$C:$C,C15,Data!$DV:$DV)+SUMIF(Data!$C:$C,C15,Data!$DX:$DX)+SUMIF(Data!$C:$C,C15,Data!$DZ:$DZ)+SUMIF(Data!$C:$C,C15,Data!$EB:$EB)+SUMIF(Data!$C:$C,C15,Data!$ED:$ED)+SUMIF(Data!$C:$C,C15,Data!$EF:$EF)+SUMIF(Data!$C:$C,C15,Data!$EH:$EH)+SUMIF(Data!$C:$C,C15,Data!$EJ:$EJ)+SUMIF(Data!$C:$C,C15,Data!$EL:$EL)+SUMIF(Data!$C:$C,C15,Data!$EN:$EN)+SUMIF(Data!$C:$C,C15,Data!$EP:$EP)+SUMIF(Data!$C:$C,C15,Data!$ER:$ER)+SUMIF(Data!$C:$C,C15,Data!$ET:$ET) -> 318.041 | I15: =G15/19 -> 2699.1121 | J15: =H15/19 -> 16.739 | K15: =IFERROR(INDEX(Data!$ES:$ES,MATCH(C15,Data!$C:$C,0)),0) -> 1999.8609 | L15: =IFERROR(INDEX(Data!$ET:$ET,MATCH(C15,Data!$C:$C,0)),0) -> 11.5 | M15: =IFERROR(INDEX(Data!$I$3:$ER$553,MATCH($C15,Data!$C$3:$C$553,0),MATCH(DATE(RIGHT($B$5,4),MID($B$5,4,2),LEFT($B$5,2))-42,Data!$I$1:$ER$1,0)),0) -> 2229.2435 | N15: {=IFERROR(INDEX(Data!$I$3:$ER$553,MATCH($C15,Data!$C$3:$C$553,0),MATCH(DATE(RIGHT($B$5,4),MID($B$5,4,2),LEFT($B$5,2))-42,Data!$I$1:$ER$1,0)+1),0)} -> 11.147 | O15: =IFERROR(INDEX(Data!$I$3:$ER$553,MATCH($C15,Data!$C$3:$C$553,0),MATCH($M$5,Data!$I$1:$ER$1,0)),0) -> 1171.6522 | P15: {=IFERROR(INDEX(Data!$I$3:$ER$553,MATCH($C15,Data!$C$3:$C$553,0),MATCH($M$5,Data!$I$1:$ER$1,0)+1),0)} -> 6.186 | Q15: =IF(R15="","",IF(H15=0,0,R15*(G15/H15))) | T15: May | U15: 46147 | V15: Old Age/Pension
A16: 202 | B16: BEEF | C16: 63526 | D16: BEEF OXTAIL | E16: 0 | F16: 0 | G16: =SUMIF(Data!$C:$C,C16,Data!$DI:$DI)+SUMIF(Data!$C:$C,C16,Data!$DK:$DK)+SUMIF(Data!$C:$C,C16,Data!$DM:$DM)+SUMIF(Data!$C:$C,C16,Data!$DO:$DO)+SUMIF(Data!$C:$C,C16,Data!$DQ:$DQ)+SUMIF(Data!$C:$C,C16,Data!$DS:$DS)+SUMIF(Data!$C:$C,C16,Data!$DU:$DU)+SUMIF(Data!$C:$C,C16,Data!$DW:$DW)+SUMIF(Data!$C:$C,C16,Data!$DY:$DY)+SUMIF(Data!$C:$C,C16,Data!$EA:$EA)+SUMIF(Data!$C:$C,C16,Data!$EC:$EC)+SUMIF(Data!$C:$C,C16,Data!$EE:$EE)+SUMIF(Data!$C:$C,C16,Data!$EG:$EG)+SUMIF(Data!$C:$C,C16,Data!$EI:$EI)+SUMIF(Data!$C:$C,C16,Data!$EK:$EK)+SUMIF(Data!$C:$C,C16,Data!$EM:$EM)+SUMIF(Data!$C:$C,C16,Data!$EO:$EO)+SUMIF(Data!$C:$C,C16,Data!$EQ:$EQ)+SUMIF(Data!$C:$C,C16,Data!$ES:$ES) -> 30369.817 | H16: =SUMIF(Data!$C:$C,C16,Data!$DJ:$DJ)+SUMIF(Data!$C:$C,C16,Data!$DL:$DL)+SUMIF(Data!$C:$C,C16,Data!$DN:$DN)+SUMIF(Data!$C:$C,C16,Data!$DP:$DP)+SUMIF(Data!$C:$C,C16,Data!$DR:$DR)+SUMIF(Data!$C:$C,C16,Data!$DT:$DT)+SUMIF(Data!$C:$C,C16,Data!$DV:$DV)+SUMIF(Data!$C:$C,C16,Data!$DX:$DX)+SUMIF(Data!$C:$C,C16,Data!$DZ:$DZ)+SUMIF(Data!$C:$C,C16,Data!$EB:$EB)+SUMIF(Data!$C:$C,C16,Data!$ED:$ED)+SUMIF(Data!$C:$C,C16,Data!$EF:$EF)+SUMIF(Data!$C:$C,C16,Data!$EH:$EH)+SUMIF(Data!$C:$C,C16,Data!$EJ:$EJ)+SUMIF(Data!$C:$C,C16,Data!$EL:$EL)+SUMIF(Data!$C:$C,C16,Data!$EN:$EN)+SUMIF(Data!$C:$C,C16,Data!$EP:$EP)+SUMIF(Data!$C:$C,C16,Data!$ER:$ER)+SUMIF(Data!$C:$C,C16,Data!$ET:$ET) -> 361.906 | I16: =G16/19 -> 1598.4114 | J16: =H16/19 -> 19.047684 | K16: =IFERROR(INDEX(Data!$ES:$ES,MATCH(C16,Data!$C:$C,0)),0) -> 774.53043 | L16: =IFERROR(INDEX(Data!$ET:$ET,MATCH(C16,Data!$C:$C,0)),0) -> 6.494 | M16: =IFERROR(INDEX(Data!$I$3:$ER$553,MATCH($C16,Data!$C$3:$C$553,0),MATCH(DATE(RIGHT($B$5,4),MID($B$5,4,2),LEFT($B$5,2))-42,Data!$I$1:$ER$1,0)),0) -> 377.51304 | N16: {=IFERROR(INDEX(Data!$I$3:$ER$553,MATCH($C16,Data!$C$3:$C$553,0),MATCH(DATE(RIGHT($B$5,4),MID($B$5,4,2),LEFT($B$5,2))-42,Data!$I$1:$ER$1,0)+1),0)} -> 4.342 | O16: =IFERROR(INDEX(Data!$I$3:$ER$553,MATCH($C16,Data!$C$3:$C$553,0),MATCH($M$5,Data!$I$1:$ER$1,0)),0) -> 0 | P16: {=IFERROR(INDEX(Data!$I$3:$ER$553,MATCH($C16,Data!$C$3:$C$553,0),MATCH($M$5,Data!$I$1:$ER$1,0)+1),0)} -> 0 | Q16: =IF(R16="","",IF(H16=0,0,R16*(G16/H16))) | T16: May | U16: 46148 | V16: Disability
A17: 202 | B17: BEEF | C17: 12150 | D17: BEEF RUMP MATURED | E17: 20165.122 | F17: 131.121 | G17: =SUMIF(Data!$C:$C,C17,Data!$DI:$DI)+SUMIF(Data!$C:$C,C17,Data!$DK:$DK)+SUMIF(Data!$C:$C,C17,Data!$DM:$DM)+SUMIF(Data!$C:$C,C17,Data!$DO:$DO)+SUMIF(Data!$C:$C,C17,Data!$DQ:$DQ)+SUMIF(Data!$C:$C,C17,Data!$DS:$DS)+SUMIF(Data!$C:$C,C17,Data!$DU:$DU)+SUMIF(Data!$C:$C,C17,Data!$DW:$DW)+SUMIF(Data!$C:$C,C17,Data!$DY:$DY)+SUMIF(Data!$C:$C,C17,Data!$EA:$EA)+SUMIF(Data!$C:$C,C17,Data!$EC:$EC)+SUMIF(Data!$C:$C,C17,Data!$EE:$EE)+SUMIF(Data!$C:$C,C17,Data!$EG:$EG)+SUMIF(Data!$C:$C,C17,Data!$EI:$EI)+SUMIF(Data!$C:$C,C17,Data!$EK:$EK)+SUMIF(Data!$C:$C,C17,Data!$EM:$EM)+SUMIF(Data!$C:$C,C17,Data!$EO:$EO)+SUMIF(Data!$C:$C,C17,Data!$EQ:$EQ)+SUMIF(Data!$C:$C,C17,Data!$ES:$ES) -> 23248.652 | H17: =SUMIF(Data!$C:$C,C17,Data!$DJ:$DJ)+SUMIF(Data!$C:$C,C17,Data!$DL:$DL)+SUMIF(Data!$C:$C,C17,Data!$DN:$DN)+SUMIF(Data!$C:$C,C17,Data!$DP:$DP)+SUMIF(Data!$C:$C,C17,Data!$DR:$DR)+SUMIF(Data!$C:$C,C17,Data!$DT:$DT)+SUMIF(Data!$C:$C,C17,Data!$DV:$DV)+SUMIF(Data!$C:$C,C17,Data!$DX:$DX)+SUMIF(Data!$C:$C,C17,Data!$DZ:$DZ)+SUMIF(Data!$C:$C,C17,Data!$EB:$EB)+SUMIF(Data!$C:$C,C17,Data!$ED:$ED)+SUMIF(Data!$C:$C,C17,Data!$EF:$EF)+SUMIF(Data!$C:$C,C17,Data!$EH:$EH)+SUMIF(Data!$C:$C,C17,Data!$EJ:$EJ)+SUMIF(Data!$C:$C,C17,Data!$EL:$EL)+SUMIF(Data!$C:$C,C17,Data!$EN:$EN)+SUMIF(Data!$C:$C,C17,Data!$EP:$EP)+SUMIF(Data!$C:$C,C17,Data!$ER:$ER)+SUMIF(Data!$C:$C,C17,Data!$ET:$ET) -> 150.43 | I17: =G17/19 -> 1223.6133 | J17: =H17/19 -> 7.9173684 | K17: =IFERROR(INDEX(Data!$ES:$ES,MATCH(C17,Data!$C:$C,0)),0) -> 435.17391 | L17: =IFERROR(INDEX(Data!$ET:$ET,MATCH(C17,Data!$C:$C,0)),0) -> 2.66 | M17: =IFERROR(INDEX(Data!$I$3:$ER$553,MATCH($C17,Data!$C$3:$C$553,0),MATCH(DATE(RIGHT($B$5,4),MID($B$5,4,2),LEFT($B$5,2))-42,Data!$I$1:$ER$1,0)),0) -> 838.45217 | N17: {=IFERROR(INDEX(Data!$I$3:$ER$553,MATCH($C17,Data!$C$3:$C$553,0),MATCH(DATE(RIGHT($B$5,4),MID($B$5,4,2),LEFT($B$5,2))-42,Data!$I$1:$ER$1,0)+1),0)} -> 4.441 | O17: =IFERROR(INDEX(Data!$I$3:$ER$553,MATCH($C17,Data!$C$3:$C$553,0),MATCH($M$5,Data!$I$1:$ER$1,0)),0) -> 727.45217 | P17: {=IFERROR(INDEX(Data!$I$3:$ER$553,MATCH($C17,Data!$C$3:$C$553,0),MATCH($M$5,Data!$I$1:$ER$1,0)+1),0)} -> 3.803 | Q17: =IF(R17="","",IF(H17=0,0,R17*(G17/H17))) | T17: May | U17: 46149 | V17: Children & Others
A18: 202 | B18: BEEF | C18: 34205 | D18: BULK RUMP MATURED | E18: 16780.435 | F18: 115.326 | G18: =SUMIF(Data!$C:$C,C18,Data!$DI:$DI)+SUMIF(Data!$C:$C,C18,Data!$DK:$DK)+SUMIF(Data!$C:$C,C18,Data!$DM:$DM)+SUMIF(Data!$C:$C,C18,Data!$DO:$DO)+SUMIF(Data!$C:$C,C18,Data!$DQ:$DQ)+SUMIF(Data!$C:$C,C18,Data!$DS:$DS)+SUMIF(Data!$C:$C,C18,Data!$DU:$DU)+SUMIF(Data!$C:$C,C18,Data!$DW:$DW)+SUMIF(Data!$C:$C,C18,Data!$DY:$DY)+SUMIF(Data!$C:$C,C18,Data!$EA:$EA)+SUMIF(Data!$C:$C,C18,Data!$EC:$EC)+SUMIF(Data!$C:$C,C18,Data!$EE:$EE)+SUMIF(Data!$C:$C,C18,Data!$EG:$EG)+SUMIF(Data!$C:$C,C18,Data!$EI:$EI)+SUMIF(Data!$C:$C,C18,Data!$EK:$EK)+SUMIF(Data!$C:$C,C18,Data!$EM:$EM)+SUMIF(Data!$C:$C,C18,Data!$EO:$EO)+SUMIF(Data!$C:$C,C18,Data!$EQ:$EQ)+SUMIF(Data!$C:$C,C18,Data!$ES:$ES) -> 22562.696 | H18: =SUMIF(Data!$C:$C,C18,Data!$DJ:$DJ)+SUMIF(Data!$C:$C,C18,Data!$DL:$DL)+SUMIF(Data!$C:$C,C18,Data!$DN:$DN)+SUMIF(Data!$C:$C,C18,Data!$DP:$DP)+SUMIF(Data!$C:$C,C18,Data!$DR:$DR)+SUMIF(Data!$C:$C,C18,Data!$DT:$DT)+SUMIF(Data!$C:$C,C18,Data!$DV:$DV)+SUMIF(Data!$C:$C,C18,Data!$DX:$DX)+SUMIF(Data!$C:$C,C18,Data!$DZ:$DZ)+SUMIF(Data!$C:$C,C18,Data!$EB:$EB)+SUMIF(Data!$C:$C,C18,Data!$ED:$ED)+SUMIF(Data!$C:$C,C18,Data!$EF:$EF)+SUMIF(Data!$C:$C,C18,Data!$EH:$EH)+SUMIF(Data!$C:$C,C18,Data!$EJ:$EJ)+SUMIF(Data!$C:$C,C18,Data!$EL:$EL)+SUMIF(Data!$C:$C,C18,Data!$EN:$EN)+SUMIF(Data!$C:$C,C18,Data!$EP:$EP)+SUMIF(Data!$C:$C,C18,Data!$ER:$ER)+SUMIF(Data!$C:$C,C18,Data!$ET:$ET) -> 147.508 | I18: =G18/19 -> 1187.5103 | J18: =H18/19 -> 7.7635789 | K18: =IFERROR(INDEX(Data!$ES:$ES,MATCH(C18,Data!$C:$C,0)),0) -> 0 | L18: =IFERROR(INDEX(Data!$ET:$ET,MATCH(C18,Data!$C:$C,0)),0) -> 0 | M18: =IFERROR(INDEX(Data!$I$3:$ER$553,MATCH($C18,Data!$C$3:$C$553,0),MATCH(DATE(RIGHT($B$5,4),MID($B$5,4,2),LEFT($B$5,2))-42,Data!$I$1:$ER$1,0)),0) -> 602.4 | N18: {=IFERROR(INDEX(Data!$I$3:$ER$553,MATCH($C18,Data!$C$3:$C$553,0),MATCH(DATE(RIGHT($B$5,4),MID($B$5,4,2),LEFT($B$5,2))-42,Data!$I$1:$ER$1,0)+1),0)} -> 3.149 | O18: =IFERROR(INDEX(Data!$I$3:$ER$553,MATCH($C18,Data!$C$3:$C$553,0),MATCH($M$5,Data!$I$1:$ER$1,0)),0) -> 395.51304 | P18: {=IFERROR(INDEX(Data!$I$3:$ER$553,MATCH($C18,Data!$C$3:$C$553,0),MATCH($M$5,Data!$I$1:$ER$1,0)+1),0)} -> 2.394 | Q18: =IF(R18="","",IF(H18=0,0,R18*(G18/H18))) | T18: June | U18: 46175 | V18: Old Age/Pension
A19: 202 | B19: BEEF | C19: 63482 | D19: TENDERISE STEAK | E19: 0 | F19: 0 | G19: =SUMIF(Data!$C:$C,C19,Data!$DI:$DI)+SUMIF(Data!$C:$C,C19,Data!$DK:$DK)+SUMIF(Data!$C:$C,C19,Data!$DM:$DM)+SUMIF(Data!$C:$C,C19,Data!$DO:$DO)+SUMIF(Data!$C:$C,C19,Data!$DQ:$DQ)+SUMIF(Data!$C:$C,C19,Data!$DS:$DS)+SUMIF(Data!$C:$C,C19,Data!$DU:$DU)+SUMIF(Data!$C:$C,C19,Data!$DW:$DW)+SUMIF(Data!$C:$C,C19,Data!$DY:$DY)+SUMIF(Data!$C:$C,C19,Data!$EA:$EA)+SUMIF(Data!$C:$C,C19,Data!$EC:$EC)+SUMIF(Data!$C:$C,C19,Data!$EE:$EE)+SUMIF(Data!$C:$C,C19,Data!$EG:$EG)+SUMIF(Data!$C:$C,C19,Data!$EI:$EI)+SUMIF(Data!$C:$C,C19,Data!$EK:$EK)+SUMIF(Data!$C:$C,C19,Data!$EM:$EM)+SUMIF(Data!$C:$C,C19,Data!$EO:$EO)+SUMIF(Data!$C:$C,C19,Data!$EQ:$EQ)+SUMIF(Data!$C:$C,C19,Data!$ES:$ES) -> 20725.009 | H19: =SUMIF(Data!$C:$C,C19,Data!$DJ:$DJ)+SUMIF(Data!$C:$C,C19,Data!$DL:$DL)+SUMIF(Data!$C:$C,C19,Data!$DN:$DN)+SUMIF(Data!$C:$C,C19,Data!$DP:$DP)+SUMIF(Data!$C:$C,C19,Data!$DR:$DR)+SUMIF(Data!$C:$C,C19,Data!$DT:$DT)+SUMIF(Data!$C:$C,C19,Data!$DV:$DV)+SUMIF(Data!$C:$C,C19,Data!$DX:$DX)+SUMIF(Data!$C:$C,C19,Data!$DZ:$DZ)+SUMIF(Data!$C:$C,C19,Data!$EB:$EB)+SUMIF(Data!$C:$C,C19,Data!$ED:$ED)+SUMIF(Data!$C:$C,C19,Data!$EF:$EF)+SUMIF(Data!$C:$C,C19,Data!$EH:$EH)+SUMIF(Data!$C:$C,C19,Data!$EJ:$EJ)+SUMIF(Data!$C:$C,C19,Data!$EL:$EL)+SUMIF(Data!$C:$C,C19,Data!$EN:$EN)+SUMIF(Data!$C:$C,C19,Data!$EP:$EP)+SUMIF(Data!$C:$C,C19,Data!$ER:$ER)+SUMIF(Data!$C:$C,C19,Data!$ET:$ET) -> 168.366 | I19: =G19/19 -> 1090.7899 | J19: =H19/19 -> 8.8613684 | K19: =IFERROR(INDEX(Data!$ES:$ES,MATCH(C19,Data!$C:$C,0)),0) -> 473.8087 | L19: =IFERROR(INDEX(Data!$ET:$ET,MATCH(C19,Data!$C:$C,0)),0) -> 4.11 | M19: =IFERROR(INDEX(Data!$I$3:$ER$553,MATCH($C19,Data!$C$3:$C$553,0),MATCH(DATE(RIGHT($B$5,4),MID($B$5,4,2),LEFT($B$5,2))-42,Data!$I$1:$ER$1,0)),0) -> 724.75652 | N19: {=IFERROR(INDEX(Data!$I$3:$ER$553,MATCH($C19,Data!$C$3:$C$553,0),MATCH(DATE(RIGHT($B$5,4),MID($B$5,4,2),LEFT($B$5,2))-42,Data!$I$1:$ER$1,0)+1),0)} -> 6.946 | O19: =IFERROR(INDEX(Data!$I$3:$ER$553,MATCH($C19,Data!$C$3:$C$553,0),MATCH($M$5,Data!$I$1:$ER$1,0)),0) -> 0 | P19: {=IFERROR(INDEX(Data!$I$3:$ER$553,MATCH($C19,Data!$C$3:$C$553,0),MATCH($M$5,Data!$I$1:$ER$1,0)+1),0)} -> 0 | Q19: =IF(R19="","",IF(H19=0,0,R19*(G19/H19))) | T19: June | U19: 46176 | V19: Disability
A20: 202 | B20: BEEF | C20: 34254 | D20: MEATY BONES | E20: 17629.626 | F20: 568.467 | G20: =SUMIF(Data!$C:$C,C20,Data!$DI:$DI)+SUMIF(Data!$C:$C,C20,Data!$DK:$DK)+SUMIF(Data!$C:$C,C20,Data!$DM:$DM)+SUMIF(Data!$C:$C,C20,Data!$DO:$DO)+SUMIF(Data!$C:$C,C20,Data!$DQ:$DQ)+SUMIF(Data!$C:$C,C20,Data!$DS:$DS)+SUMIF(Data!$C:$C,C20,Data!$DU:$DU)+SUMIF(Data!$C:$C,C20,Data!$DW:$DW)+SUMIF(Data!$C:$C,C20,Data!$DY:$DY)+SUMIF(Data!$C:$C,C20,Data!$EA:$EA)+SUMIF(Data!$C:$C,C20,Data!$EC:$EC)+SUMIF(Data!$C:$C,C20,Data!$EE:$EE)+SUMIF(Data!$C:$C,C20,Data!$EG:$EG)+SUMIF(Data!$C:$C,C20,Data!$EI:$EI)+SUMIF(Data!$C:$C,C20,Data!$EK:$EK)+SUMIF(Data!$C:$C,C20,Data!$EM:$EM)+SUMIF(Data!$C:$C,C20,Data!$EO:$EO)+SUMIF(Data!$C:$C,C20,Data!$EQ:$EQ)+SUMIF(Data!$C:$C,C20,Data!$ES:$ES) -> 23378.617 | H20: =SUMIF(Data!$C:$C,C20,Data!$DJ:$DJ)+SUMIF(Data!$C:$C,C20,Data!$DL:$DL)+SUMIF(Data!$C:$C,C20,Data!$DN:$DN)+SUMIF(Data!$C:$C,C20,Data!$DP:$DP)+SUMIF(Data!$C:$C,C20,Data!$DR:$DR)+SUMIF(Data!$C:$C,C20,Data!$DT:$DT)+SUMIF(Data!$C:$C,C20,Data!$DV:$DV)+SUMIF(Data!$C:$C,C20,Data!$DX:$DX)+SUMIF(Data!$C:$C,C20,Data!$DZ:$DZ)+SUMIF(Data!$C:$C,C20,Data!$EB:$EB)+SUMIF(Data!$C:$C,C20,Data!$ED:$ED)+SUMIF(Data!$C:$C,C20,Data!$EF:$EF)+SUMIF(Data!$C:$C,C20,Data!$EH:$EH)+SUMIF(Data!$C:$C,C20,Data!$EJ:$EJ)+SUMIF(Data!$C:$C,C20,Data!$EL:$EL)+SUMIF(Data!$C:$C,C20,Data!$EN:$EN)+SUMIF(Data!$C:$C,C20,Data!$EP:$EP)+SUMIF(Data!$C:$C,C20,Data!$ER:$ER)+SUMIF(Data!$C:$C,C20,Data!$ET:$ET) -> 673.142 | I20: =G20/19 -> 1230.4535 | J20: =H20/19 -> 35.428526 | K20: =IFERROR(INDEX(Data!$ES:$ES,MATCH(C20,Data!$C:$C,0)),0) -> 3793.6087 | L20: =IFERROR(INDEX(Data!$ET:$ET,MATCH(C20,Data!$C:$C,0)),0) -> 109.562 | M20: =IFERROR(INDEX(Data!$I$3:$ER$553,MATCH($C20,Data!$C$3:$C$553,0),MATCH(DATE(RIGHT($B$5,4),MID($B$5,4,2),LEFT($B$5,2))-42,Data!$I$1:$ER$1,0)),0) -> 1556.5478 | N20: {=IFERROR(INDEX(Data!$I$3:$ER$553,MATCH($C20,Data!$C$3:$C$553,0),MATCH(DATE(RIGHT($B$5,4),MID($B$5,4,2),LEFT($B$5,2))-42,Data!$I$1:$ER$1,0)+1),0)} -> 44.762 | O20: =IFERROR(INDEX(Data!$I$3:$ER$553,MATCH($C20,Data!$C$3:$C$553,0),MATCH($M$5,Data!$I$1:$ER$1,0)),0) -> 3392.1913 | P20: {=IFERROR(INDEX(Data!$I$3:$ER$553,MATCH($C20,Data!$C$3:$C$553,0),MATCH($M$5,Data!$I$1:$ER$1,0)+1),0)} -> 98.074 | Q20: =IF(R20="","",IF(H20=0,0,R20*(G20/H20))) | T20: June | U20: 46177 | V20: Children & Others
A21: 202 | B21: BEEF | C21: 34157 | D21: BEEF FILLET | E21: 11408.974 | F21: 52.834 | G21: =SUMIF(Data!$C:$C,C21,Data!$DI:$DI)+SUMIF(Data!$C:$C,C21,Data!$DK:$DK)+SUMIF(Data!$C:$C,C21,Data!$DM:$DM)+SUMIF(Data!$C:$C,C21,Data!$DO:$DO)+SUMIF(Data!$C:$C,C21,Data!$DQ:$DQ)+SUMIF(Data!$C:$C,C21,Data!$DS:$DS)+SUMIF(Data!$C:$C,C21,Data!$DU:$DU)+SUMIF(Data!$C:$C,C21,Data!$DW:$DW)+SUMIF(Data!$C:$C,C21,Data!$DY:$DY)+SUMIF(Data!$C:$C,C21,Data!$EA:$EA)+SUMIF(Data!$C:$C,C21,Data!$EC:$EC)+SUMIF(Data!$C:$C,C21,Data!$EE:$EE)+SUMIF(Data!$C:$C,C21,Data!$EG:$EG)+SUMIF(Data!$C:$C,C21,Data!$EI:$EI)+SUMIF(Data!$C:$C,C21,Data!$EK:$EK)+SUMIF(Data!$C:$C,C21,Data!$EM:$EM)+SUMIF(Data!$C:$C,C21,Data!$EO:$EO)+SUMIF(Data!$C:$C,C21,Data!$EQ:$EQ)+SUMIF(Data!$C:$C,C21,Data!$ES:$ES) -> 10352.635 | H21: =SUMIF(Data!$C:$C,C21,Data!$DJ:$DJ)+SUMIF(Data!$C:$C,C21,Data!$DL:$DL)+SUMIF(Data!$C:$C,C21,Data!$DN:$DN)+SUMIF(Data!$C:$C,C21,Data!$DP:$DP)+SUMIF(Data!$C:$C,C21,Data!$DR:$DR)+SUMIF(Data!$C:$C,C21,Data!$DT:$DT)+SUMIF(Data!$C:$C,C21,Data!$DV:$DV)+SUMIF(Data!$C:$C,C21,Data!$DX:$DX)+SUMIF(Data!$C:$C,C21,Data!$DZ:$DZ)+SUMIF(Data!$C:$C,C21,Data!$EB:$EB)+SUMIF(Data!$C:$C,C21,Data!$ED:$ED)+SUMIF(Data!$C:$C,C21,Data!$EF:$EF)+SUMIF(Data!$C:$C,C21,Data!$EH:$EH)+SUMIF(Data!$C:$C,C21,Data!$EJ:$EJ)+SUMIF(Data!$C:$C,C21,Data!$EL:$EL)+SUMIF(Data!$C:$C,C21,Data!$EN:$EN)+SUMIF(Data!$C:$C,C21,Data!$EP:$EP)+SUMIF(Data!$C:$C,C21,Data!$ER:$ER)+SUMIF(Data!$C:$C,C21,Data!$ET:$ET) -> 46.914 | I21: =G21/19 -> 544.87551 | J21: =H21/19 -> 2.4691579 | K21: =IFERROR(INDEX(Data!$ES:$ES,MATCH(C21,Data!$C:$C,0)),0) -> 0 | L21: =IFERROR(INDEX(Data!$ET:$ET,MATCH(C21,Data!$C:$C,0)),0) -> 0 | M21: =IFERROR(INDEX(Data!$I$3:$ER$553,MATCH($C21,Data!$C$3:$C$553,0),MATCH(DATE(RIGHT($B$5,4),MID($B$5,4,2),LEFT($B$5,2))-42,Data!$I$1:$ER$1,0)),0) -> 0 | N21: {=IFERROR(INDEX(Data!$I$3:$ER$553,MATCH($C21,Data!$C$3:$C$553,0),MATCH(DATE(RIGHT($B$5,4),MID($B$5,4,2),LEFT($B$5,2))-42,Data!$I$1:$ER$1,0)+1),0)} -> 0 | O21: =IFERROR(INDEX(Data!$I$3:$ER$553,MATCH($C21,Data!$C$3:$C$553,0),MATCH($M$5,Data!$I$1:$ER$1,0)),0) -> 116.07826 | P21: {=IFERROR(INDEX(Data!$I$3:$ER$553,MATCH($C21,Data!$C$3:$C$553,0),MATCH($M$5,Data!$I$1:$ER$1,0)+1),0)} -> 0.534 | Q21: =IF(R21="","",IF(H21=0,0,R21*(G21/H21))) | T21: July | U21: 46205 | V21: Old Age/Pension
A22: 202 | B22: BEEF | C22: 64936 | D22: OPENVELD F/R SIRLOIN2 P/KG | E22: 0 | F22: 0 | G22: =SUMIF(Data!$C:$C,C22,Data!$DI:$DI)+SUMIF(Data!$C:$C,C22,Data!$DK:$DK)+SUMIF(Data!$C:$C,C22,Data!$DM:$DM)+SUMIF(Data!$C:$C,C22,Data!$DO:$DO)+SUMIF(Data!$C:$C,C22,Data!$DQ:$DQ)+SUMIF(Data!$C:$C,C22,Data!$DS:$DS)+SUMIF(Data!$C:$C,C22,Data!$DU:$DU)+SUMIF(Data!$C:$C,C22,Data!$DW:$DW)+SUMIF(Data!$C:$C,C22,Data!$DY:$DY)+SUMIF(Data!$C:$C,C22,Data!$EA:$EA)+SUMIF(Data!$C:$C,C22,Data!$EC:$EC)+SUMIF(Data!$C:$C,C22,Data!$EE:$EE)+SUMIF(Data!$C:$C,C22,Data!$EG:$EG)+SUMIF(Data!$C:$C,C22,Data!$EI:$EI)+SUMIF(Data!$C:$C,C22,Data!$EK:$EK)+SUMIF(Data!$C:$C,C22,Data!$EM:$EM)+SUMIF(Data!$C:$C,C22,Data!$EO:$EO)+SUMIF(Data!$C:$C,C22,Data!$EQ:$EQ)+SUMIF(Data!$C:$C,C22,Data!$ES:$ES) -> 8241.9652 | H22: =SUMIF(Data!$C:$C,C22,Data!$DJ:$DJ)+SUMIF(Data!$C:$C,C22,Data!$DL:$DL)+SUMIF(Data!$C:$C,C22,Data!$DN:$DN)+SUMIF(Data!$C:$C,C22,Data!$DP:$DP)+SUMIF(Data!$C:$C,C22,Data!$DR:$DR)+SUMIF(Data!$C:$C,C22,Data!$DT:$DT)+SUMIF(Data!$C:$C,C22,Data!$DV:$DV)+SUMIF(Data!$C:$C,C22,Data!$DX:$DX)+SUMIF(Data!$C:$C,C22,Data!$DZ:$DZ)+SUMIF(Data!$C:$C,C22,Data!$EB:$EB)+SUMIF(Data!$C:$C,C22,Data!$ED:$ED)+SUMIF(Data!$C:$C,C22,Data!$EF:$EF)+SUMIF(Data!$C:$C,C22,Data!$EH:$EH)+SUMIF(Data!$C:$C,C22,Data!$EJ:$EJ)+SUMIF(Data!$C:$C,C22,Data!$EL:$EL)+SUMIF(Data!$C:$C,C22,Data!$EN:$EN)+SUMIF(Data!$C:$C,C22,Data!$EP:$EP)+SUMIF(Data!$C:$C,C22,Data!$ER:$ER)+SUMIF(Data!$C:$C,C22,Data!$ET:$ET) -> 26.425 | I22: =G22/19 -> 433.78764 | J22: =H22/19 -> 1.3907895 | K22: =IFERROR(INDEX(Data!$ES:$ES,MATCH(C22,Data!$C:$C,0)),0) -> 0 | L22: =IFERROR(INDEX(Data!$ET:$ET,MATCH(C22,Data!$C:$C,0)),0) -> 0 | M22: =IFERROR(INDEX(Data!$I$3:$ER$553,MATCH($C22,Data!$C$3:$C$553,0),MATCH(DATE(RIGHT($B$5,4),MID($B$5,4,2),LEFT($B$5,2))-42,Data!$I$1:$ER$1,0)),0) -> 0 | N22: {=IFERROR(INDEX(Data!$I$3:$ER$553,MATCH($C22,Data!$C$3:$C$553,0),MATCH(DATE(RIGHT($B$5,4),MID($B$5,4,2),LEFT($B$5,2))-42,Data!$I$1:$ER$1,0)+1),0)} -> 0 | O22: =IFERROR(INDEX(Data!$I$3:$ER$553,MATCH($C22,Data!$C$3:$C$553,0),MATCH($M$5,Data!$I$1:$ER$1,0)),0) -> 0 | P22: {=IFERROR(INDEX(Data!$I$3:$ER$553,MATCH($C22,Data!$C$3:$C$553,0),MATCH($M$5,Data!$I$1:$ER$1,0)+1),0)} -> 0 | Q22: =IF(R22="","",IF(H22=0,0,R22*(G22/H22))) | T22: July | U22: 46206 | V22: Disability
A23: 202 | B23: BEEF | C23: 12144 | D23: BEEF STIRFRY | E23: 7034.7913 | F23: 60.287 | G23: =SUMIF(Data!$C:$C,C23,Data!$DI:$DI)+SUMIF(Data!$C:$C,C23,Data!$DK:$DK)+SUMIF(Data!$C:$C,C23,Data!$DM:$DM)+SUMIF(Data!$C:$C,C23,Data!$DO:$DO)+SUMIF(Data!$C:$C,C23,Data!$DQ:$DQ)+SUMIF(Data!$C:$C,C23,Data!$DS:$DS)+SUMIF(Data!$C:$C,C23,Data!$DU:$DU)+SUMIF(Data!$C:$C,C23,Data!$DW:$DW)+SUMIF(Data!$C:$C,C23,Data!$DY:$DY)+SUMIF(Data!$C:$C,C23,Data!$EA:$EA)+SUMIF(Data!$C:$C,C23,Data!$EC:$EC)+SUMIF(Data!$C:$C,C23,Data!$EE:$EE)+SUMIF(Data!$C:$C,C23,Data!$EG:$EG)+SUMIF(Data!$C:$C,C23,Data!$EI:$EI)+SUMIF(Data!$C:$C,C23,Data!$EK:$EK)+SUMIF(Data!$C:$C,C23,Data!$EM:$EM)+SUMIF(Data!$C:$C,C23,Data!$EO:$EO)+SUMIF(Data!$C:$C,C23,Data!$EQ:$EQ)+SUMIF(Data!$C:$C,C23,Data!$ES:$ES) -> 7854.4348 | H23: =SUMIF(Data!$C:$C,C23,Data!$DJ:$DJ)+SUMIF(Data!$C:$C,C23,Data!$DL:$DL)+SUMIF(Data!$C:$C,C23,Data!$DN:$DN)+SUMIF(Data!$C:$C,C23,Data!$DP:$DP)+SUMIF(Data!$C:$C,C23,Data!$DR:$DR)+SUMIF(Data!$C:$C,C23,Data!$DT:$DT)+SUMIF(Data!$C:$C,C23,Data!$DV:$DV)+SUMIF(Data!$C:$C,C23,Data!$DX:$DX)+SUMIF(Data!$C:$C,C23,Data!$DZ:$DZ)+SUMIF(Data!$C:$C,C23,Data!$EB:$EB)+SUMIF(Data!$C:$C,C23,Data!$ED:$ED)+SUMIF(Data!$C:$C,C23,Data!$EF:$EF)+SUMIF(Data!$C:$C,C23,Data!$EH:$EH)+SUMIF(Data!$C:$C,C23,Data!$EJ:$EJ)+SUMIF(Data!$C:$C,C23,Data!$EL:$EL)+SUMIF(Data!$C:$C,C23,Data!$EN:$EN)+SUMIF(Data!$C:$C,C23,Data!$EP:$EP)+SUMIF(Data!$C:$C,C23,Data!$ER:$ER)+SUMIF(Data!$C:$C,C23,Data!$ET:$ET) -> 63.301 | I23: =G23/19 -> 413.3913 | J23: =H23/19 -> 3.3316316 | K23: =IFERROR(INDEX(Data!$ES:$ES,MATCH(C23,Data!$C:$C,0)),0) -> 109.87826 | L23: =IFERROR(INDEX(Data!$ET:$ET,MATCH(C23,Data!$C:$C,0)),0) -> 0.972 | M23: =IFERROR(INDEX(Data!$I$3:$ER$553,MATCH($C23,Data!$C$3:$C$553,0),MATCH(DATE(RIGHT($B$5,4),MID($B$5,4,2),LEFT($B$5,2))-42,Data!$I$1:$ER$1,0)),0) -> 351.7913 | N23: {=IFERROR(INDEX(Data!$I$3:$ER$553,MATCH($C23,Data!$C$3:$C$553,0),MATCH(DATE(RIGHT($B$5,4),MID($B$5,4,2),LEFT($B$5,2))-42,Data!$I$1:$ER$1,0)+1),0)} -> 3.112 | O23: =IFERROR(INDEX(Data!$I$3:$ER$553,MATCH($C23,Data!$C$3:$C$553,0),MATCH($M$5,Data!$I$1:$ER$1,0)),0) -> 406.21739 | P23: {=IFERROR(INDEX(Data!$I$3:$ER$553,MATCH($C23,Data!$C$3:$C$553,0),MATCH($M$5,Data!$I$1:$ER$1,0)+1),0)} -> 2.748 | Q23: =IF(R23="","",IF(H23=0,0,R23*(G23/H23))) | T23: July | U23: 46209 | V23: Children & Others
A24: 202 | B24: BEEF | C24: 62790 | D24: BEEF RASHER | E24: 0 | F24: 0 | G24: =SUMIF(Data!$C:$C,C24,Data!$DI:$DI)+SUMIF(Data!$C:$C,C24,Data!$DK:$DK)+SUMIF(Data!$C:$C,C24,Data!$DM:$DM)+SUMIF(Data!$C:$C,C24,Data!$DO:$DO)+SUMIF(Data!$C:$C,C24,Data!$DQ:$DQ)+SUMIF(Data!$C:$C,C24,Data!$DS:$DS)+SUMIF(Data!$C:$C,C24,Data!$DU:$DU)+SUMIF(Data!$C:$C,C24,Data!$DW:$DW)+SUMIF(Data!$C:$C,C24,Data!$DY:$DY)+SUMIF(Data!$C:$C,C24,Data!$EA:$EA)+SUMIF(Data!$C:$C,C24,Data!$EC:$EC)+SUMIF(Data!$C:$C,C24,Data!$EE:$EE)+SUMIF(Data!$C:$C,C24,Data!$EG:$EG)+SUMIF(Data!$C:$C,C24,Data!$EI:$EI)+SUMIF(Data!$C:$C,C24,Data!$EK:$EK)+SUMIF(Data!$C:$C,C24,Data!$EM:$EM)+SUMIF(Data!$C:$C,C24,Data!$EO:$EO)+SUMIF(Data!$C:$C,C24,Data!$EQ:$EQ)+SUMIF(Data!$C:$C,C24,Data!$ES:$ES) -> 6549.3391 | H24: =SUMIF(Data!$C:$C,C24,Data!$DJ:$DJ)+SUMIF(Data!$C:$C,C24,Data!$DL:$DL)+SUMIF(Data!$C:$C,C24,Data!$DN:$DN)+SUMIF(Data!$C:$C,C24,Data!$DP:$DP)+SUMIF(Data!$C:$C,C24,Data!$DR:$DR)+SUMIF(Data!$C:$C,C24,Data!$DT:$DT)+SUMIF(Data!$C:$C,C24,Data!$DV:$DV)+SUMIF(Data!$C:$C,C24,Data!$DX:$DX)+SUMIF(Data!$C:$C,C24,Data!$DZ:$DZ)+SUMIF(Data!$C:$C,C24,Data!$EB:$EB)+SUMIF(Data!$C:$C,C24,Data!$ED:$ED)+SUMIF(Data!$C:$C,C24,Data!$EF:$EF)+SUMIF(Data!$C:$C,C24,Data!$EH:$EH)+SUMIF(Data!$C:$C,C24,Data!$EJ:$EJ)+SUMIF(Data!$C:$C,C24,Data!$EL:$EL)+SUMIF(Data!$C:$C,C24,Data!$EN:$EN)+SUMIF(Data!$C:$C,C24,Data!$EP:$EP)+SUMIF(Data!$C:$C,C24,Data!$ER:$ER)+SUMIF(Data!$C:$C,C24,Data!$ET:$ET) -> 56.618 | I24: =G24/19 -> 344.70206 | J24: =H24/19 -> 2.9798947 | K24: =IFERROR(INDEX(Data!$ES:$ES,MATCH(C24,Data!$C:$C,0)),0) -> 0 | L24: =IFERROR(INDEX(Data!$ET:$ET,MATCH(C24,Data!$C:$C,0)),0) -> 0 | M24: =IFERROR(INDEX(Data!$I$3:$ER$553,MATCH($C24,Data!$C$3:$C$553,0),MATCH(DATE(RIGHT($B$5,4),MID($B$5,4,2),LEFT($B$5,2))-42,Data!$I$1:$ER$1,0)),0) -> 0 | N24: {=IFERROR(INDEX(Data!$I$3:$ER$553,MATCH($C24,Data!$C$3:$C$553,0),MATCH(DATE(RIGHT($B$5,4),MID($B$5,4,2),LEFT($B$5,2))-42,Data!$I$1:$ER$1,0)+1),0)} -> 0 | O24: =IFERROR(INDEX(Data!$I$3:$ER$553,MATCH($C24,Data!$C$3:$C$553,0),MATCH($M$5,Data!$I$1:$ER$1,0)),0) -> 0 | P24: {=IFERROR(INDEX(Data!$I$3:$ER$553,MATCH($C24,Data!$C$3:$C$553,0),MATCH($M$5,Data!$I$1:$ER$1,0)+1),0)} -> 0 | Q24: =IF(R24="","",IF(H24=0,0,R24*(G24/H24))) | T24: August | U24: 46238 | V24: Old Age/Pension
... A38: 202 | B38: BEEF | C38: 34152 | D38: BEEF BRISKET A GRADE | E38: 0 | F38: 0 | G38: =SUMIF(Data!$C:$C,C38,Data!$DI:$DI)+SUMIF(Data!$C:$C,C38,Data!$DK:$DK)+SUMIF(Data!$C:$C,C38,Data!$DM:$DM)+SUMIF(Data!$C:$C,C38,Data!$DO:$DO)+SUMIF(Data!$C:$C,C38,Data!$DQ:$DQ)+SUMIF(Data!$C:$C,C38,Data!$DS:$DS)+SUMIF(Data!$C:$C,C38,Data!$DU:$DU)+SUMIF(Data!$C:$C,C38,Data!$DW:$DW)+SUMIF(Data!$C:$C,C38,Data!$DY:$DY)+SUMIF(Data!$C:$C,C38,Data!$EA:$EA)+SUMIF(Data!$C:$C,C38,Data!$EC:$EC)+SUMIF(Data!$C:$C,C38,Data!$EE:$EE)+SUMIF(Data!$C:$C,C38,Data!$EG:$EG)+SUMIF(Data!$C:$C,C38,Data!$EI:$EI)+SUMIF(Data!$C:$C,C38,Data!$EK:$EK)+SUMIF(Data!$C:$C,C38,Data!$EM:$EM)+SUMIF(Data!$C:$C,C38,Data!$EO:$EO)+SUMIF(Data!$C:$C,C38,Data!$EQ:$EQ)+SUMIF(Data!$C:$C,C38,Data!$ES:$ES) -> 679.64348 | H38: =SUMIF(Data!$C:$C,C38,Data!$DJ:$DJ)+SUMIF(Data!$C:$C,C38,Data!$DL:$DL)+SUMIF(Data!$C:$C,C38,Data!$DN:$DN)+SUMIF(Data!$C:$C,C38,Data!$DP:$DP)+SUMIF(Data!$C:$C,C38,Data!$DR:$DR)+SUMIF(Data!$C:$C,C38,Data!$DT:$DT)+SUMIF(Data!$C:$C,C38,Data!$DV:$DV)+SUMIF(Data!$C:$C,C38,Data!$DX:$DX)+SUMIF(Data!$C:$C,C38,Data!$DZ:$DZ)+SUMIF(Data!$C:$C,C38,Data!$EB:$EB)+SUMIF(Data!$C:$C,C38,Data!$ED:$ED)+SUMIF(Data!$C:$C,C38,Data!$EF:$EF)+SUMIF(Data!$C:$C,C38,Data!$EH:$EH)+SUMIF(Data!$C:$C,C38,Data!$EJ:$EJ)+SUMIF(Data!$C:$C,C38,Data!$EL:$EL)+SUMIF(Data!$C:$C,C38,Data!$EN:$EN)+SUMIF(Data!$C:$C,C38,Data!$EP:$EP)+SUMIF(Data!$C:$C,C38,Data!$ER:$ER)+SUMIF(Data!$C:$C,C38,Data!$ET:$ET) -> 7.106 | I38: =G38/19 -> 35.770709 | J38: =H38/19 -> 0.374 | K38: =IFERROR(INDEX(Data!$ES:$ES,MATCH(C38,Data!$C:$C,0)),0) -> 0 | L38: =IFERROR(INDEX(Data!$ET:$ET,MATCH(C38,Data!$C:$C,0)),0) -> 0 | M38: =IFERROR(INDEX(Data!$I$3:$ER$553,MATCH($C38,Data!$C$3:$C$553,0),MATCH(DATE(RIGHT($B$5,4),MID($B$5,4,2),LEFT($B$5,2))-42,Data!$I$1:$ER$1,0)),0) -> 0 | N38: {=IFERROR(INDEX(Data!$I$3:$ER$553,MATCH($C38,Data!$C$3:$C$553,0),MATCH(DATE(RIGHT($B$5,4),MID($B$5,4,2),LEFT($B$5,2))-42,Data!$I$1:$ER$1,0)+1),0)} -> 0 | O38: =IFERROR(INDEX(Data!$I$3:$ER$553,MATCH($C38,Data!$C$3:$C$553,0),MATCH($M$5,Data!$I$1:$ER$1,0)),0) -> 0 | P38: {=IFERROR(INDEX(Data!$I$3:$ER$553,MATCH($C38,Data!$C$3:$C$553,0),MATCH($M$5,Data!$I$1:$ER$1,0)+1),0)} -> 0 | Q38: =IF(R38="","",IF(H38=0,0,R38*(G38/H38))) | T38: December | U38: 46360 | V38: Children & Others
A39: 202 | B39: BEEF | C39: 34159 | D39: BEEF ROAST | E39: 2444.3913 | F39: 20.508 | G39: =SUMIF(Data!$C:$C,C39,Data!$DI:$DI)+SUMIF(Data!$C:$C,C39,Data!$DK:$DK)+SUMIF(Data!$C:$C,C39,Data!$DM:$DM)+SUMIF(Data!$C:$C,C39,Data!$DO:$DO)+SUMIF(Data!$C:$C,C39,Data!$DQ:$DQ)+SUMIF(Data!$C:$C,C39,Data!$DS:$DS)+SUMIF(Data!$C:$C,C39,Data!$DU:$DU)+SUMIF(Data!$C:$C,C39,Data!$DW:$DW)+SUMIF(Data!$C:$C,C39,Data!$DY:$DY)+SUMIF(Data!$C:$C,C39,Data!$EA:$EA)+SUMIF(Data!$C:$C,C39,Data!$EC:$EC)+SUMIF(Data!$C:$C,C39,Data!$EE:$EE)+SUMIF(Data!$C:$C,C39,Data!$EG:$EG)+SUMIF(Data!$C:$C,C39,Data!$EI:$EI)+SUMIF(Data!$C:$C,C39,Data!$EK:$EK)+SUMIF(Data!$C:$C,C39,Data!$EM:$EM)+SUMIF(Data!$C:$C,C39,Data!$EO:$EO)+SUMIF(Data!$C:$C,C39,Data!$EQ:$EQ)+SUMIF(Data!$C:$C,C39,Data!$ES:$ES) -> 602.66957 | H39: =SUMIF(Data!$C:$C,C39,Data!$DJ:$DJ)+SUMIF(Data!$C:$C,C39,Data!$DL:$DL)+SUMIF(Data!$C:$C,C39,Data!$DN:$DN)+SUMIF(Data!$C:$C,C39,Data!$DP:$DP)+SUMIF(Data!$C:$C,C39,Data!$DR:$DR)+SUMIF(Data!$C:$C,C39,Data!$DT:$DT)+SUMIF(Data!$C:$C,C39,Data!$DV:$DV)+SUMIF(Data!$C:$C,C39,Data!$DX:$DX)+SUMIF(Data!$C:$C,C39,Data!$DZ:$DZ)+SUMIF(Data!$C:$C,C39,Data!$EB:$EB)+SUMIF(Data!$C:$C,C39,Data!$ED:$ED)+SUMIF(Data!$C:$C,C39,Data!$EF:$EF)+SUMIF(Data!$C:$C,C39,Data!$EH:$EH)+SUMIF(Data!$C:$C,C39,Data!$EJ:$EJ)+SUMIF(Data!$C:$C,C39,Data!$EL:$EL)+SUMIF(Data!$C:$C,C39,Data!$EN:$EN)+SUMIF(Data!$C:$C,C39,Data!$EP:$EP)+SUMIF(Data!$C:$C,C39,Data!$ER:$ER)+SUMIF(Data!$C:$C,C39,Data!$ET:$ET) -> 4.767 | I39: =G39/19 -> 31.719451 | J39: =H39/19 -> 0.25089474 | K39: =IFERROR(INDEX(Data!$ES:$ES,MATCH(C39,Data!$C:$C,0)),0) -> 0 | L39: =IFERROR(INDEX(Data!$ET:$ET,MATCH(C39,Data!$C:$C,0)),0) -> 0 | M39: =IFERROR(INDEX(Data!$I$3:$ER$553,MATCH($C39,Data!$C$3:$C$553,0),MATCH(DATE(RIGHT($B$5,4),MID($B$5,4,2),LEFT($B$5,2))-42,Data!$I$1:$ER$1,0)),0) -> 0 | N39: {=IFERROR(INDEX(Data!$I$3:$ER$553,MATCH($C39,Data!$C$3:$C$553,0),MATCH(DATE(RIGHT($B$5,4),MID($B$5,4,2),LEFT($B$5,2))-42,Data!$I$1:$ER$1,0)+1),0)} -> 0 | O39: =IFERROR(INDEX(Data!$I$3:$ER$553,MATCH($C39,Data!$C$3:$C$553,0),MATCH($M$5,Data!$I$1:$ER$1,0)),0) -> 0 | P39: {=IFERROR(INDEX(Data!$I$3:$ER$553,MATCH($C39,Data!$C$3:$C$553,0),MATCH($M$5,Data!$I$1:$ER$1,0)+1),0)} -> 0 | Q39: =IF(R39="","",IF(H39=0,0,R39*(G39/H39))) | T39: 46153
A40: 202 | B40: BEEF | C40: 12147 | D40: TENDER & TASTY BEEF KEBAB | E40: 427.61739 | F40: 2.291 | G40: =SUMIF(Data!$C:$C,C40,Data!$DI:$DI)+SUMIF(Data!$C:$C,C40,Data!$DK:$DK)+SUMIF(Data!$C:$C,C40,Data!$DM:$DM)+SUMIF(Data!$C:$C,C40,Data!$DO:$DO)+SUMIF(Data!$C:$C,C40,Data!$DQ:$DQ)+SUMIF(Data!$C:$C,C40,Data!$DS:$DS)+SUMIF(Data!$C:$C,C40,Data!$DU:$DU)+SUMIF(Data!$C:$C,C40,Data!$DW:$DW)+SUMIF(Data!$C:$C,C40,Data!$DY:$DY)+SUMIF(Data!$C:$C,C40,Data!$EA:$EA)+SUMIF(Data!$C:$C,C40,Data!$EC:$EC)+SUMIF(Data!$C:$C,C40,Data!$EE:$EE)+SUMIF(Data!$C:$C,C40,Data!$EG:$EG)+SUMIF(Data!$C:$C,C40,Data!$EI:$EI)+SUMIF(Data!$C:$C,C40,Data!$EK:$EK)+SUMIF(Data!$C:$C,C40,Data!$EM:$EM)+SUMIF(Data!$C:$C,C40,Data!$EO:$EO)+SUMIF(Data!$C:$C,C40,Data!$EQ:$EQ)+SUMIF(Data!$C:$C,C40,Data!$ES:$ES) -> 456.32174 | H40: =SUMIF(Data!$C:$C,C40,Data!$DJ:$DJ)+SUMIF(Data!$C:$C,C40,Data!$DL:$DL)+SUMIF(Data!$C:$C,C40,Data!$DN:$DN)+SUMIF(Data!$C:$C,C40,Data!$DP:$DP)+SUMIF(Data!$C:$C,C40,Data!$DR:$DR)+SUMIF(Data!$C:$C,C40,Data!$DT:$DT)+SUMIF(Data!$C:$C,C40,Data!$DV:$DV)+SUMIF(Data!$C:$C,C40,Data!$DX:$DX)+SUMIF(Data!$C:$C,C40,Data!$DZ:$DZ)+SUMIF(Data!$C:$C,C40,Data!$EB:$EB)+SUMIF(Data!$C:$C,C40,Data!$ED:$ED)+SUMIF(Data!$C:$C,C40,Data!$EF:$EF)+SUMIF(Data!$C:$C,C40,Data!$EH:$EH)+SUMIF(Data!$C:$C,C40,Data!$EJ:$EJ)+SUMIF(Data!$C:$C,C40,Data!$EL:$EL)+SUMIF(Data!$C:$C,C40,Data!$EN:$EN)+SUMIF(Data!$C:$C,C40,Data!$EP:$EP)+SUMIF(Data!$C:$C,C40,Data!$ER:$ER)+SUMIF(Data!$C:$C,C40,Data!$ET:$ET) -> 2.624 | I40: =G40/19 -> 24.016934 | J40: =H40/19 -> 0.13810526 | K40: =IFERROR(INDEX(Data!$ES:$ES,MATCH(C40,Data!$C:$C,0)),0) -> 0 | L40: =IFERROR(INDEX(Data!$ET:$ET,MATCH(C40,Data!$C:$C,0)),0) -> 0 | M40: =IFERROR(INDEX(Data!$I$3:$ER$553,MATCH($C40,Data!$C$3:$C$553,0),MATCH(DATE(RIGHT($B$5,4),MID($B$5,4,2),LEFT($B$5,2))-42,Data!$I$1:$ER$1,0)),0) -> 0 | N40: {=IFERROR(INDEX(Data!$I$3:$ER$553,MATCH($C40,Data!$C$3:$C$553,0),MATCH(DATE(RIGHT($B$5,4),MID($B$5,4,2),LEFT($B$5,2))-42,Data!$I$1:$ER$1,0)+1),0)} -> 0 | O40: =IFERROR(INDEX(Data!$I$3:$ER$553,MATCH($C40,Data!$C$3:$C$553,0),MATCH($M$5,Data!$I$1:$ER$1,0)),0) -> 0 | P40: {=IFERROR(INDEX(Data!$I$3:$ER$553,MATCH($C40,Data!$C$3:$C$553,0),MATCH($M$5,Data!$I$1:$ER$1,0)+1),0)} -> 0 | Q40: =IF(R40="","",IF(H40=0,0,R40*(G40/H40))) | S40: Target Week Start: | T40: SASSA Count in Week: | U40: {=SUMPRODUCT(($U$3:$U$38>=$T$39)*($U$3:$U$38<$T$39+7))} -> 0
A41: 202 | B41: BEEF | C41: 42859 | D41: BEEF MARROW BONES | E41: 593.53913 | F41: 9.533 | G41: =SUMIF(Data!$C:$C,C41,Data!$DI:$DI)+SUMIF(Data!$C:$C,C41,Data!$DK:$DK)+SUMIF(Data!$C:$C,C41,Data!$DM:$DM)+SUMIF(Data!$C:$C,C41,Data!$DO:$DO)+SUMIF(Data!$C:$C,C41,Data!$DQ:$DQ)+SUMIF(Data!$C:$C,C41,Data!$DS:$DS)+SUMIF(Data!$C:$C,C41,Data!$DU:$DU)+SUMIF(Data!$C:$C,C41,Data!$DW:$DW)+SUMIF(Data!$C:$C,C41,Data!$DY:$DY)+SUMIF(Data!$C:$C,C41,Data!$EA:$EA)+SUMIF(Data!$C:$C,C41,Data!$EC:$EC)+SUMIF(Data!$C:$C,C41,Data!$EE:$EE)+SUMIF(Data!$C:$C,C41,Data!$EG:$EG)+SUMIF(Data!$C:$C,C41,Data!$EI:$EI)+SUMIF(Data!$C:$C,C41,Data!$EK:$EK)+SUMIF(Data!$C:$C,C41,Data!$EM:$EM)+SUMIF(Data!$C:$C,C41,Data!$EO:$EO)+SUMIF(Data!$C:$C,C41,Data!$EQ:$EQ)+SUMIF(Data!$C:$C,C41,Data!$ES:$ES) -> 243.98261 | H41: =SUMIF(Data!$C:$C,C41,Data!$DJ:$DJ)+SUMIF(Data!$C:$C,C41,Data!$DL:$DL)+SUMIF(Data!$C:$C,C41,Data!$DN:$DN)+SUMIF(Data!$C:$C,C41,Data!$DP:$DP)+SUMIF(Data!$C:$C,C41,Data!$DR:$DR)+SUMIF(Data!$C:$C,C41,Data!$DT:$DT)+SUMIF(Data!$C:$C,C41,Data!$DV:$DV)+SUMIF(Data!$C:$C,C41,Data!$DX:$DX)+SUMIF(Data!$C:$C,C41,Data!$DZ:$DZ)+SUMIF(Data!$C:$C,C41,Data!$EB:$EB)+SUMIF(Data!$C:$C,C41,Data!$ED:$ED)+SUMIF(Data!$C:$C,C41,Data!$EF:$EF)+SUMIF(Data!$C:$C,C41,Data!$EH:$EH)+SUMIF(Data!$C:$C,C41,Data!$EJ:$EJ)+SUMIF(Data!$C:$C,C41,Data!$EL:$EL)+SUMIF(Data!$C:$C,C41,Data!$EN:$EN)+SUMIF(Data!$C:$C,C41,Data!$EP:$EP)+SUMIF(Data!$C:$C,C41,Data!$ER:$ER)+SUMIF(Data!$C:$C,C41,Data!$ET:$ET) -> 3.118 | I41: =G41/19 -> 12.84119 | J41: =H41/19 -> 0.16410526 | K41: =IFERROR(INDEX(Data!$ES:$ES,MATCH(C41,Data!$C:$C,0)),0) -> 0 | L41: =IFERROR(INDEX(Data!$ET:$ET,MATCH(C41,Data!$C:$C,0)),0) -> 0 | M41: =IFERROR(INDEX(Data!$I$3:$ER$553,MATCH($C41,Data!$C$3:$C$553,0),MATCH(DATE(RIGHT($B$5,4),MID($B$5,4,2),LEFT($B$5,2))-42,Data!$I$1:$ER$1,0)),0) -> 0 | N41: {=IFERROR(INDEX(Data!$I$3:$ER$553,MATCH($C41,Data!$C$3:$C$553,0),MATCH(DATE(RIGHT($B$5,4),MID($B$5,4,2),LEFT($B$5,2))-42,Data!$I$1:$ER$1,0)+1),0)} -> 0 | O41: =IFERROR(INDEX(Data!$I$3:$ER$553,MATCH($C41,Data!$C$3:$C$553,0),MATCH($M$5,Data!$I$1:$ER$1,0)),0) -> 113.66957 | P41: {=IFERROR(INDEX(Data!$I$3:$ER$553,MATCH($C41,Data!$C$3:$C$553,0),MATCH($M$5,Data!$I$1:$ER$1,0)+1),0)} -> 1.634 | Q41: =IF(R41="","",IF(H41=0,0,R41*(G41/H41))) | T41: Grant Types: | U41: {=_xlfn.TEXTJOIN(", ",TRUE,IF(($U$3:$U$38>=$T$39)*($U$3:$U$38<$T$39+7),$V$3:$V$38,""))}
A42: 202 | B42: BEEF | C42: 63840 | D42: BEEF ESPETADA | E42: 0 | F42: 0 | G42: =SUMIF(Data!$C:$C,C42,Data!$DI:$DI)+SUMIF(Data!$C:$C,C42,Data!$DK:$DK)+SUMIF(Data!$C:$C,C42,Data!$DM:$DM)+SUMIF(Data!$C:$C,C42,Data!$DO:$DO)+SUMIF(Data!$C:$C,C42,Data!$DQ:$DQ)+SUMIF(Data!$C:$C,C42,Data!$DS:$DS)+SUMIF(Data!$C:$C,C42,Data!$DU:$DU)+SUMIF(Data!$C:$C,C42,Data!$DW:$DW)+SUMIF(Data!$C:$C,C42,Data!$DY:$DY)+SUMIF(Data!$C:$C,C42,Data!$EA:$EA)+SUMIF(Data!$C:$C,C42,Data!$EC:$EC)+SUMIF(Data!$C:$C,C42,Data!$EE:$EE)+SUMIF(Data!$C:$C,C42,Data!$EG:$EG)+SUMIF(Data!$C:$C,C42,Data!$EI:$EI)+SUMIF(Data!$C:$C,C42,Data!$EK:$EK)+SUMIF(Data!$C:$C,C42,Data!$EM:$EM)+SUMIF(Data!$C:$C,C42,Data!$EO:$EO)+SUMIF(Data!$C:$C,C42,Data!$EQ:$EQ)+SUMIF(Data!$C:$C,C42,Data!$ES:$ES) -> 55.956522 | H42: =SUMIF(Data!$C:$C,C42,Data!$DJ:$DJ)+SUMIF(Data!$C:$C,C42,Data!$DL:$DL)+SUMIF(Data!$C:$C,C42,Data!$DN:$DN)+SUMIF(Data!$C:$C,C42,Data!$DP:$DP)+SUMIF(Data!$C:$C,C42,Data!$DR:$DR)+SUMIF(Data!$C:$C,C42,Data!$DT:$DT)+SUMIF(Data!$C:$C,C42,Data!$DV:$DV)+SUMIF(Data!$C:$C,C42,Data!$DX:$DX)+SUMIF(Data!$C:$C,C42,Data!$DZ:$DZ)+SUMIF(Data!$C:$C,C42,Data!$EB:$EB)+SUMIF(Data!$C:$C,C42,Data!$ED:$ED)+SUMIF(Data!$C:$C,C42,Data!$EF:$EF)+SUMIF(Data!$C:$C,C42,Data!$EH:$EH)+SUMIF(Data!$C:$C,C42,Data!$EJ:$EJ)+SUMIF(Data!$C:$C,C42,Data!$EL:$EL)+SUMIF(Data!$C:$C,C42,Data!$EN:$EN)+SUMIF(Data!$C:$C,C42,Data!$EP:$EP)+SUMIF(Data!$C:$C,C42,Data!$ER:$ER)+SUMIF(Data!$C:$C,C42,Data!$ET:$ET) -> 0.346 | I42: =G42/19 -> 2.9450801 | J42: =H42/19 -> 0.018210526 | K42: =IFERROR(INDEX(Data!$ES:$ES,MATCH(C42,Data!$C:$C,0)),0) -> 0 | L42: =IFERROR(INDEX(Data!$ET:$ET,MATCH(C42,Data!$C:$C,0)),0) -> 0 | M42: =IFERROR(INDEX(Data!$I$3:$ER$553,MATCH($C42,Data!$C$3:$C$553,0),MATCH(DATE(RIGHT($B$5,4),MID($B$5,4,2),LEFT($B$5,2))-42,Data!$I$1:$ER$1,0)),0) -> 0 | N42: {=IFERROR(INDEX(Data!$I$3:$ER$553,MATCH($C42,Data!$C$3:$C$553,0),MATCH(DATE(RIGHT($B$5,4),MID($B$5,4,2),LEFT($B$5,2))-42,Data!$I$1:$ER$1,0)+1),0)} -> 0 | O42: =IFERROR(INDEX(Data!$I$3:$ER$553,MATCH($C42,Data!$C$3:$C$553,0),MATCH($M$5,Data!$I$1:$ER$1,0)),0) -> 0 | P42: {=IFERROR(INDEX(Data!$I$3:$ER$553,MATCH($C42,Data!$C$3:$C$553,0),MATCH($M$5,Data!$I$1:$ER$1,0)+1),0)} -> 0 | Q42: =IF(R42="","",IF(H42=0,0,R42*(G42/H42))) | T42: Payment Dates: | U42: {=_xlfn.TEXTJOIN(", ",TRUE,IF(($U$3:$U$38>=$T$39)*($U$3:$U$38<$T$39+7),TEXT($U$3:$U$38,"dd mmm"),""))}
A43: BEEF Subtotal | E43: =SUM(E13:E42) -> 255127.61 | F43: =SUM(F13:F42) -> 2455.131 | G43: =SUM(G13:G42) -> 380494.55 | H43: =SUM(H13:H42) -> 3301.769 | I43: =AVERAGE(I13:I42) -> 667.53429 | J43: =AVERAGE(J13:J42) -> 5.7925772 | K43: =SUM(K13:K42) -> 13992.122 | L43: =SUM(L13:L42) -> 176.993 | M43: =SUM(M13:M42) -> 14651.478 | N43: =SUM(N13:N42) -> 135.869 | O43: =SUM(O13:O42) -> 14256.33 | P43: =SUM(P13:P42) -> 189.91 | Q43: =SUM(Q13:Q42) -> 0 | R43: =SUM(R13:R42) -> 0
T44: ⚠️ SASSA WEEK ALERT
A45: 204 | B45: LAMB | C45: 32041 | D45: 1/4 LAMB | E45: 17672.983 | F45: 134.054 | G45: =SUMIF(Data!$C:$C,C45,Data!$DI:$DI)+SUMIF(Data!$C:$C,C45,Data!$DK:$DK)+SUMIF(Data!$C:$C,C45,Data!$DM:$DM)+SUMIF(Data!$C:$C,C45,Data!$DO:$DO)+SUMIF(Data!$C:$C,C45,Data!$DQ:$DQ)+SUMIF(Data!$C:$C,C45,Data!$DS:$DS)+SUMIF(Data!$C:$C,C45,Data!$DU:$DU)+SUMIF(Data!$C:$C,C45,Data!$DW:$DW)+SUMIF(Data!$C:$C,C45,Data!$DY:$DY)+SUMIF(Data!$C:$C,C45,Data!$EA:$EA)+SUMIF(Data!$C:$C,C45,Data!$EC:$EC)+SUMIF(Data!$C:$C,C45,Data!$EE:$EE)+SUMIF(Data!$C:$C,C45,Data!$EG:$EG)+SUMIF(Data!$C:$C,C45,Data!$EI:$EI)+SUMIF(Data!$C:$C,C45,Data!$EK:$EK)+SUMIF(Data!$C:$C,C45,Data!$EM:$EM)+SUMIF(Data!$C:$C,C45,Data!$EO:$EO)+SUMIF(Data!$C:$C,C45,Data!$EQ:$EQ)+SUMIF(Data!$C:$C,C45,Data!$ES:$ES) -> 37132.957 | H45: =SUMIF(Data!$C:$C,C45,Data!$DJ:$DJ)+SUMIF(Data!$C:$C,C45,Data!$DL:$DL)+SUMIF(Data!$C:$C,C45,Data!$DN:$DN)+SUMIF(Data!$C:$C,C45,Data!$DP:$DP)+SUMIF(Data!$C:$C,C45,Data!$DR:$DR)+SUMIF(Data!$C:$C,C45,Data!$DT:$DT)+SUMIF(Data!$C:$C,C45,Data!$DV:$DV)+SUMIF(Data!$C:$C,C45,Data!$DX:$DX)+SUMIF(Data!$C:$C,C45,Data!$DZ:$DZ)+SUMIF(Data!$C:$C,C45,Data!$EB:$EB)+SUMIF(Data!$C:$C,C45,Data!$ED:$ED)+SUMIF(Data!$C:$C,C45,Data!$EF:$EF)+SUMIF(Data!$C:$C,C45,Data!$EH:$EH)+SUMIF(Data!$C:$C,C45,Data!$EJ:$EJ)+SUMIF(Data!$C:$C,C45,Data!$EL:$EL)+SUMIF(Data!$C:$C,C45,Data!$EN:$EN)+SUMIF(Data!$C:$C,C45,Data!$EP:$EP)+SUMIF(Data!$C:$C,C45,Data!$ER:$ER)+SUMIF(Data!$C:$C,C45,Data!$ET:$ET) -> 303.732 | I45: =G45/19 -> 1954.3661 | J45: =H45/19 -> 15.985895 | K45: =IFERROR(INDEX(Data!$ES:$ES,MATCH(C45,Data!$C:$C,0)),0) -> 0 | L45: =IFERROR(INDEX(Data!$ET:$ET,MATCH(C45,Data!$C:$C,0)),0) -> 0 | M45: =IFERROR(INDEX(Data!$I$3:$ER$553,MATCH($C45,Data!$C$3:$C$553,0),MATCH(DATE(RIGHT($B$5,4),MID($B$5,4,2),LEFT($B$5,2))-42,Data!$I$1:$ER$1,0)),0) -> 400.4087 | N45: {=IFERROR(INDEX(Data!$I$3:$ER$553,MATCH($C45,Data!$C$3:$C$553,0),MATCH(DATE(RIGHT($B$5,4),MID($B$5,4,2),LEFT($B$5,2))-42,Data!$I$1:$ER$1,0)+1),0)} -> 3.07 | O45: =IFERROR(INDEX(Data!$I$3:$ER$553,MATCH($C45,Data!$C$3:$C$553,0),MATCH($M$5,Data!$I$1:$ER$1,0)),0) -> 2184.8 | P45: {=IFERROR(INDEX(Data!$I$3:$ER$553,MATCH($C45,Data!$C$3:$C$553,0),MATCH($M$5,Data!$I$1:$ER$1,0)+1),0)} -> 14.628 | Q45: =IF(R45="","",IF(H45=0,0,R45*(G45/H45))) | T45: =IF(U40=0,"✓ No SASSA payments in selected week ("&TEXT($T$39,"dd mmm")&" - "&TEXT($T$39+6,"dd mmm")&")","⚠️ "&U40&" SASSA payment(s) in this week!") -> ✓ No SASSA payments in selected week (11 May - 17 May)
A46: 204 | B46: LAMB | C46: 34239 | D46: LAMB BEST END | E46: 20260.13 | F46: 122.72 | G46: =SUMIF(Data!$C:$C,C46,Data!$DI:$DI)+SUMIF(Data!$C:$C,C46,Data!$DK:$DK)+SUMIF(Data!$C:$C,C46,Data!$DM:$DM)+SUMIF(Data!$C:$C,C46,Data!$DO:$DO)+SUMIF(Data!$C:$C,C46,Data!$DQ:$DQ)+SUMIF(Data!$C:$C,C46,Data!$DS:$DS)+SUMIF(Data!$C:$C,C46,Data!$DU:$DU)+SUMIF(Data!$C:$C,C46,Data!$DW:$DW)+SUMIF(Data!$C:$C,C46,Data!$DY:$DY)+SUMIF(Data!$C:$C,C46,Data!$EA:$EA)+SUMIF(Data!$C:$C,C46,Data!$EC:$EC)+SUMIF(Data!$C:$C,C46,Data!$EE:$EE)+SUMIF(Data!$C:$C,C46,Data!$EG:$EG)+SUMIF(Data!$C:$C,C46,Data!$EI:$EI)+SUMIF(Data!$C:$C,C46,Data!$EK:$EK)+SUMIF(Data!$C:$C,C46,Data!$EM:$EM)+SUMIF(Data!$C:$C,C46,Data!$EO:$EO)+SUMIF(Data!$C:$C,C46,Data!$EQ:$EQ)+SUMIF(Data!$C:$C,C46,Data!$ES:$ES) -> 29576.426 | H46: =SUMIF(Data!$C:$C,C46,Data!$DJ:$DJ)+SUMIF(Data!$C:$C,C46,Data!$DL:$DL)+SUMIF(Data!$C:$C,C46,Data!$DN:$DN)+SUMIF(Data!$C:$C,C46,Data!$DP:$DP)+SUMIF(Data!$C:$C,C46,Data!$DR:$DR)+SUMIF(Data!$C:$C,C46,Data!$DT:$DT)+SUMIF(Data!$C:$C,C46,Data!$DV:$DV)+SUMIF(Data!$C:$C,C46,Data!$DX:$DX)+SUMIF(Data!$C:$C,C46,Data!$DZ:$DZ)+SUMIF(Data!$C:$C,C46,Data!$EB:$EB)+SUMIF(Data!$C:$C,C46,Data!$ED:$ED)+SUMIF(Data!$C:$C,C46,Data!$EF:$EF)+SUMIF(Data!$C:$C,C46,Data!$EH:$EH)+SUMIF(Data!$C:$C,C46,Data!$EJ:$EJ)+SUMIF(Data!$C:$C,C46,Data!$EL:$EL)+SUMIF(Data!$C:$C,C46,Data!$EN:$EN)+SUMIF(Data!$C:$C,C46,Data!$EP:$EP)+SUMIF(Data!$C:$C,C46,Data!$ER:$ER)+SUMIF(Data!$C:$C,C46,Data!$ET:$ET) -> 182.112 | I46: =G46/19 -> 1556.654 | J46: =H46/19 -> 9.5848421 | K46: =IFERROR(INDEX(Data!$ES:$ES,MATCH(C46,Data!$C:$C,0)),0) -> 1024.5043 | L46: =IFERROR(INDEX(Data!$ET:$ET,MATCH(C46,Data!$C:$C,0)),0) -> 6.546 | M46: =IFERROR(INDEX(Data!$I$3:$ER$553,MATCH($C46,Data!$C$3:$C$553,0),MATCH(DATE(RIGHT($B$5,4),MID($B$5,4,2),LEFT($B$5,2))-42,Data!$I$1:$ER$1,0)),0) -> 676.03478 | N46: {=IFERROR(INDEX(Data!$I$3:$ER$553,MATCH($C46,Data!$C$3:$C$553,0),MATCH(DATE(RIGHT($B$5,4),MID($B$5,4,2),LEFT($B$5,2))-42,Data!$I$1:$ER$1,0)+1),0)} -> 4.092 | O46: =IFERROR(INDEX(Data!$I$3:$ER$553,MATCH($C46,Data!$C$3:$C$553,0),MATCH($M$5,Data!$I$1:$ER$1,0)),0) -> 1361.7304 | P46: {=IFERROR(INDEX(Data!$I$3:$ER$553,MATCH($C46,Data!$C$3:$C$553,0),MATCH($M$5,Data!$I$1:$ER$1,0)+1),0)} -> 7.514 | Q46: =IF(R46="","",IF(H46=0,0,R46*(G46/H46))) | T46: =IF(U40>0,"Grant Types: "&U41,"")
A47: 204 | B47: LAMB | C47: 39811 | D47: LAMB LEG CHOPS | E47: 26881.513 | F47: 164.496 | G47: =SUMIF(Data!$C:$C,C47,Data!$DI:$DI)+SUMIF(Data!$C:$C,C47,Data!$DK:$DK)+SUMIF(Data!$C:$C,C47,Data!$DM:$DM)+SUMIF(Data!$C:$C,C47,Data!$DO:$DO)+SUMIF(Data!$C:$C,C47,Data!$DQ:$DQ)+SUMIF(Data!$C:$C,C47,Data!$DS:$DS)+SUMIF(Data!$C:$C,C47,Data!$DU:$DU)+SUMIF(Data!$C:$C,C47,Data!$DW:$DW)+SUMIF(Data!$C:$C,C47,Data!$DY:$DY)+SUMIF(Data!$C:$C,C47,Data!$EA:$EA)+SUMIF(Data!$C:$C,C47,Data!$EC:$EC)+SUMIF(Data!$C:$C,C47,Data!$EE:$EE)+SUMIF(Data!$C:$C,C47,Data!$EG:$EG)+SUMIF(Data!$C:$C,C47,Data!$EI:$EI)+SUMIF(Data!$C:$C,C47,Data!$EK:$EK)+SUMIF(Data!$C:$C,C47,Data!$EM:$EM)+SUMIF(Data!$C:$C,C47,Data!$EO:$EO)+SUMIF(Data!$C:$C,C47,Data!$EQ:$EQ)+SUMIF(Data!$C:$C,C47,Data!$ES:$ES) -> 29434.374 | H47: =SUMIF(Data!$C:$C,C47,Data!$DJ:$DJ)+SUMIF(Data!$C:$C,C47,Data!$DL:$DL)+SUMIF(Data!$C:$C,C47,Data!$DN:$DN)+SUMIF(Data!$C:$C,C47,Data!$DP:$DP)+SUMIF(Data!$C:$C,C47,Data!$DR:$DR)+SUMIF(Data!$C:$C,C47,Data!$DT:$DT)+SUMIF(Data!$C:$C,C47,Data!$DV:$DV)+SUMIF(Data!$C:$C,C47,Data!$DX:$DX)+SUMIF(Data!$C:$C,C47,Data!$DZ:$DZ)+SUMIF(Data!$C:$C,C47,Data!$EB:$EB)+SUMIF(Data!$C:$C,C47,Data!$ED:$ED)+SUMIF(Data!$C:$C,C47,Data!$EF:$EF)+SUMIF(Data!$C:$C,C47,Data!$EH:$EH)+SUMIF(Data!$C:$C,C47,Data!$EJ:$EJ)+SUMIF(Data!$C:$C,C47,Data!$EL:$EL)+SUMIF(Data!$C:$C,C47,Data!$EN:$EN)+SUMIF(Data!$C:$C,C47,Data!$EP:$EP)+SUMIF(Data!$C:$C,C47,Data!$ER:$ER)+SUMIF(Data!$C:$C,C47,Data!$ET:$ET) -> 157.786 | I47: =G47/19 -> 1549.1776 | J47: =H47/19 -> 8.3045263 | K47: =IFERROR(INDEX(Data!$ES:$ES,MATCH(C47,Data!$C:$C,0)),0) -> 2036.1652 | L47: =IFERROR(INDEX(Data!$ET:$ET,MATCH(C47,Data!$C:$C,0)),0) -> 13.01 | M47: =IFERROR(INDEX(Data!$I$3:$ER$553,MATCH($C47,Data!$C$3:$C$553,0),MATCH(DATE(RIGHT($B$5,4),MID($B$5,4,2),LEFT($B$5,2))-42,Data!$I$1:$ER$1,0)),0) -> 1165.3391 | N47: {=IFERROR(INDEX(Data!$I$3:$ER$553,MATCH($C47,Data!$C$3:$C$553,0),MATCH(DATE(RIGHT($B$5,4),MID($B$5,4,2),LEFT($B$5,2))-42,Data!$I$1:$ER$1,0)+1),0)} -> 6.092 | O47: =IFERROR(INDEX(Data!$I$3:$ER$553,MATCH($C47,Data!$C$3:$C$553,0),MATCH($M$5,Data!$I$1:$ER$1,0)),0) -> 1372.7739 | P47: {=IFERROR(INDEX(Data!$I$3:$ER$553,MATCH($C47,Data!$C$3:$C$553,0),MATCH($M$5,Data!$I$1:$ER$1,0)+1),0)} -> 7.894 | Q47: =IF(R47="","",IF(H47=0,0,R47*(G47/H47))) | T47: =IF(U40>0,"Payment Dates: "&U42,"")
A48: 204 | B48: LAMB | C48: 34242 | D48: LAM RIB & LOIN | E48: 27940.13 | F48: 156.75 | G48: =SUMIF(Data!$C:$C,C48,Data!$DI:$DI)+SUMIF(Data!$C:$C,C48,Data!$DK:$DK)+SUMIF(Data!$C:$C,C48,Data!$DM:$DM)+SUMIF(Data!$C:$C,C48,Data!$DO:$DO)+SUMIF(Data!$C:$C,C48,Data!$DQ:$DQ)+SUMIF(Data!$C:$C,C48,Data!$DS:$DS)+SUMIF(Data!$C:$C,C48,Data!$DU:$DU)+SUMIF(Data!$C:$C,C48,Data!$DW:$DW)+SUMIF(Data!$C:$C,C48,Data!$DY:$DY)+SUMIF(Data!$C:$C,C48,Data!$EA:$EA)+SUMIF(Data!$C:$C,C48,Data!$EC:$EC)+SUMIF(Data!$C:$C,C48,Data!$EE:$EE)+SUMIF(Data!$C:$C,C48,Data!$EG:$EG)+SUMIF(Data!$C:$C,C48,Data!$EI:$EI)+SUMIF(Data!$C:$C,C48,Data!$EK:$EK)+SUMIF(Data!$C:$C,C48,Data!$EM:$EM)+SUMIF(Data!$C:$C,C48,Data!$EO:$EO)+SUMIF(Data!$C:$C,C48,Data!$EQ:$EQ)+SUMIF(Data!$C:$C,C48,Data!$ES:$ES) -> 28525.704 | H48: =SUMIF(Data!$C:$C,C48,Data!$DJ:$DJ)+SUMIF(Data!$C:$C,C48,Data!$DL:$DL)+SUMIF(Data!$C:$C,C48,Data!$DN:$DN)+SUMIF(Data!$C:$C,C48,Data!$DP:$DP)+SUMIF(Data!$C:$C,C48,Data!$DR:$DR)+SUMIF(Data!$C:$C,C48,Data!$DT:$DT)+SUMIF(Data!$C:$C,C48,Data!$DV:$DV)+SUMIF(Data!$C:$C,C48,Data!$DX:$DX)+SUMIF(Data!$C:$C,C48,Data!$DZ:$DZ)+SUMIF(Data!$C:$C,C48,Data!$EB:$EB)+SUMIF(Data!$C:$C,C48,Data!$ED:$ED)+SUMIF(Data!$C:$C,C48,Data!$EF:$EF)+SUMIF(Data!$C:$C,C48,Data!$EH:$EH)+SUMIF(Data!$C:$C,C48,Data!$EJ:$EJ)+SUMIF(Data!$C:$C,C48,Data!$EL:$EL)+SUMIF(Data!$C:$C,C48,Data!$EN:$EN)+SUMIF(Data!$C:$C,C48,Data!$EP:$EP)+SUMIF(Data!$C:$C,C48,Data!$ER:$ER)+SUMIF(Data!$C:$C,C48,Data!$ET:$ET) -> 142.837 | I48: =G48/19 -> 1501.3529 | J48: =H48/19 -> 7.5177368 | K48: =IFERROR(INDEX(Data!$ES:$ES,MATCH(C48,Data!$C:$C,0)),0) -> 1422.8522 | L48: =IFERROR(INDEX(Data!$ET:$ET,MATCH(C48,Data!$C:$C,0)),0) -> 9.091 | M48: =IFERROR(INDEX(Data!$I$3:$ER$553,MATCH($C48,Data!$C$3:$C$553,0),MATCH(DATE(RIGHT($B$5,4),MID($B$5,4,2),LEFT($B$5,2))-42,Data!$I$1:$ER$1,0)),0) -> 1418.0348 | N48: {=IFERROR(INDEX(Data!$I$3:$ER$553,MATCH($C48,Data!$C$3:$C$553,0),MATCH(DATE(RIGHT($B$5,4),MID($B$5,4,2),LEFT($B$5,2))-42,Data!$I$1:$ER$1,0)+1),0)} -> 6.938 | O48: =IFERROR(INDEX(Data!$I$3:$ER$553,MATCH($C48,Data!$C$3:$C$553,0),MATCH($M$5,Data!$I$1:$ER$1,0)),0) -> 2195.0783 | P48: {=IFERROR(INDEX(Data!$I$3:$ER$553,MATCH($C48,Data!$C$3:$C$553,0),MATCH($M$5,Data!$I$1:$ER$1,0)+1),0)} -> 10.976 | Q48: =IF(R48="","",IF(H48=0,0,R48*(G48/H48))) | T48: =IF(U40>0,"💡 Expect higher foot traffic & sales during SASSA week!","")
A49: 204 | B49: LAMB | C49: 55100 | D49: LAMB FQ PACK | E49: 0 | F49: 0 | G49: =SUMIF(Data!$C:$C,C49,Data!$DI:$DI)+SUMIF(Data!$C:$C,C49,Data!$DK:$DK)+SUMIF(Data!$C:$C,C49,Data!$DM:$DM)+SUMIF(Data!$C:$C,C49,Data!$DO:$DO)+SUMIF(Data!$C:$C,C49,Data!$DQ:$DQ)+SUMIF(Data!$C:$C,C49,Data!$DS:$DS)+SUMIF(Data!$C:$C,C49,Data!$DU:$DU)+SUMIF(Data!$C:$C,C49,Data!$DW:$DW)+SUMIF(Data!$C:$C,C49,Data!$DY:$DY)+SUMIF(Data!$C:$C,C49,Data!$EA:$EA)+SUMIF(Data!$C:$C,C49,Data!$EC:$EC)+SUMIF(Data!$C:$C,C49,Data!$EE:$EE)+SUMIF(Data!$C:$C,C49,Data!$EG:$EG)+SUMIF(Data!$C:$C,C49,Data!$EI:$EI)+SUMIF(Data!$C:$C,C49,Data!$EK:$EK)+SUMIF(Data!$C:$C,C49,Data!$EM:$EM)+SUMIF(Data!$C:$C,C49,Data!$EO:$EO)+SUMIF(Data!$C:$C,C49,Data!$EQ:$EQ)+SUMIF(Data!$C:$C,C49,Data!$ES:$ES) -> 18316.983 | H49: =SUMIF(Data!$C:$C,C49,Data!$DJ:$DJ)+SUMIF(Data!$C:$C,C49,Data!$DL:$DL)+SUMIF(Data!$C:$C,C49,Data!$DN:$DN)+SUMIF(Data!$C:$C,C49,Data!$DP:$DP)+SUMIF(Data!$C:$C,C49,Data!$DR:$DR)+SUMIF(Data!$C:$C,C49,Data!$DT:$DT)+SUMIF(Data!$C:$C,C49,Data!$DV:$DV)+SUMIF(Data!$C:$C,C49,Data!$DX:$DX)+SUMIF(Data!$C:$C,C49,Data!$DZ:$DZ)+SUMIF(Data!$C:$C,C49,Data!$EB:$EB)+SUMIF(Data!$C:$C,C49,Data!$ED:$ED)+SUMIF(Data!$C:$C,C49,Data!$EF:$EF)+SUMIF(Data!$C:$C,C49,Data!$EH:$EH)+SUMIF(Data!$C:$C,C49,Data!$EJ:$EJ)+SUMIF(Data!$C:$C,C49,Data!$EL:$EL)+SUMIF(Data!$C:$C,C49,Data!$EN:$EN)+SUMIF(Data!$C:$C,C49,Data!$EP:$EP)+SUMIF(Data!$C:$C,C49,Data!$ER:$ER)+SUMIF(Data!$C:$C,C49,Data!$ET:$ET) -> 148.314 | I49: =G49/19 -> 964.05172 | J49: =H49/19 -> 7.806 | K49: =IFERROR(INDEX(Data!$ES:$ES,MATCH(C49,Data!$C:$C,0)),0) -> 0 | L49: =IFERROR(INDEX(Data!$ET:$ET,MATCH(C49,Data!$C:$C,0)),0) -> 0 | M49: =IFERROR(INDEX(Data!$I$3:$ER$553,MATCH($C49,Data!$C$3:$C$553,0),MATCH(DATE(RIGHT($B$5,4),MID($B$5,4,2),LEFT($B$5,2))-42,Data!$I$1:$ER$1,0)),0) -> 0 | N49: {=IFERROR(INDEX(Data!$I$3:$ER$553,MATCH($C49,Data!$C$3:$C$553,0),MATCH(DATE(RIGHT($B$5,4),MID($B$5,4,2),LEFT($B$5,2))-42,Data!$I$1:$ER$1,0)+1),0)} -> 0 | O49: =IFERROR(INDEX(Data!$I$3:$ER$553,MATCH($C49,Data!$C$3:$C$553,0),MATCH($M$5,Data!$I$1:$ER$1,0)),0) -> 0 | P49: {=IFERROR(INDEX(Data!$I$3:$ER$553,MATCH($C49,Data!$C$3:$C$553,0),MATCH($M$5,Data!$I$1:$ER$1,0)+1),0)} -> 0 | Q49: =IF(R49="","",IF(H49=0,0,R49*(G49/H49))) | T49: Source: SASSA Official Payment Schedule 2026
A50: 204 | B50: LAMB | C50: 34250 | D50: LAMB SHANK | E50: 10582.452 | F50: 70.939 | G50: =SUMIF(Data!$C:$C,C50,Data!$DI:$DI)+SUMIF(Data!$C:$C,C50,Data!$DK:$DK)+SUMIF(Data!$C:$C,C50,Data!$DM:$DM)+SUMIF(Data!$C:$C,C50,Data!$DO:$DO)+SUMIF(Data!$C:$C,C50,Data!$DQ:$DQ)+SUMIF(Data!$C:$C,C50,Data!$DS:$DS)+SUMIF(Data!$C:$C,C50,Data!$DU:$DU)+SUMIF(Data!$C:$C,C50,Data!$DW:$DW)+SUMIF(Data!$C:$C,C50,Data!$DY:$DY)+SUMIF(Data!$C:$C,C50,Data!$EA:$EA)+SUMIF(Data!$C:$C,C50,Data!$EC:$EC)+SUMIF(Data!$C:$C,C50,Data!$EE:$EE)+SUMIF(Data!$C:$C,C50,Data!$EG:$EG)+SUMIF(Data!$C:$C,C50,Data!$EI:$EI)+SUMIF(Data!$C:$C,C50,Data!$EK:$EK)+SUMIF(Data!$C:$C,C50,Data!$EM:$EM)+SUMIF(Data!$C:$C,C50,Data!$EO:$EO)+SUMIF(Data!$C:$C,C50,Data!$EQ:$EQ)+SUMIF(Data!$C:$C,C50,Data!$ES:$ES) -> 15577.87 | H50: =SUMIF(Data!$C:$C,C50,Data!$DJ:$DJ)+SUMIF(Data!$C:$C,C50,Data!$DL:$DL)+SUMIF(Data!$C:$C,C50,Data!$DN:$DN)+SUMIF(Data!$C:$C,C50,Data!$DP:$DP)+SUMIF(Data!$C:$C,C50,Data!$DR:$DR)+SUMIF(Data!$C:$C,C50,Data!$DT:$DT)+SUMIF(Data!$C:$C,C50,Data!$DV:$DV)+SUMIF(Data!$C:$C,C50,Data!$DX:$DX)+SUMIF(Data!$C:$C,C50,Data!$DZ:$DZ)+SUMIF(Data!$C:$C,C50,Data!$EB:$EB)+SUMIF(Data!$C:$C,C50,Data!$ED:$ED)+SUMIF(Data!$C:$C,C50,Data!$EF:$EF)+SUMIF(Data!$C:$C,C50,Data!$EH:$EH)+SUMIF(Data!$C:$C,C50,Data!$EJ:$EJ)+SUMIF(Data!$C:$C,C50,Data!$EL:$EL)+SUMIF(Data!$C:$C,C50,Data!$EN:$EN)+SUMIF(Data!$C:$C,C50,Data!$EP:$EP)+SUMIF(Data!$C:$C,C50,Data!$ER:$ER)+SUMIF(Data!$C:$C,C50,Data!$ET:$ET) -> 97.144 | I50: =G50/19 -> 819.88787 | J50: =H50/19 -> 5.1128421 | K50: =IFERROR(INDEX(Data!$ES:$ES,MATCH(C50,Data!$C:$C,0)),0) -> 391.77391 | L50: =IFERROR(INDEX(Data!$ET:$ET,MATCH(C50,Data!$C:$C,0)),0) -> 2.56 | M50: =IFERROR(INDEX(Data!$I$3:$ER$553,MATCH($C50,Data!$C$3:$C$553,0),MATCH(DATE(RIGHT($B$5,4),MID($B$5,4,2),LEFT($B$5,2))-42,Data!$I$1:$ER$1,0)),0) -> 535.02609 | N50: {=IFERROR(INDEX(Data!$I$3:$ER$553,MATCH($C50,Data!$C$3:$C$553,0),MATCH(DATE(RIGHT($B$5,4),MID($B$5,4,2),LEFT($B$5,2))-42,Data!$I$1:$ER$1,0)+1),0)} -> 3.342 | O50: =IFERROR(INDEX(Data!$I$3:$ER$553,MATCH($C50,Data!$C$3:$C$553,0),MATCH($M$5,Data!$I$1:$ER$1,0)),0) -> 1203.8261 | P50: {=IFERROR(INDEX(Data!$I$3:$ER$553,MATCH($C50,Data!$C$3:$C$553,0),MATCH($M$5,Data!$I$1:$ER$1,0)+1),0)} -> 8.174 | Q50: =IF(R50="","",IF(H50=0,0,R50*(G50/H50)))
A51: 204 | B51: LAMB | C51: 45848 | D51: LAMB STEW | E51: 3184.7043 | F51: 22.316 | G51: =SUMIF(Data!$C:$C,C51,Data!$DI:$DI)+SUMIF(Data!$C:$C,C51,Data!$DK:$DK)+SUMIF(Data!$C:$C,C51,Data!$DM:$DM)+SUMIF(Data!$C:$C,C51,Data!$DO:$DO)+SUMIF(Data!$C:$C,C51,Data!$DQ:$DQ)+SUMIF(Data!$C:$C,C51,Data!$DS:$DS)+SUMIF(Data!$C:$C,C51,Data!$DU:$DU)+SUMIF(Data!$C:$C,C51,Data!$DW:$DW)+SUMIF(Data!$C:$C,C51,Data!$DY:$DY)+SUMIF(Data!$C:$C,C51,Data!$EA:$EA)+SUMIF(Data!$C:$C,C51,Data!$EC:$EC)+SUMIF(Data!$C:$C,C51,Data!$EE:$EE)+SUMIF(Data!$C:$C,C51,Data!$EG:$EG)+SUMIF(Data!$C:$C,C51,Data!$EI:$EI)+SUMIF(Data!$C:$C,C51,Data!$EK:$EK)+SUMIF(Data!$C:$C,C51,Data!$EM:$EM)+SUMIF(Data!$C:$C,C51,Data!$EO:$EO)+SUMIF(Data!$C:$C,C51,Data!$EQ:$EQ)+SUMIF(Data!$C:$C,C51,Data!$ES:$ES) -> 10514.87 | H51: =SUMIF(Data!$C:$C,C51,Data!$DJ:$DJ)+SUMIF(Data!$C:$C,C51,Data!$DL:$DL)+SUMIF(Data!$C:$C,C51,Data!$DN:$DN)+SUMIF(Data!$C:$C,C51,Data!$DP:$DP)+SUMIF(Data!$C:$C,C51,Data!$DR:$DR)+SUMIF(Data!$C:$C,C51,Data!$DT:$DT)+SUMIF(Data!$C:$C,C51,Data!$DV:$DV)+SUMIF(Data!$C:$C,C51,Data!$DX:$DX)+SUMIF(Data!$C:$C,C51,Data!$DZ:$DZ)+SUMIF(Data!$C:$C,C51,Data!$EB:$EB)+SUMIF(Data!$C:$C,C51,Data!$ED:$ED)+SUMIF(Data!$C:$C,C51,Data!$EF:$EF)+SUMIF(Data!$C:$C,C51,Data!$EH:$EH)+SUMIF(Data!$C:$C,C51,Data!$EJ:$EJ)+SUMIF(Data!$C:$C,C51,Data!$EL:$EL)+SUMIF(Data!$C:$C,C51,Data!$EN:$EN)+SUMIF(Data!$C:$C,C51,Data!$EP:$EP)+SUMIF(Data!$C:$C,C51,Data!$ER:$ER)+SUMIF(Data!$C:$C,C51,Data!$ET:$ET) -> 69.384 | I51: =G51/19 -> 553.41419 | J51: =H51/19 -> 3.6517895 | K51: =IFERROR(INDEX(Data!$ES:$ES,MATCH(C51,Data!$C:$C,0)),0) -> 632.82609 | L51: =IFERROR(INDEX(Data!$ET:$ET,MATCH(C51,Data!$C:$C,0)),0) -> 4.458 | M51: =IFERROR(INDEX(Data!$I$3:$ER$553,MATCH($C51,Data!$C$3:$C$553,0),MATCH(DATE(RIGHT($B$5,4),MID($B$5,4,2),LEFT($B$5,2))-42,Data!$I$1:$ER$1,0)),0) -> 737.61739 | N51: {=IFERROR(INDEX(Data!$I$3:$ER$553,MATCH($C51,Data!$C$3:$C$553,0),MATCH(DATE(RIGHT($B$5,4),MID($B$5,4,2),LEFT($B$5,2))-42,Data!$I$1:$ER$1,0)+1),0)} -> 4.82 | O51: =IFERROR(INDEX(Data!$I$3:$ER$553,MATCH($C51,Data!$C$3:$C$553,0),MATCH($M$5,Data!$I$1:$ER$1,0)),0) -> 176.95652 | P51: {=IFERROR(INDEX(Data!$I$3:$ER$553,MATCH($C51,Data!$C$3:$C$553,0),MATCH($M$5,Data!$I$1:$ER$1,0)+1),0)} -> 1.272 | Q51: =IF(R51="","",IF(H51=0,0,R51*(G51/H51)))
A52: 204 | B52: LAMB | C52: 34241 | D52: LAMB BRAAI CHOPS | E52: 1382.6696 | F52: 9.184 | G52: =SUMIF(Data!$C:$C,C52,Data!$DI:$DI)+SUMIF(Data!$C:$C,C52,Data!$DK:$DK)+SUMIF(Data!$C:$C,C52,Data!$DM:$DM)+SUMIF(Data!$C:$C,C52,Data!$DO:$DO)+SUMIF(Data!$C:$C,C52,Data!$DQ:$DQ)+SUMIF(Data!$C:$C,C52,Data!$DS:$DS)+SUMIF(Data!$C:$C,C52,Data!$DU:$DU)+SUMIF(Data!$C:$C,C52,Data!$DW:$DW)+SUMIF(Data!$C:$C,C52,Data!$DY:$DY)+SUMIF(Data!$C:$C,C52,Data!$EA:$EA)+SUMIF(Data!$C:$C,C52,Data!$EC:$EC)+SUMIF(Data!$C:$C,C52,Data!$EE:$EE)+SUMIF(Data!$C:$C,C52,Data!$EG:$EG)+SUMIF(Data!$C:$C,C52,Data!$EI:$EI)+SUMIF(Data!$C:$C,C52,Data!$EK:$EK)+SUMIF(Data!$C:$C,C52,Data!$EM:$EM)+SUMIF(Data!$C:$C,C52,Data!$EO:$EO)+SUMIF(Data!$C:$C,C52,Data!$EQ:$EQ)+SUMIF(Data!$C:$C,C52,Data!$ES:$ES) -> 7756.2 | H52: =SUMIF(Data!$C:$C,C52,Data!$DJ:$DJ)+SUMIF(Data!$C:$C,C52,Data!$DL:$DL)+SUMIF(Data!$C:$C,C52,Data!$DN:$DN)+SUMIF(Data!$C:$C,C52,Data!$DP:$DP)+SUMIF(Data!$C:$C,C52,Data!$DR:$DR)+SUMIF(Data!$C:$C,C52,Data!$DT:$DT)+SUMIF(Data!$C:$C,C52,Data!$DV:$DV)+SUMIF(Data!$C:$C,C52,Data!$DX:$DX)+SUMIF(Data!$C:$C,C52,Data!$DZ:$DZ)+SUMIF(Data!$C:$C,C52,Data!$EB:$EB)+SUMIF(Data!$C:$C,C52,Data!$ED:$ED)+SUMIF(Data!$C:$C,C52,Data!$EF:$EF)+SUMIF(Data!$C:$C,C52,Data!$EH:$EH)+SUMIF(Data!$C:$C,C52,Data!$EJ:$EJ)+SUMIF(Data!$C:$C,C52,Data!$EL:$EL)+SUMIF(Data!$C:$C,C52,Data!$EN:$EN)+SUMIF(Data!$C:$C,C52,Data!$EP:$EP)+SUMIF(Data!$C:$C,C52,Data!$ER:$ER)+SUMIF(Data!$C:$C,C52,Data!$ET:$ET) -> 44.63 | I52: =G52/19 -> 408.22105 | J52: =H52/19 -> 2.3489474 | K52: =IFERROR(INDEX(Data!$ES:$ES,MATCH(C52,Data!$C:$C,0)),0) -> 495.26957 | L52: =IFERROR(INDEX(Data!$ET:$ET,MATCH(C52,Data!$C:$C,0)),0) -> 2.848 | M52: =IFERROR(INDEX(Data!$I$3:$ER$553,MATCH($C52,Data!$C$3:$C$553,0),MATCH(DATE(RIGHT($B$5,4),MID($B$5,4,2),LEFT($B$5,2))-42,Data!$I$1:$ER$1,0)),0) -> 242.42609 | N52: {=IFERROR(INDEX(Data!$I$3:$ER$553,MATCH($C52,Data!$C$3:$C$553,0),MATCH(DATE(RIGHT($B$5,4),MID($B$5,4,2),LEFT($B$5,2))-42,Data!$I$1:$ER$1,0)+1),0)} -> 1.394 | O52: =IFERROR(INDEX(Data!$I$3:$ER$553,MATCH($C52,Data!$C$3:$C$553,0),MATCH($M$5,Data!$I$1:$ER$1,0)),0) -> 0 | P52: {=IFERROR(INDEX(Data!$I$3:$ER$553,MATCH($C52,Data!$C$3:$C$553,0),MATCH($M$5,Data!$I$1:$ER$1,0)+1),0)} -> 0 | Q52: =IF(R52="","",IF(H52=0,0,R52*(G52/H52)))
A53: 204 | B53: LAMB | C53: 34249 | D53: LAMB RIBLETS | E53: 5236.9826 | F53: 34.618 | G53: =SUMIF(Data!$C:$C,C53,Data!$DI:$DI)+SUMIF(Data!$C:$C,C53,Data!$DK:$DK)+SUMIF(Data!$C:$C,C53,Data!$DM:$DM)+SUMIF(Data!$C:$C,C53,Data!$DO:$DO)+SUMIF(Data!$C:$C,C53,Data!$DQ:$DQ)+SUMIF(Data!$C:$C,C53,Data!$DS:$DS)+SUMIF(Data!$C:$C,C53,Data!$DU:$DU)+SUMIF(Data!$C:$C,C53,Data!$DW:$DW)+SUMIF(Data!$C:$C,C53,Data!$DY:$DY)+SUMIF(Data!$C:$C,C53,Data!$EA:$EA)+SUMIF(Data!$C:$C,C53,Data!$EC:$EC)+SUMIF(Data!$C:$C,C53,Data!$EE:$EE)+SUMIF(Data!$C:$C,C53,Data!$EG:$EG)+SUMIF(Data!$C:$C,C53,Data!$EI:$EI)+SUMIF(Data!$C:$C,C53,Data!$EK:$EK)+SUMIF(Data!$C:$C,C53,Data!$EM:$EM)+SUMIF(Data!$C:$C,C53,Data!$EO:$EO)+SUMIF(Data!$C:$C,C53,Data!$EQ:$EQ)+SUMIF(Data!$C:$C,C53,Data!$ES:$ES) -> 6099.9565 | H53: =SUMIF(Data!$C:$C,C53,Data!$DJ:$DJ)+SUMIF(Data!$C:$C,C53,Data!$DL:$DL)+SUMIF(Data!$C:$C,C53,Data!$DN:$DN)+SUMIF(Data!$C:$C,C53,Data!$DP:$DP)+SUMIF(Data!$C:$C,C53,Data!$DR:$DR)+SUMIF(Data!$C:$C,C53,Data!$DT:$DT)+SUMIF(Data!$C:$C,C53,Data!$DV:$DV)+SUMIF(Data!$C:$C,C53,Data!$DX:$DX)+SUMIF(Data!$C:$C,C53,Data!$DZ:$DZ)+SUMIF(Data!$C:$C,C53,Data!$EB:$EB)+SUMIF(Data!$C:$C,C53,Data!$ED:$ED)+SUMIF(Data!$C:$C,C53,Data!$EF:$EF)+SUMIF(Data!$C:$C,C53,Data!$EH:$EH)+SUMIF(Data!$C:$C,C53,Data!$EJ:$EJ)+SUMIF(Data!$C:$C,C53,Data!$EL:$EL)+SUMIF(Data!$C:$C,C53,Data!$EN:$EN)+SUMIF(Data!$C:$C,C53,Data!$EP:$EP)+SUMIF(Data!$C:$C,C53,Data!$ER:$ER)+SUMIF(Data!$C:$C,C53,Data!$ET:$ET) -> 39.189 | I53: =G53/19 -> 321.05034 | J53: =H53/19 -> 2.0625789 | K53: =IFERROR(INDEX(Data!$ES:$ES,MATCH(C53,Data!$C:$C,0)),0) -> 376.33913 | L53: =IFERROR(INDEX(Data!$ET:$ET,MATCH(C53,Data!$C:$C,0)),0) -> 2.405 | M53: =IFERROR(INDEX(Data!$I$3:$ER$553,MATCH($C53,Data!$C$3:$C$553,0),MATCH(DATE(RIGHT($B$5,4),MID($B$5,4,2),LEFT($B$5,2))-42,Data!$I$1:$ER$1,0)),0) -> 244.15652 | N53: {=IFERROR(INDEX(Data!$I$3:$ER$553,MATCH($C53,Data!$C$3:$C$553,0),MATCH(DATE(RIGHT($B$5,4),MID($B$5,4,2),LEFT($B$5,2))-42,Data!$I$1:$ER$1,0)+1),0)} -> 1.56 | O53: =IFERROR(INDEX(Data!$I$3:$ER$553,MATCH($C53,Data!$C$3:$C$553,0),MATCH($M$5,Data!$I$1:$ER$1,0)),0) -> 119.28696 | P53: {=IFERROR(INDEX(Data!$I$3:$ER$553,MATCH($C53,Data!$C$3:$C$553,0),MATCH($M$5,Data!$I$1:$ER$1,0)+1),0)} -> 0.722 | Q53: =IF(R53="","",IF(H53=0,0,R53*(G53/H53)))
A54: 204 | B54: LAMB | C54: 63475 | D54: SPAR T&T LAMB SKPDJIES FR P/KG | E54: 0 | F54: 0 | G54: =SUMIF(Data!$C:$C,C54,Data!$DI:$DI)+SUMIF(Data!$C:$C,C54,Data!$DK:$DK)+SUMIF(Data!$C:$C,C54,Data!$DM:$DM)+SUMIF(Data!$C:$C,C54,Data!$DO:$DO)+SUMIF(Data!$C:$C,C54,Data!$DQ:$DQ)+SUMIF(Data!$C:$C,C54,Data!$DS:$DS)+SUMIF(Data!$C:$C,C54,Data!$DU:$DU)+SUMIF(Data!$C:$C,C54,Data!$DW:$DW)+SUMIF(Data!$C:$C,C54,Data!$DY:$DY)+SUMIF(Data!$C:$C,C54,Data!$EA:$EA)+SUMIF(Data!$C:$C,C54,Data!$EC:$EC)+SUMIF(Data!$C:$C,C54,Data!$EE:$EE)+SUMIF(Data!$C:$C,C54,Data!$EG:$EG)+SUMIF(Data!$C:$C,C54,Data!$EI:$EI)+SUMIF(Data!$C:$C,C54,Data!$EK:$EK)+SUMIF(Data!$C:$C,C54,Data!$EM:$EM)+SUMIF(Data!$C:$C,C54,Data!$EO:$EO)+SUMIF(Data!$C:$C,C54,Data!$EQ:$EQ)+SUMIF(Data!$C:$C,C54,Data!$ES:$ES) -> 5669.913 | H54: =SUMIF(Data!$C:$C,C54,Data!$DJ:$DJ)+SUMIF(Data!$C:$C,C54,Data!$DL:$DL)+SUMIF(Data!$C:$C,C54,Data!$DN:$DN)+SUMIF(Data!$C:$C,C54,Data!$DP:$DP)+SUMIF(Data!$C:$C,C54,Data!$DR:$DR)+SUMIF(Data!$C:$C,C54,Data!$DT:$DT)+SUMIF(Data!$C:$C,C54,Data!$DV:$DV)+SUMIF(Data!$C:$C,C54,Data!$DX:$DX)+SUMIF(Data!$C:$C,C54,Data!$DZ:$DZ)+SUMIF(Data!$C:$C,C54,Data!$EB:$EB)+SUMIF(Data!$C:$C,C54,Data!$ED:$ED)+SUMIF(Data!$C:$C,C54,Data!$EF:$EF)+SUMIF(Data!$C:$C,C54,Data!$EH:$EH)+SUMIF(Data!$C:$C,C54,Data!$EJ:$EJ)+SUMIF(Data!$C:$C,C54,Data!$EL:$EL)+SUMIF(Data!$C:$C,C54,Data!$EN:$EN)+SUMIF(Data!$C:$C,C54,Data!$EP:$EP)+SUMIF(Data!$C:$C,C54,Data!$ER:$ER)+SUMIF(Data!$C:$C,C54,Data!$ET:$ET) -> 50.751 | I54: =G54/19 -> 298.41648 | J54: =H54/19 -> 2.6711053 | K54: =IFERROR(INDEX(Data!$ES:$ES,MATCH(C54,Data!$C:$C,0)),0) -> 457.8 | L54: =IFERROR(INDEX(Data!$ET:$ET,MATCH(C54,Data!$C:$C,0)),0) -> 4.05 | M54: =IFERROR(INDEX(Data!$I$3:$ER$553,MATCH($C54,Data!$C$3:$C$553,0),MATCH(DATE(RIGHT($B$5,4),MID($B$5,4,2),LEFT($B$5,2))-42,Data!$I$1:$ER$1,0)),0) -> 547.35652 | N54: {=IFERROR(INDEX(Data!$I$3:$ER$553,MATCH($C54,Data!$C$3:$C$553,0),MATCH(DATE(RIGHT($B$5,4),MID($B$5,4,2),LEFT($B$5,2))-42,Data!$I$1:$ER$1,0)+1),0)} -> 4.842 | O54: =IFERROR(INDEX(Data!$I$3:$ER$553,MATCH($C54,Data!$C$3:$C$553,0),MATCH($M$5,Data!$I$1:$ER$1,0)),0) -> 0 | P54: {=IFERROR(INDEX(Data!$I$3:$ER$553,MATCH($C54,Data!$C$3:$C$553,0),MATCH($M$5,Data!$I$1:$ER$1,0)+1),0)} -> 0 | Q54: =IF(R54="","",IF(H54=0,0,R54*(G54/H54)))
A55: 204 | B55: LAMB | C55: 34247 | D55: LAMB NECK | E55: 4953.2696 | F55: 34.782 | G55: =SUMIF(Data!$C:$C,C55,Data!$DI:$DI)+SUMIF(Data!$C:$C,C55,Data!$DK:$DK)+SUMIF(Data!$C:$C,C55,Data!$DM:$DM)+SUMIF(Data!$C:$C,C55,Data!$DO:$DO)+SUMIF(Data!$C:$C,C55,Data!$DQ:$DQ)+SUMIF(Data!$C:$C,C55,Data!$DS:$DS)+SUMIF(Data!$C:$C,C55,Data!$DU:$DU)+SUMIF(Data!$C:$C,C55,Data!$DW:$DW)+SUMIF(Data!$C:$C,C55,Data!$DY:$DY)+SUMIF(Data!$C:$C,C55,Data!$EA:$EA)+SUMIF(Data!$C:$C,C55,Data!$EC:$EC)+SUMIF(Data!$C:$C,C55,Data!$EE:$EE)+SUMIF(Data!$C:$C,C55,Data!$EG:$EG)+SUMIF(Data!$C:$C,C55,Data!$EI:$EI)+SUMIF(Data!$C:$C,C55,Data!$EK:$EK)+SUMIF(Data!$C:$C,C55,Data!$EM:$EM)+SUMIF(Data!$C:$C,C55,Data!$EO:$EO)+SUMIF(Data!$C:$C,C55,Data!$EQ:$EQ)+SUMIF(Data!$C:$C,C55,Data!$ES:$ES) -> 4976.6348 | H55: =SUMIF(Data!$C:$C,C55,Data!$DJ:$DJ)+SUMIF(Data!$C:$C,C55,Data!$DL:$DL)+SUMIF(Data!$C:$C,C55,Data!$DN:$DN)+SUMIF(Data!$C:$C,C55,Data!$DP:$DP)+SUMIF(Data!$C:$C,C55,Data!$DR:$DR)+SUMIF(Data!$C:$C,C55,Data!$DT:$DT)+SUMIF(Data!$C:$C,C55,Data!$DV:$DV)+SUMIF(Data!$C:$C,C55,Data!$DX:$DX)+SUMIF(Data!$C:$C,C55,Data!$DZ:$DZ)+SUMIF(Data!$C:$C,C55,Data!$EB:$EB)+SUMIF(Data!$C:$C,C55,Data!$ED:$ED)+SUMIF(Data!$C:$C,C55,Data!$EF:$EF)+SUMIF(Data!$C:$C,C55,Data!$EH:$EH)+SUMIF(Data!$C:$C,C55,Data!$EJ:$EJ)+SUMIF(Data!$C:$C,C55,Data!$EL:$EL)+SUMIF(Data!$C:$C,C55,Data!$EN:$EN)+SUMIF(Data!$C:$C,C55,Data!$EP:$EP)+SUMIF(Data!$C:$C,C55,Data!$ER:$ER)+SUMIF(Data!$C:$C,C55,Data!$ET:$ET) -> 33.774 | I55: =G55/19 -> 261.92815 | J55: =H55/19 -> 1.7775789 | K55: =IFERROR(INDEX(Data!$ES:$ES,MATCH(C55,Data!$C:$C,0)),0) -> 259.8087 | L55: =IFERROR(INDEX(Data!$ET:$ET,MATCH(C55,Data!$C:$C,0)),0) -> 1.66 | M55: =IFERROR(INDEX(Data!$I$3:$ER$553,MATCH($C55,Data!$C$3:$C$553,0),MATCH(DATE(RIGHT($B$5,4),MID($B$5,4,2),LEFT($B$5,2))-42,Data!$I$1:$ER$1,0)),0) -> 110.8 | N55: {=IFERROR(INDEX(Data!$I$3:$ER$553,MATCH($C55,Data!$C$3:$C$553,0),MATCH(DATE(RIGHT($B$5,4),MID($B$5,4,2),LEFT($B$5,2))-42,Data!$I$1:$ER$1,0)+1),0)} -> 0.724 | O55: =IFERROR(INDEX(Data!$I$3:$ER$553,MATCH($C55,Data!$C$3:$C$553,0),MATCH($M$5,Data!$I$1:$ER$1,0)),0) -> 394.13913 | P55: {=IFERROR(INDEX(Data!$I$3:$ER$553,MATCH($C55,Data!$C$3:$C$553,0),MATCH($M$5,Data!$I$1:$ER$1,0)+1),0)} -> 3.022 | Q55: =IF(R55="","",IF(H55=0,0,R55*(G55/H55)))
A56: 204 | B56: LAMB | C56: 59535 | D56: LAM STERTJIES | E56: 1068.2 | F56: 7.704 | G56: =SUMIF(Data!$C:$C,C56,Data!$DI:$DI)+SUMIF(Data!$C:$C,C56,Data!$DK:$DK)+SUMIF(Data!$C:$C,C56,Data!$DM:$DM)+SUMIF(Data!$C:$C,C56,Data!$DO:$DO)+SUMIF(Data!$C:$C,C56,Data!$DQ:$DQ)+SUMIF(Data!$C:$C,C56,Data!$DS:$DS)+SUMIF(Data!$C:$C,C56,Data!$DU:$DU)+SUMIF(Data!$C:$C,C56,Data!$DW:$DW)+SUMIF(Data!$C:$C,C56,Data!$DY:$DY)+SUMIF(Data!$C:$C,C56,Data!$EA:$EA)+SUMIF(Data!$C:$C,C56,Data!$EC:$EC)+SUMIF(Data!$C:$C,C56,Data!$EE:$EE)+SUMIF(Data!$C:$C,C56,Data!$EG:$EG)+SUMIF(Data!$C:$C,C56,Data!$EI:$EI)+SUMIF(Data!$C:$C,C56,Data!$EK:$EK)+SUMIF(Data!$C:$C,C56,Data!$EM:$EM)+SUMIF(Data!$C:$C,C56,Data!$EO:$EO)+SUMIF(Data!$C:$C,C56,Data!$EQ:$EQ)+SUMIF(Data!$C:$C,C56,Data!$ES:$ES) -> 3451.0087 | H56: =SUMIF(Data!$C:$C,C56,Data!$DJ:$DJ)+SUMIF(Data!$C:$C,C56,Data!$DL:$DL)+SUMIF(Data!$C:$C,C56,Data!$DN:$DN)+SUMIF(Data!$C:$C,C56,Data!$DP:$DP)+SUMIF(Data!$C:$C,C56,Data!$DR:$DR)+SUMIF(Data!$C:$C,C56,Data!$DT:$DT)+SUMIF(Data!$C:$C,C56,Data!$DV:$DV)+SUMIF(Data!$C:$C,C56,Data!$DX:$DX)+SUMIF(Data!$C:$C,C56,Data!$DZ:$DZ)+SUMIF(Data!$C:$C,C56,Data!$EB:$EB)+SUMIF(Data!$C:$C,C56,Data!$ED:$ED)+SUMIF(Data!$C:$C,C56,Data!$EF:$EF)+SUMIF(Data!$C:$C,C56,Data!$EH:$EH)+SUMIF(Data!$C:$C,C56,Data!$EJ:$EJ)+SUMIF(Data!$C:$C,C56,Data!$EL:$EL)+SUMIF(Data!$C:$C,C56,Data!$EN:$EN)+SUMIF(Data!$C:$C,C56,Data!$EP:$EP)+SUMIF(Data!$C:$C,C56,Data!$ER:$ER)+SUMIF(Data!$C:$C,C56,Data!$ET:$ET) -> 23.416 | I56: =G56/19 -> 181.63204 | J56: =H56/19 -> 1.2324211 | K56: =IFERROR(INDEX(Data!$ES:$ES,MATCH(C56,Data!$C:$C,0)),0) -> 50.556522 | L56: =IFERROR(INDEX(Data!$ET:$ET,MATCH(C56,Data!$C:$C,0)),0) -> 0.342 | M56: =IFERROR(INDEX(Data!$I$3:$ER$553,MATCH($C56,Data!$C$3:$C$553,0),MATCH(DATE(RIGHT($B$5,4),MID($B$5,4,2),LEFT($B$5,2))-42,Data!$I$1:$ER$1,0)),0) -> 0 | N56: {=IFERROR(INDEX(Data!$I$3:$ER$553,MATCH($C56,Data!$C$3:$C$553,0),MATCH(DATE(RIGHT($B$5,4),MID($B$5,4,2),LEFT($B$5,2))-42,Data!$I$1:$ER$1,0)+1),0)} -> 0 | O56: =IFERROR(INDEX(Data!$I$3:$ER$553,MATCH($C56,Data!$C$3:$C$553,0),MATCH($M$5,Data!$I$1:$ER$1,0)),0) -> 0 | P56: {=IFERROR(INDEX(Data!$I$3:$ER$553,MATCH($C56,Data!$C$3:$C$553,0),MATCH($M$5,Data!$I$1:$ER$1,0)+1),0)} -> 0 | Q56: =IF(R56="","",IF(H56=0,0,R56*(G56/H56)))
A57: 204 | B57: LAMB | C57: 50339 | D57: LAMB LIVER | E57: 1571.7826 | F57: 25.856 | G57: =SUMIF(Data!$C:$C,C57,Data!$DI:$DI)+SUMIF(Data!$C:$C,C57,Data!$DK:$DK)+SUMIF(Data!$C:$C,C57,Data!$DM:$DM)+SUMIF(Data!$C:$C,C57,Data!$DO:$DO)+SUMIF(Data!$C:$C,C57,Data!$DQ:$DQ)+SUMIF(Data!$C:$C,C57,Data!$DS:$DS)+SUMIF(Data!$C:$C,C57,Data!$DU:$DU)+SUMIF(Data!$C:$C,C57,Data!$DW:$DW)+SUMIF(Data!$C:$C,C57,Data!$DY:$DY)+SUMIF(Data!$C:$C,C57,Data!$EA:$EA)+SUMIF(Data!$C:$C,C57,Data!$EC:$EC)+SUMIF(Data!$C:$C,C57,Data!$EE:$EE)+SUMIF(Data!$C:$C,C57,Data!$EG:$EG)+SUMIF(Data!$C:$C,C57,Data!$EI:$EI)+SUMIF(Data!$C:$C,C57,Data!$EK:$EK)+SUMIF(Data!$C:$C,C57,Data!$EM:$EM)+SUMIF(Data!$C:$C,C57,Data!$EO:$EO)+SUMIF(Data!$C:$C,C57,Data!$EQ:$EQ)+SUMIF(Data!$C:$C,C57,Data!$ES:$ES) -> 1851.5739 | H57: =SUMIF(Data!$C:$C,C57,Data!$DJ:$DJ)+SUMIF(Data!$C:$C,C57,Data!$DL:$DL)+SUMIF(Data!$C:$C,C57,Data!$DN:$DN)+SUMIF(Data!$C:$C,C57,Data!$DP:$DP)+SUMIF(Data!$C:$C,C57,Data!$DR:$DR)+SUMIF(Data!$C:$C,C57,Data!$DT:$DT)+SUMIF(Data!$C:$C,C57,Data!$DV:$DV)+SUMIF(Data!$C:$C,C57,Data!$DX:$DX)+SUMIF(Data!$C:$C,C57,Data!$DZ:$DZ)+SUMIF(Data!$C:$C,C57,Data!$EB:$EB)+SUMIF(Data!$C:$C,C57,Data!$ED:$ED)+SUMIF(Data!$C:$C,C57,Data!$EF:$EF)+SUMIF(Data!$C:$C,C57,Data!$EH:$EH)+SUMIF(Data!$C:$C,C57,Data!$EJ:$EJ)+SUMIF(Data!$C:$C,C57,Data!$EL:$EL)+SUMIF(Data!$C:$C,C57,Data!$EN:$EN)+SUMIF(Data!$C:$C,C57,Data!$EP:$EP)+SUMIF(Data!$C:$C,C57,Data!$ER:$ER)+SUMIF(Data!$C:$C,C57,Data!$ET:$ET) -> 26.726 | I57: =G57/19 -> 97.451259 | J57: =H57/19 -> 1.4066316 | K57: =IFERROR(INDEX(Data!$ES:$ES,MATCH(C57,Data!$C:$C,0)),0) -> 179.71304 | L57: =IFERROR(INDEX(Data!$ET:$ET,MATCH(C57,Data!$C:$C,0)),0) -> 2.61 | M57: =IFERROR(INDEX(Data!$I$3:$ER$553,MATCH($C57,Data!$C$3:$C$553,0),MATCH(DATE(RIGHT($B$5,4),MID($B$5,4,2),LEFT($B$5,2))-42,Data!$I$1:$ER$1,0)),0) -> 70.234783 | N57: {=IFERROR(INDEX(Data!$I$3:$ER$553,MATCH($C57,Data!$C$3:$C$553,0),MATCH(DATE(RIGHT($B$5,4),MID($B$5,4,2),LEFT($B$5,2))-42,Data!$I$1:$ER$1,0)+1),0)} -> 1.036 | O57: =IFERROR(INDEX(Data!$I$3:$ER$553,MATCH($C57,Data!$C$3:$C$553,0),MATCH($M$5,Data!$I$1:$ER$1,0)),0) -> 160.65217 | P57: {=IFERROR(INDEX(Data!$I$3:$ER$553,MATCH($C57,Data!$C$3:$C$553,0),MATCH($M$5,Data!$I$1:$ER$1,0)+1),0)} -> 2.64 | Q57: =IF(R57="","",IF(H57=0,0,R57*(G57/H57)))
A58: 204 | B58: LAMB | C58: 34240 | D58: LAMB BRAAI RIB | E58: 3588.2957 | F58: 25.024 | G58: =SUMIF(Data!$C:$C,C58,Data!$DI:$DI)+SUMIF(Data!$C:$C,C58,Data!$DK:$DK)+SUMIF(Data!$C:$C,C58,Data!$DM:$DM)+SUMIF(Data!$C:$C,C58,Data!$DO:$DO)+SUMIF(Data!$C:$C,C58,Data!$DQ:$DQ)+SUMIF(Data!$C:$C,C58,Data!$DS:$DS)+SUMIF(Data!$C:$C,C58,Data!$DU:$DU)+SUMIF(Data!$C:$C,C58,Data!$DW:$DW)+SUMIF(Data!$C:$C,C58,Data!$DY:$DY)+SUMIF(Data!$C:$C,C58,Data!$EA:$EA)+SUMIF(Data!$C:$C,C58,Data!$EC:$EC)+SUMIF(Data!$C:$C,C58,Data!$EE:$EE)+SUMIF(Data!$C:$C,C58,Data!$EG:$EG)+SUMIF(Data!$C:$C,C58,Data!$EI:$EI)+SUMIF(Data!$C:$C,C58,Data!$EK:$EK)+SUMIF(Data!$C:$C,C58,Data!$EM:$EM)+SUMIF(Data!$C:$C,C58,Data!$EO:$EO)+SUMIF(Data!$C:$C,C58,Data!$EQ:$EQ)+SUMIF(Data!$C:$C,C58,Data!$ES:$ES) -> 1448.6957 | H58: =SUMIF(Data!$C:$C,C58,Data!$DJ:$DJ)+SUMIF(Data!$C:$C,C58,Data!$DL:$DL)+SUMIF(Data!$C:$C,C58,Data!$DN:$DN)+SUMIF(Data!$C:$C,C58,Data!$DP:$DP)+SUMIF(Data!$C:$C,C58,Data!$DR:$DR)+SUMIF(Data!$C:$C,C58,Data!$DT:$DT)+SUMIF(Data!$C:$C,C58,Data!$DV:$DV)+SUMIF(Data!$C:$C,C58,Data!$DX:$DX)+SUMIF(Data!$C:$C,C58,Data!$DZ:$DZ)+SUMIF(Data!$C:$C,C58,Data!$EB:$EB)+SUMIF(Data!$C:$C,C58,Data!$ED:$ED)+SUMIF(Data!$C:$C,C58,Data!$EF:$EF)+SUMIF(Data!$C:$C,C58,Data!$EH:$EH)+SUMIF(Data!$C:$C,C58,Data!$EJ:$EJ)+SUMIF(Data!$C:$C,C58,Data!$EL:$EL)+SUMIF(Data!$C:$C,C58,Data!$EN:$EN)+SUMIF(Data!$C:$C,C58,Data!$EP:$EP)+SUMIF(Data!$C:$C,C58,Data!$ER:$ER)+SUMIF(Data!$C:$C,C58,Data!$ET:$ET) -> 9.256 | I58: =G58/19 -> 76.24714 | J58: =H58/19 -> 0.48715789 | K58: =IFERROR(INDEX(Data!$ES:$ES,MATCH(C58,Data!$C:$C,0)),0) -> 0 | L58: =IFERROR(INDEX(Data!$ET:$ET,MATCH(C58,Data!$C:$C,0)),0) -> 0 | M58: =IFERROR(INDEX(Data!$I$3:$ER$553,MATCH($C58,Data!$C$3:$C$553,0),MATCH(DATE(RIGHT($B$5,4),MID($B$5,4,2),LEFT($B$5,2))-42,Data!$I$1:$ER$1,0)),0) -> 0 | N58: {=IFERROR(INDEX(Data!$I$3:$ER$553,MATCH($C58,Data!$C$3:$C$553,0),MATCH(DATE(RIGHT($B$5,4),MID($B$5,4,2),LEFT($B$5,2))-42,Data!$I$1:$ER$1,0)+1),0)} -> 0 | O58: =IFERROR(INDEX(Data!$I$3:$ER$553,MATCH($C58,Data!$C$3:$C$553,0),MATCH($M$5,Data!$I$1:$ER$1,0)),0) -> 61.217391 | P58: {=IFERROR(INDEX(Data!$I$3:$ER$553,MATCH($C58,Data!$C$3:$C$553,0),MATCH($M$5,Data!$I$1:$ER$1,0)+1),0)} -> 0.44 | Q58: =IF(R58="","",IF(H58=0,0,R58*(G58/H58)))
A59: 204 | B59: LAMB | C59: 34238 | D59: LAMB NIERTJIES | E59: 1087.0435 | F59: 18.944 | G59: =SUMIF(Data!$C:$C,C59,Data!$DI:$DI)+SUMIF(Data!$C:$C,C59,Data!$DK:$DK)+SUMIF(Data!$C:$C,C59,Data!$DM:$DM)+SUMIF(Data!$C:$C,C59,Data!$DO:$DO)+SUMIF(Data!$C:$C,C59,Data!$DQ:$DQ)+SUMIF(Data!$C:$C,C59,Data!$DS:$DS)+SUMIF(Data!$C:$C,C59,Data!$DU:$DU)+SUMIF(Data!$C:$C,C59,Data!$DW:$DW)+SUMIF(Data!$C:$C,C59,Data!$DY:$DY)+SUMIF(Data!$C:$C,C59,Data!$EA:$EA)+SUMIF(Data!$C:$C,C59,Data!$EC:$EC)+SUMIF(Data!$C:$C,C59,Data!$EE:$EE)+SUMIF(Data!$C:$C,C59,Data!$EG:$EG)+SUMIF(Data!$C:$C,C59,Data!$EI:$EI)+SUMIF(Data!$C:$C,C59,Data!$EK:$EK)+SUMIF(Data!$C:$C,C59,Data!$EM:$EM)+SUMIF(Data!$C:$C,C59,Data!$EO:$EO)+SUMIF(Data!$C:$C,C59,Data!$EQ:$EQ)+SUMIF(Data!$C:$C,C59,Data!$ES:$ES) -> 1494.2261 | H59: =SUMIF(Data!$C:$C,C59,Data!$DJ:$DJ)+SUMIF(Data!$C:$C,C59,Data!$DL:$DL)+SUMIF(Data!$C:$C,C59,Data!$DN:$DN)+SUMIF(Data!$C:$C,C59,Data!$DP:$DP)+SUMIF(Data!$C:$C,C59,Data!$DR:$DR)+SUMIF(Data!$C:$C,C59,Data!$DT:$DT)+SUMIF(Data!$C:$C,C59,Data!$DV:$DV)+SUMIF(Data!$C:$C,C59,Data!$DX:$DX)+SUMIF(Data!$C:$C,C59,Data!$DZ:$DZ)+SUMIF(Data!$C:$C,C59,Data!$EB:$EB)+SUMIF(Data!$C:$C,C59,Data!$ED:$ED)+SUMIF(Data!$C:$C,C59,Data!$EF:$EF)+SUMIF(Data!$C:$C,C59,Data!$EH:$EH)+SUMIF(Data!$C:$C,C59,Data!$EJ:$EJ)+SUMIF(Data!$C:$C,C59,Data!$EL:$EL)+SUMIF(Data!$C:$C,C59,Data!$EN:$EN)+SUMIF(Data!$C:$C,C59,Data!$EP:$EP)+SUMIF(Data!$C:$C,C59,Data!$ER:$ER)+SUMIF(Data!$C:$C,C59,Data!$ET:$ET) -> 24.176 | I59: =G59/19 -> 78.643478 | J59: =H59/19 -> 1.2724211 | K59: =IFERROR(INDEX(Data!$ES:$ES,MATCH(C59,Data!$C:$C,0)),0) -> 188.53913 | L59: =IFERROR(INDEX(Data!$ET:$ET,MATCH(C59,Data!$C:$C,0)),0) -> 3.098 | M59: =IFERROR(INDEX(Data!$I$3:$ER$553,MATCH($C59,Data!$C$3:$C$553,0),MATCH(DATE(RIGHT($B$5,4),MID($B$5,4,2),LEFT($B$5,2))-42,Data!$I$1:$ER$1,0)),0) -> 29.095652 | N59: {=IFERROR(INDEX(Data!$I$3:$ER$553,MATCH($C59,Data!$C$3:$C$553,0),MATCH(DATE(RIGHT($B$5,4),MID($B$5,4,2),LEFT($B$5,2))-42,Data!$I$1:$ER$1,0)+1),0)} -> 0.478 | O59: =IFERROR(INDEX(Data!$I$3:$ER$553,MATCH($C59,Data!$C$3:$C$553,0),MATCH($M$5,Data!$I$1:$ER$1,0)),0) -> 98.678261 | P59: {=IFERROR(INDEX(Data!$I$3:$ER$553,MATCH($C59,Data!$C$3:$C$553,0),MATCH($M$5,Data!$I$1:$ER$1,0)+1),0)} -> 1.81 | Q59: =IF(R59="","",IF(H59=0,0,R59*(G59/H59)))
A60: 204 | B60: LAMB | C60: 34245 | D60: LAMB LEG CHOPS | E60: 8047.1565 | F60: 51.416 | G60: =SUMIF(Data!$C:$C,C60,Data!$DI:$DI)+SUMIF(Data!$C:$C,C60,Data!$DK:$DK)+SUMIF(Data!$C:$C,C60,Data!$DM:$DM)+SUMIF(Data!$C:$C,C60,Data!$DO:$DO)+SUMIF(Data!$C:$C,C60,Data!$DQ:$DQ)+SUMIF(Data!$C:$C,C60,Data!$DS:$DS)+SUMIF(Data!$C:$C,C60,Data!$DU:$DU)+SUMIF(Data!$C:$C,C60,Data!$DW:$DW)+SUMIF(Data!$C:$C,C60,Data!$DY:$DY)+SUMIF(Data!$C:$C,C60,Data!$EA:$EA)+SUMIF(Data!$C:$C,C60,Data!$EC:$EC)+SUMIF(Data!$C:$C,C60,Data!$EE:$EE)+SUMIF(Data!$C:$C,C60,Data!$EG:$EG)+SUMIF(Data!$C:$C,C60,Data!$EI:$EI)+SUMIF(Data!$C:$C,C60,Data!$EK:$EK)+SUMIF(Data!$C:$C,C60,Data!$EM:$EM)+SUMIF(Data!$C:$C,C60,Data!$EO:$EO)+SUMIF(Data!$C:$C,C60,Data!$EQ:$EQ)+SUMIF(Data!$C:$C,C60,Data!$ES:$ES) -> 86.704348 | H60: =SUMIF(Data!$C:$C,C60,Data!$DJ:$DJ)+SUMIF(Data!$C:$C,C60,Data!$DL:$DL)+SUMIF(Data!$C:$C,C60,Data!$DN:$DN)+SUMIF(Data!$C:$C,C60,Data!$DP:$DP)+SUMIF(Data!$C:$C,C60,Data!$DR:$DR)+SUMIF(Data!$C:$C,C60,Data!$DT:$DT)+SUMIF(Data!$C:$C,C60,Data!$DV:$DV)+SUMIF(Data!$C:$C,C60,Data!$DX:$DX)+SUMIF(Data!$C:$C,C60,Data!$DZ:$DZ)+SUMIF(Data!$C:$C,C60,Data!$EB:$EB)+SUMIF(Data!$C:$C,C60,Data!$ED:$ED)+SUMIF(Data!$C:$C,C60,Data!$EF:$EF)+SUMIF(Data!$C:$C,C60,Data!$EH:$EH)+SUMIF(Data!$C:$C,C60,Data!$EJ:$EJ)+SUMIF(Data!$C:$C,C60,Data!$EL:$EL)+SUMIF(Data!$C:$C,C60,Data!$EN:$EN)+SUMIF(Data!$C:$C,C60,Data!$EP:$EP)+SUMIF(Data!$C:$C,C60,Data!$ER:$ER)+SUMIF(Data!$C:$C,C60,Data!$ET:$ET) -> 0.554 | I60: =G60/19 -> 4.5633867 | J60: =H60/19 -> 0.029157895 | K60: =IFERROR(INDEX(Data!$ES:$ES,MATCH(C60,Data!$C:$C,0)),0) -> 0 | L60: =IFERROR(INDEX(Data!$ET:$ET,MATCH(C60,Data!$C:$C,0)),0) -> 0 | M60: =IFERROR(INDEX(Data!$I$3:$ER$553,MATCH($C60,Data!$C$3:$C$553,0),MATCH(DATE(RIGHT($B$5,4),MID($B$5,4,2),LEFT($B$5,2))-42,Data!$I$1:$ER$1,0)),0) -> 0 | N60: {=IFERROR(INDEX(Data!$I$3:$ER$553,MATCH($C60,Data!$C$3:$C$553,0),MATCH(DATE(RIGHT($B$5,4),MID($B$5,4,2),LEFT($B$5,2))-42,Data!$I$1:$ER$1,0)+1),0)} -> 0 | O60: =IFERROR(INDEX(Data!$I$3:$ER$553,MATCH($C60,Data!$C$3:$C$553,0),MATCH($M$5,Data!$I$1:$ER$1,0)),0) -> 1022.0087 | P60: {=IFERROR(INDEX(Data!$I$3:$ER$553,MATCH($C60,Data!$C$3:$C$553,0),MATCH($M$5,Data!$I$1:$ER$1,0)+1),0)} -> 6.53 | Q60: =IF(R60="","",IF(H60=0,0,R60*(G60/H60)))
A61: 204 | B61: LAMB | C61: 44900 | D61: LAMB LEG ROAST | E61: 635.95652 | F61: 4.696 | G61: =SUMIF(Data!$C:$C,C61,Data!$DI:$DI)+SUMIF(Data!$C:$C,C61,Data!$DK:$DK)+SUMIF(Data!$C:$C,C61,Data!$DM:$DM)+SUMIF(Data!$C:$C,C61,Data!$DO:$DO)+SUMIF(Data!$C:$C,C61,Data!$DQ:$DQ)+SUMIF(Data!$C:$C,C61,Data!$DS:$DS)+SUMIF(Data!$C:$C,C61,Data!$DU:$DU)+SUMIF(Data!$C:$C,C61,Data!$DW:$DW)+SUMIF(Data!$C:$C,C61,Data!$DY:$DY)+SUMIF(Data!$C:$C,C61,Data!$EA:$EA)+SUMIF(Data!$C:$C,C61,Data!$EC:$EC)+SUMIF(Data!$C:$C,C61,Data!$EE:$EE)+SUMIF(Data!$C:$C,C61,Data!$EG:$EG)+SUMIF(Data!$C:$C,C61,Data!$EI:$EI)+SUMIF(Data!$C:$C,C61,Data!$EK:$EK)+SUMIF(Data!$C:$C,C61,Data!$EM:$EM)+SUMIF(Data!$C:$C,C61,Data!$EO:$EO)+SUMIF(Data!$C:$C,C61,Data!$EQ:$EQ)+SUMIF(Data!$C:$C,C61,Data!$ES:$ES) -> 73.730435 | H61: =SUMIF(Data!$C:$C,C61,Data!$DJ:$DJ)+SUMIF(Data!$C:$C,C61,Data!$DL:$DL)+SUMIF(Data!$C:$C,C61,Data!$DN:$DN)+SUMIF(Data!$C:$C,C61,Data!$DP:$DP)+SUMIF(Data!$C:$C,C61,Data!$DR:$DR)+SUMIF(Data!$C:$C,C61,Data!$DT:$DT)+SUMIF(Data!$C:$C,C61,Data!$DV:$DV)+SUMIF(Data!$C:$C,C61,Data!$DX:$DX)+SUMIF(Data!$C:$C,C61,Data!$DZ:$DZ)+SUMIF(Data!$C:$C,C61,Data!$EB:$EB)+SUMIF(Data!$C:$C,C61,Data!$ED:$ED)+SUMIF(Data!$C:$C,C61,Data!$EF:$EF)+SUMIF(Data!$C:$C,C61,Data!$EH:$EH)+SUMIF(Data!$C:$C,C61,Data!$EJ:$EJ)+SUMIF(Data!$C:$C,C61,Data!$EL:$EL)+SUMIF(Data!$C:$C,C61,Data!$EN:$EN)+SUMIF(Data!$C:$C,C61,Data!$EP:$EP)+SUMIF(Data!$C:$C,C61,Data!$ER:$ER)+SUMIF(Data!$C:$C,C61,Data!$ET:$ET) -> 0.53 | I61: =G61/19 -> 3.8805492 | J61: =H61/19 -> 0.027894737 | K61: =IFERROR(INDEX(Data!$ES:$ES,MATCH(C61,Data!$C:$C,0)),0) -> 0 | L61: =IFERROR(INDEX(Data!$ET:$ET,MATCH(C61,Data!$C:$C,0)),0) -> 0 | M61: =IFERROR(INDEX(Data!$I$3:$ER$553,MATCH($C61,Data!$C$3:$C$553,0),MATCH(DATE(RIGHT($B$5,4),MID($B$5,4,2),LEFT($B$5,2))-42,Data!$I$1:$ER$1,0)),0) -> 0 | N61: {=IFERROR(INDEX(Data!$I$3:$ER$553,MATCH($C61,Data!$C$3:$C$553,0),MATCH(DATE(RIGHT($B$5,4),MID($B$5,4,2),LEFT($B$5,2))-42,Data!$I$1:$ER$1,0)+1),0)} -> 0 | O61: =IFERROR(INDEX(Data!$I$3:$ER$553,MATCH($C61,Data!$C$3:$C$553,0),MATCH($M$5,Data!$I$1:$ER$1,0)),0) -> 0 | P61: {=IFERROR(INDEX(Data!$I$3:$ER$553,MATCH($C61,Data!$C$3:$C$553,0),MATCH($M$5,Data!$I$1:$ER$1,0)+1),0)} -> 0 | Q61: =IF(R61="","",IF(H61=0,0,R61*(G61/H61)))
A62: LAMB Subtotal | E62: =SUM(E45:E61) -> 134093.27 | F62: =SUM(F45:F61) -> 883.499 | G62: =SUM(G45:G61) -> 201987.83 | H62: =SUM(H45:H61) -> 1354.311 | I62: =AVERAGE(I45:I61) -> 625.34931 | J62: =AVERAGE(J45:J61) -> 4.1929133 | K62: =SUM(K45:K61) -> 7516.1478 | L62: =SUM(L45:L61) -> 52.678 | M62: =SUM(M45:M61) -> 6176.5304 | N62: =SUM(N45:N61) -> 38.388 | O62: =SUM(O45:O61) -> 10351.148 | P62: =SUM(P45:P61) -> 65.622 | Q62: =SUM(Q45:Q61) -> 0 | R62: =SUM(R45:R61) -> 0
