Workbook

Sheet Data
F1: 02/03/26 | H1: 09/03/26 | J1: 16/03/26 | L1: 23/03/26 | N1: 30/03/26 | P1: 06/04/26 | R1: 13/04/26 | T1: 20/04/26 | V1: 27/04/26 | X1: Perfect week
A2: > Sub-Department | B2: Sub-dep Name | C2: Product Code | D2: Product Description | E2: Department | F2: Sales excl. VAT | G2: Sales Quantity | H2: Sales excl. VAT | I2: Sales Quantity | J2: Sales excl. VAT | K2: Sales Quantity | L2: Sales excl. VAT | M2: Sales Quantity | N2: Sales excl. VAT | O2: Sales Quantity | P2: Sales excl. VAT | Q2: Sales Quantity | R2: Sales excl. VAT | S2: Sales Quantity | T2: Sales excl. VAT | U2: Sales Quantity | V2: Sales excl. VAT | W2: Sales Quantity | X2: Max weekly Sales | Y2: Max Quantity | Z2: Total sales | AA2: Total qty | AB2: Count weeks sale>0 | AC2: AVG Sales | AD2: AVG Quantity | AE2: Frequency
A3: 201 | B3: =LOOKUP(A3,Lookup!$A$1:$A$34,Lookup!$B$1:$B$34) -> BUTCHERY | C3: 11141 | D3: SPAR SLT PORK SPARERIB | E3: 2 | F3: 0 | G3: 0 | H3: 0 | I3: 0 | J3: 0 | K3: 0 | L3: 0 | M3: 0 | N3: 0 | O3: 0 | P3: 0 | Q3: 0 | R3: 0 | S3: 0 | T3: 0 | U3: 0 | V3: 0 | W3: 0 | X3: 0 | Y3: 0 | Z3: 0 | AA3: 0 | AB3: 0 | AC3: 0 | AD3: 0 | AE3: Never
A4: 201 | B4: =LOOKUP(A4,Lookup!$A$1:$A$34,Lookup!$B$1:$B$34) -> BUTCHERY | C4: 11385 | D4: ETLIN RIBS PORK SPARE FRZ | E4: 2 | F4: 0 | G4: 0 | H4: 0 | I4: 0 | J4: 0 | K4: 0 | L4: 0 | M4: 0 | N4: 0 | O4: 0 | P4: 0 | Q4: 0 | R4: 0 | S4: 0 | T4: 0 | U4: 0 | V4: 0 | W4: 0 | X4: 0 | Y4: 0 | Z4: 0 | AA4: 0 | AB4: 0 | AC4: 0 | AD4: 0 | AE4: Never
A5: 201 | B5: =LOOKUP(A5,Lookup!$A$1:$A$34,Lookup!$B$1:$B$34) -> BUTCHERY | C5: 11388 | D5: ETLIN CHIC SAHA MDM | E5: 2 | F5: 0 | G5: 0 | H5: 0 | I5: 0 | J5: 0 | K5: 0 | L5: 0 | M5: 0 | N5: 0 | O5: 0 | P5: 0 | Q5: 0 | R5: 0 | S5: 0 | T5: 0 | U5: 0 | V5: 0 | W5: 0 | X5: 0 | Y5: 0 | Z5: 0 | AA5: 0 | AB5: 0 | AC5: 0 | AD5: 0 | AE5: Never
A6: 201 | B6: =LOOKUP(A6,Lookup!$A$1:$A$34,Lookup!$B$1:$B$34) -> BUTCHERY | C6: 12151 | D6: SPAR SLT BEEF CHUCK B/IN | E6: 2 | F6: 0 | G6: 0 | H6: 0 | I6: 0 | J6: 0 | K6: 0 | L6: 0 | M6: 0 | N6: 0 | O6: 0 | P6: 0 | Q6: 0 | R6: 0 | S6: 0 | T6: 0 | U6: 0 | V6: 0 | W6: 0 | X6: 0 | Y6: 0 | Z6: 0 | AA6: 0 | AB6: 0 | AC6: 0 | AD6: 0 | AE6: Never
A7: 201 | B7: =LOOKUP(A7,Lookup!$A$1:$A$34,Lookup!$B$1:$B$34) -> BUTCHERY | C7: 12194 | D7: SPAR T&T GAMMON/TONGUE | E7: 2 | F7: 0 | G7: 0 | H7: 0 | I7: 0 | J7: 0 | K7: 0 | L7: 0 | M7: 0 | N7: 0 | O7: 0 | P7: 0 | Q7: 0 | R7: 0 | S7: 0 | T7: 0 | U7: 0 | V7: 0 | W7: 0 | X7: 0 | Y7: 0 | Z7: 0 | AA7: 0 | AB7: 0 | AC7: 0 | AD7: 0 | AE7: Never
A8: 201 | B8: =LOOKUP(A8,Lookup!$A$1:$A$34,Lookup!$B$1:$B$34) -> BUTCHERY | C8: 12314 | D8: T&T TONGUE/GAMON BOX | E8: 2 | F8: 0 | G8: 0 | H8: 0 | I8: 0 | J8: 0 | K8: 0 | L8: 0 | M8: 0 | N8: 0 | O8: 0 | P8: 0 | Q8: 0 | R8: 0 | S8: 0 | T8: 0 | U8: 0 | V8: 0 | W8: 0 | X8: 0 | Y8: 0 | Z8: 0 | AA8: 0 | AB8: 0 | AC8: 0 | AD8: 0 | AE8: Never
A9: 201 | B9: =LOOKUP(A9,Lookup!$A$1:$A$34,Lookup!$B$1:$B$34) -> BUTCHERY | C9: 15219 | D9: SPAR SLT LAMB LEG | E9: 2 | F9: 0 | G9: 0 | H9: 0 | I9: 0 | J9: 0 | K9: 0 | L9: 0 | M9: 0 | N9: 0 | O9: 0 | P9: 0 | Q9: 0 | R9: 0 | S9: 0 | T9: 0 | U9: 0 | V9: 0 | W9: 0 | X9: 0 | Y9: 0 | Z9: 0 | AA9: 0 | AB9: 0 | AC9: 0 | AD9: 0 | AE9: Never
A10: 201 | B10: =LOOKUP(A10,Lookup!$A$1:$A$34,Lookup!$B$1:$B$34) -> BUTCHERY | C10: 15227 | D10: SPAR SLT LAMB SHOULDER | E10: 2 | F10: 0 | G10: 0 | H10: 0 | I10: 0 | J10: 0 | K10: 0 | L10: 0 | M10: 0 | N10: 0 | O10: 0 | P10: 0 | Q10: 0 | R10: 0 | S10: 0 | T10: 0 | U10: 0 | V10: 0 | W10: 0 | X10: 0 | Y10: 0 | Z10: 0 | AA10: 0 | AB10: 0 | AC10: 0 | AD10: 0 | AE10: Never
A11: 201 | B11: =LOOKUP(A11,Lookup!$A$1:$A$34,Lookup!$B$1:$B$34) -> BUTCHERY | C11: 34176 | D11: BEEF STEAK BURGER | E11: 2 | F11: 0 | G11: 0 | H11: 0 | I11: 0 | J11: 0 | K11: 0 | L11: 0 | M11: 0 | N11: 0 | O11: 0 | P11: 0 | Q11: 0 | R11: 0 | S11: 0 | T11: 0 | U11: 0 | V11: 0 | W11: 0 | X11: 0 | Y11: 0 | Z11: 0 | AA11: 0 | AB11: 0 | AC11: 0 | AD11: 0 | AE11: Never
A12: 201 | B12: =LOOKUP(A12,Lookup!$A$1:$A$34,Lookup!$B$1:$B$34) -> BUTCHERY | C12: 34233 | D12: GAMMON BONELESS | E12: 2 | F12: 0 | G12: 0 | H12: 0 | I12: 0 | J12: 0 | K12: 0 | L12: 0 | M12: 0 | N12: 0 | O12: 0 | P12: 0 | Q12: 0 | R12: 0 | S12: 0 | T12: 0 | U12: 0 | V12: 0 | W12: 0 | X12: 0 | Y12: 0 | Z12: 0 | AA12: 0 | AB12: 0 | AC12: 0 | AD12: 0 | AE12: Never
A13: 201 | B13: =LOOKUP(A13,Lookup!$A$1:$A$34,Lookup!$B$1:$B$34) -> BUTCHERY | C13: 34234 | D13: GAMMON STEAKS | E13: 2 | F13: 0 | G13: 0 | H13: 0 | I13: 0 | J13: 0 | K13: 0 | L13: 0 | M13: 0 | N13: 0 | O13: 0 | P13: 0 | Q13: 0 | R13: 0 | S13: 0 | T13: 0 | U13: 0 | V13: 0 | W13: 0 | X13: 0 | Y13: 0 | Z13: 0 | AA13: 0 | AB13: 0 | AC13: 0 | AD13: 0 | AE13: Never
A14: 201 | B14: =LOOKUP(A14,Lookup!$A$1:$A$34,Lookup!$B$1:$B$34) -> BUTCHERY | C14: 34306 | D14: STEAK MINCE (EXTRA LEAN) | E14: 2 | F14: 0 | G14: 0 | H14: 0 | I14: 0 | J14: 0 | K14: 0 | L14: 0 | M14: 0 | N14: 0 | O14: 0 | P14: 0 | Q14: 0 | R14: 0 | S14: 0 | T14: 0 | U14: 0 | V14: 0 | W14: 0 | X14: 0 | Y14: 0 | Z14: 0 | AA14: 0 | AB14: 0 | AC14: 0 | AD14: 0 | AE14: Never
... A551: 224 | B551: =LOOKUP(A551,Lookup!$A$1:$A$34,Lookup!$B$1:$B$34) -> BILT& DROEWORS BUY IN | C551: 65480 | D551: BW CHILLI DROEWORS | E551: 2 | F551: 92.521739 | G551: 0.266 | H551: 29.217391 | I551: 0.084 | J551: 74.434783 | K551: 0.214 | L551: 212.17391 | M551: 0.61 | N551: 393.73913 | O551: 1.132 | P551: 130.08696 | Q551: 0.374 | R551: 84.869565 | S551: 0.244 | T551: 287.30435 | U551: 0.826 | V551: 415.30435 | W551: 1.194 | X551: 415.30435 | Y551: 1.194 | Z551: 1719.6522 | AA551: 4.944 | AB551: 9 | AC551: 191.07246 | AD551: 0.54933333 | AE551: Regular
F552: =SUM(F21:F551) -> 113539.95 | G552: =SUM(G21:G551) -> 1345.207 | H552: =SUM(H21:H551) -> 98597.73 | I552: =SUM(I21:I551) -> 1129.434 | J552: =SUM(J21:J551) -> 92194.278 | K552: =SUM(K21:K551) -> 1056.451 | L552: =SUM(L21:L551) -> 144298.19 | M552: =SUM(M21:M551) -> 1550.952 | ... AD552: =SUM(AD21:AD551) -> 1557.5562

Sheet Lookup
A1: Sub-Dep | B1: Description
A2: 201 | B2: BUTCHERY
A3: 202 | B3: BEEF
A4: 203 | B4: BUTCHERY CHICKENS
A5: 204 | B5: LAMB
A6: 205 | B6: MUTTON
A7: 206 | B7: PET MINCE/DROEWORS
A8: 207 | B8: PORK
A9: 208 | B9: BUTCHERY TURKEY
A10: 209 | B10: VEAL
A11: 210 | B11: INGREDIENTS
A12: 211 | B12: SMOKED PORK
A13: 212 | B13: SMOKED CHICKEN
... A34: 235 | B34: CHICKEN fresh

Sheet Summary
E1: Perfect week
A2: Sub-Department | B2: Description | C2: Product Code | D2: Product Description | E2: Max weekly Sales | F2: Max Quantity | G2: Total sales | H2: Total qty | I2: No weeks sale>0 | J2: AVG Sales | K2: AVG Quantity | L2: Frequency | M2: Stretch Sales | N2: Stretch Qty | P2: Stretch qty Targets
A3: 201 | B3: BUTCHERY | C3: 56247 | D3: B/WORS ROLL BUTCH | E3: 590.7 | F3: 33 | G3: 590.7 | H3: 33 | I3: 1 | J3: 590.7 | K3: 33 | L3: Rarely | M3: =IF(L3="Regular",J3+J3*($Q$5-I3), IF(L3="Often",J3+J3*($Q$4-I3), J3+J3*($Q$3-I3))) -> 1181.4 | N3: =IF(L3="Regular",K3+K3*($Q$5-I3), IF(L3="Often", K3+K3*($Q$4-I3), K3+K3*($Q$3-I3))) -> 66 | P3: Rarely | Q3: 2
A4: 201 | B4: BUTCHERY | C4: 61370 | D4: SPAR T&T BEEF 35GR BILTONG ORI | E4: 151.25217 | F4: 6 | G4: 201.66957 | H4: 8 | I4: 2 | J4: 100.83478 | K4: 4 | L4: Rarely | M4: =IF(L4="Regular",J4+J4*($Q$5-I4), IF(L4="Often",J4+J4*($Q$4-I4), J4+J4*($Q$3-I4))) -> 100.83478 | N4: =IF(L4="Regular",K4+K4*($Q$5-I4), IF(L4="Often", K4+K4*($Q$4-I4), K4+K4*($Q$3-I4))) -> 4 | P4: Often | Q4: 6
A5: 202 | B5: BEEF | C5: 34172 | D5: BULK BEEF SIRLOIN | E5: 9697.6522 | F5: 64.842 | G5: 38195.722 | H5: 248.188 | I5: 9 | J5: 4243.9691 | K5: 27.576444 | L5: Regular | M5: =IF(L5="Regular",J5+J5*($Q$5-I5), IF(L5="Often",J5+J5*($Q$4-I5), J5+J5*($Q$3-I5))) -> 4243.9691 | N5: =IF(L5="Regular",K5+K5*($Q$5-I5), IF(L5="Often", K5+K5*($Q$4-I5), K5+K5*($Q$3-I5))) -> 27.576444 | P5: Regular | Q5: 9
A6: 202 | B6: BEEF | C6: 53487 | D6: STEAK PACK | E6: 4882.8261 | F6: 40.112 | G6: 30254.165 | H6: 250.962 | I6: 9 | J6: 3361.5739 | K6: 27.884667 | L6: Regular | M6: =IF(L6="Regular",J6+J6*($Q$5-I6), IF(L6="Often",J6+J6*($Q$4-I6), J6+J6*($Q$3-I6))) -> 3361.5739 | N6: =IF(L6="Regular",K6+K6*($Q$5-I6), IF(L6="Often", K6+K6*($Q$4-I6), K6+K6*($Q$3-I6))) -> 27.884667
A7: 202 | B7: BEEF | C7: 12141 | D7: BEEF SIRLOIN | E7: 4750.3304 | F7: 27.316 | G7: 19684.817 | H7: 109.781 | I7: 9 | J7: 2187.2019 | K7: 12.197889 | L7: Regular | M7: =IF(L7="Regular",J7+J7*($Q$5-I7), IF(L7="Often",J7+J7*($Q$4-I7), J7+J7*($Q$3-I7))) -> 2187.2019 | N7: =IF(L7="Regular",K7+K7*($Q$5-I7), IF(L7="Often", K7+K7*($Q$4-I7), K7+K7*($Q$3-I7))) -> 12.197889
A8: 202 | B8: BEEF | C8: 64936 | D8: OPENVELD F/R SIRLOIN2 P/KG | E8: 6900.6522 | F8: 22.1 | G8: 7785.5565 | H8: 24.926 | I8: 4 | J8: 1946.3891 | K8: 6.2315 | L8: Often | M8: =IF(L8="Regular",J8+J8*($Q$5-I8), IF(L8="Often",J8+J8*($Q$4-I8), J8+J8*($Q$3-I8))) -> 5839.1674 | N8: =IF(L8="Regular",K8+K8*($Q$5-I8), IF(L8="Often", K8+K8*($Q$4-I8), K8+K8*($Q$3-I8))) -> 18.6945
A9: 202 | B9: BEEF | C9: 34205 | D9: BULK RUMP MATURED | E9: 2623.3565 | F9: 18.954 | G9: 10324.409 | H9: 67.808 | I9: 8 | J9: 1290.5511 | K9: 8.476 | L9: Regular | M9: =IF(L9="Regular",J9+J9*($Q$5-I9), IF(L9="Often",J9+J9*($Q$4-I9), J9+J9*($Q$3-I9))) -> 2581.1022 | N9: =IF(L9="Regular",K9+K9*($Q$5-I9), IF(L9="Often", K9+K9*($Q$4-I9), K9+K9*($Q$3-I9))) -> 16.952
A10: 202 | B10: BEEF | C10: 34254 | D10: MEATY BONES | E10: 1975.0522 | F10: 56.797 | G10: 10043.67 | H10: 289.025 | I10: 9 | J10: 1115.9633 | K10: 32.113889 | L10: Regular | M10: =IF(L10="Regular",J10+J10*($Q$5-I10), IF(L10="Often",J10+J10*($Q$4-I10), J10+J10*($Q$3-I10))) -> 1115.9633 | N10: =IF(L10="Regular",K10+K10*($Q$5-I10), IF(L10="Often", K10+K10*($Q$4-I10), K10+K10*($Q$3-I10))) -> 32.113889
A11: 202 | B11: BEEF | C11: 12172 | D11: SPAR ST RIB EYE | E11: 1483.7739 | F11: 4.266 | G11: 5119.5391 | H11: 14.749 | I11: 5 | J11: 1023.9078 | K11: 2.9498 | L11: Often | M11: =IF(L11="Regular",J11+J11*($Q$5-I11), IF(L11="Often",J11+J11*($Q$4-I11), J11+J11*($Q$3-I11))) -> 2047.8157 | N11: =IF(L11="Regular",K11+K11*($Q$5-I11), IF(L11="Often", K11+K11*($Q$4-I11), K11+K11*($Q$3-I11))) -> 5.8996
A12: 202 | B12: BEEF | C12: 63526 | D12: BEEF OXTAIL | E12: 3349.8609 | F12: 44.834 | G12: 9181.4696 | H12: 114.644 | I12: 9 | J12: 1020.1633 | K12: 12.738222 | L12: Regular | M12: =IF(L12="Regular",J12+J12*($Q$5-I12), IF(L12="Often",J12+J12*($Q$4-I12), J12+J12*($Q$3-I12))) -> 1020.1633 | N12: =IF(L12="Regular",K12+K12*($Q$5-I12), IF(L12="Often", K12+K12*($Q$4-I12), K12+K12*($Q$3-I12))) -> 12.738222
A13: 202 | B13: BEEF | C13: 63482 | D13: TENDERISE STEAK | E13: 1697.9304 | F13: 16.294 | G13: 9174.1217 | H13: 79.697 | I13: 9 | J13: 1019.3469 | K13: 8.8552222 | L13: Regular | M13: =IF(L13="Regular",J13+J13*($Q$5-I13), IF(L13="Often",J13+J13*($Q$4-I13), J13+J13*($Q$3-I13))) -> 1019.3469 | N13: =IF(L13="Regular",K13+K13*($Q$5-I13), IF(L13="Often", K13+K13*($Q$4-I13), K13+K13*($Q$3-I13))) -> 8.8552222
A14: 202 | B14: BEEF | C14: 12150 | D14: BEEF RUMP MATURED | E14: 1719.4348 | F14: 10.986 | G14: 8994.9217 | H14: 55.139 | I14: 9 | J14: 999.43575 | K14: 6.1265556 | L14: Regular | M14: =IF(L14="Regular",J14+J14*($Q$5-I14), IF(L14="Often",J14+J14*($Q$4-I14), J14+J14*($Q$3-I14))) -> 999.43575 | N14: =IF(L14="Regular",K14+K14*($Q$5-I14), IF(L14="Often", K14+K14*($Q$4-I14), K14+K14*($Q$3-I14))) -> 6.1265556
A15: 202 | B15: BEEF | C15: 34154 | D15: BEEF CHUCK A GRADE | E15: 986.0087 | F15: 9.45 | G15: 986.0087 | H15: 9.45 | I15: 1 | J15: 986.0087 | K15: 9.45 | L15: Rarely | M15: =IF(L15="Regular",J15+J15*($Q$5-I15), IF(L15="Often",J15+J15*($Q$4-I15), J15+J15*($Q$3-I15))) -> 1972.0174 | N15: =IF(L15="Regular",K15+K15*($Q$5-I15), IF(L15="Often", K15+K15*($Q$4-I15), K15+K15*($Q$3-I15))) -> 18.9
A16: 202 | B16: BEEF | C16: 34157 | D16: BEEF FILLET | E16: 1478.6261 | F16: 6.802 | G16: 4702.0957 | H16: 21.674 | I16: 7 | J16: 671.72795 | K16: 3.0962857 | L16: Often | M16: =IF(L16="Regular",J16+J16*($Q$5-I16), IF(L16="Often",J16+J16*($Q$4-I16), J16+J16*($Q$3-I16))) -> 0 | N16: =IF(L16="Regular",K16+K16*($Q$5-I16), IF(L16="Often", K16+K16*($Q$4-I16), K16+K16*($Q$3-I16))) -> 0
A17: 202 | B17: BEEF | C17: 62790 | D17: BEEF RASHER | E17: 1268.4435 | F17: 11.222 | G17: 2494.687 | H17: 22.516 | I17: 4 | J17: 623.67174 | K17: 5.629 | L17: Often | M17: =IF(L17="Regular",J17+J17*($Q$5-I17), IF(L17="Often",J17+J17*($Q$4-I17), J17+J17*($Q$3-I17))) -> 1871.0152 | N17: =IF(L17="Regular",K17+K17*($Q$5-I17), IF(L17="Often", K17+K17*($Q$4-I17), K17+K17*($Q$3-I17))) -> 16.887
... A133: 224 | B133: BILT& DROEWORS BUY IN | C133: 65480 | D133: BW CHILLI DROEWORS | E133: 415.30435 | F133: 1.194 | G133: 1719.6522 | H133: 4.944 | I133: 9 | J133: 191.07246 | K133: 0.54933333 | L133: Regular | M133: =IF(L133="Regular",J133+J133*($Q$5-I133), IF(L133="Often",J133+J133*($Q$4-I133), J133+J133*($Q$3-I133))) -> 191.07246 | N133: =IF(L133="Regular",K133+K133*($Q$5-I133), IF(L133="Often", K133+K133*($Q$4-I133), K133+K133*($Q$3-I133))) -> 0.54933333
E134: =SUM(E3:E133) -> 248594.27 | F134: =SUM(F3:F133) -> 2701.571 | G134: =SUM(G3:G133) -> 1031376.3 | H134: =SUM(H3:H133) -> 11564.752 | I134: =SUM(I3:I133) -> 889 | J134: =SUM(J3:J133) -> 140663.48 | K134: =SUM(K3:K133) -> 1557.5562 | M134: =SUM(M3:M133) -> 168220.14

Sheet Summary Pivot
A1: Analysis of sales over 9 weeks for March and April
A3: Products with actual sales during March and April | C3: Mar-April Total | E3: The Perfect Week | G3: Average week | J3: Stretch Week (Assuming Regular x 9, Often x 6 and Rarely x 3)
A4: Row Labels | B4: Frequency | C4: 9 week total sales | D4: 9 week total qty | E4: Max of Weekly sales | F4: Max of weekly QTY | G4: No of weeks with sales | H4: Average sale per week for weeks with actual sales | I4: Average quantity per week for weeks with actual sales | J4: Stretch Sales per week | K4: Stretch Qty per week
A5: BEEF
A6: BEEF GOULASH | B6: Regular | C6: 3322.8348 | D6: 27.388 | E6: 774.96522 | F6: 6.384 | G6: 9 | H6: 369.20386 | I6: 3.0431111 | J6: 369.20386 | K6: 3.0431111
A7: BEEF SIRLOIN | B7: Regular | C7: 19684.817 | D7: 109.781 | E7: 4750.3304 | F7: 27.316 | G7: 9 | H7: 2187.2019 | I7: 12.197889 | J7: 2187.2019 | K7: 12.197889
A8: BEEF STIRFRY | B8: Regular | C8: 2938.0087 | D8: 25.522 | E8: 627.2 | F8: 5.152 | G8: 8 | H8: 367.25109 | I8: 3.19025 | J8: 734.50217 | K8: 6.3805
A9: MEATY BONES | B9: Regular | C9: 10043.67 | D9: 289.025 | E9: 1975.0522 | F9: 56.797 | G9: 9 | H9: 1115.9633 | I9: 32.113889 | J9: 1115.9633 | K9: 32.113889
A10: BEEF CHUCK A GRADE | B10: Rarely | C10: 986.0087 | D10: 9.45 | E10: 986.0087 | F10: 9.45 | G10: 1 | H10: 986.0087 | I10: 9.45 | J10: 1972.0174 | K10: 18.9
A11: BEEF FILLET | B11: Often | C11: 4702.0957 | D11: 21.674 | E11: 1478.6261 | F11: 6.802 | G11: 7 | H11: 671.72795 | I11: 3.0962857 | J11: 0 | K11: 0
A12: BEEF KEBABS | B12: Rarely | C12: 288.61739 | D12: 1.844 | E12: 153.38261 | F12: 0.98 | G12: 2 | H12: 144.3087 | I12: 0.922 | J12: 144.3087 | K12: 0.922
A13: BEEF MARROW BONES | B13: Rarely | C13: 243.98261 | D13: 3.118 | E13: 110.01739 | F13: 1.406 | G13: 3 | H13: 81.327536 | I13: 1.0393333 | J13: 0 | K13: 0
A14: BEEF OXTAIL | B14: Regular | C14: 9181.4696 | D14: 114.644 | E14: 3349.8609 | F14: 44.834 | G14: 9 | H14: 1020.1633 | I14: 12.738222 | J14: 1020.1633 | K14: 12.738222
A15: BEEF RASHER | B15: Often | C15: 2494.687 | D15: 22.516 | E15: 1268.4435 | F15: 11.222 | G15: 4 | H15: 623.67174 | I15: 5.629 | J15: 1871.0152 | K15: 16.887
A16: BEEF ROAST | B16: Rarely | C16: 253.2 | D16: 2.08 | E16: 253.2 | F16: 2.08 | G16: 1 | H16: 253.2 | I16: 2.08 | J16: 506.4 | K16: 4.16
A17: BEEF RUMP MATURED | B17: Regular | C17: 8994.9217 | D17: 55.139 | E17: 1719.4348 | F17: 10.986 | G17: 9 | H17: 999.43575 | I17: 6.1265556 | J17: 999.43575 | K17: 6.1265556
... A29: YB BAVETTE PLANKIE | B29: Often | C29: 1035.4348 | D29: 5.954 | E29: 644.48696 | F29: 3.706 | G29: 4 | H29: 258.8587 | I29: 1.4885 | J29: 776.57609 | K29: 4.4655
A30: BEEF Total | C30: 175929.45 | D30: 1456.625 | E30: 48969.913 | F30: 386.001 | G30: 147 | H30: 23833.987 | I30: 190.31534 | J30: 33143.577 | K30: 245.96977
A31: BILT& DROEWORS BUY IN
A32: BEEF BILTONG WHEELS CHUTNEY | B32: Regular | C32: 2695.113 | D32: 7.768 | E32: 491.30435 | F32: 1.416 | G32: 9 | H32: 299.457 | I32: 0.86311111 | J32: 299.457 | K32: 0.86311111
A33: BW BEEF BITES CHILLI | B33: Regular | C33: 6954.8174 | D33: 16.336 | E33: 1268.6957 | F33: 2.918 | G33: 9 | H33: 772.75749 | I33: 1.8151111 | J33: 772.75749 | K33: 1.8151111
A34: BW CHILLI DROEWORS | B34: Regular | C34: 1719.6522 | D34: 4.944 | E34: 415.30435 | F34: 1.194 | G34: 9 | H34: 191.07246 | I34: 0.54933333 | J34: 191.07246 | K34: 0.54933333
A35: BW KAROO BEEF BILTONG | B35: Regular | C35: 19159.009 | D35: 55.22 | E35: 2961.6348 | F35: 8.536 | G35: 9 | H35: 2128.7787 | I35: 6.1355556 | J35: 2128.7787 | K35: 6.1355556
A36: BW KUDU DROEWORS | B36: Regular | C36: 7327.9913 | D36: 21.068 | E36: 1266.7739 | F36: 3.642 | G36: 9 | H36: 814.22126 | I36: 2.3408889 | J36: 814.22126 | K36: 2.3408889
A37: BW OUBAAS DROEWORS | B37: Regular | C37: 2512.8783 | D37: 19 | E37: 521.70435 | F37: 4 | G37: 9 | H37: 279.2087 | I37: 2.1111111 | J37: 279.2087 | K37: 2.1111111
A38: BW OUBAAS SALAMI STICKS | B38: Regular | C38: 3443.4261 | D38: 26 | E38: 652.17391 | F38: 5 | G38: 9 | H38: 382.6029 | I38: 2.8888889 | J38: 382.6029 | K38: 2.8888889
A39: BW WAGYU DROEWORS | B39: Regular | C39: 6669.1739 | D39: 19.222 | E39: 1108.1826 | F39: 3.194 | G39: 9 | H39: 741.01932 | I39: 2.1357778 | J39: 741.01932 | K39: 2.1357778
A40: CHICKEN CHILLI STIX | B40: Regular | C40: 2682.6522 | D40: 7.732 | E40: 573.87826 | F40: 1.654 | G40: 9 | H40: 298.07246 | I40: 0.85911111 | J40: 298.07246 | K40: 0.85911111
A41: DELICO SALAMI STICKS 2'S | B41: Regular | C41: 13378.148 | D41: 513 | E41: 2477.4348 | F41: 95 | G41: 9 | H41: 1486.4609 | I41: 57 | J41: 1486.4609 | K41: 57
A42: OSTRITCH DROEWORS | B42: Regular | C42: 2698.4348 | D42: 7.758 | E42: 587.82609 | F42: 1.69 | G42: 9 | H42: 299.82609 | I42: 0.862 | J42: 299.82609 | K42: 0.862
A43: BILT& DROEWORS BUY IN Total | C43: 69241.296 | D43: 698.048 | E43: 12324.913 | F43: 128.244 | G43: 99 | H43: 7693.4773 | I43: 77.560889 | J43: 7693.4773 | K43: 77.560889
A44: BILT&DROEWORS OWN
A45: BEEF BILTONG | B45: Rarely | C45: 62.817391 | D45: 0.144 | E45: 62.817391 | F45: 0.144 | G45: 1 | H45: 62.817391 | I45: 0.144 | J45: 125.63478 | K45: 0.288
A46: BILT&DROEWORS OWN Total | C46: 62.817391 | D46: 0.144 | E46: 62.817391 | F46: 0.144 | G46: 1 | H46: 62.817391 | I46: 0.144 | J46: 125.63478 | K46: 0.288
A47: BUTCH WORS/MINCE/PAT
A48: KASEGRILLER M/CLUB | B48: Regular | C48: 6604.1913 | D48: 65.478 | E48: 1189.1565 | F48: 11.79 | G48: 9 | H48: 733.79903 | I48: 7.2753333 | J48: 733.79903 | K48: 7.2753333
A49: B/VALE SPAR BOEREWORS | B49: Regular | C49: 10451.991 | D49: 92.46 | E49: 2213.1565 | F49: 19.578 | G49: 9 | H49: 1161.3324 | I49: 10.273333 | J49: 1161.3324 | K49: 10.273333
A50: BEEF LEAN MINCE | B50: Regular | C50: 33094.974 | D50: 361.318 | E50: 6251.6348 | F50: 65.364 | G50: 9 | H50: 3677.2193 | I50: 40.146444 | J50: 3677.2193 | K50: 40.146444
A51: BLK BLUEBIRDS NAMIB WORS | B51: Regular | C51: 18052.191 | D51: 173.022 | E51: 2632.7826 | F51: 25.234 | G51: 9 | H51: 2005.799 | I51: 19.224667 | J51: 2005.799 | K51: 19.224667
A52: BLUE BIRDS NAMIB WORS | B52: Regular | C52: 16102.348 | D52: 142.444 | E52: 3047.8783 | F52: 26.962 | G52: 9 | H52: 1789.1498 | I52: 15.827111 | J52: 1789.1498 | K52: 15.827111
A53: BRITOS BUDGET PATTIES | B53: Rarely | C53: 1173.7826 | D53: 15 | E53: 860.77391 | F53: 11 | G53: 3 | H53: 391.26087 | I53: 5 | J53: 0 | K53: 0
B54: Regular | C54: 3303.687 | D54: 76 | E54: 565.10435 | F54: 13 | G54: 9 | H54: 367.07633 | I54: 8.4444444 | J54: 367.07633 | K54: 8.4444444
A55: BULK KASEGRILLER M/CLUB | B55: Often | C55: 5628.7304 | D55: 58.854 | E55: 1254.9652 | F55: 13.122 | G55: 7 | H55: 804.10435 | I55: 8.4077143 | J55: 0 | K55: 0
A56: BULK B/VALE SPAR BOEREWORS | B56: Regular | C56: 12137.122 | D56: 116.328 | E56: 2725.6261 | F56: 26.124 | G56: 8 | H56: 1517.1402 | I56: 14.541 | J56: 3034.2804 | K56: 29.082
A57: BULK GRABOUW BOEREWORS | B57: Regular | C57: 17739.148 | D57: 170.022 | E57: 2885.8522 | F57: 27.66 | G57: 9 | H57: 1971.0164 | I57: 18.891333 | J57: 1971.0164 | K57: 18.891333
A58: BULK GROUND BEEF | B58: Regular | C58: 12719.904 | D58: 162.554 | E58: 2048.1304 | F58: 26.174 | G58: 8 | H58: 1589.988 | I58: 20.31925 | J58: 3179.9761 | K58: 40.6385
A59: BULK LEAN BEEF MINCE | B59: Regular | C59: 55671.487 | D59: 640.924 | E59: 9867.4783 | F59: 113.991 | G59: 9 | H59: 6185.7208 | I59: 71.213778 | J59: 6185.7208 | K59: 71.213778
A60: BULK OPPIE-KOPPIE B/WORS | B60: Often | C60: 10899.174 | D60: 104.461 | E60: 3341.2087 | F60: 32.023 | G60: 7 | H60: 1557.0248 | I60: 14.923 | J60: 0 | K60: 0
A61: BULK OUKRANS BOEREWORS | B61: Rarely | C61: 4108.8783 | D61: 39.381 | E61: 2042.0174 | F61: 19.572 | G61: 3 | H61: 1369.6261 | I61: 13.127 | J61: 0 | K61: 0
A62: BULK ROOIBERG B/WORS | B62: Often | C62: 10807.574 | D62: 112.122 | E62: 2594.3304 | F62: 27.126 | G62: 6 | H62: 1801.2623 | I62: 18.687 | J62: 1801.2623 | K62: 18.687
A63: BULK SUPER BRAAI WORS | B63: Often | C63: 2663.6609 | D63: 61.28 | E63: 1378.1391 | F63: 31.705 | G63: 5 | H63: 532.73217 | I63: 12.256 | J63: 1065.4643 | K63: 24.512
A64: BULK WILTSHIRE PORK SAUSAGE | B64: Regular | C64: 10208.148 | D64: 129.207 | E64: 1909.4174 | F64: 24.402 | G64: 8 | H64: 1276.0185 | I64: 16.150875 | J64: 2552.037 | K64: 32.30175
A65: CHARGRILL BURGER | B65: Often | C65: 9665.0609 | D65: 102.509 | E65: 2472.2957 | F65: 28.434 | G65: 6 | H65: 1610.8435 | I65: 17.084833 | J65: 1610.8435 | K65: 17.084833
A66: GRABOUW BOEREWORS | B66: Regular | C66: 21893.722 | D66: 193.684 | E66: 4432.6609 | F66: 39.215 | G66: 9 | H66: 2432.6357 | I66: 21.520444 | J66: 2432.6357 | K66: 21.520444
... A77: YB BEEF SAUSAGE | B77: Rarely | C77: 2523.3043 | D77: 26.381 | E77: 1289.2 | F77: 13.478 | G77: 2 | H77: 1261.6522 | I77: 13.1905 | J77: 1261.6522 | K77: 13.1905
A78: BUTCH WORS/MINCE/PAT Total | C78: 334014.04 | D78: 3566.47 | E78: 75035.052 | F78: 802.617 | G78: 200 | H78: 46197.209 | I78: 492.66019 | J78: 48599.819 | K78: 537.73524
A79: BUTCHERY
A80: B/WORS ROLL BUTCH | B80: Rarely | C80: 590.7 | D80: 33 | E80: 590.7 | F80: 33 | G80: 1 | H80: 590.7 | I80: 33 | J80: 1181.4 | K80: 66
A81: SPAR T&T BEEF 35GR BILTONG ORI | B81: Rarely | C81: 201.66957 | D81: 8 | E81: 151.25217 | F81: 6 | G81: 2 | H81: 100.83478 | I81: 4 | J81: 100.83478 | K81: 4
A82: BUTCHERY Total | C82: 792.36957 | D82: 41 | E82: 741.95217 | F82: 39 | G82: 3 | H82: 691.53478 | I82: 37 | J82: 1282.2348 | K82: 70
A83: BUTCHERY OSTRICH
A84: SPAR SLT OSTRICH FILLET | B84: Regular | C84: 3564.8609 | D84: 41 | E84: 782.53043 | F84: 9 | G84: 9 | H84: 396.09565 | I84: 4.5555556 | J84: 396.09565 | K84: 4.5555556
A85: BUTCHERY OSTRICH Total | C85: 3564.8609 | D85: 41 | E85: 782.53043 | F85: 9 | G85: 9 | H85: 396.09565 | I85: 4.5555556 | J85: 396.09565 | K85: 4.5555556
A86: BUTCHERY SNOEK
A87: GEVLEKTE SNOEK | B87: Regular | C87: 9009.6 | D87: 115.136 | E87: 4289.5913 | F87: 54.818 | G87: 9 | H87: 1001.0667 | I87: 12.792889 | J87: 1001.0667 | K87: 12.792889
A88: BUTCHERY SNOEK Total | C88: 9009.6 | D88: 115.136 | E88: 4289.5913 | F88: 54.818 | G88: 9 | H88: 1001.0667 | I88: 12.792889 | J88: 1001.0667 | K88: 12.792889
A89: BUTCHERY SPICE
A90: BBQ 6 GUN GRILL | B90: Regular | C90: 2373.1217 | D90: 91 | E90: 599.8 | F90: 23 | G90: 9 | H90: 263.68019 | I90: 10.111111 | J90: 263.68019 | K90: 10.111111
A91: MARAKESH RUB | B91: Rarely | C91: 40 | D91: 0.23 | E91: 40 | F91: 0.23 | G91: 1 | H91: 40 | I91: 0.23 | J91: 80 | K91: 0.46
A92: OOM FREDDIE SPRINKLE | B92: Regular | C92: 1243.4783 | D92: 110 | E92: 203.47826 | F92: 18 | G92: 9 | H92: 138.16425 | I92: 12.222222 | J92: 138.16425 | K92: 12.222222
A93: SIX GUN GRILL SPICE | B93: Rarely | C93: 106.22609 | D93: 1.018 | E93: 106.22609 | F93: 1.018 | G93: 1 | H93: 106.22609 | I93: 1.018 | J93: 212.45217 | K93: 2.036
A94: SIX GUN SPICE SHAKER | B94: Often | C94: 464.2087 | D94: 16 | E94: 125.18261 | F94: 4 | G94: 6 | H94: 77.368116 | I94: 2.6666667 | J94: 77.368116 | K94: 2.6666667
A95: YOH FLAVA BBQ | B95: Regular | C95: 3883.0696 | D95: 447 | E95: 677.58261 | F95: 78 | G95: 9 | H95: 431.45217 | I95: 49.666667 | J95: 431.45217 | K95: 49.666667
A96: YOH FLAVA CHICKEN | B96: Regular | C96: 2015.3739 | D96: 232 | E96: 286.66957 | F96: 33 | G96: 9 | H96: 223.93043 | I96: 25.777778 | J96: 223.93043 | K96: 25.777778
A97: BUTCHERY SPICE Total | C97: 10125.478 | D97: 897.248 | E97: 2038.9391 | F97: 157.248 | G97: 44 | H97: 1280.8213 | I97: 101.69244 | J97: 1427.0473 | K97: 102.94044
A98: INGREDIENTS
A99: Y B PORK SIRLION | B99: Regular | C99: 9277.313 | D99: 82.25 | E99: 2458.913 | F99: 21.754 | G99: 9 | H99: 1030.8126 | I99: 9.1388889 | J99: 1030.8126 | K99: 9.1388889
A100: INGREDIENTS Total | C100: 9277.313 | D100: 82.25 | E100: 2458.913 | F100: 21.754 | G100: 9 | H100: 1030.8126 | I100: 9.1388889 | J100: 1030.8126 | K100: 9.1388889
A101: LAMB
A102: LAMB NIERTJIES | B102: Often | C102: 766.47826 | D102: 12.594 | E102: 153.6087 | F102: 2.524 | G102: 7 | H102: 109.49689 | I102: 1.7991429 | J102: 0 | K102: 0
A103: 1/4 LAMB | B103: Often | C103: 30907.443 | D103: 260.07 | E103: 15000.261 | F103: 127.78 | G103: 5 | H103: 6181.4887 | I103: 52.014 | J103: 12362.977 | K103: 104.028
A104: LAM RIB & LOIN | B104: Regular | C104: 12468.983 | D104: 62.434 | E104: 2409.5652 | F104: 11.742 | G104: 9 | H104: 1385.4425 | I104: 6.9371111 | J104: 1385.4425 | K104: 6.9371111
A105: LAM STERTJIES | B105: Often | C105: 728.1913 | D105: 4.926 | E105: 283.23478 | F105: 1.916 | G105: 5 | H105: 145.63826 | I105: 0.9852 | J105: 291.27652 | K105: 1.9704
A106: LAMB LIVER | B106: Often | C106: 904.01739 | D106: 13.05 | E106: 182.77391 | F106: 2.628 | G106: 7 | H106: 129.14534 | I106: 1.8642857 | J106: 0 | K106: 0
A107: LAMB BEST END | B107: Regular | C107: 14259.061 | D107: 87.346 | E107: 2728.2348 | F107: 16.57 | G107: 9 | H107: 1584.3401 | I107: 9.7051111 | J107: 1584.3401 | K107: 9.7051111
A108: LAMB BRAAI CHOPS | B108: Regular | C108: 3580.0522 | D108: 20.586 | E108: 693.91304 | F108: 3.99 | G108: 9 | H108: 397.78357 | I108: 2.2873333 | J108: 397.78357 | K108: 2.2873333
A109: LAMB BRAAI RIB | B109: Often | C109: 625.42609 | D109: 3.996 | E109: 261.06087 | F109: 1.668 | G109: 4 | H109: 156.35652 | I109: 0.999 | J109: 469.06957 | K109: 2.997
A110: LAMB FQ PACK | B110: Rarely | C110: 10862.452 | D110: 89.406 | E110: 7159.6522 | F110: 58.988 | G110: 3 | H110: 3620.8174 | I110: 29.802 | J110: 0 | K110: 0
A111: LAMB LEG CHOPS | B111: Regular | C111: 13095.165 | D111: 70.006 | E111: 2628 | F111: 13.738 | G111: 9 | H111: 1455.0184 | I111: 7.7784444 | J111: 1455.0184 | K111: 7.7784444
A112: LAMB LEG ROAST | B112: Rarely | C112: 73.730435 | D112: 0.53 | E112: 73.730435 | F112: 0.53 | G112: 1 | H112: 73.730435 | I112: 0.53 | J112: 147.46087 | K112: 1.06
A113: LAMB NECK | B113: Regular | C113: 2312.6957 | D113: 16.404 | E113: 494.38261 | F113: 3.35 | G113: 9 | H113: 256.96618 | I113: 1.8226667 | J113: 256.96618 | K113: 1.8226667
... A117: SPAR T&T LAMB SKPDJIES FR P/KG | B117: Regular | C117: 2933.3826 | D117: 26.541 | E117: 599.58261 | F117: 5.428 | G117: 9 | H117: 325.9314 | I117: 2.949 | J117: 325.9314 | K117: 2.949
A118: LAMB Total | C118: 109519.43 | D118: 770.421 | E118: 35670.217 | F118: 269.854 | G118: 112 | H118: 17668.937 | I118: 131.31982 | J118: 21141.726 | K118: 157.46834
A119: MUTTON
A120: MUTTON BEST END CHOPS | B120: Regular | C120: 6937.6174 | D120: 50.888 | E120: 1172.4522 | F120: 8.48 | G120: 9 | H120: 770.84638 | I120: 5.6542222 | J120: 770.84638 | K120: 5.6542222
A121: MUTTON BRAAI CHOPS | B121: Regular | C121: 1654.913 | D121: 12.961 | E121: 332.07826 | F121: 2.546 | G121: 9 | H121: 183.87923 | I121: 1.4401111 | J121: 183.87923 | K121: 1.4401111
A122: MUTTON BRAAI RIB | B122: Rarely | C122: 305.9913 | D122: 2.346 | E122: 168.78261 | F122: 1.294 | G122: 2 | H122: 152.99565 | I122: 1.173 | J122: 152.99565 | K122: 1.173
A123: MUTTON LEG CHOP | B123: Regular | C123: 8206.6783 | D123: 59.948 | E123: 1321.0696 | F123: 9.974 | G123: 9 | H123: 911.85314 | I123: 6.6608889 | J123: 911.85314 | K123: 6.6608889
A124: MUTTON LEG ROAST | B124: Rarely | C124: 494.42609 | D124: 4.092 | E124: 494.42609 | F124: 4.092 | G124: 1 | H124: 494.42609 | I124: 4.092 | J124: 988.85217 | K124: 8.184
A125: MUTTON NECK | B125: Regular | C125: 1202.5478 | D125: 9.418 | E125: 235.01739 | F125: 1.802 | G125: 8 | H125: 150.31848 | I125: 1.17725 | J125: 300.63696 | K125: 2.3545
...

Sheet Sheet1
A1: Analysis of sales over 9 weeks for March and April
H2: Week Type
A3: Products with actual sales during March and April | B3: Average week | E3: Stretch Week | H3: Average | I3: Monday | L3: Tuesday | O3: Wednesday | R3: Thursday | U3: Friday | X3: Saturday | AA3: Sunday | AD3: Closing Stock
A4: Row Labels | B4: Frequency | C4: Average sale per week for weeks with actual sales | D4: Average quantity per week for weeks with actual sales | E4: Stretch Sales per week | F4: Stretch Qty per week | H4: Target Qty | I4: 1 | L4: 2 | O4: 3 | R4: 4 | U4: 5 | X4: 6 | AA4: 7
A5: BEEF | I5: On Hand | J5: Make | K5: Sold | L5: On Hand | M5: Make | N5: Sold | O5: On Hand | P5: Make | Q5: Sold | R5: On Hand | S5: Make | T5: Sold | U5: On Hand | V5: Make | W5: Sold | X5: On Hand | Y5: Make | Z5: Sold | AA5: On Hand | AB5: Make | AC5: Sold
A6: BEEF GOULASH | B6: Regular | C6: 369.20386 | D6: 3.0431111 | E6: 369.20386 | F6: 0.67624691 | H6: =IF($H$3="Average",ROUND(D6,0),IF($H$3="Stretch",ROUND(F6,0),0)) -> 3 | I6: 1 | J6: =IF(I6<$H6,$H6-$I6) -> 2 | K6: 1 | L6: =I6+J6-K6 -> 2 | M6: =IF(K6<$H6,$H6-L6) -> 1 | O6: =L6+M6-N6 -> 3 | P6: =IF(N6<$H6,$H6-O6) -> 0 | Q6: 3 | R6: =O6+P6-Q6 -> 0 | S6: =IF(Q6<$H6,$H6-R6,0) -> 0 | U6: =R6+S6-T6 -> 0 | V6: =IF(T6<$H6,$H6-U6) -> 3 | X6: =U6+V6-W6 -> 3 | Y6: =IF(W6<$H6,$H6-X6) -> 0 | AA6: =X6+Y6-Z6 -> 3 | AB6: =IF(Z6<$H6,$H6-AA6) -> 0
A7: BEEF SIRLOIN | B7: Regular | C7: 2187.2019 | D7: 12.197889 | E7: 2187.2019 | F7: 2.710642 | H7: =IF($H$3="Average",ROUND(D7,0),IF($H$3="Stretch",ROUND(F7,0),0)) -> 12 | I7: 1 | J7: =IF(I7<$H7,$H7-$I7) -> 11 | K7: 1 | L7: =I7+J7-K7 -> 11 | M7: =IF(K7<$H7,$H7-L7) -> 1 | O7: =L7+M7-N7 -> 12 | P7: =IF(N7<$H7,$H7-O7) -> 0 | Q7: 3 | R7: =O7+P7-Q7 -> 9 | S7: =IF(Q7<$H7,$H7-R7,0) -> 3 | U7: =R7+S7-T7 -> 12 | V7: =IF(T7<$H7,$H7-U7) -> 0 | X7: =U7+V7-W7 -> 12 | Y7: =IF(W7<$H7,$H7-X7) -> 0 | AA7: =X7+Y7-Z7 -> 12 | AB7: =IF(Z7<$H7,$H7-AA7) -> 0
A8: BEEF STIRFRY | B8: Regular | C8: 367.25109 | D8: 3.19025 | E8: 413.15747 | F8: 0.7975625 | H8: =IF($H$3="Average",ROUND(D8,0),IF($H$3="Stretch",ROUND(F8,0),0)) -> 3
A9: MEATY BONES | B9: Regular | C9: 1115.9633 | D9: 32.113889 | E9: 1115.9633 | F9: 7.1364198 | H9: =IF($H$3="Average",ROUND(D9,0),IF($H$3="Stretch",ROUND(F9,0),0)) -> 32
A10: BEEF CHUCK A GRADE | B10: Rarely | C10: 986.0087 | D10: 9.45 | E10: 2958.0261 | F10: 18.9 | H10: =IF($H$3="Average",ROUND(D10,0),IF($H$3="Stretch",ROUND(F10,0),0)) -> 9
A11: BEEF FILLET | B11: Often | C11: 671.72795 | D11: 3.0962857 | E11: 575.76681 | F11: 0.88465306 | H11: =IF($H$3="Average",ROUND(D11,0),IF($H$3="Stretch",ROUND(F11,0),0)) -> 3
A12: BEEF KEBABS | B12: Rarely | C12: 144.3087 | D12: 0.922 | E12: 216.46304 | F12: 0.922 | H12: =IF($H$3="Average",ROUND(D12,0),IF($H$3="Stretch",ROUND(F12,0),0)) -> 1
A13: BEEF MARROW BONES | B13: Rarely | C13: 81.327536 | D13: 1.0393333 | E13: 81.327536 | F13: 0.69288889 | H13: =IF($H$3="Average",ROUND(D13,0),IF($H$3="Stretch",ROUND(F13,0),0)) -> 1
A14: BEEF OXTAIL | B14: Regular | C14: 1020.1633 | D14: 12.738222 | E14: 1020.1633 | F14: 2.830716 | H14: =IF($H$3="Average",ROUND(D14,0),IF($H$3="Stretch",ROUND(F14,0),0)) -> 13
A15: BEEF RASHER | B15: Often | C15: 623.67174 | D15: 5.629 | E15: 935.50761 | F15: 2.8145 | H15: =IF($H$3="Average",ROUND(D15,0),IF($H$3="Stretch",ROUND(F15,0),0)) -> 6
A16: BEEF ROAST | B16: Rarely | C16: 253.2 | D16: 2.08 | E16: 759.6 | F16: 4.16 | H16: =IF($H$3="Average",ROUND(D16,0),IF($H$3="Stretch",ROUND(F16,0),0)) -> 2
A17: BEEF RUMP MATURED | B17: Regular | C17: 999.43575 | D17: 6.1265556 | E17: 999.43575 | F17: 1.3614568 | H17: =IF($H$3="Average",ROUND(D17,0),IF($H$3="Stretch",ROUND(F17,0),0)) -> 6
A18: BEEF SHIN B/IN | B18: Often | C18: 388.7913 | D18: 4.685 | E18: 583.18696 | F18: 2.3425 | H18: =IF($H$3="Average",ROUND(D18,0),IF($H$3="Stretch",ROUND(F18,0),0)) -> 5
A19: BEEF SHORT RIB | B19: Rarely | C19: 293.69565 | D19: 2.424 | E19: 293.69565 | F19: 1.616 | H19: =IF($H$3="Average",ROUND(D19,0),IF($H$3="Stretch",ROUND(F19,0),0)) -> 2
... A29: YB BAVETTE PLANKIE | B29: Often | C29: 258.8587 | D29: 1.4885 | E29: 388.28804 | F29: 0.74425 | H29: =IF($H$3="Average",ROUND(D29,0),IF($H$3="Stretch",ROUND(F29,0),0)) -> 1
A30: BEEF Total | C30: 23833.987 | D30: 190.31534 | E30: 28309.46 | F30: 71.727284 | H30: =IF($H$3="Average",ROUND(D30,0),IF($H$3="Stretch",ROUND(F30,0),0)) -> 190
A31: BILT& DROEWORS BUY IN | H31: =IF($H$3="Average",ROUND(D31,0),IF($H$3="Stretch",ROUND(F31,0),0)) -> 0
A32: BEEF BILTONG WHEELS CHUTNEY | B32: Regular | C32: 299.457 | D32: 0.86311111 | E32: 299.457 | F32: 0.19180247 | H32: =IF($H$3="Average",ROUND(D32,0),IF($H$3="Stretch",ROUND(F32,0),0)) -> 1
A33: BW BEEF BITES CHILLI | B33: Regular | C33: 772.75749 | D33: 1.8151111 | E33: 772.75749 | F33: 0.40335802 | H33: =IF($H$3="Average",ROUND(D33,0),IF($H$3="Stretch",ROUND(F33,0),0)) -> 2
A34: BW CHILLI DROEWORS | B34: Regular | C34: 191.07246 | D34: 0.54933333 | E34: 191.07246 | F34: 0.12207407 | H34: =IF($H$3="Average",ROUND(D34,0),IF($H$3="Stretch",ROUND(F34,0),0)) -> 1
A35: BW KAROO BEEF BILTONG | B35: Regular | C35: 2128.7787 | D35: 6.1355556 | E35: 2128.7787 | F35: 1.3634568 | H35: =IF($H$3="Average",ROUND(D35,0),IF($H$3="Stretch",ROUND(F35,0),0)) -> 6
A36: BW KUDU DROEWORS | B36: Regular | C36: 814.22126 | D36: 2.3408889 | E36: 814.22126 | F36: 0.52019753 | H36: =IF($H$3="Average",ROUND(D36,0),IF($H$3="Stretch",ROUND(F36,0),0)) -> 2
A37: BW OUBAAS DROEWORS | B37: Regular | C37: 279.2087 | D37: 2.1111111 | E37: 279.2087 | F37: 0.4691358 | H37: =IF($H$3="Average",ROUND(D37,0),IF($H$3="Stretch",ROUND(F37,0),0)) -> 2
A38: BW OUBAAS SALAMI STICKS | B38: Regular | C38: 382.6029 | D38: 2.8888889 | E38: 382.6029 | F38: 0.64197531 | H38: =IF($H$3="Average",ROUND(D38,0),IF($H$3="Stretch",ROUND(F38,0),0)) -> 3
A39: BW WAGYU DROEWORS | B39: Regular | C39: 741.01932 | D39: 2.1357778 | E39: 741.01932 | F39: 0.47461728 | H39: =IF($H$3="Average",ROUND(D39,0),IF($H$3="Stretch",ROUND(F39,0),0)) -> 2
A40: CHICKEN CHILLI STIX | B40: Regular | C40: 298.07246 | D40: 0.85911111 | E40: 298.07246 | F40: 0.19091358 | H40: =IF($H$3="Average",ROUND(D40,0),IF($H$3="Stretch",ROUND(F40,0),0)) -> 1
A41: DELICO SALAMI STICKS 2'S | B41: Regular | C41: 1486.4609 | D41: 57 | E41: 1486.4609 | F41: 12.666667 | H41: =IF($H$3="Average",ROUND(D41,0),IF($H$3="Stretch",ROUND(F41,0),0)) -> 57
A42: OSTRITCH DROEWORS | B42: Regular | C42: 299.82609 | D42: 0.862 | E42: 299.82609 | F42: 0.19155556 | H42: =IF($H$3="Average",ROUND(D42,0),IF($H$3="Stretch",ROUND(F42,0),0)) -> 1
A43: BILT& DROEWORS BUY IN Total | C43: 7693.4773 | D43: 77.560889 | E43: 7693.4773 | F43: 17.235753 | H43: =IF($H$3="Average",ROUND(D43,0),IF($H$3="Stretch",ROUND(F43,0),0)) -> 78
A44: BILT&DROEWORS OWN | H44: =IF($H$3="Average",ROUND(D44,0),IF($H$3="Stretch",ROUND(F44,0),0)) -> 0
A45: BEEF BILTONG | B45: Rarely | C45: 62.817391 | D45: 0.144 | E45: 188.45217 | F45: 0.288 | H45: =IF($H$3="Average",ROUND(D45,0),IF($H$3="Stretch",ROUND(F45,0),0)) -> 0
A46: BILT&DROEWORS OWN Total | C46: 62.817391 | D46: 0.144 | E46: 188.45217 | F46: 0.288 | H46: =IF($H$3="Average",ROUND(D46,0),IF($H$3="Stretch",ROUND(F46,0),0)) -> 0
A47: BUTCH WORS/MINCE/PAT | H47: =IF($H$3="Average",ROUND(D47,0),IF($H$3="Stretch",ROUND(F47,0),0)) -> 0
A48: KASEGRILLER M/CLUB | B48: Regular | C48: 733.79903 | D48: 7.2753333 | E48: 733.79903 | F48: 1.6167407 | H48: =IF($H$3="Average",ROUND(D48,0),IF($H$3="Stretch",ROUND(F48,0),0)) -> 7
A49: B/VALE SPAR BOEREWORS | B49: Regular | C49: 1161.3324 | D49: 10.273333 | E49: 1161.3324 | F49: 2.282963 | H49: =IF($H$3="Average",ROUND(D49,0),IF($H$3="Stretch",ROUND(F49,0),0)) -> 10
A50: BEEF LEAN MINCE | B50: Regular | C50: 3677.2193 | D50: 40.146444 | E50: 3677.2193 | F50: 8.9214321 | H50: =IF($H$3="Average",ROUND(D50,0),IF($H$3="Stretch",ROUND(F50,0),0)) -> 40
A51: BLK BLUEBIRDS NAMIB WORS | B51: Regular | C51: 2005.799 | D51: 19.224667 | E51: 2005.799 | F51: 4.2721481 | H51: =IF($H$3="Average",ROUND(D51,0),IF($H$3="Stretch",ROUND(F51,0),0)) -> 19
A52: BLUE BIRDS NAMIB WORS | B52: Regular | C52: 1789.1498 | D52: 15.827111 | E52: 1789.1498 | F52: 3.5171358 | H52: =IF($H$3="Average",ROUND(D52,0),IF($H$3="Stretch",ROUND(F52,0),0)) -> 16
A53: BRITOS BUDGET PATTIES | B53: Rarely | C53: 391.26087 | D53: 5 | E53: 391.26087 | F53: 3.3333333 | H53: =IF($H$3="Average",ROUND(D53,0),IF($H$3="Stretch",ROUND(F53,0),0)) -> 5
B54: Regular | C54: 367.07633 | D54: 8.4444444 | E54: 367.07633 | F54: 1.8765432 | H54: =IF($H$3="Average",ROUND(D54,0),IF($H$3="Stretch",ROUND(F54,0),0)) -> 8
A55: BULK KASEGRILLER M/CLUB | B55: Often | C55: 804.10435 | D55: 8.4077143 | E55: 689.2323 | F55: 2.4022041 | H55: =IF($H$3="Average",ROUND(D55,0),IF($H$3="Stretch",ROUND(F55,0),0)) -> 8
A56: BULK B/VALE SPAR BOEREWORS | B56: Regular | C56: 1517.1402 | D56: 14.541 | E56: 1706.7827 | F56: 3.63525 | H56: =IF($H$3="Average",ROUND(D56,0),IF($H$3="Stretch",ROUND(F56,0),0)) -> 15
A57: BULK GRABOUW BOEREWORS | B57: Regular | C57: 1971.0164 | D57: 18.891333 | E57: 1971.0164 | F57: 4.1980741 | H57: =IF($H$3="Average",ROUND(D57,0),IF($H$3="Stretch",ROUND(F57,0),0)) -> 19
A58: BULK GROUND BEEF | B58: Regular | C58: 1589.988 | D58: 20.31925 | E58: 1788.7365 | F58: 5.0798125 | H58: =IF($H$3="Average",ROUND(D58,0),IF($H$3="Stretch",ROUND(F58,0),0)) -> 20
A59: BULK LEAN BEEF MINCE | B59: Regular | C59: 6185.7208 | D59: 71.213778 | E59: 6185.7208 | F59: 15.825284 | H59: =IF($H$3="Average",ROUND(D59,0),IF($H$3="Stretch",ROUND(F59,0),0)) -> 71
A60: BULK OPPIE-KOPPIE B/WORS | B60: Often | C60: 1557.0248 | D60: 14.923 | E60: 1334.5927 | F60: 4.2637143 | H60: =IF($H$3="Average",ROUND(D60,0),IF($H$3="Stretch",ROUND(F60,0),0)) -> 15
A61: BULK OUKRANS BOEREWORS | B61: Rarely | C61: 1369.6261 | D61: 13.127 | E61: 1369.6261 | F61: 8.7513333 | H61: =IF($H$3="Average",ROUND(D61,0),IF($H$3="Stretch",ROUND(F61,0),0)) -> 13
A62: BULK ROOIBERG B/WORS | B62: Often | C62: 1801.2623 | D62: 18.687 | E62: 1801.2623 | F62: 6.229 | H62: =IF($H$3="Average",ROUND(D62,0),IF($H$3="Stretch",ROUND(F62,0),0)) -> 19
A63: BULK SUPER BRAAI WORS | B63: Often | C63: 532.73217 | D63: 12.256 | E63: 639.27861 | F63: 4.9024 | H63: =IF($H$3="Average",ROUND(D63,0),IF($H$3="Stretch",ROUND(F63,0),0)) -> 12
A64: BULK WILTSHIRE PORK SAUSAGE | B64: Regular | C64: 1276.0185 | D64: 16.150875 | E64: 1435.5208 | F64: 4.0377187 | H64: =IF($H$3="Average",ROUND(D64,0),IF($H$3="Stretch",ROUND(F64,0),0)) -> 16
A65: CHARGRILL BURGER | B65: Often | C65: 1610.8435 | D65: 17.084833 | E65: 1610.8435 | F65: 5.6949444 | H65: =IF($H$3="Average",ROUND(D65,0),IF($H$3="Stretch",ROUND(F65,0),0)) -> 17
A66: GRABOUW BOEREWORS | B66: Regular | C66: 2432.6357 | D66: 21.520444 | E66: 2432.6357 | F66: 4.782321 | H66: =IF($H$3="Average",ROUND(D66,0),IF($H$3="Stretch",ROUND(F66,0),0)) -> 22
... A77: YB BEEF SAUSAGE | B77: Rarely | C77: 1261.6522 | D77: 13.1905 | E77: 1892.4783 | F77: 13.1905 | H77: =IF($H$3="Average",ROUND(D77,0),IF($H$3="Stretch",ROUND(F77,0),0)) -> 13
A78: BUTCH WORS/MINCE/PAT Total | C78: 46197.209 | D78: 492.66019 | E78: 48336.109 | F78: 163.73695 | H78: =IF($H$3="Average",ROUND(D78,0),IF($H$3="Stretch",ROUND(F78,0),0)) -> 493
A79: BUTCHERY | H79: =IF($H$3="Average",ROUND(D79,0),IF($H$3="Stretch",ROUND(F79,0),0)) -> 0
A80: B/WORS ROLL BUTCH | B80: Rarely | C80: 590.7 | D80: 33 | E80: 1772.1 | F80: 66 | H80: =IF($H$3="Average",ROUND(D80,0),IF($H$3="Stretch",ROUND(F80,0),0)) -> 33
A81: SPAR T&T BEEF 35GR BILTONG ORI | B81: Rarely | C81: 100.83478 | D81: 4 | E81: 151.25217 | F81: 4 | H81: =IF($H$3="Average",ROUND(D81,0),IF($H$3="Stretch",ROUND(F81,0),0)) -> 4
A82: BUTCHERY Total | C82: 691.53478 | D82: 37 | E82: 1923.3522 | F82: 70 | H82: =IF($H$3="Average",ROUND(D82,0),IF($H$3="Stretch",ROUND(F82,0),0)) -> 37
A83: BUTCHERY OSTRICH | H83: =IF($H$3="Average",ROUND(D83,0),IF($H$3="Stretch",ROUND(F83,0),0)) -> 0
A84: SPAR SLT OSTRICH FILLET | B84: Regular | C84: 396.09565 | D84: 4.5555556 | E84: 396.09565 | F84: 1.0123457 | H84: =IF($H$3="Average",ROUND(D84,0),IF($H$3="Stretch",ROUND(F84,0),0)) -> 5
A85: BUTCHERY OSTRICH Total | C85: 396.09565 | D85: 4.5555556 | E85: 396.09565 | F85: 1.0123457 | H85: =IF($H$3="Average",ROUND(D85,0),IF($H$3="Stretch",ROUND(F85,0),0)) -> 5
A86: BUTCHERY SNOEK | H86: =IF($H$3="Average",ROUND(D86,0),IF($H$3="Stretch",ROUND(F86,0),0)) -> 0
A87: GEVLEKTE SNOEK | B87: Regular | C87: 1001.0667 | D87: 12.792889 | E87: 1001.0667 | F87: 2.8428642 | H87: =IF($H$3="Average",ROUND(D87,0),IF($H$3="Stretch",ROUND(F87,0),0)) -> 13
A88: BUTCHERY SNOEK Total | C88: 1001.0667 | D88: 12.792889 | E88: 1001.0667 | F88: 2.8428642 | H88: =IF($H$3="Average",ROUND(D88,0),IF($H$3="Stretch",ROUND(F88,0),0)) -> 13
A89: BUTCHERY SPICE | H89: =IF($H$3="Average",ROUND(D89,0),IF($H$3="Stretch",ROUND(F89,0),0)) -> 0
A90: BBQ 6 GUN GRILL | B90: Regular | C90: 263.68019 | D90: 10.111111 | E90: 263.68019 | F90: 2.2469136 | H90: =IF($H$3="Average",ROUND(D90,0),IF($H$3="Stretch",ROUND(F90,0),0)) -> 10
A91: MARAKESH RUB | B91: Rarely | C91: 40 | D91: 0.23 | E91: 120 | F91: 0.46 | H91: =IF($H$3="Average",ROUND(D91,0),IF($H$3="Stretch",ROUND(F91,0),0)) -> 0
A92: OOM FREDDIE SPRINKLE | B92: Regular | C92: 138.16425 | D92: 12.222222 | E92: 138.16425 | F92: 2.7160494 | H92: =IF($H$3="Average",ROUND(D92,0),IF($H$3="Stretch",ROUND(F92,0),0)) -> 12
A93: SIX GUN GRILL SPICE | B93: Rarely | C93: 106.22609 | D93: 1.018 | E93: 318.67826 | F93: 2.036 | H93: =IF($H$3="Average",ROUND(D93,0),IF($H$3="Stretch",ROUND(F93,0),0)) -> 1
A94: SIX GUN SPICE SHAKER | B94: Often | C94: 77.368116 | D94: 2.6666667 | E94: 77.368116 | F94: 0.88888889 | H94: =IF($H$3="Average",ROUND(D94,0),IF($H$3="Stretch",ROUND(F94,0),0)) -> 3
A95: YOH FLAVA BBQ | B95: Regular | C95: 431.45217 | D95: 49.666667 | E95: 431.45217 | F95: 11.037037 | H95: =IF($H$3="Average",ROUND(D95,0),IF($H$3="Stretch",ROUND(F95,0),0)) -> 50
A96: YOH FLAVA CHICKEN | B96: Regular | C96: 223.93043 | D96: 25.777778 | E96: 223.93043 | F96: 5.7283951 | H96: =IF($H$3="Average",ROUND(D96,0),IF($H$3="Stretch",ROUND(F96,0),0)) -> 26
A97: BUTCHERY SPICE Total | C97: 1280.8213 | D97: 101.69244 | E97: 1573.2734 | F97: 25.113284 | H97: =IF($H$3="Average",ROUND(D97,0),IF($H$3="Stretch",ROUND(F97,0),0)) -> 102
A98: INGREDIENTS | H98: =IF($H$3="Average",ROUND(D98,0),IF($H$3="Stretch",ROUND(F98,0),0)) -> 0
A99: Y B PORK SIRLION | B99: Regular | C99: 1030.8126 | D99: 9.1388889 | E99: 1030.8126 | F99: 2.0308642 | H99: =IF($H$3="Average",ROUND(D99,0),IF($H$3="Stretch",ROUND(F99,0),0)) -> 9
A100: INGREDIENTS Total | C100: 1030.8126 | D100: 9.1388889 | E100: 1030.8126 | F100: 2.0308642 | H100: =IF($H$3="Average",ROUND(D100,0),IF($H$3="Stretch",ROUND(F100,0),0)) -> 9
A101: LAMB | H101: =IF($H$3="Average",ROUND(D101,0),IF($H$3="Stretch",ROUND(F101,0),0)) -> 0
A102: LAMB NIERTJIES | B102: Often | C102: 109.49689 | D102: 1.7991429 | E102: 93.854481 | F102: 0.51404082 | H102: =IF($H$3="Average",ROUND(D102,0),IF($H$3="Stretch",ROUND(F102,0),0)) -> 2
A103: 1/4 LAMB | B103: Often | C103: 6181.4887 | D103: 52.014 | E103: 7417.7864 | F103: 20.8056 | H103: =IF($H$3="Average",ROUND(D103,0),IF($H$3="Stretch",ROUND(F103,0),0)) -> 52
A104: LAM RIB & LOIN | B104: Regular | C104: 1385.4425 | D104: 6.9371111 | E104: 1385.4425 | F104: 1.5415802 | H104: =IF($H$3="Average",ROUND(D104,0),IF($H$3="Stretch",ROUND(F104,0),0)) -> 7
A105: LAM STERTJIES | B105: Often | C105: 145.63826 | D105: 0.9852 | E105: 174.76591 | F105: 0.39408 | H105: =IF($H$3="Average",ROUND(D105,0),IF($H$3="Stretch",ROUND(F105,0),0)) -> 1
A106: LAMB LIVER | B106: Often | C106: 129.14534 | D106: 1.8642857 | E106: 110.69601 | F106: 0.53265306 | H106: =IF($H$3="Average",ROUND(D106,0),IF($H$3="Stretch",ROUND(F106,0),0)) -> 2
A107: LAMB BEST END | B107: Regular | C107: 1584.3401 | D107: 9.7051111 | E107: 1584.3401 | F107: 2.1566914 | H107: =IF($H$3="Average",ROUND(D107,0),IF($H$3="Stretch",ROUND(F107,0),0)) -> 10
A108: LAMB BRAAI CHOPS | B108: Regular | C108: 397.78357 | D108: 2.2873333 | E108: 397.78357 | F108: 0.5082963 | H108: =IF($H$3="Average",ROUND(D108,0),IF($H$3="Stretch",ROUND(F108,0),0)) -> 2
A109: LAMB BRAAI RIB | B109: Often | C109: 156.35652 | D109: 0.999 | E109: 234.53478 | F109: 0.4995 | H109: =IF($H$3="Average",ROUND(D109,0),IF($H$3="Stretch",ROUND(F109,0),0)) -> 1
A110: LAMB FQ PACK | B110: Rarely | C110: 3620.8174 | D110: 29.802 | E110: 3620.8174 | F110: 19.868 | H110: =IF($H$3="Average",ROUND(D110,0),IF($H$3="Stretch",ROUND(F110,0),0)) -> 30
A111: LAMB LEG CHOPS | B111: Regular | C111: 1455.0184 | D111: 7.7784444 | E111: 1455.0184 | F111: 1.7285432 | H111: =IF($H$3="Average",ROUND(D111,0),IF($H$3="Stretch",ROUND(F111,0),0)) -> 8
A112: LAMB LEG ROAST | B112: Rarely | C112: 73.730435 | D112: 0.53 | E112: 221.1913 | F112: 1.06 | H112: =IF($H$3="Average",ROUND(D112,0),IF($H$3="Stretch",ROUND(F112,0),0)) -> 1
A113: LAMB NECK | B113: Regular | C113: 256.96618 | D113: 1.8226667 | E113: 256.96618 | F113: 0.40503704 | H113: =IF($H$3="Average",ROUND(D113,0),IF($H$3="Stretch",ROUND(F113,0),0)) -> 2
... A117: SPAR T&T LAMB SKPDJIES FR P/KG | B117: Regular | C117: 325.9314 | D117: 2.949 | E117: 325.9314 | F117: 0.65533333 | H117: =IF($H$3="Average",ROUND(D117,0),IF($H$3="Stretch",ROUND(F117,0),0)) -> 3
A118: LAMB Total | C118: 17668.937 | D118: 131.31982 | E118: 19203.245 | F118: 53.415438 | H118: =IF($H$3="Average",ROUND(D118,0),IF($H$3="Stretch",ROUND(F118,0),0)) -> 131
A119: MUTTON | H119: =IF($H$3="Average",ROUND(D119,0),IF($H$3="Stretch",ROUND(F119,0),0)) -> 0
A120: MUTTON BEST END CHOPS | B120: Regular | C120: 770.84638 | D120: 5.6542222 | E120: 770.84638 | F120: 1.2564938 | H120: =IF($H$3="Average",ROUND(D120,0),IF($H$3="Stretch",ROUND(F120,0),0)) -> 6
A121: MUTTON BRAAI CHOPS | B121: Regular | C121: 183.87923 | D121: 1.4401111 | E121: 183.87923 | F121: 0.32002469 | H121: =IF($H$3="Average",ROUND(D121,0),IF($H$3="Stretch",ROUND(F121,0),0)) -> 1
A122: MUTTON BRAAI RIB | B122: Rarely | C122: 152.99565 | D122: 1.173 | E122: 229.49348 | F122: 1.173 | H122: =IF($H$3="Average",ROUND(D122,0),IF($H$3="Stretch",ROUND(F122,0),0)) -> 1
...

Sheet Sales Insights
A1: 📊 Butchery Sales Insights Dashboard - 9 Week Analysis (Mar-Apr)
A3: 🥇 INSIGHT 1: Category Performance Ranking (by Total Sales) | F3: 🏆 INSIGHT 3: Top 10 Products by Total Sales | J3: 📋 GRAND TOTALS
A4: Category | B4: Total Sales (9 wks) | C4: Total Qty | D4: Avg Weekly Sales | F4: Product | G4: Total Sales | H4: Category | J4: Total 9-Week Sales: | K4: R 1,031,376
A5: BUTCH WORS/MINCE/PAT | B5: 334014 | C5: 3566 | D5: 46197 | F5: PORK SHOULDER BRAAI CHOPS | G5: 71881 | H5: PORK | J5: Total Quantity Sold: | K5: 11,565 units
A6: PORK | B6: 267158 | C6: 3346 | D6: 35378 | F6: BULK LEAN BEEF MINCE | G6: 55671 | H6: WORS/MINCE | J6: Avg Weekly Sales: | K6: R 140,663
A7: BEEF | B7: 175929 | C7: 1457 | D7: 23834 | F7: PORK RIB/LOIN CHOPS | G7: 47431 | H7: PORK | J7: Products Analyzed: | K7: 132 products
A8: LAMB | B8: 109519 | C8: 770 | D8: 17669 | F8: BULK BEEF SIRLOIN | G8: 38195 | H8: BEEF | J8: Active Selling Weeks: | K8: 889 (product-weeks)
A9: BILT & DROEWORS BUY IN | B9: 69241 | C9: 698 | D9: 7693 | F9: BEEF LEAN MINCE | G9: 33095 | H9: WORS/MINCE
A10: MUTTON | B10: 37108 | C10: 284 | D10: 4764 | F10: 1/4 LAMB | G10: 30907 | H10: LAMB
A11: BUTCHERY SPICE | B11: 10125 | C11: 897 | D11: 1281 | F11: STEAK PACK | G11: 30254 | H11: BEEF
A12: BUTCHERY SNOEK | B12: 9010 | C12: 115 | D12: 1001 | F12: BULK PORK NECK STEAK | G12: 26515 | H12: PORK
A13: INGREDIENTS | B13: 9277 | C13: 82 | D13: 1031 | F13: GRABOUW BOEREWORS | G13: 21894 | H13: WORS/MINCE
A14: PET MINCE/DROEWORS | B14: 5573 | C14: 266 | D14: 664 | F14: BEEF SIRLOIN | G14: 19685 | H14: BEEF
A17: 📈 INSIGHT 2: Sales Frequency Patterns | F17: 💡 INSIGHT 4: Growth Opportunity (Stretch vs Avg)
A18: Frequency | B18: Count of Products | C18: Description | F18: Category | G18: Avg Weekly Sales | H18: Stretch Target | I18: Upside %
A19: Regular | B19: 80 | C19: Sales 9 out of 9 weeks - RELIABLE | F19: BUTCH WORS/MINCE | G19: 46197 | H19: 48600 | I19: =((H19-G19)/G19) -> 0.052016365
A20: Often | B20: 35 | C20: Sales 5-8 weeks - GROWING POTENTIAL | F20: PORK | G20: 35378 | H20: 46194 | I20: =((H20-G20)/G20) -> 0.30572672
A21: Rarely | B21: 17 | C21: Sales 1-4 weeks - NEEDS ATTENTION | F21: BEEF | G21: 23834 | H21: 33144 | I21: =((H21-G21)/G21) -> 0.39061844
F22: LAMB | G22: 17669 | H22: 21142 | I22: =((H22-G22)/G22) -> 0.19655895
F23: MUTTON | G23: 4764 | H23: 5113 | I23: =((H23-G23)/G23) -> 0.073257767
A47: 🔑 KEY TAKEAWAYS & RECOMMENDATIONS
A49: 1️⃣ TOP PERFORMER: Wors/Mince/Patties dominates with R334K (32% of total sales) - Focus on maintaining stock levels
A50: 2️⃣ PORK STAR: Pork Shoulder Braai Chops is the #1 single product (R71.9K) - Consider promotional bundles
A51: 3️⃣ GROWTH OPPORTUNITY: PORK has 31% upside potential (R35K avg → R46K stretch target)
A52: 4️⃣ CONSISTENCY WINS: 60% of products sell 'Regularly' (9/9 weeks) - These are your reliable revenue drivers
A53: 5️⃣ ATTENTION NEEDED: 17 products sell 'Rarely' (1-4 weeks) - Consider promotions, repositioning, or delisting
A54: 6️⃣ LAMB POTENTIAL: 1/4 Lamb has high per-transaction value (R30.9K from only 5 weeks) - Better availability opportunity

Sheet March vs April
A1: 📊 MARCH vs APRIL: Weekly Sales Comparison & Variance Analysis
A3: 📅 WEEKLY SALES BREAKDOWN
B5: MARCH (5 Weeks) | G5: March | H5: March | I5: APRIL (4 Weeks) | M5: April | N5: April | O5: Avg
A6: Week | B6: Week 1 | C6: Week 2 | D6: Week 3 | E6: Week 4 | F6: Week 5 | G6: Total | H6: Avg/Wk | I6: Week 1 | J6: Week 2 | K6: Week 3 | L6: Week 4 | M6: Total | N6: Avg/Wk | O6: Variance
A7: Date | B7: 46083 | C7: 46090 | D7: 46097 | E7: 46104 | F7: 46111 | I7: 46118 | J7: 46125 | K7: 46132 | L7: 46139 | O7: Apr-Mar
A8: TOTAL SALES | B8: =SUMIF(Data!F:F,">0",Data!F:F) -> 227079.9 | C8: =SUMIF(Data!H:H,">0",Data!H:H) -> 197195.46 | D8: =SUMIF(Data!J:J,">0",Data!J:J) -> 184388.56 | E8: =SUMIF(Data!L:L,">0",Data!L:L) -> 288596.38 | F8: =SUMIF(Data!N:N,">0",Data!N:N) -> 286859.43 | G8: =SUM(B8:F8) -> 1184119.7 | H8: =G8/5 -> 236823.95 | I8: =SUMIF(Data!P:P,">0",Data!P:P) -> 179693.03 | J8: =SUMIF(Data!R:R,">0",Data!R:R) -> 174205.15 | K8: =SUMIF(Data!T:T,">0",Data!T:T) -> 264691.1 | L8: =SUMIF(Data!V:V,">0",Data!V:V) -> 260043.55 | M8: =SUM(I8:L8) -> 878632.82 | N8: =M8/4 -> 219658.2 | O8: =N8-H8 -> -17165.742
A10: 📦 SALES BY CATEGORY
A11: Category | B11: Week 1 | C11: Week 2 | D11: Week 3 | E11: Week 4 | F11: Week 5 | G11: Mar Total | H11: Mar Avg | I11: Week 1 | J11: Week 2 | K11: Week 3 | L11: Week 4 | M11: Apr Total | N11: Apr Avg | O11: Variance
A12: BEEF | B12: =SUMIF(Data!$B:$B,"BEEF",Data!$F:$F) -> 23725.974 | C12: =SUMIF(Data!$B:$B,"BEEF",Data!$H:$H) -> 17387.157 | D12: =SUMIF(Data!$B:$B,"BEEF",Data!$J:$J) -> 16551.348 | E12: =SUMIF(Data!$B:$B,"BEEF",Data!$L:$L) -> 26909.991 | F12: =SUMIF(Data!$B:$B,"BEEF",Data!$N:$N) -> 21533.965 | G12: =SUM(B12:F12) -> 106108.43 | H12: =G12/5 -> 21221.687 | I12: =SUMIF(Data!$B:$B,"BEEF",Data!$P:$P) -> 12573.504 | J12: =SUMIF(Data!$B:$B,"BEEF",Data!$R:$R) -> 14651.478 | K12: =SUMIF(Data!$B:$B,"BEEF",Data!$T:$T) -> 20630.557 | L12: =SUMIF(Data!$B:$B,"BEEF",Data!$V:$V) -> 21965.478 | M12: =SUM(I12:L12) -> 69821.017 | N12: =M12/4 -> 17455.254 | O12: =N12-H12 -> -3766.4326
A13: PORK | B13: =SUMIF(Data!$B:$B,"PORK",Data!$F:$F) -> 28630.47 | C13: =SUMIF(Data!$B:$B,"PORK",Data!$H:$H) -> 27864.243 | D13: =SUMIF(Data!$B:$B,"PORK",Data!$J:$J) -> 26016.183 | E13: =SUMIF(Data!$B:$B,"PORK",Data!$L:$L) -> 38961.878 | F13: =SUMIF(Data!$B:$B,"PORK",Data!$N:$N) -> 40240.687 | G13: =SUM(B13:F13) -> 161713.46 | H13: =G13/5 -> 32342.692 | I13: =SUMIF(Data!$B:$B,"PORK",Data!$P:$P) -> 23092.426 | J13: =SUMIF(Data!$B:$B,"PORK",Data!$R:$R) -> 21468.104 | K13: =SUMIF(Data!$B:$B,"PORK",Data!$T:$T) -> 32821.226 | L13: =SUMIF(Data!$B:$B,"PORK",Data!$V:$V) -> 28063.217 | M13: =SUM(I13:L13) -> 105444.97 | N13: =M13/4 -> 26361.243 | O13: =N13-H13 -> -5981.4487
A14: LAMB | B14: =SUMIF(Data!$B:$B,"LAMB",Data!$F:$F) -> 6809.7826 | C14: =SUMIF(Data!$B:$B,"LAMB",Data!$H:$H) -> 7706.6696 | D14: =SUMIF(Data!$B:$B,"LAMB",Data!$J:$J) -> 6749.7652 | E14: =SUMIF(Data!$B:$B,"LAMB",Data!$L:$L) -> 13589.235 | F14: =SUMIF(Data!$B:$B,"LAMB",Data!$N:$N) -> 17694.643 | G14: =SUM(B14:F14) -> 52550.096 | H14: =G14/5 -> 10510.019 | I14: =SUMIF(Data!$B:$B,"LAMB",Data!$P:$P) -> 7647.8957 | J14: =SUMIF(Data!$B:$B,"LAMB",Data!$R:$R) -> 6176.5304 | K14: =SUMIF(Data!$B:$B,"LAMB",Data!$T:$T) -> 22848.504 | L14: =SUMIF(Data!$B:$B,"LAMB",Data!$V:$V) -> 20296.409 | M14: =SUM(I14:L14) -> 56969.339 | N14: =M14/4 -> 14242.335 | O14: =N14-H14 -> 3732.3157
A15: MUTTON | B15: =SUMIF(Data!$B:$B,"MUTTON",Data!$F:$F) -> 1995.9217 | C15: =SUMIF(Data!$B:$B,"MUTTON",Data!$H:$H) -> 5630.2 | D15: =SUMIF(Data!$B:$B,"MUTTON",Data!$J:$J) -> 3179.6435 | E15: =SUMIF(Data!$B:$B,"MUTTON",Data!$L:$L) -> 5563.5043 | F15: =SUMIF(Data!$B:$B,"MUTTON",Data!$N:$N) -> 5494.7478 | G15: =SUM(B15:F15) -> 21864.017 | H15: =G15/5 -> 4372.8035 | I15: =SUMIF(Data!$B:$B,"MUTTON",Data!$P:$P) -> 2615.4087 | J15: =SUMIF(Data!$B:$B,"MUTTON",Data!$R:$R) -> 4047.1043 | K15: =SUMIF(Data!$B:$B,"MUTTON",Data!$T:$T) -> 3175.2348 | L15: =SUMIF(Data!$B:$B,"MUTTON",Data!$V:$V) -> 5406.713 | M15: =SUM(I15:L15) -> 15244.461 | N15: =M15/4 -> 3811.1152 | O15: =N15-H15 -> -561.68826
A16: WORS/MINCE/PAT | B16: =SUMIF(Data!$B:$B,"BUTCH WORS/MINCE/PAT",Data!$F:$F) -> 39450 | C16: =SUMIF(Data!$B:$B,"BUTCH WORS/MINCE/PAT",Data!$H:$H) -> 30977.365 | D16: =SUMIF(Data!$B:$B,"BUTCH WORS/MINCE/PAT",Data!$J:$J) -> 30462.948 | E16: =SUMIF(Data!$B:$B,"BUTCH WORS/MINCE/PAT",Data!$L:$L) -> 43151.565 | F16: =SUMIF(Data!$B:$B,"BUTCH WORS/MINCE/PAT",Data!$N:$N) -> 41844.643 | G16: =SUM(B16:F16) -> 185886.52 | H16: =G16/5 -> 37177.304 | I16: =SUMIF(Data!$B:$B,"BUTCH WORS/MINCE/PAT",Data!$P:$P) -> 34155.383 | J16: =SUMIF(Data!$B:$B,"BUTCH WORS/MINCE/PAT",Data!$R:$R) -> 31334.722 | K16: =SUMIF(Data!$B:$B,"BUTCH WORS/MINCE/PAT",Data!$T:$T) -> 40959.565 | L16: =SUMIF(Data!$B:$B,"BUTCH WORS/MINCE/PAT",Data!$V:$V) -> 41677.852 | M16: =SUM(I16:L16) -> 148127.52 | N16: =M16/4 -> 37031.88 | O16: =N16-H16 -> -145.42391
A17: BILT & DROEWORS | B17: =SUMIF(Data!$B:$B,"BILT& DROEWORS BUY IN",Data!$F:$F) -> 7886.9739 | C17: =SUMIF(Data!$B:$B,"BILT& DROEWORS BUY IN",Data!$H:$H) -> 6466.9391 | D17: =SUMIF(Data!$B:$B,"BILT& DROEWORS BUY IN",Data!$J:$J) -> 6232.9652 | E17: =SUMIF(Data!$B:$B,"BILT& DROEWORS BUY IN",Data!$L:$L) -> 9835.8087 | F17: =SUMIF(Data!$B:$B,"BILT& DROEWORS BUY IN",Data!$N:$N) -> 8640.4783 | G17: =SUM(B17:F17) -> 39063.165 | H17: =G17/5 -> 7812.633 | I17: =SUMIF(Data!$B:$B,"BILT& DROEWORS BUY IN",Data!$P:$P) -> 5832.6174 | J17: =SUMIF(Data!$B:$B,"BILT& DROEWORS BUY IN",Data!$R:$R) -> 6585.3043 | K17: =SUMIF(Data!$B:$B,"BILT& DROEWORS BUY IN",Data!$T:$T) -> 8325.4783 | L17: =SUMIF(Data!$B:$B,"BILT& DROEWORS BUY IN",Data!$V:$V) -> 9434.7304 | M17: =SUM(I17:L17) -> 30178.13 | N17: =M17/4 -> 7544.5326 | O17: =N17-H17 -> -268.10043
A18: BUTCHERY SPICE | B18: =SUMIF(Data!$B:$B,"BUTCHERY SPICE",Data!$F:$F) -> 1354.9391 | C18: =SUMIF(Data!$B:$B,"BUTCHERY SPICE",Data!$H:$H) -> 893.28696 | D18: =SUMIF(Data!$B:$B,"BUTCHERY SPICE",Data!$J:$J) -> 734.26087 | E18: =SUMIF(Data!$B:$B,"BUTCHERY SPICE",Data!$L:$L) -> 1573.6783 | F18: =SUMIF(Data!$B:$B,"BUTCHERY SPICE",Data!$N:$N) -> 1228.713 | G18: =SUM(B18:F18) -> 5784.8783 | H18: =G18/5 -> 1156.9757 | I18: =SUMIF(Data!$B:$B,"BUTCHERY SPICE",Data!$P:$P) -> 782.87826 | J18: =SUMIF(Data!$B:$B,"BUTCHERY SPICE",Data!$R:$R) -> 1235.7652 | K18: =SUMIF(Data!$B:$B,"BUTCHERY SPICE",Data!$T:$T) -> 1581.6522 | L18: =SUMIF(Data!$B:$B,"BUTCHERY SPICE",Data!$V:$V) -> 740.30435 | M18: =SUM(I18:L18) -> 4340.6 | N18: =M18/4 -> 1085.15 | O18: =N18-H18 -> -71.825652
A19: SNOEK | B19: =SUMIF(Data!$B:$B,"BUTCHERY SNOEK",Data!$F:$F) -> 563.42609 | C19: =SUMIF(Data!$B:$B,"BUTCHERY SNOEK",Data!$H:$H) -> 437.74783 | D19: =SUMIF(Data!$B:$B,"BUTCHERY SNOEK",Data!$J:$J) -> 331.0087 | E19: =SUMIF(Data!$B:$B,"BUTCHERY SNOEK",Data!$L:$L) -> 1473.9478 | F19: =SUMIF(Data!$B:$B,"BUTCHERY SNOEK",Data!$N:$N) -> 4289.5913 | G19: =SUM(B19:F19) -> 7095.7217 | H19: =G19/5 -> 1419.1443 | I19: =SUMIF(Data!$B:$B,"BUTCHERY SNOEK",Data!$P:$P) -> 489.22609 | J19: =SUMIF(Data!$B:$B,"BUTCHERY SNOEK",Data!$R:$R) -> 392.66957 | K19: =SUMIF(Data!$B:$B,"BUTCHERY SNOEK",Data!$T:$T) -> 514.73913 | L19: =SUMIF(Data!$B:$B,"BUTCHERY SNOEK",Data!$V:$V) -> 517.24348 | M19: =SUM(I19:L19) -> 1913.8783 | N19: =M19/4 -> 478.46957 | O19: =N19-H19 -> -940.67478
A20: OSTRICH | B20: =SUMIF(Data!$B:$B,"BUTCHERY OSTRICH",Data!$F:$F) -> 782.53043 | C20: =SUMIF(Data!$B:$B,"BUTCHERY OSTRICH",Data!$H:$H) -> 173.89565 | D20: =SUMIF(Data!$B:$B,"BUTCHERY OSTRICH",Data!$J:$J) -> 521.68696 | E20: =SUMIF(Data!$B:$B,"BUTCHERY OSTRICH",Data!$L:$L) -> 347.7913 | F20: =SUMIF(Data!$B:$B,"BUTCHERY OSTRICH",Data!$N:$N) -> 434.73913 | G20: =SUM(B20:F20) -> 2260.6435 | H20: =G20/5 -> 452.1287 | I20: =SUMIF(Data!$B:$B,"BUTCHERY OSTRICH",Data!$P:$P) -> 347.7913 | J20: =SUMIF(Data!$B:$B,"BUTCHERY OSTRICH",Data!$R:$R) -> 260.84348 | K20: =SUMIF(Data!$B:$B,"BUTCHERY OSTRICH",Data!$T:$T) -> 260.84348 | L20: =SUMIF(Data!$B:$B,"BUTCHERY OSTRICH",Data!$V:$V) -> 434.73913 | M20: =SUM(I20:L20) -> 1304.2174 | N20: =M20/4 -> 326.05435 | O20: =N20-H20 -> -126.07435 | Q20: Category | R20: March Avg | S20: April Avg
A21: PET MINCE | B21: =SUMIF(Data!$B:$B,"PET MINCE/DROEWORS",Data!$F:$F) -> 1001.4087 | C21: =SUMIF(Data!$B:$B,"PET MINCE/DROEWORS",Data!$H:$H) -> 784.73913 | D21: =SUMIF(Data!$B:$B,"PET MINCE/DROEWORS",Data!$J:$J) -> 412.76522 | E21: =SUMIF(Data!$B:$B,"PET MINCE/DROEWORS",Data!$L:$L) -> 381.46087 | F21: =SUMIF(Data!$B:$B,"PET MINCE/DROEWORS",Data!$N:$N) -> 816.32174 | G21: =SUM(B21:F21) -> 3396.6957 | H21: =G21/5 -> 679.33913 | I21: =SUMIF(Data!$B:$B,"PET MINCE/DROEWORS",Data!$P:$P) -> 459.70435 | J21: =SUMIF(Data!$B:$B,"PET MINCE/DROEWORS",Data!$R:$R) -> 550.64348 | K21: =SUMIF(Data!$B:$B,"PET MINCE/DROEWORS",Data!$T:$T) -> 833.49565 | L21: =SUMIF(Data!$B:$B,"PET MINCE/DROEWORS",Data!$V:$V) -> 332.15652 | M21: =SUM(I21:L21) -> 2176 | N21: =M21/4 -> 544 | O21: =N21-H21 -> -135.33913 | Q21: BEEF | R21: =H12 -> 21221.687 | S21: =N12 -> 17455.254
Q22: PORK | R22: =H13 -> 32342.692 | S22: =N13 -> 26361.243
Q23: LAMB | R23: =H14 -> 10510.019 | S23: =N14 -> 14242.335
A24: 📈 VARIANCE ANALYSIS SUMMARY | Q24: MUTTON | R24: =H15 -> 4372.8035 | S24: =N15 -> 3811.1152
A25: Metric | B25: March Total | C25: April Total | D25: Difference (R) | E25: % Change | F25: Mar Avg/Wk | G25: Apr Avg/Wk | Q25: WORS/MINCE/PAT | R25: =H16 -> 37177.304 | S25: =N16 -> 37031.88
A26: Total Sales | B26: =G8 -> 1184119.7 | C26: =M8 -> 878632.82 | D26: =C26-B26 -> -305486.91 | E26: =IF(B26=0,0,(C26-B26)/B26) -> -0.25798651 | F26: =H8 -> 236823.95 | G26: =N8 -> 219658.2 | Q26: BILT & DROEWORS | R26: =H17 -> 7812.633 | S26: =N17 -> 7544.5326
A29: 📊 WEEK-BY-WEEK TREND (All 9 Weeks)
A30: Week # | B30: 1 | C30: 2 | D30: 3 | E30: 4 | F30: 5 | G30: 6 | H30: 7 | I30: 8 | J30: 9 | K30: Best Week
A31: Month | B31: Mar | C31: Mar | D31: Mar | E31: Mar | F31: Mar | G31: Apr | H31: Apr | I31: Apr | J31: Apr
A32: Date | B32: 46083 | C32: 46090 | D32: 46097 | E32: 46104 | F32: 46111 | G32: 46118 | H32: 46125 | I32: 46132 | J32: 46139
A33: Sales (R) | B33: =B8 -> 227079.9 | C33: =C8 -> 197195.46 | D33: =D8 -> 184388.56 | E33: =E8 -> 288596.38 | F33: =F8 -> 286859.43 | G33: =I8 -> 179693.03 | H33: =J8 -> 174205.15 | I33: =K8 -> 264691.1 | J33: =L8 -> 260043.55 | K33: =MAX(B33:J33) -> 288596.38
A34: WoW Change | B34: - | C34: =C33-B33 -> -29884.443 | D34: =D33-C33 -> -12806.904 | E34: =E33-D33 -> 104207.83 | F34: =F33-E33 -> -1736.9565 | G34: =G33-F33 -> -107166.4 | H34: =H33-G33 -> -5487.8783 | I34: =I33-H33 -> 90485.948 | J34: =J33-I33 -> -4647.5478
A35: WoW % Change | B35: - | C35: =IF(B33=0,0,C34/B33) -> -0.13160321 | D35: =IF(C33=0,0,D34/C33) -> -0.064945229 | E35: =IF(D33=0,0,E34/D33) -> 0.56515343 | F35: =IF(E33=0,0,F34/E33) -> -0.0060186358 | G35: =IF(F33=0,0,G34/F33) -> -0.37358507 | H35: =IF(G33=0,0,H34/G33) -> -0.030540296 | I35: =IF(H33=0,0,I34/H33) -> 0.51942178 | J35: =IF(I33=0,0,J34/I33) -> -0.017558384
A38: 🔑 KEY INSIGHTS | Q38: Week | R38: Change (R)
Q39: Wk2 | R39: =C34 -> -29884.443
A40: 1️⃣ MARCH vs APRIL TOTAL: March outperformed April by approximately R305K (5 weeks vs 4 weeks) | Q40: Wk3 | R40: =D34 -> -12806.904
A41: 2️⃣ WEEKLY AVERAGE: Compare Mar Avg (R237K) vs Apr Avg (R220K) for fair comparison - April is ~7% lower | Q41: Wk4 | R41: =E34 -> 104207.83
A42: 3️⃣ PEAK WEEKS: Weeks 4 & 5 of March (23-Mar, 30-Mar) were the strongest performers | Q42: Wk5(Mar) | R42: =F34 -> -1736.9565
A43: 4️⃣ APRIL RECOVERY: Weeks 3 & 4 of April showed strong recovery vs April's slow start | Q43: Wk1(Apr) | R43: =G34 -> -107166.4
A44: 5️⃣ TREND: Sales dipped in early April (Week 1-2) but recovered to near-March levels by end of April | Q44: Wk2(Apr) | R44: =H34 -> -5487.8783
Q45: Wk3(Apr) | R45: =I34 -> 90485.948
Q46: Wk4(Apr) | R46: =J34 -> -4647.5478
